Workbook
Name \A: #REF!
Name \A: #REF!
Name \B: #REF!
Name \B: #REF!
Name \C: #REF!
Name \D: #REF!
Name \E: #REF!
Name \F: #REF!
Name \i: #REF!
Name \M: #REF!
Name \N: #REF!
Name \O: #REF!
Name \P: #REF!
Name \Q: #REF!
Name \S: #REF!
Name \T: #REF!
Name \U: #REF!
Name \w: #REF!
Name \X: #REF!
Name \Y: #REF!
Name \Z: #REF!
Name ____7HILLS: #REF!
Name ____Ins2: #REF!
Name ____Ins3: #REF!
Name ____NML9798: #REF!
Name ____NML98: #REF!
Name ____PEG1: #REF!
Name ____RR1: #REF!
Name ____SKY98: #REF!
Name ___1Module2_.PRINT_BCCAM: #N/A
Name ___7HILLS: #REF!
Name ___Ins2: #REF!
Name ___Ins3: #REF!
Name ___MT1: #REF!
Name ___MT2: #REF!
Name ___MT3: #REF!
Name ___NML9798: #REF!
Name ___NML98: #REF!
Name ___PEG1: #REF!
Name ___RR1: #REF!
Name ___SKY98: #REF!
Name __1Module2_.PRINT_BCCAM: #N/A
Name __2Module2_.PRINT_BCPR: #N/A
Name __3Module2_.PRINT_BCTAX: #N/A
Name __4Module2_.PRINT_HSUM: #N/A
Name __5_96100: #REF!
Name __7HILLS: #REF!
Name __96100: #REF!
Name __Ins2: #REF!
Name __Ins3: #REF!
Name __MT1: #REF!
Name __MT2: #REF!
Name __MT3: #REF!
Name __NML9798: #REF!
Name __NML98: #REF!
Name __PEG1: #REF!
Name __RR1: #REF!
Name __SKY98: #REF!
Name __soa202: #REF!
Name __soa207: #REF!

Sheet Scenario 1 - Phase 1
A1: Project Details | D1: Unit Breakdown | H1: Breakdown Per Building | N1: List of Take offs | R1: List of Take offs
A2: Project | B2: Robindale & 215 | D2: Unit Type | E2: Number | F2: % | H2: Bldg. | I2: Unit | J2: GSF | N2: Slab SF | O2: =B8/3 -> 103714 | P2: GSF / 3 | R2: 1x1 Counter tops | S2: 14490 | T2: SF
A3: Budget Level | B3: Level 1 | D3: Studios | E3: 0 | F3: =E3/$E$8 -> 0 | H3: 1 | I3: 155 | J3: 141378 | N3: Elevators | O3: 4 | P3: Count Est. | R3: 2x1 Counter Tops | S3: 9294 | T3: SF
A4: Product | B4: Senior | D4: 1 Br - 1 Ba | E4: =77+18+96+30 -> 221 | F4: =E4/$E$8 -> 0.63688761 | H4: 2 | I4: 192 | J4: 169764 | N4: Trash Encl. | O4: 10 | P4: Count Est. 1 per 35 Units | R4: 1x1 Cab Boxes | T4: Boxes
A5: Start Date | B5: 45809 | D5: 2 Br - 1 Ba | E5: =39+21+39+27 -> 126 | F5: =E5/$E$8 -> 0.36311239 | N5: Stairs | O5: 11 | P5: Count | R5: 2x1 Cab Boxes | T5: Boxes
A6: Timline | B6: 24 | D6: 2 Br - 2 Ba | E6: 0 | F6: =E6/$E$8 -> 0 | H6: Totals | I6: =SUM(I3:I5) -> 347 | J6: =SUM(J3:J5) -> 311142 | N6: Pool | O6: 2 | R6: 1x1 Decks | S6: =83*48 -> 3984 | T6: SF
A7: Floors | B7: 3 | D7: 3 Br - 2 Ba | E7: 0 | F7: =E7/$E$8 -> 0 | N7: Gym | O7: 2 | R7: 2x1 Decks | T7: SF
A8: Bldg SF | B8: =J6 -> 311142 | D8: Totals | E8: =SUM(E3:E7) -> 347 | F8: =E8/$E$8 -> 1 | H8: TOTAL COST | J8: =L326 -> 59260086 | N8: Iron Rail | O8: =B8/196333*1600 -> 2535.6267 | P8: Prorate to Bruner SF | R8: Pavers | T8: SF
A9: Acres | B9: 11.7 | D9: Parking | H9: PER UNIT | J9: =J8/E8 -> 170778.35 | N9: Roofing | O9: =(47980+59843)/100 -> 1078.23 | P9: Square | R9: Site Landscaping | S9: =37800+16*200+10600+7900+17600 -> 77100 | T9: Building 1 SF
A10: Site SF | B10: =B9*43560 -> 509652 | D10: Garage Parking | F10: 0 | H10: PER GSF | J10: =J8/B8 -> 190.45994 | N10: Stucco | O10: =(SUM(O14:O16)*40)/9 -> 15620 | P10: Square Yard | R10: Site Landscaping | S10: =21300+24400+20800+6800+4300+12000+22*200 -> 94000 | T10: Building 2 SF
A11: Buildings | B11: 2 | D11: Cover Parking | F11: 0 | N11: Liavable Area | O11: =(120244+147789) -> 268033 | P11: SF | R11: Site Landscaping | S11: 0 | T11: Building 3 SF
A12: Reports Available | D12: Open Parking | F12: =706-190 -> 516 | N12: Carports | O12: =F15*60% -> 309.6 | P12: 60% of spaces (Bruner) | R12: Pool Fence | S12: =103*2+24*2 -> 254
A13: Site Evaluation Report (GCW) | D13: Accessible Parking | F13: =ROUNDUP(E8*0.02,0) -> 7 | N13: Seal Coat | O13: =44500+31000+29000+33400+36700+5600+4900+100400-82500 -> 203000 | P13: Asphalt SF | R13: Dog Park Fence | S13: =67*2+52*2+9+8 -> 255
A14: Soils Report (Universal) | D14: Private Garages | F14: 0 | N14: Building Perimeter | O14: =1545*110% -> 1699.5 | P14: Bldg 1 LF | R14: Corridor | S14: =(2440+1725)*3 -> 12495 | T14: Building 1 SF
A15: Alta Survey (Wallace) | D15: Total Parking Provided | F15: =SUM(F10:F12) -> 516 | N15: Building Perimeter | O15: =1650*110% -> 1815 | P15: Bldg 2 LF | R15: Corridor | S15: =(2450+1950)*3 -> 13200 | T15: Building 2 SF
A16: Plans | D16: Parking Ratio | F16: =SUM(F10:F12)/E8 -> 1.4870317 | N16: Building Perimeter | O16: 0 | P16: Bldg 3 LF | R16: Corridor | S16: 0 | T16: Building 3 SF
R17: Pool Deck | S17: =9800-815-185-125*8 -> 7800 | T17: SF
A19: Description | B19: Cost Code | C19: Cost Category | D19: Subjob | E19: Source | F19: Unit Meas. | G19: Quantity | H19: Unit Cost | I19: Escalation % | J19: T. Unit Cost | K19: Sub Total | L19: Total | N19: Description / Details
A20: General Requirements | B20: 01 | L20: =K21 -> 2008563.6
A21: General Requirements | B21: 01 | C21: S | F21: Mo | G21: =B6 -> 24 | H21: 83690.15 | I21: 0 | J21: =H21*(1+I21) -> 83690.15 | K21: =J21*G21 -> 2008563.6
A22: Existing Conditions | B22: 02 | L22: =K23 -> 8000
A23: Potholing | B23: 02-3213 | C23: S | D23: ON-SITE | E23: Allowance | G23: 1 | H23: 8000 | I23: 0 | J23: =H23*(1+I23) -> 8000 | K23: =J23*G23 -> 8000
A24: Concrete | B24: 03 | L24: =SUM(K25:K34) -> 1975170
A25: Slabs | B25: 03-3101 | C25: S | D25: BUILDING | E25: Torrey Pines | F25: SF | G25: =J6/3 -> 103714 | H25: 11.99 | I25: 0 | J25: =H25*(1+I25) -> 11.99 | K25: =J25*G25 -> 1243530.9
A26: Deepened Footings | B26: 03-3101 | C26: S | D26: BUILDING | E26: N/A | J26: =H26*(1+I26) -> 0 | K26: =J26*G26 -> 0
A27: Concrete Slab Repairs | B27: 03-3101 | C27: RR | D27: BUILDING | E27: Allowance | F27: LS | G27: 1 | H27: =2500*3 -> 7500 | I27: 0 | J27: =H27*(1+I27) -> 7500 | K27: =J27*G27 -> 7500
A28: Pump House Concrete | B28: 03-3101 | C28: S | D28: PUMPHOUSE | E28: Torrey Pines | F28: SF | G28: 300 | H28: 11.99 | I28: 0 | J28: =H28*(1+I28) -> 11.99 | K28: =J28*G28 -> 3597
A29: Trash Enclosure Concrete | B29: 03-3102 | C29: S | D29: OTHER SITE | E29: Russell IV | F29: Count | G29: =O4 -> 10 | H29: 2698 | I29: 0 | J29: =H29*(1+I29) -> 2698 | K29: =J29*G29 -> 26980
A30: Pool Area Shower Concrete | B30: 03-3105 | C30: S | D30: POOL AREA | E30: Torrey Pines | F30: LS | G30: =O6 -> 2 | H30: 2500 | I30: 0 | J30: =H30*(1+I30) -> 2500 | K30: =J30*G30 -> 5000
A31: Cabana Concrete | B31: 03-3107 | C31: S | D31: POOL AREA | E31: N/A | J31: =H31*(1+I31) -> 0 | K31: =J31*G31 -> 0
A32: Pool Equipment Foundation | B32: 03-3108 | C32: S | D32: POOL EQUIP | E32: N/A | J32: =H32*(1+I32) -> 0 | K32: =J32*G32 -> 0
A33: Lightweight Concrete | B33: 03-3116 | C33: S | D33: BUILDING | E33: Torrey Pines | F33: SF | G33: =J6/3*2 -> 207428 | H33: 2.94 | I33: 0 | J33: =H33*(1+I33) -> 2.94 | K33: =J33*G33 -> 609838.32
A34: Deck Concrete | B34: 03-5001 | C34: S | D34: BUILDING | E34: Torrey Pines | F34: SF | G34: =SUM($S$6:$S$7) -> 3984 | H34: 19.76 | I34: 0 | J34: =H34*(1+I34) -> 19.76 | K34: =J34*G34 -> 78723.84
A35: Parking Garage | B35: 03-G | L35: =SUM(K36:K43) -> 0
A36: Parking Garage Structure | C36: S | E36: N/A | J36: =H36*(1+I36) -> 0 | K36: =J36*G36 -> 0
A37: Core Slab Precast Concrete | C37: S | E37: N/A | J37: =H37*(1+I37) -> 0 | K37: =J37*G37 -> 0
A38: Concrete Slab on Grade | C38: S | E38: N/A | J38: =H38*(1+I38) -> 0 | K38: =J38*G38 -> 0
A39: Concrete Topping Slab 4" / Level | C39: S | E39: N/A | J39: =H39*(1+I39) -> 0 | K39: =J39*G39 -> 0
A40: Electrical | C40: S | E40: N/A | J40: =H40*(1+I40) -> 0 | K40: =J40*G40 -> 0
A41: Dry Sprinklers | C41: S | E41: N/A | J41: =H41*(1+I41) -> 0 | K41: =J41*G41 -> 0
A42: Mechanical Ventilation | C42: S | E42: N/A | J42: =H42*(1+I42) -> 0 | K42: =J42*G42 -> 0
A43: Stairs and Railings | C43: S | E43: N/A | J43: =H43*(1+I43) -> 0 | K43: =J43*G43 -> 0
A44: Masonry | B44: 04 | L44: =SUM(K45:K49) -> 171000
A45: Elevator Shaft | B45: 04-2201 | C45: S | D45: BUILDING | E45: Torrey Pines | F45: Count | G45: =$O$3 -> 4 | H45: 28500 | I45: 0 | J45: =H45*(1+I45) -> 28500 | K45: =J45*G45 -> 114000
A46: Trash Enclosure | B46: 04-2202 | C46: S | D46: OTHER SITE | E46: Torrey Pines | F46: Count | G46: =$O$4 -> 10 | H46: 5700 | I46: 0 | J46: =H46*(1+I46) -> 5700 | K46: =J46*G46 -> 57000
A47: Masonry Veneer | B47: 04-4301 | C47: S | D47: ON-SITE | E47: N/A | J47: =H47*(1+I47) -> 0 | K47: =J47*G47 -> 0
A48: Masonry Veneer Pool Area | B48: 04-4305 | C48: S | D48: POOL AREA | E48: N/A | J48: =H48*(1+I48) -> 0 | K48: =J48*G48 -> 0
A49: Pool Eq. Shower Stone | B49: 04-4306 | C49: S | D49: POOL EQUIP | E49: N/A | J49: =H49*(1+I49) -> 0 | K49: =J49*G49 -> 0
A50: Metals | B50: 05 | L50: =SUM(K51:K58) -> 392720.43
A51: Structural Steel | B51: 05-1201 | C51: S | D51: BUILDING | E51: N/A | H51: 186154 | I51: 0 | J51: =H51*(1+I51) -> 186154 | K51: =J51*G51 -> 0 | N51: Per Derek No Structural Steel in Common Areas
A52: Elevator Shaft Iron | B52: 05-1202 | C52: S | D52: BUILDING | E52: Russell IV | F52: Count | G52: =$O$3 -> 4 | H52: 5990 | I52: 0 | J52: =H52*(1+I52) -> 5990 | K52: =J52*G52 -> 23960
A53: Stair Handrails | B53: 05-5201 | C53: S | D53: BUILDING | E53: Russell IV | F53: LS | G53: =$O$5 -> 11 | H53: 11750 | I53: 0 | J53: =H53*(1+I53) -> 11750 | K53: =J53*G53 -> 129250
A54: Garage Stair Railings | B54: 05-5201 | C54: S | D54: BUILDING | E54: N/A | H54: 0 | I54: 0 | J54: =H54*(1+I54) -> 0 | K54: =J54*G54 -> 0
A55: Cabana Iron | B55: 05-7004 | C55: S | D55: POOL AREA | E55: N/A | H55: 0 | I55: 0 | J55: =H55*(1+I55) -> 0 | K55: =J55*G55 -> 0
A56: Pool Equipment Gate | B56: 05-7005 | C56: S | D56: POOL EQUIP | E56: Russell IV | F56: Count | G56: =$O$6 -> 2 | H56: 1950 | I56: 0 | J56: =H56*(1+I56) -> 1950 | K56: =J56*G56 -> 3900
A57: Iron Railings | B57: 05-7300 | C57: S | D57: BUILDING | E57: Russell IV | F57: Linear Foot | G57: =$O$8 -> 2535.6267 | H57: 92.92 | I57: 0 | J57: =H57*(1+I57) -> 92.92 | K57: =J57*G57 -> 235610.43
A58: Cable Railings | B58: 05-7316 | C58: S | D58: COMMON AREA | E58: N/A | H58: 0 | I58: 0 | J58: =H58*(1+I58) -> 0 | K58: =J58*G58 -> 0
A59: Wood, Plastics, & Composites | B59: 06 | L59: =SUM(K60:K71) -> 7663075.4
A60: Dumpsters | B60: 06-0111 | C60: S | D60: DUMPSTERS | E60: Torrey Pines | F60: Unit | G60: =E8 -> 347 | H60: 79 | I60: 0 | J60: =H60*(1+I60) -> 79 | K60: =J60*G60 -> 27413
A61: Framing | B61: 06-1100 | C61: S | D61: BUILDING | E61: Torrey Pines | F61: SF | G61: =B8 -> 311142 | H61: 19.92 | I61: 0 | J61: =H61*(1+I61) -> 19.92 | K61: =J61*G61 -> 6197948.6
A62: Framing - Crane | B62: 06-1100 | C62: S | D62: BUILDING | E62: N/A | I62: 0 | J62: =H62*(1+I62) -> 0 | K62: =J62*G62 -> 0
A63: Cabana Framing | B63: 06-1109 | C63: S | D63: COMMON AREA | E63: N/A | I63: 0 | J63: =H63*(1+I63) -> 0 | K63: =J63*G63 -> 0
A64: BBQ Framing | B64: 06-1110 | C64: S | D64: COMMON AREA | E64: Pebble | F64: LS | G64: 2 | H64: 2810 | I64: 0 | J64: =H64*(1+I64) -> 2810 | K64: =J64*G64 -> 5620
A65: Fireplace Framing | B65: 06-1111 | C65: S | D65: COMMON AREA | E65: N/A | I65: 0 | J65: =H65*(1+I65) -> 0 | K65: =J65*G65 -> 0
A66: Trellis | B66: 06-1114 | C66: S | D66: BUILDING | E66: N/A | I66: 0 | J66: =H66*(1+I66) -> 0 | K66: =J66*G66 -> 0
A67: Pool Equipment Framing | B67: 06-1114 | C67: S | D67: POOL EQUIP | E67: N/A | I67: 0 | J67: =H67*(1+I67) -> 0 | K67: =J67*G67 -> 0
A68: Finish Carpentry - Units | B68: 06-2001 | C68: S | D68: BUILDING | E68: Pebble | F68: Unit | G68: =E8 -> 347 | H68: 3081 | I68: 0 | J68: =H68*(1+I68) -> 3081 | K68: =J68*G68 -> 1069107
A69: Finish Carpentry - Common | B69: 06-2001 | C69: S | D69: COMMON AREA | E69: Pebble | F69: SF | G69: =B8 -> 311142 | H69: 1.16 | I69: 0 | J69: =H69*(1+I69) -> 1.16 | K69: =J69*G69 -> 360924.72
A70: BBQ Trim | B70: 06-2006 | C70: S | D70: COMMON AREA | E70: Pebble | F70: LS | G70: 2 | H70: 1031 | I70: 0 | J70: =H70*(1+I70) -> 1031 | K70: =J70*G70 -> 2062
A71: Shutters | B71: 06-4919 | C71: S | D71: BUILDING | E71: N/A | I71: 0 | J71: =H71*(1+I71) -> 0 | K71: =J71*G71 -> 0
A72: Thermal & Moisture Protection | B72: 07 | L72: =SUM(K73:K83) -> 1573821.8
A73: Insulation | B73: 07-2101 | C73: S | D73: BUILDING | E73: Torrey Pines | F73: SF | G73: =B8 -> 311142 | H73: 2.54 | I73: 0 | J73: =H73*(1+I73) -> 2.54 | K73: =J73*G73 -> 790300.68
A74: Roofing | B74: 07-3001 | C74: S | D74: BUILDING | E74: Torrey Pines | F74: Square | G74: =O9 -> 1078.23 | H74: 603 | I74: 0 | J74: =H74*(1+I74) -> 603 | K74: =J74*G74 -> 650172.69
A75: Cabana Roofing | B75: 07-3002 | C75: S | D75: COMMON AREA | E75: N/A | I75: 0 | J75: =H75*(1+I75) -> 0 | K75: =J75*G75 -> 0
A76: Pump House Roofing | B76: 07-3002 | C76: S | D76: PUMPHOUSE | E76: Allowance | F76: LS | G76: 1 | H76: 6700 | I76: 0 | J76: =H76*(1+I76) -> 6700 | K76: =J76*G76 -> 6700
A77: Pool Equipment Roofing | B77: 07-3003 | C77: S | D77: POOL EQUIP | E77: N/A | I77: 0 | J77: =H77*(1+I77) -> 0 | K77: =J77*G77 -> 0
A78: Trash Enclosure Cover | B78: 07-6101 | C78: S | D78: OTHER SITE | E78: Torrey Pines | F78: Count | G78: =$O$4 -> 10 | H78: 7000 | I78: 0 | J78: =H78*(1+I78) -> 7000 | K78: =J78*G78 -> 70000
A79: Pigeon Proofing | B79: 07-7001 | C79: S | D79: BUILDING | E79: Torrey Pines | F79: SF | G79: =$B$8 -> 311142 | H79: 0.08 | I79: 0 | J79: =H79*(1+I79) -> 0.08 | K79: =J79*G79 -> 24891.36
A80: Gutters and Downspouts | B80: 07-7124 | C80: S | D80: BUILDING | E80: Torrey Pines | F80: SF | G80: =$B$8 -> 311142 | H80: 0.05 | I80: 0 | J80: =H80*(1+I80) -> 0.05 | K80: =J80*G80 -> 15557.1
A81: Roof Ladders | B81: 07-7210 | C81: S | D81: BUILDING | E81: Torrey Pines | F81: Count | G81: =2*$B$11 -> 4 | H81: 1550 | I81: 0 | J81: =H81*(1+I81) -> 1550 | K81: =J81*G81 -> 6200 | N81: 2 Per building
A82: Roof Access Doors | B82: 07-7233 | C82: S | D82: BUILDING | E82: Torrey Pines | F82: Count | G82: =2*$B$11 -> 4 | H82: 2500 | I82: 0 | J82: =H82*(1+I82) -> 2500 | K82: =J82*G82 -> 10000 | N82: 2 Per building
A83: Roof Winch | B83: 07-7250 | C83: S | D83: BUILDING | E83: N/A | I83: 0 | J83: =H83*(1+I83) -> 0 | K83: =J83*G83 -> 0
A84: Openings | B84: 08 | L84: =SUM(K85:K99) -> 548400.7
A85: Dumpsters | B85: 08-0151 | C85: S | D85: DUMPSTERS | F85: Per Unit | G85: =$E$8 -> 347 | H85: 79 | I85: 0 | J85: =H85*(1+I85) -> 79 | K85: =J85*G85 -> 27413
A86: Entry Doors | B86: 08-1001 | C86: S | D86: COMMON AREA | E86: N/A | I86: 0 | J86: =H86*(1+I86) -> 0 | K86: =J86*G86 -> 0
A87: Common Doors | B87: 08-1002 | C87: S | D87: COMMON AREA | E87: Included | I87: 0 | J87: =H87*(1+I87) -> 0 | K87: =J87*G87 -> 0
A88: Pocket Doors - 3 Panel | B88: 08-1002 | C88: S | D88: BUILDING | E88: N/A | I88: 0 | J88: =H88*(1+I88) -> 0 | K88: =J88*G88 -> 0
A89: Garage Doors | B89: 08-3619 | C89: S | D89: BUILDING | E89: N/A | I89: 0 | J89: =H89*(1+I89) -> 0 | K89: =J89*G89 -> 0
A90: Windows and Sliding Glass Doors | B90: 08-5301 | C90: S | D90: BUILDING | E90: Decatur | F90: Per Unit | G90: =$E$8 -> 347 | H90: =1131*110% -> 1244.1 | I90: 0 | J90: =H90*(1+I90) -> 1244.1 | K90: =J90*G90 -> 431702.7 | N90: Per Solar Industries include +10% Due to New Energy Star U Factor Requirement Less than or equall to 0.28
A91: Windows Repair and Replacement | B91: 08-5301 | C91: RR | D91: BUILDING | E91: Allowance | F91: Per Unit | G91: =$E$8 -> 347 | H91: 75 | I91: 0 | J91: =H91*(1+I91) -> 75 | K91: =J91*G91 -> 26025
A92: Pool Equipment Windows | B92: 08-5303 | C92: S | D92: POOL EQUIP | E92: N/A | I92: 0 | J92: =H92*(1+I92) -> 0 | K92: =J92*G92 -> 0
A93: Pool Glass Walls | B93: 08-8001 | C93: S | D93: POOL AREA | E93: N/A | I93: 0 | J93: =H93*(1+I93) -> 0 | K93: =J93*G93 -> 0
A94: Fixed Glass | B94: 08-8002 | C94: S | D94: BUILDING | E94: N/A | I94: 0 | J94: =H94*(1+I94) -> 0 | K94: =J94*G94 -> 0
A95: Mirrors - LED | B95: 08-8301 | C95: S | D95: BUILDING | E95: N/A | I95: 0 | J95: =H95*(1+I95) -> 0 | K95: =J95*G95 -> 0
A96: Mirrors - LED Install | B96: 08-8302 | C96: S | D96: BUILDING | E96: N/A | I96: 0 | J96: =H96*(1+I96) -> 0 | K96: =J96*G96 -> 0
A97: Mirrors - Framed | B97: 08-8301 | C97: S | D97: BUILDING | E97: N/A | I97: 0 | J97: =H97*(1+I97) -> 0 | K97: =J97*G97 -> 0
A98: Mirrors - Polished Edges (Units) | B98: 08-8301 | C98: S | D98: BUILDING | E98: Russell IV | F98: Unit | G98: =$E$8 -> 347 | H98: 180 | I98: 0 | J98: =H98*(1+I98) -> 180 | K98: =J98*G98 -> 62460
A99: Mirrors - Polished Edges (Restrooms) | B99: 08-8301 | C99: S | D99: BUILDING | E99: Russell IV | F99: Count | G99: =$B$11*2 -> 4 | H99: 200 | I99: 0 | J99: =H99*(1+I99) -> 200 | K99: =J99*G99 -> 800
A100: Finishes | B100: 09 | L100: =SUM(K101:K136) -> 5170494.2
A101: Cost Prep Labor | B101: 09-0101 | C101: S | D101: BUILDING | E101: Wigwam | F101: SF | G101: =$B$8 -> 311142 | H101: 0.05 | I101: 0 | J101: =H101*(1+I101) -> 0.05 | K101: =J101*G101 -> 15557.1
...

Sheet _REFERENCE888777888
A1: WorkSheet Name | B1: Report Code | C1: Company Id | D1: Job Id | E1: Start Date | F1: End Date | G1: Payroll Subledger | H1: Pay Period Id

Sheet LEVEL 3
A1: Project Details | D1: Unit Breakdown | H1: Unit Matrix | N1: List of Take offs | Q1: List of Take offs | T1: List of Take offs
A2: Project | B2: Bruner Senior | D2: Unit Type | E2: Number | F2: % | H2: Unit Type | I2: Number | J2: % | K2: SF | N2: Slab SF | O2: =24424+23698 -> 48122 | P2: GSF | Q2: Counter tops | R2: 11437.45 | S2: SF | T2: Fitness Center | U2: 1316 | V2: SF
A3: Budget Level | B3: Level 3 | D3: Studios | E3: 0 | F3: =E3/$E$8 -> 0 | H3: A1A | I3: 5 | J3: =I3/$E$8 -> 0.025773196 | K3: 663 | N3: Elevators | O3: 2 | P3: Count | Q3: Blinds | R3: 513 | AG3: Railing Estimate | AK3: Building 3 | AL3: =21*7 -> 147 | AN3: Stucco | AR3: Building 3 | AS3: =15000+6560+6500+15400+4570+4635+4540+4250 -> 61455
A4: Product | B4: Senior | D4: 1 Br - 1 Ba | E4: 126 | F4: =E4/$E$8 -> 0.64948454 | H4: B1A | I4: 73 | J4: =I4/$E$8 -> 0.37628866 | K4: 663 | N4: Elevators Stops | O4: 8 | P4: Count | Q4: Landscaping | R4: 39274 | S4: SF | AG4: Building 1 | AL4: =14*7 -> 98 | AN4: Building 1
A5: Start Date | B5: 45809 | D5: 2 Br - 1 Ba | E5: 68 | F5: =E5/$E$8 -> 0.35051546 | H5: B1B | I5: 48 | J5: =I5/$E$8 -> 0.24742268 | K5: 675 | N5: Trash Encl. | O5: 4 | P5: Site Plan | AG5: Northwest | AH5: =21*4+8*8+7*6 -> 190 | AL5: =8*22 -> 176 | AN5: Northwest | AO5: 19256
A6: Timeline | B6: 20 | D6: 2 Br - 2 Ba | E6: 0 | F6: =E6/$E$8 -> 0 | H6: A2A | I6: 5 | J6: =I6/$E$8 -> 0.025773196 | K6: 888 | N6: Stairs | O6: 7 | P6: Count | Q6: 1x1 Decks | R6: 0 | S6: SF | AG6: Southwest | AH6: =14*4+21*2+8*6 -> 146 | AL6: =7*10 -> 70 | AN6: Southwest | AO6: 8980
A7: Floors | B7: 4 | D7: 3 Br - 2 Ba | E7: 0 | F7: =E7/$E$8 -> 0 | H7: B2A | I7: 46 | J7: =I7/$E$8 -> 0.2371134 | K7: 888 | N7: Pool | O7: 1 | Q7: 2x1 Decks | S7: SF | AG7: Northeast | AH7: =21*2+14*2+8*6 -> 118 | AL7: =SUM(AL3:AL6) -> 491 | AN7: Northeast | AO7: 8850
A8: Bldg. SF | B8: 196289 | D8: Totals | E8: =SUM(E3:E7) -> 194 | F8: =E8/$E$8 -> 1 | H8: B2B | I8: 17 | J8: =I8/$E$8 -> 0.087628866 | K8: 955 | N8: Gym | O8: 1 | Q8: Lightweight | R8: 147250 | S8: SF | AG8: Southeast | AH8: =21*2+14*8+8*12+7*8 -> 306 | AN8: Southeast | AO8: 19965
A9: Acres | B9: 4.9 | D9: Parking | H9: Totals | I9: =SUM(I3:I8) -> 194 | J9: =SUM(J3:J8) -> 1 | K9: =SUMPRODUCT(I3:I8,K3:K8) -> 145637 | N9: Iron Rail | O9: 1593 | P9: LF | Q9: Pavers | R9: 0 | S9: SF | AG9: More | AH9: =21*4+8*6 -> 132 | AI9: =SUM(AH5:AH9) -> 892 | AN9: More | AO9: =5870+6250+6290+5915 -> 24325 | AP9: =SUM(AO5:AO9) -> 81376
A10: Site SF | B10: =B9*43560 -> 213444 | D10: Cover Parking | F10: 127 | N10: Roofing | O10: =(12209+13565+13960+10629)/100 -> 503.63 | P10: Square | Q10: Pool Deck | R10: 0 | S10: SF
A11: Buildings | B11: 1 | D11: Cover Accesible Parking | F11: 3 | N11: Stucco | O11: 11824 | P11: Square Yard | Q11: Pool Fence | R11: 0 | S11: LF | AG11: Building 2 & 5 | AK11: Building 4 | AL11: =14*8 -> 112 | AN11: Building 2 & 5 | AR11: Building 4 | AS11: =5782+5760+8825+9150 -> 29517
A12: Reports Available | D12: Open Parking | F12: 45 | N12: Livable Area | O12: 0 | P12: SF | Q12: Dog Park Fence | R12: 0 | S12: LF | AG12: Northwest | AL12: =20*8 -> 160 | AN12: Northwest
A13: Site Evaluation Report (GCW) | B13: N | D13: Accessible Parking | F13: 11 | N13: Carports | O13: =F10+F11 -> 130 | P13: Count | Q13: Common Bldg. 1 | R13: 0 | S13: SF | AG13: Southwest | AL13: =8*18 -> 144 | AN13: Southwest
A14: Soils Report (Nova or Universal) | B14: Y - 4/21/20 | D14: Waiver | F14: 8 | H14: TOTAL COST | J14: =L335 -> 33486712 | N14: Stairs Landings | O14: 60 | P14: Landings | Q14: Asphalt | R14: 75608 | AG14: Northeast | AL14: =7*12 -> 84 | AN14: Northeast
A15: Alta Survey (Wallace) | B15: Y - 1/21/20 | D15: Total Parking Provided | F15: =SUM(F10:F14) -> 194 | H15: PER UNIT | J15: =J14/E8 -> 172611.92 | N15: Pump House | O15: 1 | P15: EA | Q15: Pavers | R15: 350 | AG15: Southeast | AH15: =21*2+14*2+8*6+7*6 -> 160 | AI15: =AH15*2 -> 320 | AL15: =SUM(AL11:AL14) -> 500 | AN15: Southeast | AO15: =5035+5775+1960+1960 -> 14730 | AP15: =AO15*2 -> 29460
A16: Plans | B16: N | D16: Parking Ratio | F16: =SUM(F10:F13)/E8 -> 0.95876289 | H16: PER GSF | J16: =J14/B8 -> 170.59902 | N16: Lock Boxes | O16: 0 | P16: EA | Q16: Pavers Pool | R16: 4500
N17: Awning Small | O17: 0 | P17: EA | AG17: B1B Railings | AH17: =12.5*62 -> 775 | AN17: B1B Railings | AO17: =12.5*62 -> 775
N18: Awning Large | O18: 0 | P18: EA
A19: Description | B19: Cost Code | C19: Cost Category | D19: Sub job | E19: Source | F19: UMO | G19: QTY | H19: U.P. | I19: Escal % | J19: Total U.P. | K19: Sub Total | L19: Total | M19: Description / Details
A20: General Requirements | B20: 01 | L20: =K21 -> 1674318
A21: General Requirement | B21: 01 | C21: S | F21: Mo | G21: =$B$6 -> 20 | H21: =1674318/20 -> 83715.9 | I21: 0 | J21: =H21*(1+I21) -> 83715.9 | K21: =J21*G21 -> 1674318 | AG21: Common Areas Flooring | AJ21: Level | AK21: SF
A22: Existing Conditions | B22: 02 | L22: =K23 -> 3500 | AG22: Bathrooms | AJ22: 1 | AK22: 273.4
A23: Potholing | B23: 02-3213 | C23: S | D23: ON-SITE | E23: Allowance | G23: 1 | H23: 3500 | I23: 0 | J23: =H23*(1+I23) -> 3500 | K23: =J23*G23 -> 3500 | AG23: Fitness Center | AJ23: 1 | AK23: 1281.48
A24: Concrete | B24: 03 | L24: =SUM(K25:K34) -> 1089279.8 | AG24: Food Pantry | AJ24: 1 | AK24: 655.42
A25: Slabs | B25: 03-3101 | C25: S | D25: BUILDING | E25: Torrey Pines | F25: SF | G25: =O2 -> 48122 | H25: 11.99 | I25: 0 | J25: =H25*(1+I25) -> 11.99 | K25: =J25*G25 -> 576982.78 | M25: NRC proposal is at $534k or $11.01/sf. | AG25: Great Room | AJ25: 1 | AK25: 1520.89
A26: Deepened Footings | B26: 03-3101 | C26: S | D26: BUILDING | E26: N/A | J26: =H26*(1+I26) -> 0 | K26: =J26*G26 -> 0 | AG26: Hallway | AJ26: 1 | AK26: 5652.7
A27: Concrete Slab Repairs | B27: 03-3101 | C27: RR | D27: BUILDING | E27: Allowance | F27: LS | G27: 1 | H27: 2500 | I27: 0 | J27: =H27*(1+I27) -> 2500 | K27: =J27*G27 -> 2500 | AG27: Main Entry Hallway | AJ27: 1 | AK27: 937.64
A28: Pump House Concrete | B28: 03-3101 | C28: S | D28: PUMPHOUSE | E28: Torrey Pines | F28: SF | G28: 300 | H28: 11.99 | J28: =H28*(1+I28) -> 11.99 | K28: =J28*G28 -> 3597 | AG28: Offices and Leasing | AJ28: 1 | AK28: 555.22
A29: Trash Enclosure Concrete | B29: 03-3102 | C29: S | D29: OTHER SITE | E29: Allowance | F29: SF | G29: =230*4 -> 920 | H29: 11.99 | I29: 0 | J29: =H29*(1+I29) -> 11.99 | K29: =J29*G29 -> 11030.8 | AG29: Hallway | AJ29: 2 | AK29: 5596.41
A30: Pool Area Shower Concrete | B30: 03-3105 | C30: S | D30: POOL AREA | E30: Allowance | F30: LS | G30: =$O$7 -> 1 | H30: 2500 | I30: 0 | J30: =H30*(1+I30) -> 2500 | K30: =J30*G30 -> 2500 | AG30: Wellness/Media/Lounge | AJ30: 2 | AK30: 794.24
A31: Cabana Concrete | B31: 03-3107 | C31: S | D31: POOL AREA | E31: N/A | J31: =H31*(1+I31) -> 0 | K31: =J31*G31 -> 0 | AG31: Hallway | AJ31: 3 | AK31: 5570.59
A32: Pool Equipment Foundation | B32: 03-3108 | C32: S | D32: POOL EQUIP | E32: N/A | J32: =H32*(1+I32) -> 0 | K32: =J32*G32 -> 0 | AG32: Computer/Library/Salon | AJ32: 3 | AK32: 780.29
A33: Lightweight Concrete | B33: 03-3116 | C33: S | D33: BUILDING | E33: Torrey Pines | F33: SF | G33: =R8 -> 147250 | H33: 2.94 | I33: 0 | J33: =H33*(1+I33) -> 2.94 | K33: =J33*G33 -> 432915 | AG33: Hallway | AJ33: 4 | AK33: 5680.05
A34: Deck Concrete | B34: 03-5001 | C34: S | D34: BUILDING | E34: Torrey Pines | F34: SF | G34: 3024 | H34: 19.76 | I34: 0 | J34: =H34*(1+I34) -> 19.76 | K34: =J34*G34 -> 59754.24 | AG34: Laundry/Lounge | AJ34: 4 | AK34: 799.74
A35: Parking Garage | B35: 03-G | L35: =SUM(K36:K43) -> 0 | AG35: Stairwell Landing | AJ35: ALL | AK35: 4823.54
A36: Parking Garage Structure | C36: S | E36: N/A | J36: =H36*(1+I36) -> 0 | K36: =J36*G36 -> 0
A37: Core Slab Precast Concrete | C37: S | E37: N/A | J37: =H37*(1+I37) -> 0 | K37: =J37*G37 -> 0
A38: Concrete Slab on Grade | C38: S | E38: N/A | J38: =H38*(1+I38) -> 0 | K38: =J38*G38 -> 0
A39: Concrete Topping Slab 4" / Level | C39: S | E39: N/A | J39: =H39*(1+I39) -> 0 | K39: =J39*G39 -> 0
A40: Electrical | C40: S | E40: N/A | J40: =H40*(1+I40) -> 0 | K40: =J40*G40 -> 0
A41: Dry Sprinklers | C41: S | E41: N/A | J41: =H41*(1+I41) -> 0 | K41: =J41*G41 -> 0
A42: Mechanical Ventilation | C42: S | E42: N/A | J42: =H42*(1+I42) -> 0 | K42: =J42*G42 -> 0
A43: Stairs and Railings | C43: S | E43: N/A | J43: =H43*(1+I43) -> 0 | K43: =J43*G43 -> 0
A44: Masonry | B44: 04 | L44: =SUM(K45:K49) -> 112800
A45: Elevator Shaft | B45: 04-2201 | C45: S | D45: BUILDING | E45: Torrey Pines | F45: Stop | G45: =O4 -> 8 | H45: 9500 | I45: 0 | J45: =H45*(1+I45) -> 9500 | K45: =J45*G45 -> 76000
A46: Trash Enclosure | B46: 04-2202 | C46: S | D46: OTHER SITE | E46: Torrey Pines | F46: Count | G46: =$O$5 -> 4 | H46: 5700 | I46: 0 | J46: =H46*(1+I46) -> 5700 | K46: =J46*G46 -> 22800
A47: Masonry Veneer | B47: 04-4301 | C47: S | D47: ON-SITE | E47: N/A | H47: 0 | J47: =H47*(1+I47) -> 0 | K47: =J47*G47 -> 0
A48: Masonry Veneer Pool Area | B48: 04-4305 | C48: S | D48: POOL AREA | E48: Allowance | F48: LS | G48: =$O$7 -> 1 | H48: 5000 | I48: 0 | J48: =H48*(1+I48) -> 5000 | K48: =J48*G48 -> 5000
A49: Pool Eq. Shower Stone | B49: 04-4306 | C49: A | D49: POOL EQUIP | E49: Torrey Pines | F49: LS | G49: =$O$7 -> 1 | H49: 9000 | I49: 0 | J49: =H49*(1+I49) -> 9000 | K49: =J49*G49 -> 9000
A50: Metals | B50: 05 | L50: =SUM(K51:K58) -> 325412.13
A51: Structural Steel | B51: 05-1201 | C51: S | D51: BUILDING | E51: Torrey Pines | F51: LBS | G51: 31706.95 | H51: 3.5584037 | I51: 0 | J51: =H51*(1+I51) -> 3.5584037 | K51: =J51*G51 -> 112826.13
A52: Elevator Shaft Iron | B52: 05-1202 | C52: S | D52: BUILDING | E52: Torrey Pines | F52: Count | G52: =$O$3 -> 2 | H52: =1950+2090 -> 4040 | I52: 0 | J52: =H52*(1+I52) -> 4040 | K52: =J52*G52 -> 8080
A53: Stair Handrails | B53: 05-5201 | C53: S | D53: BUILDING | E53: Torrey Pines | F53: Flight | G53: =O6*4 -> 28 | H53: 2000 | I53: 0 | J53: =H53*(1+I53) -> 2000 | K53: =J53*G53 -> 56000 | M53: Updated
A54: Garage Stair Railings | B54: 05-5201 | C54: S | D54: BUILDING | E54: N/A | H54: 0 | I54: 0 | J54: =H54*(1+I54) -> 0 | K54: =J54*G54 -> 0
A55: Cabana Iron | B55: 05-7004 | C55: S | D55: POOL AREA | E55: N/A | H55: 0 | I55: 0 | J55: =H55*(1+I55) -> 0 | K55: =J55*G55 -> 0
A56: Pool Equipment Gate | B56: 05-7005 | C56: S | D56: POOL EQUIP | E56: Torrey Pines | F56: Count | G56: 1 | H56: 1950 | I56: 0 | J56: =H56*(1+I56) -> 1950 | K56: =J56*G56 -> 1950
A57: Iron Railings | B57: 05-7300 | C57: S | D57: BUILDING | E57: Torrey Pines | F57: LF | G57: =$O$9 -> 1593 | H57: 92 | I57: 0 | J57: =H57*(1+I57) -> 92 | K57: =J57*G57 -> 146556 | M57: Missed 105 Juliet/Faux balconies in takeoff ($100K)
A58: Cable Railings | B58: 05-7316 | C58: S | D58: COMMON AREA | E58: N/A | H58: 0 | I58: 0 | J58: =H58*(1+I58) -> 0 | K58: =J58*G58 -> 0
A59: Wood, Plastics, & Composites | B59: 06 | L59: =SUM(K60:K72) -> 4804000.7
A60: Framing | B60: 06-1100 | C60: S | D60: BUILDING | E60: Moving Ave | F60: SF | G60: =B8 -> 196289 | H60: =20.5-15000/G60 -> 20.423582 | I60: 0 | J60: =H60*(1+I60) -> 20.423582 | K60: =J60*G60 -> 4008924.5 | M60: National Builders proposal $4.1M, Gilmore at $3.67M
A61: Framing - Pump House | B61: 06-1100 | C61: S | D61: PUMPHOUSE | E61: Allowance | F61: LS | G61: 1 | H61: 15000 | I61: 0 | J61: =H61*(1+I61) -> 15000 | K61: =J61*G61 -> 15000 | M61: New line item added for pump house framing.
A62: Framing - Crane | B62: 06-1100 | C62: S | D62: BUILDING | E62: N/A | I62: 0 | J62: =H62*(1+I62) -> 0 | K62: =J62*G62 -> 0
A63: Cabana Framing | B63: 06-1109 | C63: S | D63: COMMON AREA | E63: N/A | I63: 0 | J63: =H63*(1+I63) -> 0 | K63: =J63*G63 -> 0
A64: BBQ Framing | B64: 06-1110 | C64: S | D64: COMMON AREA | E64: Allowance | F64: LS | G64: 1 | H64: 2500 | I64: 0 | J64: =H64*(1+I64) -> 2500 | K64: =J64*G64 -> 2500
A65: Fireplace Framing | B65: 06-1111 | C65: S | D65: COMMON AREA | E65: N/A | I65: 0 | J65: =H65*(1+I65) -> 0 | K65: =J65*G65 -> 0
A66: Trellis | B66: 06-1114 | C66: S | D66: BUILDING | E66: N/A | I66: 0 | J66: =H66*(1+I66) -> 0 | K66: =J66*G66 -> 0
A67: Pool Equipment Framing | B67: 06-1114 | C67: S | D67: POOL EQUIP | E67: N/A | I67: 0 | J67: =H67*(1+I67) -> 0 | K67: =J67*G67 -> 0
A68: Finish Carpentry - Units | B68: 06-2001 | C68: S | D68: BUILDING | E68: Torrey Pines | F68: Unit | G68: =$E$8 -> 194 | H68: =3192.5-4500/194 -> 3169.3041 | I68: 0 | J68: =H68*(1+I68) -> 3169.3041 | K68: =J68*G68 -> 614845
A69: Finish Carpentry - Common | B69: 06-2001 | C69: S | D69: COMMON AREA | E69: Torrey Pines | F69: SF | G69: =B8 -> 196289 | H69: 0.8 | I69: 0 | J69: =H69*(1+I69) -> 0.8 | K69: =J69*G69 -> 157031.2
A70: Finish Carpentry - Pump House | B70: 06-2001 | C70: S | D70: PUMPHOUSE | E70: Allowance | F70: LS | G70: 1 | H70: 4500 | I70: 0 | J70: =H70*(1+I70) -> 4500 | K70: =J70*G70 -> 4500 | M70: New Line item for pump house
A71: BBQ Trim | B71: 06-2006 | C71: S | D71: COMMON AREA | E71: Allowance | F71: LS | G71: 1 | H71: 1200 | I71: 0 | J71: =H71*(1+I71) -> 1200 | K71: =J71*G71 -> 1200
A72: Shutters | B72: 06-4919 | C72: S | D72: BUILDING | E72: N/A | I72: 0 | J72: =H72*(1+I72) -> 0 | K72: =J72*G72 -> 0
A73: Thermal & Moisture Protection | B73: 07 | L73: =SUM(K74:K85) -> 905486.76
A74: Insulation | B74: 07-2101 | C74: S | D74: BUILDING | E74: Torrey Pines | F74: SF | G74: =B8 -> 196289 | H74: =2.7-2500/G74 -> 2.6872637 | I74: 0 | J74: =H74*(1+I74) -> 2.6872637 | K74: =J74*G74 -> 527480.3 | M74: It includes the material increased since for 2nd half of 2024.
A75: Insulation - Pump House | B75: 07-2101 | C75: S | D75: PUMPHOUSE | E75: Allowance | F75: LS | G75: 1 | H75: 2500 | I75: 0 | J75: =H75*(1+I75) -> 2500 | K75: =J75*G75 -> 2500 | M75: New Line item for pump house
A76: Roofing | B76: 07-3001 | C76: S | D76: BUILDING | E76: Torrey Pines | F76: Squares | G76: =$O$10 -> 503.63 | H76: 603 | I76: 0 | J76: =H76*(1+I76) -> 603 | K76: =J76*G76 -> 303688.89
A77: Cabana Roofing | B77: 07-3002 | C77: S | D77: COMMON AREA | E77: N/A | I77: 0 | J77: =H77*(1+I77) -> 0 | K77: =J77*G77 -> 0
A78: Pump House Roofing | B78: 07-3002 | C78: S | D78: PUMPHOUSE | E78: Allowance | F78: LS | G78: 1 | H78: 7500 | I78: 0 | J78: =H78*(1+I78) -> 7500 | K78: =J78*G78 -> 7500
A79: Pool Equipment Roofing | B79: 07-3003 | C79: S | D79: POOL EQUIP | E79: Allowance | F79: LS | G79: =O7 -> 1 | H79: 7500 | I79: 0 | J79: =H79*(1+I79) -> 7500 | K79: =J79*G79 -> 7500
A80: Trash Enclosure Cover | B80: 07-6101 | C80: S | D80: OTHER SITE | E80: Decatur | F80: Count | G80: =$O$5 -> 4 | H80: 5800 | I80: 0 | J80: =H80*(1+I80) -> 5800 | K80: =J80*G80 -> 23200
A81: Pigeon Proofing | B81: 07-7001 | C81: S | D81: BUILDING | E81: Torrey Pines | F81: SF | G81: =$B$8 -> 196289 | H81: 0.08 | I81: 0 | J81: =H81*(1+I81) -> 0.08 | K81: =J81*G81 -> 15703.12
A82: Gutters and Downspouts | B82: 07-7124 | C82: S | D82: BUILDING | E82: Torrey Pines | F82: SF | G82: =$B$8 -> 196289 | H82: 0.05 | I82: 0 | J82: =H82*(1+I82) -> 0.05 | K82: =J82*G82 -> 9814.45
A83: Roof Ladders | B83: 07-7210 | C83: S | D83: BUILDING | E83: Torrey Pines | F83: Count | G83: =2*$B$11 -> 2 | H83: 1550 | I83: 0 | J83: =H83*(1+I83) -> 1550 | K83: =J83*G83 -> 3100
A84: Roof Access Doors | B84: 07-7233 | C84: S | D84: BUILDING | E84: Torrey Pines | F84: Count | G84: =2*$B$11 -> 2 | H84: 2500 | I84: 0 | J84: =H84*(1+I84) -> 2500 | K84: =J84*G84 -> 5000
A85: Roof Winch | B85: 07-7250 | C85: S | D85: BUILDING | E85: N/A | I85: 0 | J85: =H85*(1+I85) -> 0 | K85: =J85*G85 -> 0
A86: Openings | B86: 08 | L86: =SUM(K87:K100) -> 279109.58
A87: Entry Doors | B87: 08-1001 | C87: S | D87: COMMON AREA | E87: Allowance | F87: Count | G87: 1 | H87: 8000 | I87: 0 | J87: =H87*(1+I87) -> 8000 | K87: =J87*G87 -> 8000
A88: Common Doors | B88: 08-1002 | C88: S | D88: COMMON AREA | E88: Included | I88: 0 | J88: =H88*(1+I88) -> 0 | K88: =J88*G88 -> 0
A89: Pocket Doors - 3 Panel | B89: 08-1002 | C89: S | D89: BUILDING | E89: N/A | I89: 0 | J89: =H89*(1+I89) -> 0 | K89: =J89*G89 -> 0
A90: Garage Doors | B90: 08-3619 | C90: S | D90: BUILDING | E90: N/A | I90: 0 | J90: =H90*(1+I90) -> 0 | K90: =J90*G90 -> 0
A91: Windows and Sliding Glass Doors | B91: 08-5301 | C91: S | D91: BUILDING | E91: Torrey Pines | F91: Per Unit | G91: =$E$8 -> 194 | H91: 1157.8947 | I91: 0 | J91: =H91*(1+I91) -> 1157.8947 | K91: =J91*G91 -> 224631.58
A92: Windows Repair and Replacement | B92: 08-5301 | C92: RR | D92: BUILDING | E92: Allowance | F92: Per Unit | G92: =$E$8 -> 194 | H92: 75 | I92: 0 | J92: =H92*(1+I92) -> 75 | K92: =J92*G92 -> 14550
A93: Pool Equipment Windows | B93: 08-5303 | C93: S | D93: POOL EQUIP | E93: N/A | I93: 0 | J93: =H93*(1+I93) -> 0 | K93: =J93*G93 -> 0
A94: Pool Glass Walls | B94: 08-8001 | C94: S | D94: POOL AREA | E94: N/A | I94: 0 | J94: =H94*(1+I94) -> 0 | K94: =J94*G94 -> 0
A95: Fixed Glass | B95: 08-8002 | C95: S | D95: BUILDING | E95: N/A | I95: 0 | J95: =H95*(1+I95) -> 0 | K95: =J95*G95 -> 0
A96: Mirrors - LED | B96: 08-8301 | C96: S | D96: BUILDING | E96: N/A | I96: 0 | J96: =H96*(1+I96) -> 0 | K96: =J96*G96 -> 0
A97: Mirrors - LED Install | B97: 08-8302 | C97: S | D97: BUILDING | E97: N/A | I97: 0 | J97: =H97*(1+I97) -> 0 | K97: =J97*G97 -> 0
A98: Mirrors - Framed | B98: 08-8301 | C98: S | D98: BUILDING | E98: N/A | I98: 0 | J98: =H98*(1+I98) -> 0 | K98: =J98*G98 -> 0
A99: Mirrors - Polished Edges (Units) | B99: 08-8301 | C99: S | D99: BUILDING | E99: Pebble | F99: Unit | G99: =E8 -> 194 | H99: 162 | I99: 0 | J99: =H99*(1+I99) -> 162 | K99: =J99*G99 -> 31428
A100: Mirrors - Polished Edges (Restrooms) | B100: 08-8301 | C100: S | D100: BUILDING | E100: Allowance | F100: Count | G100: 2 | H100: 250 | I100: 0 | J100: =H100*(1+I100) -> 250 | K100: =J100*G100 -> 500
...

Sheet LEVEL 2 (Match)
A1: Project Details | D1: Unit Breakdown | H1: Unit Matrix | N1: List of Take offs | Q1: List of Take offs | T1: List of Take offs
A2: Project | B2: Bruner Senior | D2: Unit Type | E2: Number | F2: % | H2: Unit Type | I2: Number | J2: % | K2: SF | N2: Slab SF | O2: =24424+23698 -> 48122 | P2: GSF | Q2: Counter tops | R2: 11437.45 | S2: SF | T2: Fitness Center | U2: 1316 | V2: SF
A3: Budget Level | B3: Level 2 | D3: Studios | E3: 0 | F3: =E3/$E$8 -> 0 | H3: A1A | I3: 5 | J3: =I3/$E$8 -> 0.025773196 | K3: 663 | N3: Elevators | O3: 2 | P3: Count | Q3: Blinds | R3: 513 | AG3: Railing Estimate | AK3: Building 3 | AL3: =21*7 -> 147 | AN3: Stucco | AR3: Building 3 | AS3: =15000+6560+6500+15400+4570+4635+4540+4250 -> 61455
A4: Product | B4: Senior | D4: 1 Br - 1 Ba | E4: 126 | F4: =E4/$E$8 -> 0.64948454 | H4: B1A | I4: 73 | J4: =I4/$E$8 -> 0.37628866 | K4: 663 | N4: Elevators Stops | O4: 8 | P4: Count | Q4: Landscaping | R4: 39274 | S4: SF | AG4: Building 1 | AL4: =14*7 -> 98 | AN4: Building 1
A5: Start Date | B5: 45809 | D5: 2 Br - 1 Ba | E5: 68 | F5: =E5/$E$8 -> 0.35051546 | H5: B1B | I5: 48 | J5: =I5/$E$8 -> 0.24742268 | K5: 675 | N5: Trash Encl. | O5: 4 | P5: Site Plan | AG5: Northwest | AH5: =21*4+8*8+7*6 -> 190 | AL5: =8*22 -> 176 | AN5: Northwest | AO5: 19256
A6: Timeline | B6: 20 | D6: 2 Br - 2 Ba | E6: 0 | F6: =E6/$E$8 -> 0 | H6: A2A | I6: 5 | J6: =I6/$E$8 -> 0.025773196 | K6: 888 | N6: Stairs | O6: 7 | P6: Count | Q6: 1x1 Decks | R6: 0 | S6: SF | AG6: Southwest | AH6: =14*4+21*2+8*6 -> 146 | AL6: =7*10 -> 70 | AN6: Southwest | AO6: 8980
A7: Floors | B7: 4 | D7: 3 Br - 2 Ba | E7: 0 | F7: =E7/$E$8 -> 0 | H7: B2A | I7: 46 | J7: =I7/$E$8 -> 0.2371134 | K7: 888 | N7: Pool | O7: 1 | Q7: 2x1 Decks | S7: SF | AG7: Northeast | AH7: =21*2+14*2+8*6 -> 118 | AL7: =SUM(AL3:AL6) -> 491 | AN7: Northeast | AO7: 8850
A8: Bldg. SF | B8: 196289 | D8: Totals | E8: =SUM(E3:E7) -> 194 | F8: =E8/$E$8 -> 1 | H8: B2B | I8: 17 | J8: =I8/$E$8 -> 0.087628866 | K8: 955 | N8: Gym | O8: 1 | Q8: Lightweight | R8: 147250 | S8: SF | AG8: Southeast | AH8: =21*2+14*8+8*12+7*8 -> 306 | AN8: Southeast | AO8: 19965
A9: Acres | B9: 4.9 | D9: Parking | H9: Totals | I9: =SUM(I3:I8) -> 194 | J9: =SUM(J3:J8) -> 1 | K9: =SUMPRODUCT(I3:I8,K3:K8) -> 145637 | N9: Iron Rail | O9: 1593 | P9: LF | Q9: Pavers | R9: 0 | S9: SF | AG9: More | AH9: =21*4+8*6 -> 132 | AI9: =SUM(AH5:AH9) -> 892 | AN9: More | AO9: =5870+6250+6290+5915 -> 24325 | AP9: =SUM(AO5:AO9) -> 81376
A10: Site SF | B10: =B9*43560 -> 213444 | D10: Cover Parking | F10: 127 | N10: Roofing | O10: =(12209+13565+13960+10629)/100 -> 503.63 | P10: Square | Q10: Pool Deck | R10: 0 | S10: SF
A11: Buildings | B11: 1 | D11: Cover Accesible Parking | F11: 3 | N11: Stucco | O11: 11824 | P11: Square Yard | Q11: Pool Fence | R11: 0 | S11: LF | AG11: Building 2 & 5 | AK11: Building 4 | AL11: =14*8 -> 112 | AN11: Building 2 & 5 | AR11: Building 4 | AS11: =5782+5760+8825+9150 -> 29517
A12: Reports Available | D12: Open Parking | F12: 45 | N12: Livable Area | O12: 0 | P12: SF | Q12: Dog Park Fence | R12: 0 | S12: LF | AG12: Northwest | AL12: =20*8 -> 160 | AN12: Northwest
A13: Site Evaluation Report (GCW) | B13: N | D13: Accessible Parking | F13: 11 | N13: Carports | O13: =F10+F11 -> 130 | P13: Count | Q13: Common Bldg. 1 | R13: 0 | S13: SF | AG13: Southwest | AL13: =8*18 -> 144 | AN13: Southwest
A14: Soils Report (Nova or Universal) | B14: Y - 4/21/20 | D14: Waiver | F14: 8 | H14: TOTAL COST | J14: =L330 -> 33757309 | N14: Stairs Landings | O14: 60 | P14: Landings | Q14: Asphalt | R14: 75608 | AG14: Northeast | AL14: =7*12 -> 84 | AN14: Northeast
A15: Alta Survey (Wallace) | B15: Y - 1/21/20 | D15: Total Parking Provided | F15: =SUM(F10:F14) -> 194 | H15: PER UNIT | J15: =J14/E8 -> 174006.75 | N15: Pump House | O15: 1 | P15: EA | Q15: Pavers | R15: 350 | AG15: Southeast | AH15: =21*2+14*2+8*6+7*6 -> 160 | AI15: =AH15*2 -> 320 | AL15: =SUM(AL11:AL14) -> 500 | AN15: Southeast | AO15: =5035+5775+1960+1960 -> 14730 | AP15: =AO15*2 -> 29460
A16: Plans | B16: N | D16: Parking Ratio | F16: =SUM(F10:F13)/E8 -> 0.95876289 | H16: PER GSF | J16: =J14/B8 -> 171.97759 | N16: Lock Boxes | O16: 0 | P16: EA | Q16: Pavers Pool | R16: 4500
N17: Awning Small | O17: 0 | P17: EA | AG17: B1B Railings | AH17: =12.5*62 -> 775 | AN17: B1B Railings | AO17: =12.5*62 -> 775
N18: Awning Large | O18: 0 | P18: EA
A19: Description | B19: Cost Code | C19: Cost Category | D19: Sub job | E19: Source | F19: UMO | G19: Quantity | H19: U.P. | I19: Escal % | J19: Total U.P. | K19: Sub Total | L19: Total | M19: Description / Details
A20: General Requirements | B20: 01 | L20: =K21 -> 1692096
A21: General Requirement | B21: 01 | C21: S | F21: Mo | G21: =$B$6 -> 20 | H21: =1692096/20 -> 84604.8 | I21: 0 | J21: =H21*(1+I21) -> 84604.8 | K21: =J21*G21 -> 1692096
A22: Existing Conditions | B22: 02 | L22: =K23 -> 3500
A23: Potholing | B23: 02-3213 | C23: S | D23: ON-SITE | E23: Allowance | G23: 1 | H23: 3500 | I23: 0 | J23: =H23*(1+I23) -> 3500 | K23: =J23*G23 -> 3500
A24: Concrete | B24: 03 | L24: =SUM(K25:K34) -> 1089279.8
A25: Slabs | B25: 03-3101 | C25: S | D25: BUILDING | E25: Torrey Pines | F25: SF | G25: =O2 -> 48122 | H25: 11.99 | I25: 0 | J25: =H25*(1+I25) -> 11.99 | K25: =J25*G25 -> 576982.78 | M25: Conventional slab
A26: Deepened Footings | B26: 03-3101 | C26: S | D26: BUILDING | E26: N/A | J26: =H26*(1+I26) -> 0 | K26: =J26*G26 -> 0
A27: Concrete Slab Repairs | B27: 03-3101 | C27: RR | D27: BUILDING | E27: Allowance | F27: LS | G27: 1 | H27: 2500 | I27: 0 | J27: =H27*(1+I27) -> 2500 | K27: =J27*G27 -> 2500
A28: Pump House Concrete | B28: 03-3101 | C28: S | D28: PUMPHOUSE | E28: Torrey Pines | F28: SF | G28: 300 | H28: 11.99 | J28: =H28*(1+I28) -> 11.99 | K28: =J28*G28 -> 3597
A29: Trash Enclosure Concrete | B29: 03-3102 | C29: S | D29: OTHER SITE | E29: Allowance | F29: SF | G29: =230*4 -> 920 | H29: 11.99 | I29: 0 | J29: =H29*(1+I29) -> 11.99 | K29: =J29*G29 -> 11030.8
A30: Pool Area Shower Concrete | B30: 03-3105 | C30: S | D30: POOL AREA | E30: Torrey Pines | F30: LS | G30: =$O$7 -> 1 | H30: 2500 | I30: 0 | J30: =H30*(1+I30) -> 2500 | K30: =J30*G30 -> 2500
A31: Cabana Concrete | B31: 03-3107 | C31: S | D31: POOL AREA | E31: N/A | J31: =H31*(1+I31) -> 0 | K31: =J31*G31 -> 0
A32: Pool Equipment Foundation | B32: 03-3108 | C32: S | D32: POOL EQUIP | E32: N/A | J32: =H32*(1+I32) -> 0 | K32: =J32*G32 -> 0
A33: Lightweight Concrete | B33: 03-3116 | C33: S | D33: BUILDING | E33: Torrey Pines | F33: SF | G33: =R8 -> 147250 | H33: 2.94 | I33: 0 | J33: =H33*(1+I33) -> 2.94 | K33: =J33*G33 -> 432915 | AI33: =237250/B8 -> 1.208677
A34: Deck Concrete | B34: 03-5001 | C34: S | D34: BUILDING | E34: Torrey Pines | F34: SF | G34: 3024 | H34: 19.76 | I34: 0 | J34: =H34*(1+I34) -> 19.76 | K34: =J34*G34 -> 59754.24 | AI34: =237250/194 -> 1222.9381
A35: Parking Garage | B35: 03-G | L35: =SUM(K36:K43) -> 0
A36: Parking Garage Structure | C36: S | E36: N/A | J36: =H36*(1+I36) -> 0 | K36: =J36*G36 -> 0
A37: Core Slab Precast Concrete | C37: S | E37: N/A | J37: =H37*(1+I37) -> 0 | K37: =J37*G37 -> 0
A38: Concrete Slab on Grade | C38: S | E38: N/A | J38: =H38*(1+I38) -> 0 | K38: =J38*G38 -> 0
A39: Concrete Topping Slab 4" / Level | C39: S | E39: N/A | J39: =H39*(1+I39) -> 0 | K39: =J39*G39 -> 0
A40: Electrical | C40: S | E40: N/A | J40: =H40*(1+I40) -> 0 | K40: =J40*G40 -> 0
A41: Dry Sprinklers | C41: S | E41: N/A | J41: =H41*(1+I41) -> 0 | K41: =J41*G41 -> 0
A42: Mechanical Ventilation | C42: S | E42: N/A | J42: =H42*(1+I42) -> 0 | K42: =J42*G42 -> 0
A43: Stairs and Railings | C43: S | E43: N/A | J43: =H43*(1+I43) -> 0 | K43: =J43*G43 -> 0
A44: Masonry | B44: 04 | L44: =SUM(K45:K49) -> 112800
A45: Elevator Shaft | B45: 04-2201 | C45: S | D45: BUILDING | E45: Torrey Pines | F45: Stop | G45: =O4 -> 8 | H45: 9500 | I45: 0 | J45: =H45*(1+I45) -> 9500 | K45: =J45*G45 -> 76000
A46: Trash Enclosure | B46: 04-2202 | C46: S | D46: OTHER SITE | E46: Torrey Pines | F46: Count | G46: =$O$5 -> 4 | H46: 5700 | I46: 0 | J46: =H46*(1+I46) -> 5700 | K46: =J46*G46 -> 22800
A47: Masonry Veneer | B47: 04-4301 | C47: S | D47: ON-SITE | E47: N/A | H47: 0 | J47: =H47*(1+I47) -> 0 | K47: =J47*G47 -> 0
A48: Masonry Veneer Pool Area | B48: 04-4305 | C48: S | D48: POOL AREA | E48: Allowance | F48: LS | G48: =$O$7 -> 1 | H48: 5000 | I48: 0 | J48: =H48*(1+I48) -> 5000 | K48: =J48*G48 -> 5000
A49: Pool Eq. Shower Stone | B49: 04-4306 | C49: A | D49: POOL EQUIP | E49: Torrey Pines | F49: LS | G49: =$O$7 -> 1 | H49: 9000 | I49: 0 | J49: =H49*(1+I49) -> 9000 | K49: =J49*G49 -> 9000
A50: Metals | B50: 05 | L50: =SUM(K51:K58) -> 325412.13
A51: Structural Steel | B51: 05-1201 | C51: S | D51: BUILDING | E51: Torrey Pines | F51: LBS | G51: 31706.95 | H51: 3.5584037 | I51: 0 | J51: =H51*(1+I51) -> 3.5584037 | K51: =J51*G51 -> 112826.13
A52: Elevator Shaft Iron | B52: 05-1202 | C52: S | D52: BUILDING | E52: Torrey Pines | F52: Count | G52: =$O$3 -> 2 | H52: =1950+2090 -> 4040 | I52: 0 | J52: =H52*(1+I52) -> 4040 | K52: =J52*G52 -> 8080
A53: Stair Handrails | B53: 05-5201 | C53: S | D53: BUILDING | E53: Torrey Pines | F53: Flight | G53: =O6*4 -> 28 | H53: 2000 | I53: 0 | J53: =H53*(1+I53) -> 2000 | K53: =J53*G53 -> 56000
A54: Garage Stair Railings | B54: 05-5201 | C54: S | D54: BUILDING | E54: N/A | H54: 0 | I54: 0 | J54: =H54*(1+I54) -> 0 | K54: =J54*G54 -> 0
A55: Cabana Iron | B55: 05-7004 | C55: S | D55: POOL AREA | E55: N/A | H55: 0 | I55: 0 | J55: =H55*(1+I55) -> 0 | K55: =J55*G55 -> 0
A56: Pool Equipment Gate | B56: 05-7005 | C56: S | D56: POOL EQUIP | E56: Torrey Pines | F56: Count | G56: 1 | H56: 1950 | I56: 0 | J56: =H56*(1+I56) -> 1950 | K56: =J56*G56 -> 1950
A57: Iron Railings | B57: 05-7300 | C57: S | D57: BUILDING | E57: Torrey Pines | F57: LF | G57: =$O$9 -> 1593 | H57: 92 | I57: 0 | J57: =H57*(1+I57) -> 92 | K57: =J57*G57 -> 146556
A58: Cable Railings | B58: 05-7316 | C58: S | D58: COMMON AREA | E58: N/A | H58: 0 | I58: 0 | J58: =H58*(1+I58) -> 0 | K58: =J58*G58 -> 0
A59: Wood, Plastics, & Composites | B59: 06 | L59: =SUM(K60:K71) -> 4804000.7
A60: Dumpsters | B60: 06-0111 | C60: S | D60: DUMPSTERS | I60: 0 | J60: =H60*(1+I60) -> 0 | K60: =J60*G60 -> 0 | M60: Included in Construction Cleaning Contract
A61: Framing | B61: 06-1100 | C61: S | D61: BUILDING | E61: Moving Ave | F61: SF | G61: =B8 -> 196289 | H61: 20.5 | I61: 0 | J61: =H61*(1+I61) -> 20.5 | K61: =J61*G61 -> 4023924.5
A62: Framing - Crane | B62: 06-1100 | C62: S | D62: BUILDING | E62: N/A | I62: 0 | J62: =H62*(1+I62) -> 0 | K62: =J62*G62 -> 0
A63: Cabana Framing | B63: 06-1109 | C63: S | D63: COMMON AREA | E63: N/A | I63: 0 | J63: =H63*(1+I63) -> 0 | K63: =J63*G63 -> 0
A64: BBQ Framing | B64: 06-1110 | C64: S | D64: COMMON AREA | E64: Allowance | F64: LS | G64: 1 | H64: 2500 | I64: 0 | J64: =H64*(1+I64) -> 2500 | K64: =J64*G64 -> 2500
A65: Fireplace Framing | B65: 06-1111 | C65: S | D65: COMMON AREA | E65: N/A | I65: 0 | J65: =H65*(1+I65) -> 0 | K65: =J65*G65 -> 0
A66: Trellis | B66: 06-1114 | C66: S | D66: BUILDING | E66: N/A | I66: 0 | J66: =H66*(1+I66) -> 0 | K66: =J66*G66 -> 0
A67: Pool Equipment Framing | B67: 06-1114 | C67: S | D67: POOL EQUIP | E67: N/A | I67: 0 | J67: =H67*(1+I67) -> 0 | K67: =J67*G67 -> 0
A68: Finish Carpentry - Units | B68: 06-2001 | C68: S | D68: BUILDING | E68: Torrey Pines | F68: Unit | G68: =$E$8 -> 194 | H68: 3192.5 | I68: 0 | J68: =H68*(1+I68) -> 3192.5 | K68: =J68*G68 -> 619345
A69: Finish Carpentry - Common | B69: 06-2001 | C69: S | D69: COMMON AREA | E69: Torrey Pines | F69: SF | G69: =B8 -> 196289 | H69: 0.8 | I69: 0 | J69: =H69*(1+I69) -> 0.8 | K69: =J69*G69 -> 157031.2
A70: BBQ Trim | B70: 06-2006 | C70: S | D70: COMMON AREA | E70: Allowance | F70: LS | G70: 1 | H70: 1200 | I70: 0 | J70: =H70*(1+I70) -> 1200 | K70: =J70*G70 -> 1200
A71: Shutters | B71: 06-4919 | C71: S | D71: BUILDING | E71: N/A | I71: 0 | J71: =H71*(1+I71) -> 0 | K71: =J71*G71 -> 0
A72: Thermal & Moisture Protection | B72: 07 | L72: =SUM(K73:K83) -> 905486.76
A73: Insulation | B73: 07-2101 | C73: S | D73: BUILDING | E73: Torrey Pines | F73: SF | G73: =B8 -> 196289 | H73: 2.7 | I73: 0 | J73: =H73*(1+I73) -> 2.7 | K73: =J73*G73 -> 529980.3 | M73: It includes the material increased since for 2nd half of 2024.
A74: Roofing | B74: 07-3001 | C74: S | D74: BUILDING | E74: Torrey Pines | F74: Squares | G74: =$O$10 -> 503.63 | H74: 603 | I74: 0 | J74: =H74*(1+I74) -> 603 | K74: =J74*G74 -> 303688.89
A75: Cabana Roofing | B75: 07-3002 | C75: S | D75: COMMON AREA | E75: N/A | I75: 0 | J75: =H75*(1+I75) -> 0 | K75: =J75*G75 -> 0
A76: Pump House Roofing | B76: 07-3002 | C76: S | D76: PUMPHOUSE | E76: Allowance | F76: LS | G76: 1 | H76: 7500 | I76: 0 | J76: =H76*(1+I76) -> 7500 | K76: =J76*G76 -> 7500
A77: Pool Equipment Roofing | B77: 07-3003 | C77: S | D77: POOL EQUIP | E77: Allowance | F77: LS | G77: =O7 -> 1 | H77: 7500 | I77: 0 | J77: =H77*(1+I77) -> 7500 | K77: =J77*G77 -> 7500
A78: Trash Enclosure Cover | B78: 07-6101 | C78: S | D78: OTHER SITE | E78: Decatur | F78: Count | G78: =$O$5 -> 4 | H78: 5800 | I78: 0 | J78: =H78*(1+I78) -> 5800 | K78: =J78*G78 -> 23200
A79: Pigeon Proofing | B79: 07-7001 | C79: S | D79: BUILDING | E79: Torrey Pines | F79: SF | G79: =$B$8 -> 196289 | H79: 0.08 | I79: 0 | J79: =H79*(1+I79) -> 0.08 | K79: =J79*G79 -> 15703.12
A80: Gutters and Downspouts | B80: 07-7124 | C80: S | D80: BUILDING | E80: Torrey Pines | F80: SF | G80: =$B$8 -> 196289 | H80: 0.05 | I80: 0 | J80: =H80*(1+I80) -> 0.05 | K80: =J80*G80 -> 9814.45
A81: Roof Ladders | B81: 07-7210 | C81: S | D81: BUILDING | E81: Torrey Pines | F81: Count | G81: =2*$B$11 -> 2 | H81: 1550 | I81: 0 | J81: =H81*(1+I81) -> 1550 | K81: =J81*G81 -> 3100 | M81: 2 Per building
A82: Roof Access Doors | B82: 07-7233 | C82: S | D82: BUILDING | E82: Torrey Pines | F82: Count | G82: =2*$B$11 -> 2 | H82: 2500 | I82: 0 | J82: =H82*(1+I82) -> 2500 | K82: =J82*G82 -> 5000 | M82: 2 Per building
A83: Roof Winch | B83: 07-7250 | C83: S | D83: BUILDING | E83: N/A | I83: 0 | J83: =H83*(1+I83) -> 0 | K83: =J83*G83 -> 0
A84: Openings | B84: 08 | L84: =SUM(K85:K99) -> 279109.58
A85: Dumpsters | B85: 08-0151 | C85: S | D85: DUMPSTERS | I85: 0 | J85: =H85*(1+I85) -> 0 | K85: =J85*G85 -> 0 | M85: Inclunded with Construction Cleaning Contract.
A86: Entry Doors | B86: 08-1001 | C86: S | D86: COMMON AREA | E86: Allowance | F86: Count | G86: 1 | H86: 8000 | I86: 0 | J86: =H86*(1+I86) -> 8000 | K86: =J86*G86 -> 8000
A87: Common Doors | B87: 08-1002 | C87: S | D87: COMMON AREA | E87: Included | I87: 0 | J87: =H87*(1+I87) -> 0 | K87: =J87*G87 -> 0
A88: Pocket Doors - 3 Panel | B88: 08-1002 | C88: S | D88: BUILDING | E88: N/A | I88: 0 | J88: =H88*(1+I88) -> 0 | K88: =J88*G88 -> 0
A89: Garage Doors | B89: 08-3619 | C89: S | D89: BUILDING | E89: N/A | I89: 0 | J89: =H89*(1+I89) -> 0 | K89: =J89*G89 -> 0
A90: Windows and Sliding Glass Doors | B90: 08-5301 | C90: S | D90: BUILDING | E90: Torrey Pines | F90: Per Unit | G90: =$E$8 -> 194 | H90: 1157.8947 | I90: 0 | J90: =H90*(1+I90) -> 1157.8947 | K90: =J90*G90 -> 224631.58
A91: Windows Repair and Replacement | B91: 08-5301 | C91: RR | D91: BUILDING | E91: Allowance | F91: Per Unit | G91: =$E$8 -> 194 | H91: 75 | I91: 0 | J91: =H91*(1+I91) -> 75 | K91: =J91*G91 -> 14550
A92: Pool Equipment Windows | B92: 08-5303 | C92: S | D92: POOL EQUIP | E92: N/A | I92: 0 | J92: =H92*(1+I92) -> 0 | K92: =J92*G92 -> 0
A93: Pool Glass Walls | B93: 08-8001 | C93: S | D93: POOL AREA | E93: N/A | I93: 0 | J93: =H93*(1+I93) -> 0 | K93: =J93*G93 -> 0
A94: Fixed Glass | B94: 08-8002 | C94: S | D94: BUILDING | E94: N/A | I94: 0 | J94: =H94*(1+I94) -> 0 | K94: =J94*G94 -> 0
A95: Mirrors - LED | B95: 08-8301 | C95: S | D95: BUILDING | E95: N/A | I95: 0 | J95: =H95*(1+I95) -> 0 | K95: =J95*G95 -> 0
A96: Mirrors - LED Install | B96: 08-8302 | C96: S | D96: BUILDING | E96: N/A | I96: 0 | J96: =H96*(1+I96) -> 0 | K96: =J96*G96 -> 0
A97: Mirrors - Framed | B97: 08-8301 | C97: S | D97: BUILDING | E97: N/A | I97: 0 | J97: =H97*(1+I97) -> 0 | K97: =J97*G97 -> 0
A98: Mirrors - Polished Edges (Units) | B98: 08-8301 | C98: S | D98: BUILDING | E98: Pebble | F98: Unit | G98: =E8 -> 194 | H98: 162 | I98: 0 | J98: =H98*(1+I98) -> 162 | K98: =J98*G98 -> 31428
A99: Mirrors - Polished Edges (Restrooms) | B99: 08-8301 | C99: S | D99: BUILDING | E99: Allowance | F99: Count | G99: 2 | H99: 250 | I99: 0 | J99: =H99*(1+I99) -> 250 | K99: =J99*G99 -> 500
A100: Finishes | B100: 09 | L100: =SUM(K101:K136) -> 3261602.4
...

Sheet Comparison to Previous
A1: BRUNER SENIOR | C1: LEVEL 1 | F1: LEVEL 2 | O1: LEVEL 3
F2: Project Details | K2: Unit Breakdown | O2: Project Details | T2: Unit Breakdown
F3: Project | G3: Bruner Senior | K3: Unit Type | L3: Number | M3: % | O3: Project | P3: Bruner Senior | T3: Unit Type | U3: Number | V3: %
F4: Budget Level | G4: Level 2 | K4: Studios | L4: 0 | M4: 0 | O4: Budget Level | P4: Level 2 | T4: Studios | U4: 0 | V4: =U4/$U$9 -> 0
F5: Product | G5: Senior | K5: 1 Br - 1 Ba | L5: 126 | M5: 0.64948454 | O5: Product | P5: Senior | T5: 1 Br - 1 Ba | U5: 126 | V5: =U5/$U$9 -> 0.64948454
F6: Start Date | G6: 45809 | K6: 2 Br - 1 Ba | L6: 68 | M6: 0.35051546 | O6: Start Date | P6: 45809 | T6: 2 Br - 1 Ba | U6: 68 | V6: =U6/$U$9 -> 0.35051546
F7: Timeline | G7: 20 | K7: 2 Br - 2 Ba | L7: 0 | M7: 0 | O7: Timeline | P7: 20 | T7: 2 Br - 2 Ba | U7: 0 | V7: =U7/$U$9 -> 0
F8: Floors | G8: 4 | K8: 3 Br - 2 Ba | L8: 0 | M8: 0 | O8: Floors | P8: 4 | T8: 3 Br - 2 Ba | U8: 0 | V8: =U8/$U$9 -> 0
F9: Bldg. SF | G9: 196289 | K9: Totals | L9: 194 | M9: =L9/$L$9 -> 1 | O9: Bldg. SF | P9: 196289 | T9: Totals | U9: =SUM(U4:U8) -> 194 | V9: =U9/$U$9 -> 1
F10: Acres | G10: 4.9 | K10: Parking | O10: Acres | P10: 4.9 | T10: Parking
F11: Site SF | G11: 213444 | K11: Garage Parking | M11: 127 | O11: Site SF | P11: =P10*43560 -> 213444 | T11: Cover Parking | V11: 127
F12: Buildings | G12: 1 | K12: Cover Parking | M12: 3 | O12: Buildings | P12: 1 | T12: Cover Acc. Parking | V12: 3
K13: Open Parking | M13: 45 | T13: Open Parking | V13: 45
K14: Accessible Parking | M14: 11 | Q14: Net Change | T14: Accessible Parking | V14: 11
F15: TOTAL COST | G15: =M314 -> 33757309 | K15: Private Garages | M15: 8 | O15: TOTAL COST | P15: =V314 -> 33486712 | Q15: =P15-G15 -> -270597.42 | R15: =Q15/G15 -> -0.0080159653 | T15: Waiver | V15: 8
F16: PER UNIT | G16: =G15/L9 -> 174006.75 | K16: Total Parking Provided | M16: 194 | O16: PER UNIT | P16: =P15/U9 -> 172611.92 | Q16: =P16-G16 -> -1394.8321 | T16: Total Parking Provided | V16: =SUM(V11:V15) -> 194
F17: PER GSF | G17: =G15/G9 -> 171.97759 | K17: Parking Ratio | M17: 0.95876289 | O17: PER GSF | P17: =P15/P9 -> 170.59902 | Q17: =P17-G17 -> -1.3785664 | T17: Parking Ratio | V17: =SUM(V11:V14)/U9 -> 0.95876289 | X17: Conditions | Z17: Conditions
X18: 50000 | Z18: 0.05
A19: Description | C19: Total | D19: Variance | F19: Source | G19: UOM | H19: QTY | I19: U.P. | J19: % | K19: Total U.P. | L19: Sub Total | M19: Total | O19: Source | P19: UOM | Q19: QTY | R19: U.P. | S19: % | T19: Total U.P. | U19: Sub Total | V19: Total | X19: PV$ | Z19: PV% | AB19: Notes
A20: General Requirements | C20: 1673802.9 | D20: =V20-C20 -> 515.07497 | M20: ='LEVEL 2 (Match)'!L20 -> 1692096 | V20: ='LEVEL 3'!L20 -> 1674318 | X20: =V20-M20 -> -17778 | Z20: =IF(M20=0,0,X20/M20) -> -0.010506496
A21: Existing Conditions | C21: 3500 | D21: =V21-C21 -> 0 | M21: ='LEVEL 2 (Match)'!L22 -> 3500 | V21: ='LEVEL 3'!L22 -> 3500 | X21: =V21-M21 -> 0 | Z21: =IF(M21=0,0,X21/M21) -> 0
A22: Slabs | D22: =V22-C22 -> 0 | F22: Torrey Pines | G22: SF | H22: 48122 | I22: 11.99 | J22: 0 | K22: 11.99 | L22: ='LEVEL 2 (Match)'!K25 -> 576982.78 | O22: Torrey Pines | P22: ='LEVEL 3'!F25 -> SF | Q22: ='LEVEL 3'!G25 -> 48122 | R22: ='LEVEL 3'!H25 -> 11.99 | S22: ='LEVEL 3'!I25 -> 0 | T22: ='LEVEL 3'!J25 -> 11.99 | U22: ='LEVEL 3'!K25 -> 576982.78 | X22: =U22-L22 -> 0 | Z22: =IF(L22=0,0,X22/L22) -> 0
A23: Deepened Footings | D23: =V23-C23 -> 0 | F23: N/A | K23: 0 | L23: ='LEVEL 2 (Match)'!K26 -> 0 | O23: N/A | P23: ='LEVEL 3'!F26 -> 0 | Q23: ='LEVEL 3'!G26 -> 0 | R23: ='LEVEL 3'!H26 -> 0 | S23: ='LEVEL 3'!I26 -> 0 | T23: ='LEVEL 3'!J26 -> 0 | U23: ='LEVEL 3'!K26 -> 0 | X23: =U23-L23 -> 0 | Z23: =IF(L23=0,0,X23/L23) -> 0
A24: Concrete Slab Repairs | D24: =V24-C24 -> 0 | F24: Allowance | G24: LS | H24: 1 | I24: 2500 | J24: 0 | K24: 2500 | L24: ='LEVEL 2 (Match)'!K27 -> 2500 | O24: Allowance | P24: ='LEVEL 3'!F27 -> LS | Q24: ='LEVEL 3'!G27 -> 1 | R24: ='LEVEL 3'!H27 -> 2500 | S24: ='LEVEL 3'!I27 -> 0 | T24: ='LEVEL 3'!J27 -> 2500 | U24: ='LEVEL 3'!K27 -> 2500 | X24: =U24-L24 -> 0 | Z24: =IF(L24=0,0,X24/L24) -> 0
A25: Pump House Concrete | D25: =V25-C25 -> 0 | F25: Torrey Pines | G25: SF | H25: 300 | I25: 11.99 | K25: 11.99 | L25: ='LEVEL 2 (Match)'!K28 -> 3597 | O25: Torrey Pines | P25: ='LEVEL 3'!F28 -> SF | Q25: ='LEVEL 3'!G28 -> 300 | R25: ='LEVEL 3'!H28 -> 11.99 | S25: ='LEVEL 3'!I28 -> 0 | T25: ='LEVEL 3'!J28 -> 11.99 | U25: ='LEVEL 3'!K28 -> 3597 | X25: =U25-L25 -> 0 | Z25: =IF(L25=0,0,X25/L25) -> 0
A26: Trash Enclosure Concrete | D26: =V26-C26 -> 0 | F26: Allowance | G26: SF | H26: 920 | I26: 11.99 | J26: 0 | K26: 11.99 | L26: ='LEVEL 2 (Match)'!K29 -> 11030.8 | O26: Allowance | P26: ='LEVEL 3'!F29 -> SF | Q26: ='LEVEL 3'!G29 -> 920 | R26: ='LEVEL 3'!H29 -> 11.99 | S26: ='LEVEL 3'!I29 -> 0 | T26: ='LEVEL 3'!J29 -> 11.99 | U26: ='LEVEL 3'!K29 -> 11030.8 | X26: =U26-L26 -> 0 | Z26: =IF(L26=0,0,X26/L26) -> 0
A27: Pool Area Shower Concrete | D27: =V27-C27 -> 0 | F27: Torrey Pines | G27: LS | H27: 1 | I27: 2500 | J27: 0 | K27: 2500 | L27: ='LEVEL 2 (Match)'!K30 -> 2500 | O27: Torrey Pines | P27: ='LEVEL 3'!F30 -> LS | Q27: ='LEVEL 3'!G30 -> 1 | R27: ='LEVEL 3'!H30 -> 2500 | S27: ='LEVEL 3'!I30 -> 0 | T27: ='LEVEL 3'!J30 -> 2500 | U27: ='LEVEL 3'!K30 -> 2500 | X27: =U27-L27 -> 0 | Z27: =IF(L27=0,0,X27/L27) -> 0
A28: Cabana Concrete | D28: =V28-C28 -> 0 | F28: N/A | K28: 0 | L28: ='LEVEL 2 (Match)'!K31 -> 0 | O28: N/A | P28: ='LEVEL 3'!F31 -> 0 | Q28: ='LEVEL 3'!G31 -> 0 | R28: ='LEVEL 3'!H31 -> 0 | S28: ='LEVEL 3'!I31 -> 0 | T28: ='LEVEL 3'!J31 -> 0 | U28: ='LEVEL 3'!K31 -> 0 | X28: =U28-L28 -> 0 | Z28: =IF(L28=0,0,X28/L28) -> 0
A29: Pool Equipment Foundation | D29: =V29-C29 -> 0 | F29: N/A | K29: 0 | L29: ='LEVEL 2 (Match)'!K32 -> 0 | O29: N/A | P29: ='LEVEL 3'!F32 -> 0 | Q29: ='LEVEL 3'!G32 -> 0 | R29: ='LEVEL 3'!H32 -> 0 | S29: ='LEVEL 3'!I32 -> 0 | T29: ='LEVEL 3'!J32 -> 0 | U29: ='LEVEL 3'!K32 -> 0 | X29: =U29-L29 -> 0 | Z29: =IF(L29=0,0,X29/L29) -> 0
A30: Lightweight Concrete | D30: =V30-C30 -> 0 | F30: Torrey Pines | G30: SF | H30: 147250 | I30: 2.94 | J30: 0 | K30: 2.94 | L30: ='LEVEL 2 (Match)'!K33 -> 432915 | O30: Torrey Pines | P30: ='LEVEL 3'!F33 -> SF | Q30: ='LEVEL 3'!G33 -> 147250 | R30: ='LEVEL 3'!H33 -> 2.94 | S30: ='LEVEL 3'!I33 -> 0 | T30: ='LEVEL 3'!J33 -> 2.94 | U30: ='LEVEL 3'!K33 -> 432915 | X30: =U30-L30 -> 0 | Z30: =IF(L30=0,0,X30/L30) -> 0
A31: Deck Concrete | D31: =V31-C31 -> 0 | F31: Torrey Pines | G31: SF | H31: 3024 | I31: 19.76 | J31: 0 | K31: 19.76 | L31: ='LEVEL 2 (Match)'!K34 -> 59754.24 | O31: Torrey Pines | P31: ='LEVEL 3'!F34 -> SF | Q31: ='LEVEL 3'!G34 -> 3024 | R31: ='LEVEL 3'!H34 -> 19.76 | S31: ='LEVEL 3'!I34 -> 0 | T31: ='LEVEL 3'!J34 -> 19.76 | U31: ='LEVEL 3'!K34 -> 59754.24 | X31: =U31-L31 -> 0 | Z31: =IF(L31=0,0,X31/L31) -> 0
A32: Concrete | C32: 1082096 | D32: =V32-C32 -> 7183.85 | M32: =SUM(L22:L31) -> 1089279.8 | V32: ='LEVEL 3'!L24 -> 1089279.8 | X32: =V32-M32 -> 0 | Z32: =IF(M32=0,0,X32/M32) -> 0
A33: Elevator Shaft | D33: =V33-C33 -> 0 | F33: Torrey Pines | G33: Stop | H33: 8 | I33: 9500 | J33: 0 | K33: 9500 | L33: 76000 | O33: Torrey Pines | P33: ='LEVEL 3'!F45 -> Stop | Q33: ='LEVEL 3'!G45 -> 8 | R33: ='LEVEL 3'!H45 -> 9500 | S33: ='LEVEL 3'!I45 -> 0 | T33: ='LEVEL 3'!J45 -> 9500 | U33: ='LEVEL 3'!K45 -> 76000 | X33: =U33-L33 -> 0 | Z33: =IF(L33=0,0,X33/L33) -> 0
A34: Trash Enclosure | D34: =V34-C34 -> 0 | F34: Torrey Pines | G34: Count | H34: 4 | I34: 5700 | J34: 0 | K34: 5700 | L34: 22800 | O34: Torrey Pines | P34: ='LEVEL 3'!F46 -> Count | Q34: ='LEVEL 3'!G46 -> 4 | R34: ='LEVEL 3'!H46 -> 5700 | S34: ='LEVEL 3'!I46 -> 0 | T34: ='LEVEL 3'!J46 -> 5700 | U34: ='LEVEL 3'!K46 -> 22800 | X34: =U34-L34 -> 0 | Z34: =IF(L34=0,0,X34/L34) -> 0
A35: Masonry Veneer | D35: =V35-C35 -> 0 | F35: N/A | I35: 0 | K35: 0 | L35: 0 | O35: N/A | P35: ='LEVEL 3'!F47 -> 0 | Q35: ='LEVEL 3'!G47 -> 0 | R35: ='LEVEL 3'!H47 -> 0 | S35: ='LEVEL 3'!I47 -> 0 | T35: ='LEVEL 3'!J47 -> 0 | U35: ='LEVEL 3'!K47 -> 0 | X35: =U35-L35 -> 0 | Z35: =IF(L35=0,0,X35/L35) -> 0
A36: Masonry Veneer Pool Area | D36: =V36-C36 -> 0 | F36: Allowance | G36: LS | H36: 1 | I36: 5000 | J36: 0 | K36: 5000 | L36: 5000 | O36: Allowance | P36: ='LEVEL 3'!F48 -> LS | Q36: ='LEVEL 3'!G48 -> 1 | R36: ='LEVEL 3'!H48 -> 5000 | S36: ='LEVEL 3'!I48 -> 0 | T36: ='LEVEL 3'!J48 -> 5000 | U36: ='LEVEL 3'!K48 -> 5000 | X36: =U36-L36 -> 0 | Z36: =IF(L36=0,0,X36/L36) -> 0
A37: Pool Eq. Shower Stone | D37: =V37-C37 -> 0 | F37: Torrey Pines | G37: LS | H37: 1 | I37: 9000 | J37: 0 | K37: 9000 | L37: 9000 | O37: Torrey Pines | P37: ='LEVEL 3'!F49 -> LS | Q37: ='LEVEL 3'!G49 -> 1 | R37: ='LEVEL 3'!H49 -> 9000 | S37: ='LEVEL 3'!I49 -> 0 | T37: ='LEVEL 3'!J49 -> 9000 | U37: ='LEVEL 3'!K49 -> 9000 | X37: =U37-L37 -> 0 | Z37: =IF(L37=0,0,X37/L37) -> 0
A38: Masonry | C38: 115440 | D38: =V38-C38 -> -2640 | M38: =SUM(L33:L37) -> 112800 | V38: ='LEVEL 3'!L44 -> 112800 | X38: =V38-M38 -> 0 | Z38: =IF(M38=0,0,X38/M38) -> 0
A39: Structural Steel | D39: =V39-C39 -> 0 | F39: Torrey Pines | G39: LBS | H39: 31706.95 | I39: 3.5584037 | J39: 0 | K39: 3.5584037 | L39: 112826.13 | O39: Torrey Pines | P39: ='LEVEL 3'!F51 -> LBS | Q39: ='LEVEL 3'!G51 -> 31706.95 | R39: ='LEVEL 3'!H51 -> 3.5584037 | S39: ='LEVEL 3'!I51 -> 0 | T39: ='LEVEL 3'!J51 -> 3.5584037 | U39: ='LEVEL 3'!K51 -> 112826.13 | X39: =U39-L39 -> 0 | Z39: =IF(L39=0,0,X39/L39) -> 0
A40: Elevator Shaft Iron | D40: =V40-C40 -> 0 | F40: Torrey Pines | G40: Count | H40: 2 | I40: 4040 | J40: 0 | K40: 4040 | L40: 8080 | O40: Torrey Pines | P40: ='LEVEL 3'!F52 -> Count | Q40: ='LEVEL 3'!G52 -> 2 | R40: ='LEVEL 3'!H52 -> 4040 | S40: ='LEVEL 3'!I52 -> 0 | T40: ='LEVEL 3'!J52 -> 4040 | U40: ='LEVEL 3'!K52 -> 8080 | X40: =U40-L40 -> 0 | Z40: =IF(L40=0,0,X40/L40) -> 0
A41: Stair Handrails | D41: =V41-C41 -> 0 | F41: Torrey Pines | G41: Flight | H41: 28 | I41: 2000 | J41: 0 | K41: 2000 | L41: 56000 | O41: Bruner Proposal | P41: ='LEVEL 3'!F53 -> Flight | Q41: ='LEVEL 3'!G53 -> 28 | R41: ='LEVEL 3'!H53 -> 2000 | S41: ='LEVEL 3'!I53 -> 0 | T41: ='LEVEL 3'!J53 -> 2000 | U41: ='LEVEL 3'!K53 -> 56000 | X41: =U41-L41 -> 0 | Z41: =IF(L41=0,0,X41/L41) -> 0
A42: Garage Stair Railings | D42: =V42-C42 -> 0 | F42: N/A | I42: 0 | J42: 0 | K42: 0 | L42: 0 | O42: N/A | P42: ='LEVEL 3'!F54 -> 0 | Q42: ='LEVEL 3'!G54 -> 0 | R42: ='LEVEL 3'!H54 -> 0 | S42: ='LEVEL 3'!I54 -> 0 | T42: ='LEVEL 3'!J54 -> 0 | U42: ='LEVEL 3'!K54 -> 0 | X42: =U42-L42 -> 0 | Z42: =IF(L42=0,0,X42/L42) -> 0
A43: Cabana Iron | D43: =V43-C43 -> 0 | F43: N/A | I43: 0 | J43: 0 | K43: 0 | L43: 0 | O43: N/A | P43: ='LEVEL 3'!F55 -> 0 | Q43: ='LEVEL 3'!G55 -> 0 | R43: ='LEVEL 3'!H55 -> 0 | S43: ='LEVEL 3'!I55 -> 0 | T43: ='LEVEL 3'!J55 -> 0 | U43: ='LEVEL 3'!K55 -> 0 | X43: =U43-L43 -> 0 | Z43: =IF(L43=0,0,X43/L43) -> 0
A44: Pool Equipment Gate | D44: =V44-C44 -> 0 | F44: Torrey Pines | G44: Count | H44: 1 | I44: 1950 | J44: 0 | K44: 1950 | L44: 1950 | O44: Torrey Pines | P44: ='LEVEL 3'!F56 -> Count | Q44: ='LEVEL 3'!G56 -> 1 | R44: ='LEVEL 3'!H56 -> 1950 | S44: ='LEVEL 3'!I56 -> 0 | T44: ='LEVEL 3'!J56 -> 1950 | U44: ='LEVEL 3'!K56 -> 1950 | X44: =U44-L44 -> 0 | Z44: =IF(L44=0,0,X44/L44) -> 0
A45: Iron Railings | D45: =V45-C45 -> 0 | F45: Torrey Pines | G45: LF | H45: 1593 | I45: 92 | J45: 0 | K45: 92 | L45: 146556 | O45: Bruner Proposal | P45: ='LEVEL 3'!F57 -> LF | Q45: ='LEVEL 3'!G57 -> 1593 | R45: ='LEVEL 3'!H57 -> 92 | S45: ='LEVEL 3'!I57 -> 0 | T45: ='LEVEL 3'!J57 -> 92 | U45: ='LEVEL 3'!K57 -> 146556 | X45: =U45-L45 -> 0 | Z45: =IF(L45=0,0,X45/L45) -> 0 | AB45: Missed 105 Juliet/Faux balconies $100k
A46: Cable Railings | D46: =V46-C46 -> 0 | F46: N/A | I46: 0 | J46: 0 | K46: 0 | L46: 0 | O46: N/A | P46: ='LEVEL 3'!F58 -> 0 | Q46: ='LEVEL 3'!G58 -> 0 | R46: ='LEVEL 3'!H58 -> 0 | S46: ='LEVEL 3'!I58 -> 0 | T46: ='LEVEL 3'!J58 -> 0 | U46: ='LEVEL 3'!K58 -> 0 | X46: =U46-L46 -> 0 | Z46: =IF(L46=0,0,X46/L46) -> 0
A47: Metals | C47: 335138.42 | D47: =V47-C47 -> -9726.2966 | M47: =SUM(L39:L46) -> 325412.13 | V47: ='LEVEL 3'!L50 -> 325412.13 | X47: =V47-M47 -> 0 | Z47: =IF(M47=0,0,X47/M47) -> 0
A48: Framing | D48: =V48-C48 -> 0 | F48: Moving Ave | G48: SF | H48: 196289 | I48: 20.5 | J48: 0 | K48: 20.5 | L48: 4023924.5 | O48: Torrey Pines | P48: ='LEVEL 3'!F60 -> SF | Q48: ='LEVEL 3'!G60 -> 196289 | R48: ='LEVEL 3'!H60 -> 20.423582 | S48: ='LEVEL 3'!I60 -> 0 | T48: ='LEVEL 3'!J60 -> 20.423582 | U48: ='LEVEL 3'!K60 -> 4008924.5 | X48: =U48-L48 -> -15000 | Z48: =IF(L48=0,0,X48/L48) -> -0.0037277041
A49: Framing - Pump House | D49: =V49-C49 -> 0 | O49: Torrey Pines | P49: ='LEVEL 3'!F61 -> LS | Q49: ='LEVEL 3'!G61 -> 1 | R49: ='LEVEL 3'!H61 -> 15000 | S49: ='LEVEL 3'!I61 -> 0 | T49: ='LEVEL 3'!J61 -> 15000 | U49: ='LEVEL 3'!K61 -> 15000
A50: Framing - Crane | D50: =V50-C50 -> 0 | F50: N/A | J50: 0 | K50: 0 | L50: 0 | O50: N/A | P50: ='LEVEL 3'!F62 -> 0 | Q50: ='LEVEL 3'!G62 -> 0 | R50: ='LEVEL 3'!H62 -> 0 | S50: ='LEVEL 3'!I62 -> 0 | T50: ='LEVEL 3'!J62 -> 0 | U50: ='LEVEL 3'!K62 -> 0 | X50: =U50-L50 -> 0 | Z50: =IF(L50=0,0,X50/L50) -> 0
A51: Cabana Framing | D51: =V51-C51 -> 0 | F51: N/A | J51: 0 | K51: 0 | L51: 0 | O51: N/A | P51: ='LEVEL 3'!F63 -> 0 | Q51: ='LEVEL 3'!G63 -> 0 | R51: ='LEVEL 3'!H63 -> 0 | S51: ='LEVEL 3'!I63 -> 0 | T51: ='LEVEL 3'!J63 -> 0 | U51: ='LEVEL 3'!K63 -> 0 | X51: =U51-L51 -> 0 | Z51: =IF(L51=0,0,X51/L51) -> 0
A52: BBQ Framing | D52: =V52-C52 -> 0 | F52: Allowance | G52: LS | H52: 1 | I52: 2500 | J52: 0 | K52: 2500 | L52: 2500 | O52: Allowance | P52: ='LEVEL 3'!F64 -> LS | Q52: ='LEVEL 3'!G64 -> 1 | R52: ='LEVEL 3'!H64 -> 2500 | S52: ='LEVEL 3'!I64 -> 0 | T52: ='LEVEL 3'!J64 -> 2500 | U52: ='LEVEL 3'!K64 -> 2500 | X52: =U52-L52 -> 0 | Z52: =IF(L52=0,0,X52/L52) -> 0
A53: Fireplace Framing | D53: =V53-C53 -> 0 | F53: N/A | J53: 0 | K53: 0 | L53: 0 | O53: N/A | P53: ='LEVEL 3'!F65 -> 0 | Q53: ='LEVEL 3'!G65 -> 0 | R53: ='LEVEL 3'!H65 -> 0 | S53: ='LEVEL 3'!I65 -> 0 | T53: ='LEVEL 3'!J65 -> 0 | U53: ='LEVEL 3'!K65 -> 0 | X53: =U53-L53 -> 0 | Z53: =IF(L53=0,0,X53/L53) -> 0
A54: Trellis | D54: =V54-C54 -> 0 | F54: N/A | J54: 0 | K54: 0 | L54: 0 | O54: N/A | P54: ='LEVEL 3'!F66 -> 0 | Q54: ='LEVEL 3'!G66 -> 0 | R54: ='LEVEL 3'!H66 -> 0 | S54: ='LEVEL 3'!I66 -> 0 | T54: ='LEVEL 3'!J66 -> 0 | U54: ='LEVEL 3'!K66 -> 0 | X54: =U54-L54 -> 0 | Z54: =IF(L54=0,0,X54/L54) -> 0
A55: Pool Equipment Framing | D55: =V55-C55 -> 0 | F55: N/A | J55: 0 | K55: 0 | L55: 0 | O55: N/A | P55: ='LEVEL 3'!F67 -> 0 | Q55: ='LEVEL 3'!G67 -> 0 | R55: ='LEVEL 3'!H67 -> 0 | S55: ='LEVEL 3'!I67 -> 0 | T55: ='LEVEL 3'!J67 -> 0 | U55: ='LEVEL 3'!K67 -> 0 | X55: =U55-L55 -> 0 | Z55: =IF(L55=0,0,X55/L55) -> 0
A56: Finish Carpentry - Units | D56: =V56-C56 -> 0 | F56: Torrey Pines | G56: Unit | H56: 194 | I56: 3192.5 | J56: 0 | K56: 3192.5 | L56: 619345 | O56: Torrey Pines | P56: ='LEVEL 3'!F68 -> Unit | Q56: ='LEVEL 3'!G68 -> 194 | R56: ='LEVEL 3'!H68 -> 3169.3041 | S56: ='LEVEL 3'!I68 -> 0 | T56: ='LEVEL 3'!J68 -> 3169.3041 | U56: ='LEVEL 3'!K68 -> 614845 | X56: =U56-L56 -> -4500 | Z56: =IF(L56=0,0,X56/L56) -> -0.0072657404
A57: Finish Carpentry - Common | D57: =V57-C57 -> 0 | F57: Torrey Pines | G57: SF | H57: 196289 | I57: 0.8 | J57: 0 | K57: 0.8 | L57: 157031.2 | O57: Torrey Pines | P57: ='LEVEL 3'!F69 -> SF | Q57: ='LEVEL 3'!G69 -> 196289 | R57: ='LEVEL 3'!H69 -> 0.8 | S57: ='LEVEL 3'!I69 -> 0 | T57: ='LEVEL 3'!J69 -> 0.8 | U57: ='LEVEL 3'!K69 -> 157031.2 | X57: =U57-L57 -> 0 | Z57: =IF(L57=0,0,X57/L57) -> 0
A58: Finish Carpentry - Pump House | D58: =V58-C58 -> 0 | O58: Torrey Pines | P58: ='LEVEL 3'!F70 -> LS | Q58: ='LEVEL 3'!G70 -> 1 | R58: ='LEVEL 3'!H70 -> 4500 | S58: ='LEVEL 3'!I70 -> 0 | T58: ='LEVEL 3'!J70 -> 4500 | U58: ='LEVEL 3'!K70 -> 4500
A59: BBQ Trim | D59: =V59-C59 -> 0 | F59: Allowance | G59: LS | H59: 1 | I59: 1200 | J59: 0 | K59: 1200 | L59: 1200 | O59: Allowance | P59: ='LEVEL 3'!F71 -> LS | Q59: ='LEVEL 3'!G71 -> 1 | R59: ='LEVEL 3'!H71 -> 1200 | S59: ='LEVEL 3'!I71 -> 0 | T59: ='LEVEL 3'!J71 -> 1200 | U59: ='LEVEL 3'!K71 -> 1200 | X59: =U59-L59 -> 0 | Z59: =IF(L59=0,0,X59/L59) -> 0
A60: Shutters | D60: =V60-C60 -> 0 | F60: N/A | J60: 0 | K60: 0 | L60: 0 | O60: N/A | P60: ='LEVEL 3'!F72 -> 0 | Q60: ='LEVEL 3'!G72 -> 0 | R60: ='LEVEL 3'!H72 -> 0 | S60: ='LEVEL 3'!I72 -> 0 | T60: ='LEVEL 3'!J72 -> 0 | U60: ='LEVEL 3'!K72 -> 0 | X60: =U60-L60 -> 0 | Z60: =IF(L60=0,0,X60/L60) -> 0
A61: Wood, Plastics, & Composites | C61: 4869453.8 | D61: =V61-C61 -> -65453.08 | M61: =SUM(L48:L60) -> 4804000.7 | V61: ='LEVEL 3'!L59 -> 4804000.7 | X61: =V61-M61 -> 0 | Z61: =IF(M61=0,0,X61/M61) -> 0
A62: Insulation | D62: =V62-C62 -> 0 | F62: Torrey Pines | G62: SF | H62: 196289 | I62: 2.7 | J62: 0 | K62: 2.7 | L62: 529980.3 | O62: Torrey Pines | P62: ='LEVEL 3'!F74 -> SF | Q62: ='LEVEL 3'!G74 -> 196289 | R62: ='LEVEL 3'!H74 -> 2.6872637 | S62: ='LEVEL 3'!I74 -> 0 | T62: ='LEVEL 3'!J74 -> 2.6872637 | U62: ='LEVEL 3'!K74 -> 527480.3 | X62: =U62-L62 -> -2500 | Z62: =IF(L62=0,0,X62/L62) -> -0.0047171565
A63: Insulation - Pump House | D63: =V63-C63 -> 0 | O63: Torrey Pines | P63: ='LEVEL 3'!F75 -> LS | Q63: ='LEVEL 3'!G75 -> 1 | R63: ='LEVEL 3'!H75 -> 2500 | S63: ='LEVEL 3'!I75 -> 0 | T63: ='LEVEL 3'!J75 -> 2500 | U63: ='LEVEL 3'!K75 -> 2500
A64: Roofing | D64: =V64-C64 -> 0 | F64: Torrey Pines | G64: Squares | H64: 503.63 | I64: 603 | J64: 0 | K64: 603 | L64: 303688.89 | O64: Torrey Pines | P64: ='LEVEL 3'!F76 -> Squares | Q64: ='LEVEL 3'!G76 -> 503.63 | R64: ='LEVEL 3'!H76 -> 603 | S64: ='LEVEL 3'!I76 -> 0 | T64: ='LEVEL 3'!J76 -> 603 | U64: ='LEVEL 3'!K76 -> 303688.89 | X64: =U64-L64 -> 0 | Z64: =IF(L64=0,0,X64/L64) -> 0
A65: Cabana Roofing | D65: =V65-C65 -> 0 | F65: N/A | J65: 0 | K65: 0 | L65: 0 | O65: N/A | P65: ='LEVEL 3'!F77 -> 0 | Q65: ='LEVEL 3'!G77 -> 0 | R65: ='LEVEL 3'!H77 -> 0 | S65: ='LEVEL 3'!I77 -> 0 | T65: ='LEVEL 3'!J77 -> 0 | U65: ='LEVEL 3'!K77 -> 0 | X65: =U65-L65 -> 0 | Z65: =IF(L65=0,0,X65/L65) -> 0
A66: Pump House Roofing | D66: =V66-C66 -> 0 | F66: Allowance | G66: LS | H66: 1 | I66: 7500 | J66: 0 | K66: 7500 | L66: 7500 | O66: Allowance | P66: ='LEVEL 3'!F78 -> LS | Q66: ='LEVEL 3'!G78 -> 1 | R66: ='LEVEL 3'!H78 -> 7500 | S66: ='LEVEL 3'!I78 -> 0 | T66: ='LEVEL 3'!J78 -> 7500 | U66: ='LEVEL 3'!K78 -> 7500 | X66: =U66-L66 -> 0 | Z66: =IF(L66=0,0,X66/L66) -> 0
A67: Pool Equipment Roofing | D67: =V67-C67 -> 0 | F67: Allowance | G67: LS | H67: 1 | I67: 7500 | J67: 0 | K67: 7500 | L67: 7500 | O67: Allowance | P67: ='LEVEL 3'!F79 -> LS | Q67: ='LEVEL 3'!G79 -> 1 | R67: ='LEVEL 3'!H79 -> 7500 | S67: ='LEVEL 3'!I79 -> 0 | T67: ='LEVEL 3'!J79 -> 7500 | U67: ='LEVEL 3'!K79 -> 7500 | X67: =U67-L67 -> 0 | Z67: =IF(L67=0,0,X67/L67) -> 0
A68: Trash Enclosure Cover | D68: =V68-C68 -> 0 | F68: Decatur | G68: Count | H68: 4 | I68: 5800 | J68: 0 | K68: 5800 | L68: 23200 | O68: Decatur | P68: ='LEVEL 3'!F80 -> Count | Q68: ='LEVEL 3'!G80 -> 4 | R68: ='LEVEL 3'!H80 -> 5800 | S68: ='LEVEL 3'!I80 -> 0 | T68: ='LEVEL 3'!J80 -> 5800 | U68: ='LEVEL 3'!K80 -> 23200 | X68: =U68-L68 -> 0 | Z68: =IF(L68=0,0,X68/L68) -> 0
A69: Pigeon Proofing | D69: =V69-C69 -> 0 | F69: Torrey Pines | G69: SF | H69: 196289 | I69: 0.08 | J69: 0 | K69: 0.08 | L69: 15703.12 | O69: Torrey Pines | P69: ='LEVEL 3'!F81 -> SF | Q69: ='LEVEL 3'!G81 -> 196289 | R69: ='LEVEL 3'!H81 -> 0.08 | S69: ='LEVEL 3'!I81 -> 0 | T69: ='LEVEL 3'!J81 -> 0.08 | U69: ='LEVEL 3'!K81 -> 15703.12 | X69: =U69-L69 -> 0 | Z69: =IF(L69=0,0,X69/L69) -> 0
A70: Gutters and Downspouts | D70: =V70-C70 -> 0 | F70: Torrey Pines | G70: SF | H70: 196289 | I70: 0.05 | J70: 0 | K70: 0.05 | L70: 9814.45 | O70: Torrey Pines | P70: ='LEVEL 3'!F82 -> SF | Q70: ='LEVEL 3'!G82 -> 196289 | R70: ='LEVEL 3'!H82 -> 0.05 | S70: ='LEVEL 3'!I82 -> 0 | T70: ='LEVEL 3'!J82 -> 0.05 | U70: ='LEVEL 3'!K82 -> 9814.45 | X70: =U70-L70 -> 0 | Z70: =IF(L70=0,0,X70/L70) -> 0
A71: Roof Ladders | D71: =V71-C71 -> 0 | F71: Torrey Pines | G71: Count | H71: 2 | I71: 1550 | J71: 0 | K71: 1550 | L71: 3100 | O71: Torrey Pines | P71: ='LEVEL 3'!F83 -> Count | Q71: ='LEVEL 3'!G83 -> 2 | R71: ='LEVEL 3'!H83 -> 1550 | S71: ='LEVEL 3'!I83 -> 0 | T71: ='LEVEL 3'!J83 -> 1550 | U71: ='LEVEL 3'!K83 -> 3100 | X71: =U71-L71 -> 0 | Z71: =IF(L71=0,0,X71/L71) -> 0
A72: Roof Access Doors | D72: =V72-C72 -> 0 | F72: Torrey Pines | G72: Count | H72: 2 | I72: 2500 | J72: 0 | K72: 2500 | L72: 5000 | O72: Torrey Pines | P72: ='LEVEL 3'!F84 -> Count | Q72: ='LEVEL 3'!G84 -> 2 | R72: ='LEVEL 3'!H84 -> 2500 | S72: ='LEVEL 3'!I84 -> 0 | T72: ='LEVEL 3'!J84 -> 2500 | U72: ='LEVEL 3'!K84 -> 5000 | X72: =U72-L72 -> 0 | Z72: =IF(L72=0,0,X72/L72) -> 0
A73: Roof Winch | D73: =V73-C73 -> 0 | F73: N/A | J73: 0 | K73: 0 | L73: 0 | O73: N/A | P73: ='LEVEL 3'!F85 -> 0 | Q73: ='LEVEL 3'!G85 -> 0 | R73: ='LEVEL 3'!H85 -> 0 | S73: ='LEVEL 3'!I85 -> 0 | T73: ='LEVEL 3'!J85 -> 0 | U73: ='LEVEL 3'!K85 -> 0 | X73: =U73-L73 -> 0 | Z73: =IF(L73=0,0,X73/L73) -> 0
A74: Thermal & Moisture Protection | C74: 898961.39 | D74: =V74-C74 -> 6525.37 | M74: =SUM(L62:L73) -> 905486.76 | V74: ='LEVEL 3'!L73 -> 905486.76 | X74: =V74-M74 -> 0 | Z74: =IF(M74=0,0,X74/M74) -> 0
A75: Entry Doors | D75: =V75-C75 -> 0 | F75: Allowance | G75: Count | H75: 1 | I75: 8000 | J75: 0 | K75: 8000 | L75: 8000 | O75: Allowance | P75: ='LEVEL 3'!F87 -> Count | Q75: ='LEVEL 3'!G87 -> 1 | R75: ='LEVEL 3'!H87 -> 8000 | S75: ='LEVEL 3'!I87 -> 0 | T75: ='LEVEL 3'!J87 -> 8000 | U75: ='LEVEL 3'!K87 -> 8000 | X75: =U75-L75 -> 0 | Z75: =IF(L75=0,0,X75/L75) -> 0
A76: Common Doors | D76: =V76-C76 -> 0 | F76: Included | J76: 0 | K76: 0 | L76: 0 | O76: Included | P76: ='LEVEL 3'!F88 -> 0 | Q76: ='LEVEL 3'!G88 -> 0 | R76: ='LEVEL 3'!H88 -> 0 | S76: ='LEVEL 3'!I88 -> 0 | T76: ='LEVEL 3'!J88 -> 0 | U76: ='LEVEL 3'!K88 -> 0 | X76: =U76-L76 -> 0 | Z76: =IF(L76=0,0,X76/L76) -> 0
A77: Pocket Doors - 3 Panel | D77: =V77-C77 -> 0 | F77: N/A | J77: 0 | K77: 0 | L77: 0 | O77: N/A | P77: ='LEVEL 3'!F89 -> 0 | Q77: ='LEVEL 3'!G89 -> 0 | R77: ='LEVEL 3'!H89 -> 0 | S77: ='LEVEL 3'!I89 -> 0 | T77: ='LEVEL 3'!J89 -> 0 | U77: ='LEVEL 3'!K89 -> 0 | X77: =U77-L77 -> 0 | Z77: =IF(L77=0,0,X77/L77) -> 0
A78: Garage Doors | D78: =V78-C78 -> 0 | F78: N/A | J78: 0 | K78: 0 | L78: 0 | O78: N/A | P78: ='LEVEL 3'!F90 -> 0 | Q78: ='LEVEL 3'!G90 -> 0 | R78: ='LEVEL 3'!H90 -> 0 | S78: ='LEVEL 3'!I90 -> 0 | T78: ='LEVEL 3'!J90 -> 0 | U78: ='LEVEL 3'!K90 -> 0 | X78: =U78-L78 -> 0 | Z78: =IF(L78=0,0,X78/L78) -> 0
A79: Windows and Sliding Glass Doors | D79: =V79-C79 -> 0 | F79: Torrey Pines | G79: Per Unit | H79: 194 | I79: 1157.8947 | J79: 0 | K79: 1157.8947 | L79: 224631.58 | O79: Torrey Pines | P79: ='LEVEL 3'!F91 -> Per Unit | Q79: ='LEVEL 3'!G91 -> 194 | R79: ='LEVEL 3'!H91 -> 1157.8947 | S79: ='LEVEL 3'!I91 -> 0 | T79: ='LEVEL 3'!J91 -> 1157.8947 | U79: ='LEVEL 3'!K91 -> 224631.58 | X79: =U79-L79 -> 0 | Z79: =IF(L79=0,0,X79/L79) -> 0
A80: Windows Repair and Replacement | D80: =V80-C80 -> 0 | F80: Allowance | G80: Per Unit | H80: 194 | I80: 75 | J80: 0 | K80: 75 | L80: 14550 | O80: Allowance | P80: ='LEVEL 3'!F92 -> Per Unit | Q80: ='LEVEL 3'!G92 -> 194 | R80: ='LEVEL 3'!H92 -> 75 | S80: ='LEVEL 3'!I92 -> 0 | T80: ='LEVEL 3'!J92 -> 75 | U80: ='LEVEL 3'!K92 -> 14550 | X80: =U80-L80 -> 0 | Z80: =IF(L80=0,0,X80/L80) -> 0
A81: Pool Equipment Windows | D81: =V81-C81 -> 0 | F81: N/A | J81: 0 | K81: 0 | L81: 0 | O81: N/A | P81: ='LEVEL 3'!F93 -> 0 | Q81: ='LEVEL 3'!G93 -> 0 | R81: ='LEVEL 3'!H93 -> 0 | S81: ='LEVEL 3'!I93 -> 0 | T81: ='LEVEL 3'!J93 -> 0 | U81: ='LEVEL 3'!K93 -> 0 | X81: =U81-L81 -> 0 | Z81: =IF(L81=0,0,X81/L81) -> 0
A82: Pool Glass Walls | D82: =V82-C82 -> 0 | F82: N/A | J82: 0 | K82: 0 | L82: 0 | O82: N/A | P82: ='LEVEL 3'!F94 -> 0 | Q82: ='LEVEL 3'!G94 -> 0 | R82: ='LEVEL 3'!H94 -> 0 | S82: ='LEVEL 3'!I94 -> 0 | T82: ='LEVEL 3'!J94 -> 0 | U82: ='LEVEL 3'!K94 -> 0 | X82: =U82-L82 -> 0 | Z82: =IF(L82=0,0,X82/L82) -> 0
A83: Fixed Glass | D83: =V83-C83 -> 0 | F83: N/A | J83: 0 | K83: 0 | L83: 0 | O83: N/A | P83: ='LEVEL 3'!F95 -> 0 | Q83: ='LEVEL 3'!G95 -> 0 | R83: ='LEVEL 3'!H95 -> 0 | S83: ='LEVEL 3'!I95 -> 0 | T83: ='LEVEL 3'!J95 -> 0 | U83: ='LEVEL 3'!K95 -> 0 | X83: =U83-L83 -> 0 | Z83: =IF(L83=0,0,X83/L83) -> 0
A84: Mirrors - LED | D84: =V84-C84 -> 0 | F84: N/A | J84: 0 | K84: 0 | L84: 0 | O84: N/A | P84: ='LEVEL 3'!F96 -> 0 | Q84: ='LEVEL 3'!G96 -> 0 | R84: ='LEVEL 3'!H96 -> 0 | S84: ='LEVEL 3'!I96 -> 0 | T84: ='LEVEL 3'!J96 -> 0 | U84: ='LEVEL 3'!K96 -> 0 | X84: =U84-L84 -> 0 | Z84: =IF(L84=0,0,X84/L84) -> 0
A85: Mirrors - LED Install | D85: =V85-C85 -> 0 | F85: N/A | J85: 0 | K85: 0 | L85: 0 | O85: N/A | P85: ='LEVEL 3'!F97 -> 0 | Q85: ='LEVEL 3'!G97 -> 0 | R85: ='LEVEL 3'!H97 -> 0 | S85: ='LEVEL 3'!I97 -> 0 | T85: ='LEVEL 3'!J97 -> 0 | U85: ='LEVEL 3'!K97 -> 0 | X85: =U85-L85 -> 0 | Z85: =IF(L85=0,0,X85/L85) -> 0
A86: Mirrors - Framed | D86: =V86-C86 -> 0 | F86: N/A | J86: 0 | K86: 0 | L86: 0 | O86: N/A | P86: ='LEVEL 3'!F98 -> 0 | Q86: ='LEVEL 3'!G98 -> 0 | R86: ='LEVEL 3'!H98 -> 0 | S86: ='LEVEL 3'!I98 -> 0 | T86: ='LEVEL 3'!J98 -> 0 | U86: ='LEVEL 3'!K98 -> 0 | X86: =U86-L86 -> 0 | Z86: =IF(L86=0,0,X86/L86) -> 0
A87: Mirrors - Polished Edges (Units) | D87: =V87-C87 -> 0 | F87: Pebble | G87: Unit | H87: 194 | I87: 162 | J87: 0 | K87: 162 | L87: 31428 | O87: Pebble | P87: ='LEVEL 3'!F99 -> Unit | Q87: ='LEVEL 3'!G99 -> 194 | R87: ='LEVEL 3'!H99 -> 162 | S87: ='LEVEL 3'!I99 -> 0 | T87: ='LEVEL 3'!J99 -> 162 | U87: ='LEVEL 3'!K99 -> 31428 | X87: =U87-L87 -> 0 | Z87: =IF(L87=0,0,X87/L87) -> 0
A88: Mirrors - Polished Edges (Restrooms) | D88: =V88-C88 -> 0 | F88: Allowance | G88: Count | H88: 2 | I88: 250 | J88: 0 | K88: 250 | L88: 500 | O88: Allowance | P88: ='LEVEL 3'!F100 -> Count | Q88: ='LEVEL 3'!G100 -> 2 | R88: ='LEVEL 3'!H100 -> 250 | S88: ='LEVEL 3'!I100 -> 0 | T88: ='LEVEL 3'!J100 -> 250 | U88: ='LEVEL 3'!K100 -> 500 | X88: =U88-L88 -> 0 | Z88: =IF(L88=0,0,X88/L88) -> 0
A89: Openings | C89: 336446.8 | D89: =V89-C89 -> -57337.221 | M89: =SUM(L75:L88) -> 279109.58 | V89: ='LEVEL 3'!L86 -> 279109.58 | X89: =V89-M89 -> 0 | Z89: =IF(M89=0,0,X89/M89) -> 0
A90: Cost Prep Labor | D90: =V90-C90 -> 0 | F90: N/A | J90: 0 | K90: 0 | L90: 0 | O90: N/A | P90: 0 | Q90: 0 | R90: 0 | S90: 0 | T90: 0 | U90: 0 | X90: =U90-L90 -> 0 | Z90: =IF(L90=0,0,X90/L90) -> 0
A91: Cost Prep Mat | D91: =V91-C91 -> 0 | F91: Allowance | G91: LS | H91: 1 | I91: 10000 | J91: 0 | K91: 10000 | L91: 10000 | O91: N/A | P91: ='LEVEL 3'!F102 -> LS | Q91: ='LEVEL 3'!G102 -> 1 | R91: ='LEVEL 3'!H102 -> 10000 | S91: ='LEVEL 3'!I102 -> 0 | T91: ='LEVEL 3'!J102 -> 10000 | U91: ='LEVEL 3'!K102 -> 10000 | X91: =U91-L91 -> 0 | Z91: =IF(L91=0,0,X91/L91) -> 0
A92: Clean Up - Final | D92: =V92-C92 -> 0 | F92: Torrey Pines | G92: SF | H92: 196289 | I92: 0.85 | J92: 0 | K92: 0.85 | L92: 166845.65 | O92: Torrey Pines | P92: ='LEVEL 3'!F103 -> SF | Q92: ='LEVEL 3'!G103 -> 196289 | R92: ='LEVEL 3'!H103 -> 0.85 | S92: ='LEVEL 3'!I103 -> 0 | T92: ='LEVEL 3'!J103 -> 0.85 | U92: ='LEVEL 3'!K103 -> 166845.65 | X92: =U92-L92 -> 0 | Z92: =IF(L92=0,0,X92/L92) -> 0
A93: Clean Up - During Construction | D93: =V93-C93 -> 0 | F93: Allowance | G93: LS | H93: 1 | I93: 50000 | J93: 0 | K93: 50000 | L93: 50000 | O93: Allowance | P93: ='LEVEL 3'!F104 -> LS | Q93: ='LEVEL 3'!G104 -> 1 | R93: ='LEVEL 3'!H104 -> 50000 | S93: ='LEVEL 3'!I104 -> 0 | T93: ='LEVEL 3'!J104 -> 50000 | U93: ='LEVEL 3'!K104 -> 50000 | X93: =U93-L93 -> 0 | Z93: =IF(L93=0,0,X93/L93) -> 0
A94: Dumpsters | D94: =V94-C94 -> 0 | F94: Allowance | G94: Unit | H94: 194 | I94: 79 | J94: 0 | K94: 79 | L94: 15326 | O94: Allowance | P94: ='LEVEL 3'!F105 -> Unit | Q94: ='LEVEL 3'!G105 -> 194 | R94: ='LEVEL 3'!H105 -> 79 | S94: ='LEVEL 3'!I105 -> 0 | T94: ='LEVEL 3'!J105 -> 79 | U94: ='LEVEL 3'!K105 -> 15326 | X94: =U94-L94 -> 0 | Z94: =IF(L94=0,0,X94/L94) -> 0
A95: Clean Up - Hauling Exterior | D95: =V95-C95 -> 0 | F95: Allowance | G95: LS | H95: 1 | I95: 10000 | J95: 0 | K95: 10000 | L95: 10000 | O95: N/A | P95: ='LEVEL 3'!F106 -> LS | Q95: ='LEVEL 3'!G106 -> 1 | R95: ='LEVEL 3'!H106 -> 10000 | S95: ='LEVEL 3'!I106 -> 0 | T95: ='LEVEL 3'!J106 -> 10000 | U95: ='LEVEL 3'!K106 -> 10000 | X95: =U95-L95 -> 0 | Z95: =IF(L95=0,0,X95/L95) -> 0
A96: Stucco | D96: =V96-C96 -> 0 | F96: Torrey Pines | G96: SY | H96: 11824 | I96: 40.82 | J96: 0 | K96: 40.82 | L96: 482655.68 | O96: Torrey Pines | P96: ='LEVEL 3'!F107 -> SY | Q96: ='LEVEL 3'!G107 -> 11824 | R96: ='LEVEL 3'!H107 -> 40.82 | S96: ='LEVEL 3'!I107 -> 0 | T96: ='LEVEL 3'!J107 -> 40.82 | U96: ='LEVEL 3'!K107 -> 482655.68 | X96: =U96-L96 -> 0 | Z96: =IF(L96=0,0,X96/L96) -> 0
A97: Stucco - Pump House | D97: =V97-C97 -> 0 | F97: Allowance | G97: LS | H97: 1 | I97: 6000 | J97: 0 | K97: 6000 | L97: 6000 | O97: Allowance | P97: ='LEVEL 3'!F108 -> LS | Q97: ='LEVEL 3'!G108 -> 1 | R97: ='LEVEL 3'!H108 -> 6000 | S97: ='LEVEL 3'!I108 -> 0 | T97: ='LEVEL 3'!J108 -> 6000 | U97: ='LEVEL 3'!K108 -> 6000 | X97: =U97-L97 -> 0 | Z97: =IF(L97=0,0,X97/L97) -> 0
A98: Stucco - Walls | D98: =V98-C98 -> 0 | F98: N/A | J98: 0 | K98: 0 | L98: 0 | O98: N/A | P98: ='LEVEL 3'!F109 -> 0 | Q98: ='LEVEL 3'!G109 -> 0 | R98: ='LEVEL 3'!H109 -> 0 | S98: ='LEVEL 3'!I109 -> 0 | T98: ='LEVEL 3'!J109 -> 0 | U98: ='LEVEL 3'!K109 -> 0 | X98: =U98-L98 -> 0 | Z98: =IF(L98=0,0,X98/L98) -> 0
A99: Stucco - Pool Area | D99: =V99-C99 -> 0 | F99: Allowance | G99: LS | H99: 1 | I99: 2000 | J99: 0 | K99: 2000 | L99: 2000 | O99: Allowance | P99: ='LEVEL 3'!F110 -> LS | Q99: ='LEVEL 3'!G110 -> 1 | R99: ='LEVEL 3'!H110 -> 2000 | S99: ='LEVEL 3'!I110 -> 0 | T99: ='LEVEL 3'!J110 -> 2000 | U99: ='LEVEL 3'!K110 -> 2000 | X99: =U99-L99 -> 0 | Z99: =IF(L99=0,0,X99/L99) -> 0
A100: Stucco - Cabana | D100: =V100-C100 -> 0 | F100: N/A | J100: 0 | K100: 0 | L100: 0 | O100: N/A | P100: ='LEVEL 3'!F111 -> 0 | Q100: ='LEVEL 3'!G111 -> 0 | R100: ='LEVEL 3'!H111 -> 0 | S100: ='LEVEL 3'!I111 -> 0 | T100: ='LEVEL 3'!J111 -> 0 | U100: ='LEVEL 3'!K111 -> 0 | X100: =U100-L100 -> 0 | Z100: =IF(L100=0,0,X100/L100) -> 0
...

Sheet Comparison to Other
H1: SENIOR / AFFORABLE PROJECTS
C2: Bruner Senior | H2: South Nellis | I2: Torrey Pines | J2: Decatur | K2: Pebble
E3: Units | F3: ='LEVEL 3'!E8 -> 194 | H3: 50 | I3: 190 | J3: 276 | K3: 195
A4: Budget | E4: GSF | F4: ='LEVEL 3'!B8 -> 196289 | H4: 34388 | I4: 188825 | J4: 258464 | K4: 184108
A5: Proposal/Contract | E5: Acres | F5: ='LEVEL 3'!B9 -> 4.9 | H5: 1.3 | I5: 5 | J5: 9.45 | K5: 5
E6: Site SF | F6: =F5*43560 -> 213444 | H6: =H5*43560 -> 56628 | I6: =I5*43560 -> 217800 | J6: 411642 | K6: 217800
A7: Description | B7: % | C7: Cost | D7: UOM | E7: U | F7: PU | H7: PU | I7: PU | J7: PU | K7: PU
A8: Framing | B8: =C8/$C$29 -> 0.11971688 | C8: =VLOOKUP(A8,'LEVEL 3'!$A$21:$K$330,11,FALSE) -> 4008924.5 | D8: SF | E8: =$F$4 -> 196289 | F8: =C8/E8 -> 20.423582 | H8: 20.075375 | I8: 19.921525 | J8: 22.888453 | K8: =3500080/$K$4 -> 19.011015
A9: HVAC Standard | B9: =C9/$C$29 -> 0.061570769 | C9: =VLOOKUP(A9,'LEVEL 3'!$A$21:$K$330,11,FALSE) -> 2061802.6 | D9: Unit | E9: =$F$3 -> 194 | F9: =C9/E9 -> 10627.848 | H9: 10148.68 | I9: 9739.2737 | J9: 10104.674 | K9: =1797559/$K$3 -> 9218.2513
A10: Electrical | B10: =C10/$C$29 -> 0.057054555 | C10: =VLOOKUP(A10,'LEVEL 3'!$A$21:$K$330,11,FALSE) -> 1910569.4 | D10: SF (Bldg) | E10: =$F$4 -> 196289 | F10: =C10/E10 -> 9.7334513 | H10: 12.504362 | I10: 9.2699537 | J10: 10.176018 | K10: =2234019.82/$K$4 -> 12.13429
A11: Drywall | B11: =C11/$C$29 -> 0.046906301 | C11: =VLOOKUP(A11,'LEVEL 3'!$A$21:$K$330,11,FALSE) -> 1570737.8 | D11: SF (Bldg) | E11: =$F$4 -> 196289 | F11: =C11/E11 -> 8.0021691 | H11: 7.7384864 | I11: 8.0157077 | J11: 7.3585311 | K11: =1487010/$K$4 -> 8.0768353
A12: 1 Bathroom Unit | B12: =C12/$C$29 -> 0.060952693 | C12: =VLOOKUP(A12,'LEVEL 3'!$A$21:$K$330,11,FALSE) -> 2041105.3 | D12: 1 Bath Unit | E12: =F3 -> 194 | F12: =C12/E12 -> 10521.161 | H12: 10196.24 | I12: 10526.311 | J12: 11042.514 | K12: =1959791/$K$3 -> 10050.21
A13: Appliances | B13: =C13/$C$29 -> 0.018547372 | C13: =VLOOKUP(A13,'LEVEL 3'!$A$21:$K$330,11,FALSE) -> 621090.5 | D13: Unit | E13: =$F$3 -> 194 | F13: =C13/E13 -> 3201.4974 | H13: 4007.85 | I13: 2926 | J13: 3454.4783 | K13: 3201.4974
A14: Sprinkler System | B14: =C14/$C$29 -> 0.014361161 | C14: =VLOOKUP(A14,'LEVEL 3'!$A$21:$K$330,11,FALSE) -> 480908.05 | D14: SF (Bldg) | E14: =$F$4 -> 196289 | F14: =C14/E14 -> 2.45 | H14: 3.2147842 | I14: 2.453065 | J14: =644184/$J$4 -> 2.4923548 | K14: 2.4480196
A15: Cabinets Units | B15: =C15/$C$29 -> 0.018237443 | C15: =VLOOKUP(A15,'LEVEL 3'!$A$21:$K$330,11,FALSE) -> 610712 | D15: Unit | E15: =$F$3 -> 194 | F15: =C15/E15 -> 3148 | H15: 1330 | I15: 3778.0053 | J15: 3651.0797 | K15: =607178/$K$3 -> 3113.7333
A16: Windows and Sliding Glass Doors | B16: =C16/$C$29 -> 0.0067080811 | C16: =VLOOKUP(A16,'LEVEL 3'!$A$21:$K$330,11,FALSE) -> 224631.58 | D16: Unit | E16: =$F$3 -> 194 | F16: =C16/E16 -> 1157.8947 | H16: 1647.191 | I16: =220000/I3 -> 1157.8947 | J16: =388836/$J$3 -> 1408.8261 | K16: =144157.93/$K$3 -> 739.27144
A17: Finish Carpentry - Units | B17: =C17/$C$29 -> 0.018360865 | C17: =VLOOKUP(A17,'LEVEL 3'!$A$21:$K$330,11,FALSE) -> 614845 | D17: Unit | E17: =$F$3 -> 194 | F17: =C17/E17 -> 3169.3041 | H17: 3036 | I17: 3192.5 | J17: 2901.2899 | K17: 3081.2308
A18: Slabs | B18: =C18/$C$29 -> 0.017230201 | C18: =VLOOKUP(A18,'LEVEL 3'!$A$21:$K$330,11,FALSE) -> 576982.78 | D18: SF (Slab) | E18: ='LEVEL 3'!$O$2 -> 48122 | F18: =C18/E18 -> 11.99 | H18: 16.778816 | I18: 11.989967 | J18: 15.882903 | K18: 16.060895
A19: Insulation | B19: =C19/$C$29 -> 0.015751929 | C19: =VLOOKUP(A19,'LEVEL 3'!$A$21:$K$330,11,FALSE) -> 527480.3 | D19: SF (Bldg) | E19: =$F$4 -> 196289 | F19: =C19/E19 -> 2.6872637 | H19: 2.5423113 | I19: 2.6983715 | J19: 2.2715182 | K19: =460480/$K$4 -> 2.5011406
A20: Fire Alarm / Two Way Comm AOR | B20: =C20/$C$29 -> 0.0094103597 | C20: =VLOOKUP(A20,'LEVEL 3'!$A$21:$K$330,11,FALSE) -> 315122 | D20: Unit | E20: =$F$3 -> 194 | F20: =C20/E20 -> 1624.3402 | H20: =2.27404908689078*H4/H3 -> 1564 | I20: 1662.7789 | J20: 2101 | K20: 1466.6667
A21: Site Landscaping | B21: =C21/$C$29 -> 0.020004507 | C21: =VLOOKUP(A21,'LEVEL 3'!$A$21:$K$330,11,FALSE) -> 669885.17 | D21: SF | E21: ='LEVEL 3'!G256 -> 39274 | F21: =C21/$E$21 -> 17.056708 | H21: 10.527712 | I21: 15.584553 | J21: 16.652199 | K21: 21.389001
A22: Stucco | B22: =C22/$C$29 -> 0.01441335 | C22: =VLOOKUP(A22,'LEVEL 3'!$A$21:$K$330,11,FALSE) -> 482655.68 | D22: SY (Bldg) | E22: ='LEVEL 3'!$G$107 -> 11824 | F22: =C22/E22 -> 40.82 | H22: 39.371016 | I22: 40.818674 | J22: 42.234692 | K22: 46.688382
A23: Counter Tops Units | B23: =C23/$C$29 -> 0.0090816491 | C23: =VLOOKUP(A23,'LEVEL 3'!$A$21:$K$330,11,FALSE) -> 304114.56 | D23: Unit | E23: =$F$3 -> 194 | F23: =C23/E23 -> 1567.6008 | H23: 754 | I23: 1628.8895 | J23: 1551.7283 | K23: 1600.2513
A24: Lightweight Concrete | B24: =C24/$C$29 -> 0.012927964 | C24: =VLOOKUP(A24,'LEVEL 3'!$A$21:$K$330,11,FALSE) -> 432915 | D24: SF (No Slab) | E24: ='LEVEL 3'!$G$33 -> 147250 | F24: =C24/E24 -> 2.94 | H24: 2.9324031 | I24: 2.9421304 | J24: 1.2965678 | K24: 1.1
A25: Pools and Spas | B25: =C25/$C$29 -> 0.007316335 | C25: =VLOOKUP(A25,'LEVEL 3'!$A$21:$K$330,11,FALSE) -> 245000 | D25: LS | E25: 1 | F25: =C25/E25 -> 245000 | H25: N/A | I25: 245000 | J25: 228710 | K25: 208310
A26: Painting | B26: =C26/$C$29 -> 0.010755662 | C26: =VLOOKUP(A26,'LEVEL 3'!$A$21:$K$330,11,FALSE) -> 360171.76 | D26: SF (Bldg) | E26: =$F$4 -> 196289 | F26: =C26/E26 -> 1.8349055 | H26: 2.0533616 | I26: 1.8370925 | J26: 2.0978638 | K26: =355696/$K$4 -> 1.9319964
A27: Roofing | B27: =C27/$C$29 -> 0.0090689374 | C27: =VLOOKUP(A27,'LEVEL 3'!$A$21:$K$330,11,FALSE) -> 303688.89 | D27: Square | E27: ='LEVEL 3'!$O$10 -> 503.63 | F27: =C27/E27 -> 603 | H27: 491.39689 | I27: 603.3984 | J27: 598.38652 | K27: 535.7424
A28: Fire Pump | B28: =C28/$C$29 -> 0.0039717247 | C28: =VLOOKUP(A28,'LEVEL 3'!$A$21:$K$330,11,FALSE) -> 133000 | D28: Unit | E28: =$F$3 -> 194 | F28: =C28/E28 -> 685.56701 | H28: N/A | I28: =133300/$I$3 -> 701.57895 | J28: =113160/$J$3 -> 410 | K28: =120800/$K$3 -> 619.48718
A29: Total Hard Costs | C29: ='LEVEL 3'!$L$335 -> 33486712 | D29: GSF | E29: =$F$4 -> 196289 | F29: =C29/E29 -> 170.59902

Sheet Sheet3
A2: Carports Budget
A4: 116 Total Carports
A6: Item | B6: Source | C6: Unit | D6: Qty | E6: Unit Cost | F6: Total
A7: Carport Non Solar | B7: Pebble | C7: EA | D7: =130-D8 -> 91 | E7: 2064 | F7: =D7*E7 -> 187824
A8: Carport Solar (30% of Total Spaces) | B8: Pebble | C8: EA | D8: =130*0.3 -> 39 | E8: 2623 | F8: =D8*E8 -> 102297
A9: Hard Dig (50% * Unit Cost) | B9: Pebble | C9: EA | D9: =SUM($D$7:$D$8)/2 -> 65 | E9: 250 | F9: =D9*E9 -> 16250
A10: Spoil Removal ($75 per Space) | B10: Pebble | C10: EA | D10: 130 | E10: 75 | F10: =D10*E10 -> 9750
A11: Permit | B11: Pebble | C11: LS | D11: 1 | E11: 1815 | F11: =D11*E11 -> 1815
A12: QAA | B12: Pebble | C12: LS | D12: 1 | E12: 2500 | F12: =D12*E12 -> 2500
F13: =SUM(F7:F12) -> 320436

Sheet Comparison to Previous (Match)
A1: BRUNER SENIOR | C1: LEVEL 1 | L1: LEVEL 2
C2: Project Details | H2: Unit Breakdown | L2: Project Details | Q2: Unit Breakdown
C3: Project | D3: Bruner Senior | H3: Unit Type | I3: Number | J3: % | L3: Project | M3: Bruner Senior | Q3: Unit Type | R3: Number | S3: %
C4: Budget Level | D4: Level 1 | H4: Studios | I4: 0 | J4: =I4/$I$9 -> 0 | L4: Budget Level | M4: Level 2 | Q4: Studios | R4: 0 | S4: =R4/$R$9 -> 0
C5: Product | D5: Senior | H5: 1 Br - 1 Ba | I5: 126 | J5: =I5/$I$9 -> 0.64948454 | L5: Product | M5: Senior | Q5: 1 Br - 1 Ba | R5: 126 | S5: =R5/$R$9 -> 0.64948454
C6: Start Date | D6: 45809 | H6: 2 Br - 1 Ba | I6: 68 | J6: =I6/$I$9 -> 0.35051546 | L6: Start Date | M6: 45809 | Q6: 2 Br - 1 Ba | R6: 68 | S6: =R6/$R$9 -> 0.35051546
C7: Timeline | D7: 20 | H7: 2 Br - 2 Ba | I7: 0 | J7: =I7/$I$9 -> 0 | L7: Timeline | M7: 20 | Q7: 2 Br - 2 Ba | R7: 0 | S7: =R7/$R$9 -> 0
C8: Floors | D8: 4 | H8: 3 Br - 2 Ba | I8: 0 | J8: =I8/$I$9 -> 0 | L8: Floors | M8: 4 | Q8: 3 Br - 2 Ba | R8: 0 | S8: =R8/$R$9 -> 0
C9: Bldg. SF | D9: 196333 | H9: Totals | I9: 194 | J9: =I9/$I$9 -> 1 | L9: Bldg. SF | M9: 196289 | Q9: Totals | R9: =SUM(R4:R8) -> 194 | S9: =R9/$R$9 -> 1
C10: Acres | D10: 4.9 | H10: Parking | L10: Acres | M10: 4.9 | Q10: Parking
C11: Site SF | D11: =D10*43560 -> 213444 | H11: Garage Parking | J11: 0 | L11: Site SF | M11: =M10*43560 -> 213444 | Q11: Cover Parking | S11: 127
C12: Buildings | D12: 1 | H12: Cover Parking | J12: 116 | L12: Buildings | M12: 1 | Q12: Cover Acc. Parking | S12: 3
H13: Open Parking | J13: 83 | Q13: Open Parking | S13: 45
H14: Accessible Parking | J14: 6 | N14: Net Change | Q14: Accessible Parking | S14: 11
C15: TOTAL COST | D15: =J330 -> 33916915 | H15: Private Garages | J15: 0 | L15: TOTAL COST | M15: =S330 -> 33460484 | N15: =M15-D15 -> -456430.63 | O15: =N15/D15 -> -0.013457316 | Q15: Waiver | S15: 8
C16: PER UNIT | D16: =D15/I9 -> 174829.46 | H16: Total Parking Provided | J16: =SUM(J11:J15) -> 205 | L16: PER UNIT | M16: =M15/R9 -> 172476.72 | N16: =M16-D16 -> -2352.7352 | Q16: Total Parking Provided | S16: =SUM(S11:S15) -> 194
C17: PER GSF | D17: =D15/D9 -> 172.75198 | H17: Parking Ratio | J17: =SUM(J11:J14)/I9 -> 1.056701 | L17: PER GSF | M17: =M15/M9 -> 170.46541 | N17: =M17-D17 -> -2.2865751 | Q17: Parking Ratio | S17: =SUM(S11:S14)/R9 -> 0.95876289 | U17: Conditions | W17: Conditions
U18: 50000 | W18: 0.05
A19: Description | C19: Source | D19: UOM | E19: QTY | F19: U.P. | G19: % | H19: Total U.P. | I19: Sub Total | J19: Total | L19: Source | M19: UOM | N19: QTY | O19: U.P. | P19: % | Q19: Total U.P. | R19: Sub Total | S19: Total | U19: PV$ | W19: PV% | Y19: Notes
A20: General Requirements | J20: 1700096 | S20: ='LEVEL 2 (Match)'!L20 -> 1692096 | U20: =S20-J20 -> -8000 | W20: =IF(J20=0,0,U20/J20) -> -0.0047056166
A21: General Requirement | D21: Mo | E21: 20 | F21: 83690.146 | G21: 0 | H21: 83690.146 | I21: 1673802.9 | M21: ='LEVEL 3'!F21 -> Mo | N21: ='LEVEL 3'!G21 -> 20 | O21: ='LEVEL 2 (Match)'!H21 -> 84604.8 | P21: ='LEVEL 2 (Match)'!I21 -> 0 | Q21: ='LEVEL 2 (Match)'!J21 -> 84604.8 | R21: ='LEVEL 2 (Match)'!K21 -> 1692096 | U21: =R21-I21 -> 18293.075 | W21: =U21/I21 -> 0.010929049
A22: Existing Conditions | J22: 3500 | S22: ='LEVEL 3'!L22 -> 3500 | U22: =S22-J22 -> 0 | W22: =IF(J22=0,0,U22/J22) -> 0
A23: Potholing | C23: Allowance | E23: 1 | F23: 3500 | G23: 0 | H23: 3500 | I23: 3500 | L23: Allowance | M23: ='LEVEL 3'!F23 -> 0 | N23: ='LEVEL 3'!G23 -> 1 | O23: ='LEVEL 3'!H23 -> 3500 | P23: ='LEVEL 3'!I23 -> 0 | Q23: ='LEVEL 3'!J23 -> 3500 | R23: ='LEVEL 3'!K23 -> 3500 | U23: =R23-I23 -> 0 | W23: =IF(I23=0,0,U23/I23) -> 0
A24: Concrete | J24: 1159855 | S24: ='LEVEL 3'!L24 -> 1089279.8 | U24: =S24-J24 -> -70575.18 | W24: =IF(J24=0,0,U24/J24) -> -0.060848278
A25: Slabs | C25: Torrey Pines | D25: SF | E25: 47527 | F25: =H25/(1+G25) -> 11.990476 | G25: 0.05 | H25: 12.59 | I25: 598341.17 | L25: Torrey Pines | M25: ='LEVEL 3'!F25 -> SF | N25: ='LEVEL 3'!G25 -> 48122 | O25: ='LEVEL 3'!H25 -> 11.99 | P25: ='LEVEL 3'!I25 -> 0 | Q25: ='LEVEL 3'!J25 -> 11.99 | R25: ='LEVEL 3'!K25 -> 576982.78 | U25: =R25-I25 -> -21358.39 | W25: =IF(I25=0,0,U25/I25) -> -0.035696006
A26: Deepened Footings | C26: N/A | H26: 0 | I26: 0 | L26: N/A | M26: ='LEVEL 3'!F26 -> 0 | N26: ='LEVEL 3'!G26 -> 0 | O26: ='LEVEL 3'!H26 -> 0 | P26: ='LEVEL 3'!I26 -> 0 | Q26: ='LEVEL 3'!J26 -> 0 | R26: ='LEVEL 3'!K26 -> 0 | U26: =R26-I26 -> 0 | W26: =IF(I26=0,0,U26/I26) -> 0
A27: Concrete Slab Repairs | C27: Allowance | D27: LS | E27: 1 | F27: 2500 | G27: 0 | H27: 2500 | I27: 2500 | L27: Allowance | M27: ='LEVEL 3'!F27 -> LS | N27: ='LEVEL 3'!G27 -> 1 | O27: ='LEVEL 3'!H27 -> 2500 | P27: ='LEVEL 3'!I27 -> 0 | Q27: ='LEVEL 3'!J27 -> 2500 | R27: ='LEVEL 3'!K27 -> 2500 | U27: =R27-I27 -> 0 | W27: =IF(I27=0,0,U27/I27) -> 0
A28: Pump House Concrete | C28: Torrey Pines | D28: SF | E28: 300 | F28: 12.62 | H28: 12.62 | I28: 3786 | L28: Torrey Pines | M28: ='LEVEL 3'!F28 -> SF | N28: ='LEVEL 3'!G28 -> 300 | O28: ='LEVEL 3'!H28 -> 11.99 | P28: ='LEVEL 3'!I28 -> 0 | Q28: ='LEVEL 3'!J28 -> 11.99 | R28: ='LEVEL 3'!K28 -> 3597 | U28: =R28-I28 -> -189 | W28: =IF(I28=0,0,U28/I28) -> -0.049920761
A29: Trash Enclosure Concrete | C29: Russell IV | D29: Count | E29: 4 | F29: 2698 | G29: 0 | H29: 2698 | I29: 10792 | L29: Allowance | M29: ='LEVEL 3'!F29 -> SF | N29: ='LEVEL 3'!G29 -> 920 | O29: ='LEVEL 3'!H29 -> 11.99 | P29: ='LEVEL 3'!I29 -> 0 | Q29: ='LEVEL 3'!J29 -> 11.99 | R29: ='LEVEL 3'!K29 -> 11030.8 | U29: =R29-I29 -> 238.8 | W29: =IF(I29=0,0,U29/I29) -> 0.022127502
A30: Pool Area Shower Concrete | C30: Torrey Pines | D30: LS | E30: 1 | F30: 2500 | G30: 0 | H30: 2500 | I30: 2500 | L30: Torrey Pines | M30: ='LEVEL 3'!F30 -> LS | N30: ='LEVEL 3'!G30 -> 1 | O30: ='LEVEL 3'!H30 -> 2500 | P30: ='LEVEL 3'!I30 -> 0 | Q30: ='LEVEL 3'!J30 -> 2500 | R30: ='LEVEL 3'!K30 -> 2500 | U30: =R30-I30 -> 0 | W30: =IF(I30=0,0,U30/I30) -> 0
A31: Cabana Concrete | C31: N/A | H31: 0 | I31: 0 | L31: N/A | M31: ='LEVEL 3'!F31 -> 0 | N31: ='LEVEL 3'!G31 -> 0 | O31: ='LEVEL 3'!H31 -> 0 | P31: ='LEVEL 3'!I31 -> 0 | Q31: ='LEVEL 3'!J31 -> 0 | R31: ='LEVEL 3'!K31 -> 0 | U31: =R31-I31 -> 0 | W31: =IF(I31=0,0,U31/I31) -> 0
A32: Pool Equipment Foundation | C32: N/A | H32: 0 | I32: 0 | L32: N/A | M32: ='LEVEL 3'!F32 -> 0 | N32: ='LEVEL 3'!G32 -> 0 | O32: ='LEVEL 3'!H32 -> 0 | P32: ='LEVEL 3'!I32 -> 0 | Q32: ='LEVEL 3'!J32 -> 0 | R32: ='LEVEL 3'!K32 -> 0 | U32: =R32-I32 -> 0 | W32: =IF(I32=0,0,U32/I32) -> 0
A33: Lightweight Concrete | C33: Torrey Pines | D33: SF | E33: 147250 | F33: 2.94 | G33: 0.1 | H33: 323 | I33: 476205.69 | L33: Torrey Pines | M33: ='LEVEL 3'!F33 -> SF | N33: ='LEVEL 3'!G33 -> 147250 | O33: ='LEVEL 3'!H33 -> 2.94 | P33: ='LEVEL 3'!I33 -> 0 | Q33: ='LEVEL 3'!J33 -> 2.94 | R33: ='LEVEL 3'!K33 -> 432915 | U33: =R33-I33 -> -43290.69 | W33: =IF(I33=0,0,U33/I33) -> -0.090907545
A34: Deck Concrete | C34: Torrey Pines | D34: SF | E34: 3024 | F34: 19.76 | G34: 0.1 | H34: 21.74 | I34: 65729.66 | L34: Torrey Pines | M34: ='LEVEL 3'!F34 -> SF | N34: ='LEVEL 3'!G34 -> 3024 | O34: ='LEVEL 3'!H34 -> 19.76 | P34: ='LEVEL 3'!I34 -> 0 | Q34: ='LEVEL 3'!J34 -> 19.76 | R34: ='LEVEL 3'!K34 -> 59754.24 | U34: =R34-I34 -> -5975.42 | W34: =IF(I34=0,0,U34/I34) -> -0.090909036
A35: Parking Garage | J35: 0 | S35: ='LEVEL 3'!L35 -> 0 | U35: =S35-J35 -> 0 | W35: =IF(J35=0,0,U35/J35) -> 0
A36: Parking Garage Structure | C36: N/A | H36: 0 | I36: 0 | L36: N/A | M36: ='LEVEL 3'!F36 -> 0 | N36: ='LEVEL 3'!G36 -> 0 | O36: ='LEVEL 3'!H36 -> 0 | P36: ='LEVEL 3'!I36 -> 0 | Q36: ='LEVEL 3'!J36 -> 0 | R36: ='LEVEL 3'!K36 -> 0 | U36: =R36-I36 -> 0 | W36: =IF(I36=0,0,U36/I36) -> 0
A37: Core Slab Precast Concrete | C37: N/A | H37: 0 | I37: 0 | L37: N/A | M37: ='LEVEL 3'!F37 -> 0 | N37: ='LEVEL 3'!G37 -> 0 | O37: ='LEVEL 3'!H37 -> 0 | P37: ='LEVEL 3'!I37 -> 0 | Q37: ='LEVEL 3'!J37 -> 0 | R37: ='LEVEL 3'!K37 -> 0 | U37: =R37-I37 -> 0 | W37: =IF(I37=0,0,U37/I37) -> 0
A38: Concrete Slab on Grade | C38: N/A | H38: 0 | I38: 0 | L38: N/A | M38: ='LEVEL 3'!F38 -> 0 | N38: ='LEVEL 3'!G38 -> 0 | O38: ='LEVEL 3'!H38 -> 0 | P38: ='LEVEL 3'!I38 -> 0 | Q38: ='LEVEL 3'!J38 -> 0 | R38: ='LEVEL 3'!K38 -> 0 | U38: =R38-I38 -> 0 | W38: =IF(I38=0,0,U38/I38) -> 0
A39: Concrete Topping Slab 4" / Level | C39: N/A | H39: 0 | I39: 0 | L39: N/A | M39: ='LEVEL 3'!F39 -> 0 | N39: ='LEVEL 3'!G39 -> 0 | O39: ='LEVEL 3'!H39 -> 0 | P39: ='LEVEL 3'!I39 -> 0 | Q39: ='LEVEL 3'!J39 -> 0 | R39: ='LEVEL 3'!K39 -> 0 | U39: =R39-I39 -> 0 | W39: =IF(I39=0,0,U39/I39) -> 0
A40: Electrical | C40: N/A | H40: 0 | I40: 0 | L40: N/A | M40: ='LEVEL 3'!F40 -> 0 | N40: ='LEVEL 3'!G40 -> 0 | O40: ='LEVEL 3'!H40 -> 0 | P40: ='LEVEL 3'!I40 -> 0 | Q40: ='LEVEL 3'!J40 -> 0 | R40: ='LEVEL 3'!K40 -> 0 | U40: =R40-I40 -> 0 | W40: =IF(I40=0,0,U40/I40) -> 0
A41: Dry Sprinklers | C41: N/A | H41: 0 | I41: 0 | L41: N/A | M41: ='LEVEL 3'!F41 -> 0 | N41: ='LEVEL 3'!G41 -> 0 | O41: ='LEVEL 3'!H41 -> 0 | P41: ='LEVEL 3'!I41 -> 0 | Q41: ='LEVEL 3'!J41 -> 0 | R41: ='LEVEL 3'!K41 -> 0 | U41: =R41-I41 -> 0 | W41: =IF(I41=0,0,U41/I41) -> 0
A42: Mechanical Ventilation | C42: N/A | H42: 0 | I42: 0 | L42: N/A | M42: ='LEVEL 3'!F42 -> 0 | N42: ='LEVEL 3'!G42 -> 0 | O42: ='LEVEL 3'!H42 -> 0 | P42: ='LEVEL 3'!I42 -> 0 | Q42: ='LEVEL 3'!J42 -> 0 | R42: ='LEVEL 3'!K42 -> 0 | U42: =R42-I42 -> 0 | W42: =IF(I42=0,0,U42/I42) -> 0
A43: Stairs and Railings | C43: N/A | H43: 0 | I43: 0 | L43: N/A | M43: ='LEVEL 3'!F43 -> 0 | N43: ='LEVEL 3'!G43 -> 0 | O43: ='LEVEL 3'!H43 -> 0 | P43: ='LEVEL 3'!I43 -> 0 | Q43: ='LEVEL 3'!J43 -> 0 | R43: ='LEVEL 3'!K43 -> 0 | U43: =R43-I43 -> 0 | W43: =IF(I43=0,0,U43/I43) -> 0
A44: Masonry | J44: 115440 | S44: ='LEVEL 3'!L44 -> 112800 | U44: =S44-J44 -> -2640 | W44: =IF(J44=0,0,U44/J44) -> -0.022869023
A45: Elevator Shaft | C45: Torrey Pines | D45: Count | E45: 2 | F45: 39900 | G45: 0 | H45: 39900 | I45: 79800 | L45: Torrey Pines | M45: ='LEVEL 3'!F45 -> Stop | N45: ='LEVEL 3'!G45 -> 8 | O45: ='LEVEL 3'!H45 -> 9500 | P45: ='LEVEL 3'!I45 -> 0 | Q45: ='LEVEL 3'!J45 -> 9500 | R45: ='LEVEL 3'!K45 -> 76000 | U45: =R45-I45 -> -3800 | W45: =IF(I45=0,0,U45/I45) -> -0.047619048
A46: Trash Enclosure | C46: Torrey Pines | D46: Count | E46: 4 | F46: 5985 | G46: 0 | H46: 5985 | I46: 23940 | L46: Torrey Pines | M46: ='LEVEL 3'!F46 -> Count | N46: ='LEVEL 3'!G46 -> 4 | O46: ='LEVEL 3'!H46 -> 5700 | P46: ='LEVEL 3'!I46 -> 0 | Q46: ='LEVEL 3'!J46 -> 5700 | R46: ='LEVEL 3'!K46 -> 22800 | U46: =R46-I46 -> -1140 | W46: =IF(I46=0,0,U46/I46) -> -0.047619048
A47: Masonry Veneer | C47: N/A | F47: 0 | H47: 0 | I47: 0 | L47: N/A | M47: ='LEVEL 3'!F47 -> 0 | N47: ='LEVEL 3'!G47 -> 0 | O47: ='LEVEL 3'!H47 -> 0 | P47: ='LEVEL 3'!I47 -> 0 | Q47: ='LEVEL 3'!J47 -> 0 | R47: ='LEVEL 3'!K47 -> 0 | U47: =R47-I47 -> 0 | W47: =IF(I47=0,0,U47/I47) -> 0
A48: Masonry Veneer Pool Area | C48: Russell IV | D48: LS | E48: 1 | F48: 6000 | G48: 0 | H48: 6000 | I48: 6000 | L48: Allowance | M48: ='LEVEL 3'!F48 -> LS | N48: ='LEVEL 3'!G48 -> 1 | O48: ='LEVEL 3'!H48 -> 5000 | P48: ='LEVEL 3'!I48 -> 0 | Q48: ='LEVEL 3'!J48 -> 5000 | R48: ='LEVEL 3'!K48 -> 5000 | U48: =R48-I48 -> -1000 | W48: =IF(I48=0,0,U48/I48) -> -0.16666667
A49: Pool Eq. Shower Stone | C49: Allowance | D49: LS | E49: 1 | F49: 5700 | G49: 0 | H49: 5700 | I49: 5700 | L49: Torrey Pines | M49: ='LEVEL 3'!F49 -> LS | N49: ='LEVEL 3'!G49 -> 1 | O49: ='LEVEL 3'!H49 -> 9000 | P49: ='LEVEL 3'!I49 -> 0 | Q49: ='LEVEL 3'!J49 -> 9000 | R49: ='LEVEL 3'!K49 -> 9000 | U49: =R49-I49 -> 3300 | W49: =IF(I49=0,0,U49/I49) -> 0.57894737
A50: Metals | J50: 438442 | S50: ='LEVEL 3'!L50 -> 325412.13 | U50: =S50-J50 -> -113029.87 | W50: =IF(J50=0,0,U50/J50) -> -0.25779892 | Y50: Structural Steel was $186k based on Wigwam, now TP $113K and takeoff.
A51: Structural Steel | C51: Torrey Pines | D51: LS | E51: 1 | F51: 82850 | G51: 0 | H51: 82850 | I51: 186154 | L51: Torrey Pines | M51: ='LEVEL 3'!F51 -> LBS | N51: ='LEVEL 3'!G51 -> 31706.95 | O51: ='LEVEL 3'!H51 -> 3.5584037 | P51: ='LEVEL 3'!I51 -> 0 | Q51: ='LEVEL 3'!J51 -> 3.5584037 | R51: ='LEVEL 3'!K51 -> 112826.13 | U51: =R51-I51 -> -73327.872 | W51: =IF(I51=0,0,U51/I51) -> -0.39390973
A52: Elevator Shaft Iron | C52: Russell IV | D52: Count | E52: 2 | F52: 5990 | G52: 0 | H52: 5990 | I52: 11980 | L52: Torrey Pines | M52: ='LEVEL 3'!F52 -> Count | N52: ='LEVEL 3'!G52 -> 2 | O52: ='LEVEL 3'!H52 -> 4040 | P52: ='LEVEL 3'!I52 -> 0 | Q52: ='LEVEL 3'!J52 -> 4040 | R52: ='LEVEL 3'!K52 -> 8080 | U52: =R52-I52 -> -3900 | W52: =IF(I52=0,0,U52/I52) -> -0.32554257
A53: Stair Handrails | C53: Pebble | D53: Count | E53: 7 | F53: 11750 | G53: 0 | H53: 11750 | I53: 82250 | L53: Torrey Pines | M53: ='LEVEL 3'!F53 -> Flight | N53: ='LEVEL 3'!G53 -> 28 | O53: ='LEVEL 3'!H53 -> 2000 | P53: ='LEVEL 3'!I53 -> 0 | Q53: ='LEVEL 3'!J53 -> 2000 | R53: ='LEVEL 3'!K53 -> 56000 | U53: =R53-I53 -> -26250 | W53: =IF(I53=0,0,U53/I53) -> -0.31914894
A54: Garage Stair Railings | C54: N/A | F54: 0 | G54: 0 | H54: 0 | I54: 0 | L54: N/A | M54: ='LEVEL 3'!F54 -> 0 | N54: ='LEVEL 3'!G54 -> 0 | O54: ='LEVEL 3'!H54 -> 0 | P54: ='LEVEL 3'!I54 -> 0 | Q54: ='LEVEL 3'!J54 -> 0 | R54: ='LEVEL 3'!K54 -> 0 | U54: =R54-I54 -> 0 | W54: =IF(I54=0,0,U54/I54) -> 0
A55: Cabana Iron | C55: N/A | F55: 0 | G55: 0 | H55: 0 | I55: 0 | L55: N/A | M55: ='LEVEL 3'!F55 -> 0 | N55: ='LEVEL 3'!G55 -> 0 | O55: ='LEVEL 3'!H55 -> 0 | P55: ='LEVEL 3'!I55 -> 0 | Q55: ='LEVEL 3'!J55 -> 0 | R55: ='LEVEL 3'!K55 -> 0 | U55: =R55-I55 -> 0 | W55: =IF(I55=0,0,U55/I55) -> 0
A56: Pool Equipment Gate | C56: Russell IV | D56: Count | E56: 1 | F56: 1950 | G56: 0 | H56: 1950 | I56: 1950 | L56: Torrey Pines | M56: ='LEVEL 3'!F56 -> Count | N56: ='LEVEL 3'!G56 -> 1 | O56: ='LEVEL 3'!H56 -> 1950 | P56: ='LEVEL 3'!I56 -> 0 | Q56: ='LEVEL 3'!J56 -> 1950 | R56: ='LEVEL 3'!K56 -> 1950 | U56: =R56-I56 -> 0 | W56: =IF(I56=0,0,U56/I56) -> 0
A57: Iron Railings | C57: Russell IV | D57: LF | E57: 1593 | F57: 97.9965 | G57: 0 | H57: 97.9965 | I57: 156108.42 | L57: Torrey Pines | M57: ='LEVEL 3'!F57 -> LF | N57: ='LEVEL 3'!G57 -> 1593 | O57: ='LEVEL 3'!H57 -> 92 | P57: ='LEVEL 3'!I57 -> 0 | Q57: ='LEVEL 3'!J57 -> 92 | R57: ='LEVEL 3'!K57 -> 146556 | U57: =R57-I57 -> -9552.42 | W57: =IF(I57=0,0,U57/I57) -> -0.061190934
A58: Cable Railings | C58: N/A | F58: 0 | G58: 0 | H58: 0 | I58: 0 | L58: N/A | M58: ='LEVEL 3'!F58 -> 0 | N58: ='LEVEL 3'!G58 -> 0 | O58: ='LEVEL 3'!H58 -> 0 | P58: ='LEVEL 3'!I58 -> 0 | Q58: ='LEVEL 3'!J58 -> 0 | R58: ='LEVEL 3'!K58 -> 0 | U58: =R58-I58 -> 0 | W58: =IF(I58=0,0,U58/I58) -> 0
A59: Wood, Plastics, & Composites | J59: 5146676 | S59: ='LEVEL 3'!L59 -> 4804000.7 | U59: =S59-J59 -> -342675.3 | W59: =IF(J59=0,0,U59/J59) -> -0.066581868 | Y59: Framing was at $21.91 now at $20.50 based on T12 Average.
A60: Dumpsters | C60: Torrey Pines | D60: Unit | E60: 194 | F60: 79 | G60: 0 | H60: 79 | I60: 15326 | M60: ='LEVEL 3'!#REF! -> #REF! | N60: ='LEVEL 3'!#REF! -> #REF! | O60: ='LEVEL 3'!#REF! -> #REF! | P60: ='LEVEL 3'!#REF! -> #REF! | Q60: ='LEVEL 3'!#REF! -> #REF! | R60: ='LEVEL 3'!#REF! -> #REF! | U60: =R60-I60 -> #REF! | W60: =IF(I60=0,0,U60/I60) -> #REF!
A61: Framing | C61: Torrey Pines | D61: SF | E61: 196333 | F61: =H61/(1+G61) -> 19.918182 | G61: 0.1 | H61: 21.91 | I61: 4302048.7 | L61: Torrey Pines | M61: ='LEVEL 3'!F60 -> SF | N61: ='LEVEL 3'!G60 -> 196289 | O61: ='LEVEL 3'!H60 -> 20.423582 | P61: ='LEVEL 3'!I60 -> 0 | Q61: ='LEVEL 3'!J60 -> 20.423582 | R61: ='LEVEL 3'!K60 -> 4008924.5 | U61: =R61-I61 -> -293124.2 | W61: =IF(I61=0,0,U61/I61) -> -0.068135956
A62: Framing - Crane | C62: N/A | G62: 0 | H62: 0 | I62: 0 | L62: N/A | M62: ='LEVEL 3'!F62 -> 0 | N62: ='LEVEL 3'!G62 -> 0 | O62: ='LEVEL 3'!H62 -> 0 | P62: ='LEVEL 3'!I62 -> 0 | Q62: ='LEVEL 3'!J62 -> 0 | R62: ='LEVEL 3'!K62 -> 0 | U62: =R62-I62 -> 0 | W62: =IF(I62=0,0,U62/I62) -> 0
A63: Cabana Framing | C63: N/A | G63: 0 | H63: 0 | I63: 0 | L63: N/A | M63: ='LEVEL 3'!F63 -> 0 | N63: ='LEVEL 3'!G63 -> 0 | O63: ='LEVEL 3'!H63 -> 0 | P63: ='LEVEL 3'!I63 -> 0 | Q63: ='LEVEL 3'!J63 -> 0 | R63: ='LEVEL 3'!K63 -> 0 | U63: =R63-I63 -> 0 | W63: =IF(I63=0,0,U63/I63) -> 0
A64: BBQ Framing | C64: Pebble | D64: LS | E64: 1 | F64: 2810 | G64: 0 | H64: 2810 | I64: 2810 | L64: Allowance | M64: ='LEVEL 3'!F64 -> LS | N64: ='LEVEL 3'!G64 -> 1 | O64: ='LEVEL 3'!H64 -> 2500 | P64: ='LEVEL 3'!I64 -> 0 | Q64: ='LEVEL 3'!J64 -> 2500 | R64: ='LEVEL 3'!K64 -> 2500 | U64: =R64-I64 -> -310 | W64: =IF(I64=0,0,U64/I64) -> -0.11032028
A65: Fireplace Framing | C65: N/A | G65: 0 | H65: 0 | I65: 0 | L65: N/A | M65: ='LEVEL 3'!F65 -> 0 | N65: ='LEVEL 3'!G65 -> 0 | O65: ='LEVEL 3'!H65 -> 0 | P65: ='LEVEL 3'!I65 -> 0 | Q65: ='LEVEL 3'!J65 -> 0 | R65: ='LEVEL 3'!K65 -> 0 | U65: =R65-I65 -> 0 | W65: =IF(I65=0,0,U65/I65) -> 0
A66: Trellis | C66: N/A | G66: 0 | H66: 0 | I66: 0 | L66: N/A | M66: ='LEVEL 3'!F66 -> 0 | N66: ='LEVEL 3'!G66 -> 0 | O66: ='LEVEL 3'!H66 -> 0 | P66: ='LEVEL 3'!I66 -> 0 | Q66: ='LEVEL 3'!J66 -> 0 | R66: ='LEVEL 3'!K66 -> 0 | U66: =R66-I66 -> 0 | W66: =IF(I66=0,0,U66/I66) -> 0
A67: Pool Equipment Framing | C67: N/A | G67: 0 | H67: 0 | I67: 0 | L67: N/A | M67: ='LEVEL 3'!F67 -> 0 | N67: ='LEVEL 3'!G67 -> 0 | O67: ='LEVEL 3'!H67 -> 0 | P67: ='LEVEL 3'!I67 -> 0 | Q67: ='LEVEL 3'!J67 -> 0 | R67: ='LEVEL 3'!K67 -> 0 | U67: =R67-I67 -> 0 | W67: =IF(I67=0,0,U67/I67) -> 0
A68: Finish Carpentry - Units | C68: Pebble | D68: Unit | E68: 194 | F68: 3081 | G68: 0 | H68: 3081 | I68: 597714 | L68: Torrey Pines | M68: ='LEVEL 3'!F68 -> Unit | N68: ='LEVEL 3'!G68 -> 194 | O68: ='LEVEL 3'!H68 -> 3169.3041 | P68: ='LEVEL 3'!I68 -> 0 | Q68: ='LEVEL 3'!J68 -> 3169.3041 | R68: ='LEVEL 3'!K68 -> 614845 | U68: =R68-I68 -> 17131 | W68: =IF(I68=0,0,U68/I68) -> 0.028660865
A69: Finish Carpentry - Common | C69: Pebble | D69: SF | E69: 196333 | F69: 1.16 | G69: 0 | H69: 1.16 | I69: 227746.28 | L69: Torrey Pines | M69: ='LEVEL 3'!F69 -> SF | N69: ='LEVEL 3'!G69 -> 196289 | O69: ='LEVEL 3'!H69 -> 0.8 | P69: ='LEVEL 3'!I69 -> 0 | Q69: ='LEVEL 3'!J69 -> 0.8 | R69: ='LEVEL 3'!K69 -> 157031.2 | U69: =R69-I69 -> -70715.08 | W69: =IF(I69=0,0,U69/I69) -> -0.31049939
A70: BBQ Trim | C70: Pebble | D70: LS | E70: 1 | F70: 1031 | G70: 0 | H70: 1031 | I70: 1031 | L70: Allowance | M70: ='LEVEL 3'!F71 -> LS | N70: ='LEVEL 3'!G71 -> 1 | O70: ='LEVEL 3'!H71 -> 1200 | P70: ='LEVEL 3'!I71 -> 0 | Q70: ='LEVEL 3'!J71 -> 1200 | R70: ='LEVEL 3'!K71 -> 1200 | U70: =R70-I70 -> 169 | W70: =IF(I70=0,0,U70/I70) -> 0.16391853
A71: Shutters | C71: N/A | G71: 0 | H71: 0 | I71: 0 | L71: N/A | M71: ='LEVEL 3'!F72 -> 0 | N71: ='LEVEL 3'!G72 -> 0 | O71: ='LEVEL 3'!H72 -> 0 | P71: ='LEVEL 3'!I72 -> 0 | Q71: ='LEVEL 3'!J72 -> 0 | R71: ='LEVEL 3'!K72 -> 0 | U71: =R71-I71 -> 0 | W71: =IF(I71=0,0,U71/I71) -> 0
A72: Thermal & Moisture Protection | J72: 865299 | S72: ='LEVEL 3'!L73 -> 905486.76 | U72: =S72-J72 -> 40187.76 | W72: =IF(J72=0,0,U72/J72) -> 0.046443784
A73: Insulation | C73: Torrey Pines | D73: SF | E73: 196333 | F73: 2.54 | G73: 0 | H73: 2.54 | I73: 498685.82 | L73: Torrey Pines | M73: ='LEVEL 3'!F74 -> SF | N73: ='LEVEL 3'!G74 -> 196289 | O73: ='LEVEL 3'!H74 -> 2.6872637 | P73: ='LEVEL 3'!I74 -> 0 | Q73: ='LEVEL 3'!J74 -> 2.6872637 | R73: ='LEVEL 3'!K74 -> 527480.3 | U73: =R73-I73 -> 28794.48 | W73: =IF(I73=0,0,U73/I73) -> 0.057740723
A74: Roofing | C74: Torrey Pines | D74: LS | E74: 1 | F74: 298290 | G74: 0 | H74: 298290 | I74: 298290 | L74: Torrey Pines | M74: ='LEVEL 3'!F76 -> Squares | N74: ='LEVEL 3'!G76 -> 503.63 | O74: ='LEVEL 3'!H76 -> 603 | P74: ='LEVEL 3'!I76 -> 0 | Q74: ='LEVEL 3'!J76 -> 603 | R74: ='LEVEL 3'!K76 -> 303688.89 | U74: =R74-I74 -> 5398.89 | W74: =IF(I74=0,0,U74/I74) -> 0.018099467
A75: Cabana Roofing | C75: N/A | G75: 0 | H75: 0 | I75: 0 | L75: N/A | M75: ='LEVEL 3'!F77 -> 0 | N75: ='LEVEL 3'!G77 -> 0 | O75: ='LEVEL 3'!H77 -> 0 | P75: ='LEVEL 3'!I77 -> 0 | Q75: ='LEVEL 3'!J77 -> 0 | R75: ='LEVEL 3'!K77 -> 0 | U75: =R75-I75 -> 0 | W75: =IF(I75=0,0,U75/I75) -> 0
A76: Pump House Roofing | C76: Allowance | D76: LS | E76: 1 | F76: 6700 | G76: 0 | H76: 6700 | I76: 6700 | L76: Allowance | M76: ='LEVEL 3'!F78 -> LS | N76: ='LEVEL 3'!G78 -> 1 | O76: ='LEVEL 3'!H78 -> 7500 | P76: ='LEVEL 3'!I78 -> 0 | Q76: ='LEVEL 3'!J78 -> 7500 | R76: ='LEVEL 3'!K78 -> 7500 | U76: =R76-I76 -> 800 | W76: =IF(I76=0,0,U76/I76) -> 0.11940299
A77: Pool Equipment Roofing | C77: Pebble | D77: LS | E77: 1 | F77: 7049 | G77: 0 | H77: 7049 | I77: 7049 | L77: Allowance | M77: ='LEVEL 3'!F79 -> LS | N77: ='LEVEL 3'!G79 -> 1 | O77: ='LEVEL 3'!H79 -> 7500 | P77: ='LEVEL 3'!I79 -> 0 | Q77: ='LEVEL 3'!J79 -> 7500 | R77: ='LEVEL 3'!K79 -> 7500 | U77: =R77-I77 -> 451 | W77: =IF(I77=0,0,U77/I77) -> 0.063980706
A78: Trash Enclosure Cover | C78: Pebble | D78: Count | E78: 4 | F78: 5800 | G78: 0 | H78: 5800 | I78: 23200 | L78: Decatur | M78: ='LEVEL 3'!F80 -> Count | N78: ='LEVEL 3'!G80 -> 4 | O78: ='LEVEL 3'!H80 -> 5800 | P78: ='LEVEL 3'!I80 -> 0 | Q78: ='LEVEL 3'!J80 -> 5800 | R78: ='LEVEL 3'!K80 -> 23200 | U78: =R78-I78 -> 0 | W78: =IF(I78=0,0,U78/I78) -> 0
A79: Pigeon Proofing | C79: Torrey Pines | D79: SF | E79: 196333 | F79: 0.08 | G79: 0 | H79: 0.08 | I79: 15706.64 | L79: Torrey Pines | M79: ='LEVEL 3'!F81 -> SF | N79: ='LEVEL 3'!G81 -> 196289 | O79: ='LEVEL 3'!H81 -> 0.08 | P79: ='LEVEL 3'!I81 -> 0 | Q79: ='LEVEL 3'!J81 -> 0.08 | R79: ='LEVEL 3'!K81 -> 15703.12 | U79: =R79-I79 -> -3.52 | W79: =IF(I79=0,0,U79/I79) -> -0.00022410904
A80: Gutters and Downspouts | C80: Torrey Pines | D80: SF | E80: 196333 | F80: 0.05 | G80: 0 | H80: 0.05 | I80: 9816.65 | L80: Torrey Pines | M80: ='LEVEL 3'!F82 -> SF | N80: ='LEVEL 3'!G82 -> 196289 | O80: ='LEVEL 3'!H82 -> 0.05 | P80: ='LEVEL 3'!I82 -> 0 | Q80: ='LEVEL 3'!J82 -> 0.05 | R80: ='LEVEL 3'!K82 -> 9814.45 | U80: =R80-I80 -> -2.2 | W80: =IF(I80=0,0,U80/I80) -> -0.00022410904
A81: Roof Ladders | C81: Torrey Pines | D81: Count | E81: 2 | F81: 1550 | G81: 0 | H81: 1550 | I81: 3100 | L81: Torrey Pines | M81: ='LEVEL 3'!F83 -> Count | N81: ='LEVEL 3'!G83 -> 2 | O81: ='LEVEL 3'!H83 -> 1550 | P81: ='LEVEL 3'!I83 -> 0 | Q81: ='LEVEL 3'!J83 -> 1550 | R81: ='LEVEL 3'!K83 -> 3100 | U81: =R81-I81 -> 0 | W81: =IF(I81=0,0,U81/I81) -> 0
A82: Roof Access Doors | C82: Torrey Pines | D82: Count | E82: 2 | F82: 2500 | G82: 0 | H82: 2500 | I82: 5000 | L82: Torrey Pines | M82: ='LEVEL 3'!F84 -> Count | N82: ='LEVEL 3'!G84 -> 2 | O82: ='LEVEL 3'!H84 -> 2500 | P82: ='LEVEL 3'!I84 -> 0 | Q82: ='LEVEL 3'!J84 -> 2500 | R82: ='LEVEL 3'!K84 -> 5000 | U82: =R82-I82 -> 0 | W82: =IF(I82=0,0,U82/I82) -> 0
A83: Roof Winch | C83: N/A | G83: 0 | H83: 0 | I83: 0 | L83: N/A | M83: ='LEVEL 3'!F85 -> 0 | N83: ='LEVEL 3'!G85 -> 0 | O83: ='LEVEL 3'!H85 -> 0 | P83: ='LEVEL 3'!I85 -> 0 | Q83: ='LEVEL 3'!J85 -> 0 | R83: ='LEVEL 3'!K85 -> 0 | U83: =R83-I83 -> 0 | W83: =IF(I83=0,0,U83/I83) -> 0
A84: Openings | J84: 292564 | S84: ='LEVEL 3'!L86 -> 279109.58 | U84: =S84-J84 -> -13454.421 | W84: =IF(J84=0,0,U84/J84) -> -0.045987958
A85: Dumpsters | C85: Latest | D85: Per Unit | E85: 194 | F85: 79 | G85: 0 | H85: 79 | I85: 15326 | M85: ='LEVEL 3'!#REF! -> #REF! | N85: ='LEVEL 3'!#REF! -> #REF! | O85: ='LEVEL 3'!#REF! -> #REF! | P85: ='LEVEL 3'!#REF! -> #REF! | Q85: ='LEVEL 3'!#REF! -> #REF! | R85: ='LEVEL 3'!#REF! -> #REF! | U85: =R85-I85 -> #REF! | W85: =IF(I85=0,0,U85/I85) -> #REF!
A86: Entry Doors | C86: Count | D86: Count | E86: 1 | F86: 7954 | G86: 0 | H86: 7954 | I86: 7954 | L86: Allowance | M86: ='LEVEL 3'!F87 -> Count | N86: ='LEVEL 3'!G87 -> 1 | O86: ='LEVEL 3'!H87 -> 8000 | P86: ='LEVEL 3'!I87 -> 0 | Q86: ='LEVEL 3'!J87 -> 8000 | R86: ='LEVEL 3'!K87 -> 8000 | U86: =R86-I86 -> 46 | W86: =IF(I86=0,0,U86/I86) -> 0.0057832537
A87: Common Doors | C87: Included | G87: 0 | H87: 0 | I87: 0 | L87: Included | M87: ='LEVEL 3'!F88 -> 0 | N87: ='LEVEL 3'!G88 -> 0 | O87: ='LEVEL 3'!H88 -> 0 | P87: ='LEVEL 3'!I88 -> 0 | Q87: ='LEVEL 3'!J88 -> 0 | R87: ='LEVEL 3'!K88 -> 0 | U87: =R87-I87 -> 0 | W87: =IF(I87=0,0,U87/I87) -> 0
A88: Pocket Doors - 3 Panel | C88: N/A | G88: 0 | H88: 0 | I88: 0 | L88: N/A | M88: ='LEVEL 3'!F89 -> 0 | N88: ='LEVEL 3'!G89 -> 0 | O88: ='LEVEL 3'!H89 -> 0 | P88: ='LEVEL 3'!I89 -> 0 | Q88: ='LEVEL 3'!J89 -> 0 | R88: ='LEVEL 3'!K89 -> 0 | U88: =R88-I88 -> 0 | W88: =IF(I88=0,0,U88/I88) -> 0
A89: Garage Doors | C89: N/A | G89: 0 | H89: 0 | I89: 0 | L89: N/A | M89: ='LEVEL 3'!F90 -> 0 | N89: ='LEVEL 3'!G90 -> 0 | O89: ='LEVEL 3'!H90 -> 0 | P89: ='LEVEL 3'!I90 -> 0 | Q89: ='LEVEL 3'!J90 -> 0 | R89: ='LEVEL 3'!K90 -> 0 | U89: =R89-I89 -> 0 | W89: =IF(I89=0,0,U89/I89) -> 0
A90: Windows and Sliding Glass Doors | C90: Decatur | D90: Per Unit | E90: 194 | F90: 1131 | G90: 0 | H90: 1357.2 | I90: 219414 | L90: Torrey Pines | M90: ='LEVEL 3'!F91 -> Per Unit | N90: ='LEVEL 3'!G91 -> 194 | O90: ='LEVEL 3'!H91 -> 1157.8947 | P90: ='LEVEL 3'!I91 -> 0 | Q90: ='LEVEL 3'!J91 -> 1157.8947 | R90: ='LEVEL 3'!K91 -> 224631.58 | U90: =R90-I90 -> 5217.5789 | W90: =IF(I90=0,0,U90/I90) -> 0.023779608
A91: Windows Repair and Replacement | C91: Allowance | D91: Per Unit | E91: 194 | F91: 75 | G91: 0 | H91: 75 | I91: 14550 | L91: Allowance | M91: ='LEVEL 3'!F92 -> Per Unit | N91: ='LEVEL 3'!G92 -> 194 | O91: ='LEVEL 3'!H92 -> 75 | P91: ='LEVEL 3'!I92 -> 0 | Q91: ='LEVEL 3'!J92 -> 75 | R91: ='LEVEL 3'!K92 -> 14550 | U91: =R91-I91 -> 0 | W91: =IF(I91=0,0,U91/I91) -> 0
A92: Pool Equipment Windows | C92: N/A | G92: 0 | H92: 0 | I92: 0 | L92: N/A | M92: ='LEVEL 3'!F93 -> 0 | N92: ='LEVEL 3'!G93 -> 0 | O92: ='LEVEL 3'!H93 -> 0 | P92: ='LEVEL 3'!I93 -> 0 | Q92: ='LEVEL 3'!J93 -> 0 | R92: ='LEVEL 3'!K93 -> 0 | U92: =R92-I92 -> 0 | W92: =IF(I92=0,0,U92/I92) -> 0
A93: Pool Glass Walls | C93: N/A | G93: 0 | H93: 0 | I93: 0 | L93: N/A | M93: ='LEVEL 3'!F94 -> 0 | N93: ='LEVEL 3'!G94 -> 0 | O93: ='LEVEL 3'!H94 -> 0 | P93: ='LEVEL 3'!I94 -> 0 | Q93: ='LEVEL 3'!J94 -> 0 | R93: ='LEVEL 3'!K94 -> 0 | U93: =R93-I93 -> 0 | W93: =IF(I93=0,0,U93/I93) -> 0
A94: Fixed Glass | C94: N/A | G94: 0 | H94: 0 | I94: 0 | L94: N/A | M94: ='LEVEL 3'!F95 -> 0 | N94: ='LEVEL 3'!G95 -> 0 | O94: ='LEVEL 3'!H95 -> 0 | P94: ='LEVEL 3'!I95 -> 0 | Q94: ='LEVEL 3'!J95 -> 0 | R94: ='LEVEL 3'!K95 -> 0 | U94: =R94-I94 -> 0 | W94: =IF(I94=0,0,U94/I94) -> 0
A95: Mirrors - LED | C95: N/A | G95: 0 | H95: 0 | I95: 0 | L95: N/A | M95: ='LEVEL 3'!F96 -> 0 | N95: ='LEVEL 3'!G96 -> 0 | O95: ='LEVEL 3'!H96 -> 0 | P95: ='LEVEL 3'!I96 -> 0 | Q95: ='LEVEL 3'!J96 -> 0 | R95: ='LEVEL 3'!K96 -> 0 | U95: =R95-I95 -> 0 | W95: =IF(I95=0,0,U95/I95) -> 0
A96: Mirrors - LED Install | C96: N/A | G96: 0 | H96: 0 | I96: 0 | L96: N/A | M96: ='LEVEL 3'!F97 -> 0 | N96: ='LEVEL 3'!G97 -> 0 | O96: ='LEVEL 3'!H97 -> 0 | P96: ='LEVEL 3'!I97 -> 0 | Q96: ='LEVEL 3'!J97 -> 0 | R96: ='LEVEL 3'!K97 -> 0 | U96: =R96-I96 -> 0 | W96: =IF(I96=0,0,U96/I96) -> 0
A97: Mirrors - Framed | C97: N/A | G97: 0 | H97: 0 | I97: 0 | L97: N/A | M97: ='LEVEL 3'!F98 -> 0 | N97: ='LEVEL 3'!G98 -> 0 | O97: ='LEVEL 3'!H98 -> 0 | P97: ='LEVEL 3'!I98 -> 0 | Q97: ='LEVEL 3'!J98 -> 0 | R97: ='LEVEL 3'!K98 -> 0 | U97: =R97-I97 -> 0 | W97: =IF(I97=0,0,U97/I97) -> 0
A98: Mirrors - Polished Edges (Units) | C98: Russell IV | D98: Unit | E98: 194 | F98: 180 | G98: 0 | H98: 180 | I98: 34920 | L98: Pebble | M98: ='LEVEL 3'!F99 -> Unit | N98: ='LEVEL 3'!G99 -> 194 | O98: ='LEVEL 3'!H99 -> 162 | P98: ='LEVEL 3'!I99 -> 0 | Q98: ='LEVEL 3'!J99 -> 162 | R98: ='LEVEL 3'!K99 -> 31428 | U98: =R98-I98 -> -3492 | W98: =IF(I98=0,0,U98/I98) -> -0.1
A99: Mirrors - Polished Edges (Restrooms) | C99: Russell IV | D99: Count | E99: 2 | F99: 200 | G99: 0 | H99: 200 | I99: 400 | L99: Allowance | M99: ='LEVEL 3'!F100 -> Count | N99: ='LEVEL 3'!G100 -> 2 | O99: ='LEVEL 3'!H100 -> 250 | P99: ='LEVEL 3'!I100 -> 0 | Q99: ='LEVEL 3'!J100 -> 250 | R99: ='LEVEL 3'!K100 -> 500 | U99: =R99-I99 -> 100 | W99: =IF(I99=0,0,U99/I99) -> 0.25
A100: Finishes | J100: 3322642 | S100: ='LEVEL 3'!L101 -> 3261602.4 | U100: =S100-J100 -> -61039.647 | W100: =IF(J100=0,0,U100/J100) -> -0.018370817
...

Sheet Sheet1
E2: Unit | F2: ='LEVEL 3'!E8 -> 194 | H2: Building GSF | I2: ='LEVEL 3'!B8 -> 196289
A3: Description | B3: Ovation (Level 1) | C3: Zebel | E3: Ovation (Level 1) | F3: Zebel | H3: Ovation (Level 1) | I3: Zebel
A4: General Requirements | B4: 2175943.9 | C4: 2708450 | E4: =B4/$F$2 -> 11216.206 | F4: =C4/$F$2 -> 13961.082 | H4: =B4/$I$2 -> 11.085409 | I4: =C4/$I$2 -> 13.798277
A5: Existing Conditions | B5: 12000 | C5: 17374 | E5: =B5/$F$2 -> 61.85567 | F5: =C5/$F$2 -> 89.556701 | H5: =B5/$I$2 -> 0.061134348 | I5: =C5/$I$2 -> 0.088512347
A6: Concrete | B6: 2933768.7 | C6: 2862222 | E6: =B6/$F$2 -> 15122.519 | F6: =C6/$F$2 -> 14753.722 | H6: =B6/$I$2 -> 14.94617 | I6: =C6/$I$2 -> 14.581673
A7: Masonry | B7: 205500 | C7: 365194 | E7: =B7/$F$2 -> 1059.2784 | F7: =C7/$F$2 -> 1882.4433 | H7: =B7/$I$2 -> 1.0469257 | I7: =C7/$I$2 -> 1.8604914
A8: Metals | B8: 526095.76 | C8: 438859 | E8: =B8/$F$2 -> 2711.8338 | F8: =C8/$F$2 -> 2262.1598 | H8: =B8/$I$2 -> 2.6802101 | I8: =C8/$I$2 -> 2.2357799
A9: Wood, Plastics, & Composites | B9: 10813331 | C9: 11191767 | E9: =B9/$F$2 -> 55738.819 | F9: =C9/$F$2 -> 57689.521 | H9: =B9/$I$2 -> 55.088828 | I9: =C9/$I$2 -> 57.016781
A10: Thermal & Moisture Protection | B10: 2357905.8 | C10: 2147257 | E10: =B10/$F$2 -> 12154.154 | F10: =C10/$F$2 -> 11068.335 | H10: =B10/$I$2 -> 12.012419 | I10: =C10/$I$2 -> 10.939263
A11: Openings | B11: 648077.1 | C11: 968281 | E11: =B11/$F$2 -> 3340.6036 | F11: =C11/$F$2 -> 4991.1392 | H11: =B11/$I$2 -> 3.3016476 | I11: =C11/$I$2 -> 4.9329356
A12: Finishes | B12: 7174763.2 | C12: 7630096 | E12: =B12/$F$2 -> 36983.315 | F12: =C12/$F$2 -> 39330.392 | H12: =B12/$I$2 -> 36.552039 | I12: =C12/$I$2 -> 38.871745
A13: Specialties | B13: 582625.36 | C13: 422978 | E13: =B13/$F$2 -> 3003.2235 | F13: =C13/$F$2 -> 2180.299 | H13: =B13/$I$2 -> 2.9682018 | I13: =C13/$I$2 -> 2.1548737
A14: Equipment | B14: 1290418 | C14: 1608724 | E14: =B14/$F$2 -> 6651.6392 | F14: =C14/$F$2 -> 8292.3918 | H14: =B14/$I$2 -> 6.5740719 | I14: =C14/$I$2 -> 8.195691
A15: Furnishings | B15: 1990135.6 | C15: 4165522 | E15: =B15/$F$2 -> 10258.431 | F15: =C15/$F$2 -> 21471.763 | H15: =B15/$I$2 -> 10.138803 | I15: =C15/$I$2 -> 21.221373
... A22: Communications | B22: 260127.49 | C22: 231 | E22: =B22/$F$2 -> 1340.8634 | F22: =C22/$F$2 -> 1.1907216 | H22: =B22/$I$2 -> 1.325227 | I22: =C22/$I$2 -> 0.0011768362
A23: Electronic Safety & Security | B23: 1177692 | E23: =B23/$F$2 -> 6070.5773 | F23: =C23/$F$2 -> 0 | H23: =B23/$I$2 -> 5.999786 | I23: =C23/$I$2 -> 0
A24: Earthwork | B24: 2238333.6 | E24: =B24/$F$2 -> 11537.802 | F24: =C24/$F$2 -> 0 | H24: =B24/$I$2 -> 11.403255 | I24: =C24/$I$2 -> 0
A25: Exterior Improvements | B25: 7660331.2 | E25: =B25/$F$2 -> 39486.243 | F25: =C25/$F$2 -> 0 | H25: =B25/$I$2 -> 39.025779 | I25: =C25/$I$2 -> 0
A26: Utilities | B26: 5948000.1 | E26: =B26/$F$2 -> 30659.794 | F26: =C26/$F$2 -> 0 | H26: =B26/$I$2 -> 30.302259 | I26: =C26/$I$2 -> 0
A27: Transportation | B27: 15000 | E27: =B27/$F$2 -> 77.319588 | F27: =C27/$F$2 -> 0 | H27: =B27/$I$2 -> 0.076417935 | I27: =C27/$I$2 -> 0
A28: Electrical Power Generation | B28: 445775 | E28: =B28/$F$2 -> 2297.8093 | F28: =C28/$F$2 -> 0 | H28: =B28/$I$2 -> 2.2710137 | I28: =C28/$I$2 -> 0
A29: Field Surveys, Staking | B29: 427358.97 | E29: =B29/$F$2 -> 2202.8813 | F29: =C29/$F$2 -> 0 | H29: =B29/$I$2 -> 2.1771927 | I29: =C29/$I$2 -> 0
A30: Bid Risk | B30: 1264427.3 | E30: =B30/$F$2 -> 6517.6667 | F30: =C30/$F$2 -> 0 | H30: =B30/$I$2 -> 6.4416617 | I30: =C30/$I$2 -> 0
A31: FFE | B31: 1498772 | E31: =B31/$F$2 -> 7725.6289 | F31: =C31/$F$2 -> 0 | H31: =B31/$I$2 -> 7.6355374 | I31: =C31/$I$2 -> 0
A32: Construction Contingency | B32: 3333086.9 | E32: =B32/$F$2 -> 17180.86 | F32: =C32/$F$2 -> 0 | H32: =B32/$I$2 -> 16.980508 | I32: =C32/$I$2 -> 0
A33: Sub Bonds | B33: 821877.77 | E33: =B33/$F$2 -> 4236.4834 | F33: =C33/$F$2 -> 0 | H33: =B33/$I$2 -> 4.1870801 | I33: =C33/$I$2 -> 0
A34: GL Insurance | B34: 438231.78 | E34: =B34/$F$2 -> 2258.9267 | F34: =C34/$F$2 -> 0 | H34: =B34/$I$2 -> 2.2325845 | I34: =C34/$I$2 -> 0
... A36: Total Hard Costs | B36: 78574003 | E36: =B36/$F$2 -> 405020.64 | F36: =C36/$F$2 -> 0 | H36: =B36/$I$2 -> 400.29754 | I36: =C36/$I$2 -> 0

Sheet Combined Ph 1 & 2
B1: TOTAL COST | K1: PER UNIT | T1: PER GROSS SQUARE FOOT
B3: Phase 1 | E3: Phase 2 | H3: TOTAL | K3: Phase 1 | N3: Phase 2 | Q3: TOTAL | T3: Phase 1 | W3: Phase 2 | Z3: TOTAL
A4: Description | B4: Sub Total | C4: Total | E4: Sub Total | F4: Total | H4: Sub Total | I4: Total | K4: Sub Total | L4: Total | N4: Sub Total | O4: Total | Q4: Sub Total | R4: Total | T4: Sub Total | U4: Total | W4: Sub Total | X4: Total | Z4: Sub Total | AA4: Total
A5: General Requirements | C5: =B6 -> 2008563.6 | F5: =E6 -> 1674318 | I5: =H6 -> 3682881.6 | L5: =C5/'Scenario 1 - Phase 1'!$E$8 -> 5788.3677 | O5: =F5/'LEVEL 3'!$E$8 -> 8630.5052 | R5: =I5/('Scenario 1 - Phase 1'!$E$8+'LEVEL 3'!$E$8) -> 6807.5445 | U5: =C5/'Scenario 1 - Phase 1'!$B$8 -> 6.4554564 | X5: =F5/'LEVEL 3'!$B$8 -> 8.5298616 | AA5: =I5/('Scenario 1 - Phase 1'!$B$8+'LEVEL 3'!$B$8) -> 7.2578963
A6: General Requirements | B6: ='Scenario 1 - Phase 1'!K21 -> 2008563.6 | E6: ='LEVEL 3'!K21 -> 1674318 | H6: =B6+E6 -> 3682881.6 | K6: =B6/'Scenario 1 - Phase 1'!$E$8 -> 5788.3677 | N6: =E6/'LEVEL 3'!$E$8 -> 8630.5052 | Q6: =H6/('Scenario 1 - Phase 1'!$E$8+'LEVEL 3'!$E$8) -> 6807.5445 | T6: =B6/'Scenario 1 - Phase 1'!$B$8 -> 6.4554564 | W6: =E6/'LEVEL 3'!$B$8 -> 8.5298616 | Z6: =H6/('Scenario 1 - Phase 1'!$B$8+'LEVEL 3'!$B$8) -> 7.2578963
A7: Existing Conditions | C7: =B8 -> 8000 | F7: =E8 -> 3500 | I7: =H8 -> 11500 | L7: =K8 -> 23.054755 | O7: =N8 -> 18.041237 | R7: =Q8 -> 21.256932 | U7: =C7/'Scenario 1 - Phase 1'!$B$8 -> 0.025711733 | X7: =F7/'LEVEL 3'!$B$8 -> 0.017830851 | AA7: =I7/('Scenario 1 - Phase 1'!$B$8+'LEVEL 3'!$B$8) -> 0.02266318
A8: Potholing | B8: ='Scenario 1 - Phase 1'!K23 -> 8000 | E8: ='LEVEL 3'!K23 -> 3500 | H8: =B8+E8 -> 11500 | K8: =B8/'Scenario 1 - Phase 1'!$E$8 -> 23.054755 | N8: =E8/'LEVEL 3'!$E$8 -> 18.041237 | Q8: =H8/('Scenario 1 - Phase 1'!$E$8+'LEVEL 3'!$E$8) -> 21.256932 | T8: =B8/'Scenario 1 - Phase 1'!$B$8 -> 0.025711733 | W8: =E8/'LEVEL 3'!$B$8 -> 0.017830851 | Z8: =H8/('Scenario 1 - Phase 1'!$B$8+'LEVEL 3'!$B$8) -> 0.02266318
A9: Concrete | C9: =SUM(B10:B19) -> 1975170 | F9: =SUM(E10:E19) -> 1089279.8 | I9: =SUM(H10:H19) -> 3064449.8 | L9: =SUM(K10:K19) -> 5692.1326 | O9: =SUM(N10:N19) -> 5614.8444 | R9: =SUM(Q10:Q19) -> 5664.4174 | U9: =C9/'Scenario 1 - Phase 1'!$B$8 -> 6.3481305 | X9: =F9/'LEVEL 3'!$B$8 -> 5.5493676 | AA9: =I9/('Scenario 1 - Phase 1'!$B$8+'LEVEL 3'!$B$8) -> 6.0391459
A10: Slabs | B10: ='Scenario 1 - Phase 1'!K25 -> 1243530.9 | E10: ='LEVEL 3'!K25 -> 576982.78 | H10: =B10+E10 -> 1820513.6 | K10: =B10/'Scenario 1 - Phase 1'!$E$8 -> 3583.6624 | N10: =E10/'LEVEL 3'!$E$8 -> 2974.138 | Q10: =H10/('Scenario 1 - Phase 1'!$E$8+'LEVEL 3'!$E$8) -> 3365.0899 | T10: =B10/'Scenario 1 - Phase 1'!$B$8 -> 3.9966667 | W10: =E10/'LEVEL 3'!$B$8 -> 2.9394555 | Z10: =H10/('Scenario 1 - Phase 1'!$B$8+'LEVEL 3'!$B$8) -> 3.5877068
A11: Deepened Footings | B11: ='Scenario 1 - Phase 1'!K26 -> 0 | E11: ='LEVEL 3'!K26 -> 0 | H11: =B11+E11 -> 0 | K11: =B11/'Scenario 1 - Phase 1'!$E$8 -> 0 | N11: =E11/'LEVEL 3'!$E$8 -> 0 | Q11: =H11/('Scenario 1 - Phase 1'!$E$8+'LEVEL 3'!$E$8) -> 0 | T11: =B11/'Scenario 1 - Phase 1'!$B$8 -> 0 | W11: =E11/'LEVEL 3'!$B$8 -> 0 | Z11: =H11/('Scenario 1 - Phase 1'!$B$8+'LEVEL 3'!$B$8) -> 0
A12: Concrete Slab Repairs | B12: ='Scenario 1 - Phase 1'!K27 -> 7500 | E12: ='LEVEL 3'!K27 -> 2500 | H12: =B12+E12 -> 10000 | K12: =B12/'Scenario 1 - Phase 1'!$E$8 -> 21.613833 | N12: =E12/'LEVEL 3'!$E$8 -> 12.886598 | Q12: =H12/('Scenario 1 - Phase 1'!$E$8+'LEVEL 3'!$E$8) -> 18.484288 | T12: =B12/'Scenario 1 - Phase 1'!$B$8 -> 0.02410475 | W12: =E12/'LEVEL 3'!$B$8 -> 0.012736322 | Z12: =H12/('Scenario 1 - Phase 1'!$B$8+'LEVEL 3'!$B$8) -> 0.019707113
A13: Pump House Concrete | B13: ='Scenario 1 - Phase 1'!K28 -> 3597 | E13: ='LEVEL 3'!K28 -> 3597 | H13: =B13+E13 -> 7194 | K13: =B13/'Scenario 1 - Phase 1'!$E$8 -> 10.365994 | N13: =E13/'LEVEL 3'!$E$8 -> 18.541237 | Q13: =H13/('Scenario 1 - Phase 1'!$E$8+'LEVEL 3'!$E$8) -> 13.297597 | T13: =B13/'Scenario 1 - Phase 1'!$B$8 -> 0.011560638 | W13: =E13/'LEVEL 3'!$B$8 -> 0.018325021 | Z13: =H13/('Scenario 1 - Phase 1'!$B$8+'LEVEL 3'!$B$8) -> 0.014177297
A14: Trash Enclosure Concrete | B14: ='Scenario 1 - Phase 1'!K29 -> 26980 | E14: ='LEVEL 3'!K29 -> 11030.8 | H14: =B14+E14 -> 38010.8 | K14: =B14/'Scenario 1 - Phase 1'!$E$8 -> 77.752161 | N14: =E14/'LEVEL 3'!$E$8 -> 56.859794 | Q14: =H14/('Scenario 1 - Phase 1'!$E$8+'LEVEL 3'!$E$8) -> 70.260259 | T14: =B14/'Scenario 1 - Phase 1'!$B$8 -> 0.086712819 | W14: =E14/'LEVEL 3'!$B$8 -> 0.05619673 | Z14: =H14/('Scenario 1 - Phase 1'!$B$8+'LEVEL 3'!$B$8) -> 0.074908313
A15: Pool Area Shower Concrete | B15: ='Scenario 1 - Phase 1'!K30 -> 5000 | E15: ='LEVEL 3'!K30 -> 2500 | H15: =B15+E15 -> 7500 | K15: =B15/'Scenario 1 - Phase 1'!$E$8 -> 14.409222 | N15: =E15/'LEVEL 3'!$E$8 -> 12.886598 | Q15: =H15/('Scenario 1 - Phase 1'!$E$8+'LEVEL 3'!$E$8) -> 13.863216 | T15: =B15/'Scenario 1 - Phase 1'!$B$8 -> 0.016069833 | W15: =E15/'LEVEL 3'!$B$8 -> 0.012736322 | Z15: =H15/('Scenario 1 - Phase 1'!$B$8+'LEVEL 3'!$B$8) -> 0.014780335
A16: Cabana Concrete | B16: ='Scenario 1 - Phase 1'!K31 -> 0 | E16: ='LEVEL 3'!K31 -> 0 | H16: =B16+E16 -> 0 | K16: =B16/'Scenario 1 - Phase 1'!$E$8 -> 0 | N16: =E16/'LEVEL 3'!$E$8 -> 0 | Q16: =H16/('Scenario 1 - Phase 1'!$E$8+'LEVEL 3'!$E$8) -> 0 | T16: =B16/'Scenario 1 - Phase 1'!$B$8 -> 0 | W16: =E16/'LEVEL 3'!$B$8 -> 0 | Z16: =H16/('Scenario 1 - Phase 1'!$B$8+'LEVEL 3'!$B$8) -> 0
A17: Pool Equipment Foundation | B17: ='Scenario 1 - Phase 1'!K32 -> 0 | E17: ='LEVEL 3'!K32 -> 0 | H17: =B17+E17 -> 0 | K17: =B17/'Scenario 1 - Phase 1'!$E$8 -> 0 | N17: =E17/'LEVEL 3'!$E$8 -> 0 | Q17: =H17/('Scenario 1 - Phase 1'!$E$8+'LEVEL 3'!$E$8) -> 0 | T17: =B17/'Scenario 1 - Phase 1'!$B$8 -> 0 | W17: =E17/'LEVEL 3'!$B$8 -> 0 | Z17: =H17/('Scenario 1 - Phase 1'!$B$8+'LEVEL 3'!$B$8) -> 0
A18: Lightweight Concrete | B18: ='Scenario 1 - Phase 1'!K33 -> 609838.32 | E18: ='LEVEL 3'!K33 -> 432915 | H18: =B18+E18 -> 1042753.3 | K18: =B18/'Scenario 1 - Phase 1'!$E$8 -> 1757.4591 | N18: =E18/'LEVEL 3'!$E$8 -> 2231.5206 | Q18: =H18/('Scenario 1 - Phase 1'!$E$8+'LEVEL 3'!$E$8) -> 1927.4553 | T18: =B18/'Scenario 1 - Phase 1'!$B$8 -> 1.96 | W18: =E18/'LEVEL 3'!$B$8 -> 2.205498 | Z18: =H18/('Scenario 1 - Phase 1'!$B$8+'LEVEL 3'!$B$8) -> 2.0549657
A19: Deck Concrete | B19: ='Scenario 1 - Phase 1'!K34 -> 78723.84 | E19: ='LEVEL 3'!K34 -> 59754.24 | H19: =B19+E19 -> 138478.08 | K19: =B19/'Scenario 1 - Phase 1'!$E$8 -> 226.86986 | N19: =E19/'LEVEL 3'!$E$8 -> 308.01155 | Q19: =H19/('Scenario 1 - Phase 1'!$E$8+'LEVEL 3'!$E$8) -> 255.96688 | T19: =B19/'Scenario 1 - Phase 1'!$B$8 -> 0.25301579 | W19: =E19/'LEVEL 3'!$B$8 -> 0.30441971 | Z19: =H19/('Scenario 1 - Phase 1'!$B$8+'LEVEL 3'!$B$8) -> 0.27290032
A20: Parking Garage | C20: =SUM(B21:B28) -> 0 | F20: =SUM(E21:E28) -> 0 | I20: =SUM(H21:H28) -> 0 | L20: =SUM(K21:K28) -> 0 | O20: =SUM(N21:N28) -> 0 | R20: =SUM(Q21:Q28) -> 0 | U20: =C20/'Scenario 1 - Phase 1'!$B$8 -> 0 | X20: =F20/'LEVEL 3'!$B$8 -> 0 | AA20: =I20/('Scenario 1 - Phase 1'!$B$8+'LEVEL 3'!$B$8) -> 0
A21: Parking Garage Structure | B21: ='Scenario 1 - Phase 1'!K36 -> 0 | E21: ='LEVEL 3'!K36 -> 0 | H21: =B21+E21 -> 0 | K21: =B21/'Scenario 1 - Phase 1'!$E$8 -> 0 | N21: =E21/'LEVEL 3'!$E$8 -> 0 | Q21: =H21/('Scenario 1 - Phase 1'!$E$8+'LEVEL 3'!$E$8) -> 0 | T21: =B21/'Scenario 1 - Phase 1'!$B$8 -> 0 | W21: =E21/'LEVEL 3'!$B$8 -> 0 | Z21: =H21/('Scenario 1 - Phase 1'!$B$8+'LEVEL 3'!$B$8) -> 0
A22: Core Slab Precast Concrete | B22: ='Scenario 1 - Phase 1'!K37 -> 0 | E22: ='LEVEL 3'!K37 -> 0 | H22: =B22+E22 -> 0 | K22: =B22/'Scenario 1 - Phase 1'!$E$8 -> 0 | N22: =E22/'LEVEL 3'!$E$8 -> 0 | Q22: =H22/('Scenario 1 - Phase 1'!$E$8+'LEVEL 3'!$E$8) -> 0 | T22: =B22/'Scenario 1 - Phase 1'!$B$8 -> 0 | W22: =E22/'LEVEL 3'!$B$8 -> 0 | Z22: =H22/('Scenario 1 - Phase 1'!$B$8+'LEVEL 3'!$B$8) -> 0
A23: Concrete Slab on Grade | B23: ='Scenario 1 - Phase 1'!K38 -> 0 | E23: ='LEVEL 3'!K38 -> 0 | H23: =B23+E23 -> 0 | K23: =B23/'Scenario 1 - Phase 1'!$E$8 -> 0 | N23: =E23/'LEVEL 3'!$E$8 -> 0 | Q23: =H23/('Scenario 1 - Phase 1'!$E$8+'LEVEL 3'!$E$8) -> 0 | T23: =B23/'Scenario 1 - Phase 1'!$B$8 -> 0 | W23: =E23/'LEVEL 3'!$B$8 -> 0 | Z23: =H23/('Scenario 1 - Phase 1'!$B$8+'LEVEL 3'!$B$8) -> 0
A24: Concrete Topping Slab 4" / Level | B24: ='Scenario 1 - Phase 1'!K39 -> 0 | E24: ='LEVEL 3'!K39 -> 0 | H24: =B24+E24 -> 0 | K24: =B24/'Scenario 1 - Phase 1'!$E$8 -> 0 | N24: =E24/'LEVEL 3'!$E$8 -> 0 | Q24: =H24/('Scenario 1 - Phase 1'!$E$8+'LEVEL 3'!$E$8) -> 0 | T24: =B24/'Scenario 1 - Phase 1'!$B$8 -> 0 | W24: =E24/'LEVEL 3'!$B$8 -> 0 | Z24: =H24/('Scenario 1 - Phase 1'!$B$8+'LEVEL 3'!$B$8) -> 0
A25: Electrical | B25: ='Scenario 1 - Phase 1'!K40 -> 0 | E25: ='LEVEL 3'!K40 -> 0 | H25: =B25+E25 -> 0 | K25: =B25/'Scenario 1 - Phase 1'!$E$8 -> 0 | N25: =E25/'LEVEL 3'!$E$8 -> 0 | Q25: =H25/('Scenario 1 - Phase 1'!$E$8+'LEVEL 3'!$E$8) -> 0 | T25: =B25/'Scenario 1 - Phase 1'!$B$8 -> 0 | W25: =E25/'LEVEL 3'!$B$8 -> 0 | Z25: =H25/('Scenario 1 - Phase 1'!$B$8+'LEVEL 3'!$B$8) -> 0
A26: Dry Sprinklers | B26: ='Scenario 1 - Phase 1'!K41 -> 0 | E26: ='LEVEL 3'!K41 -> 0 | H26: =B26+E26 -> 0 | K26: =B26/'Scenario 1 - Phase 1'!$E$8 -> 0 | N26: =E26/'LEVEL 3'!$E$8 -> 0 | Q26: =H26/('Scenario 1 - Phase 1'!$E$8+'LEVEL 3'!$E$8) -> 0 | T26: =B26/'Scenario 1 - Phase 1'!$B$8 -> 0 | W26: =E26/'LEVEL 3'!$B$8 -> 0 | Z26: =H26/('Scenario 1 - Phase 1'!$B$8+'LEVEL 3'!$B$8) -> 0
A27: Mechanical Ventilation | B27: ='Scenario 1 - Phase 1'!K42 -> 0 | E27: ='LEVEL 3'!K42 -> 0 | H27: =B27+E27 -> 0 | K27: =B27/'Scenario 1 - Phase 1'!$E$8 -> 0 | N27: =E27/'LEVEL 3'!$E$8 -> 0 | Q27: =H27/('Scenario 1 - Phase 1'!$E$8+'LEVEL 3'!$E$8) -> 0 | T27: =B27/'Scenario 1 - Phase 1'!$B$8 -> 0 | W27: =E27/'LEVEL 3'!$B$8 -> 0 | Z27: =H27/('Scenario 1 - Phase 1'!$B$8+'LEVEL 3'!$B$8) -> 0
A28: Stairs and Railings | B28: ='Scenario 1 - Phase 1'!K43 -> 0 | E28: ='LEVEL 3'!K43 -> 0 | H28: =B28+E28 -> 0 | K28: =B28/'Scenario 1 - Phase 1'!$E$8 -> 0 | N28: =E28/'LEVEL 3'!$E$8 -> 0 | Q28: =H28/('Scenario 1 - Phase 1'!$E$8+'LEVEL 3'!$E$8) -> 0 | T28: =B28/'Scenario 1 - Phase 1'!$B$8 -> 0 | W28: =E28/'LEVEL 3'!$B$8 -> 0 | Z28: =H28/('Scenario 1 - Phase 1'!$B$8+'LEVEL 3'!$B$8) -> 0
A29: Masonry | C29: =SUM(B30:B34) -> 171000 | F29: =SUM(E30:E34) -> 112800 | I29: =SUM(H30:H34) -> 283800 | L29: =SUM(K30:K34) -> 492.79539 | O29: =SUM(N30:N34) -> 581.4433 | R29: =SUM(Q30:Q34) -> 524.5841 | U29: =C29/'Scenario 1 - Phase 1'!$B$8 -> 0.54958829 | X29: =F29/'LEVEL 3'!$B$8 -> 0.57466287 | AA29: =I29/('Scenario 1 - Phase 1'!$B$8+'LEVEL 3'!$B$8) -> 0.55928786
A30: Elevator Shaft | B30: ='Scenario 1 - Phase 1'!K45 -> 114000 | E30: ='LEVEL 3'!K45 -> 76000 | H30: =B30+E30 -> 190000 | K30: =B30/'Scenario 1 - Phase 1'!$E$8 -> 328.53026 | N30: =E30/'LEVEL 3'!$E$8 -> 391.75258 | Q30: =H30/('Scenario 1 - Phase 1'!$E$8+'LEVEL 3'!$E$8) -> 351.20148 | T30: =B30/'Scenario 1 - Phase 1'!$B$8 -> 0.36639219 | W30: =E30/'LEVEL 3'!$B$8 -> 0.3871842 | Z30: =H30/('Scenario 1 - Phase 1'!$B$8+'LEVEL 3'!$B$8) -> 0.37443514
A31: Trash Enclosure | B31: ='Scenario 1 - Phase 1'!K46 -> 57000 | E31: ='LEVEL 3'!K46 -> 22800 | H31: =B31+E31 -> 79800 | K31: =B31/'Scenario 1 - Phase 1'!$E$8 -> 164.26513 | N31: =E31/'LEVEL 3'!$E$8 -> 117.52577 | Q31: =H31/('Scenario 1 - Phase 1'!$E$8+'LEVEL 3'!$E$8) -> 147.50462 | T31: =B31/'Scenario 1 - Phase 1'!$B$8 -> 0.1831961 | W31: =E31/'LEVEL 3'!$B$8 -> 0.11615526 | Z31: =H31/('Scenario 1 - Phase 1'!$B$8+'LEVEL 3'!$B$8) -> 0.15726276
A32: Masonry Veneer | B32: ='Scenario 1 - Phase 1'!K47 -> 0 | E32: ='LEVEL 3'!K47 -> 0 | H32: =B32+E32 -> 0 | K32: =B32/'Scenario 1 - Phase 1'!$E$8 -> 0 | N32: =E32/'LEVEL 3'!$E$8 -> 0 | Q32: =H32/('Scenario 1 - Phase 1'!$E$8+'LEVEL 3'!$E$8) -> 0 | T32: =B32/'Scenario 1 - Phase 1'!$B$8 -> 0 | W32: =E32/'LEVEL 3'!$B$8 -> 0 | Z32: =H32/('Scenario 1 - Phase 1'!$B$8+'LEVEL 3'!$B$8) -> 0
A33: Masonry Veneer Pool Area | B33: ='Scenario 1 - Phase 1'!K48 -> 0 | E33: ='LEVEL 3'!K48 -> 5000 | H33: =B33+E33 -> 5000 | K33: =B33/'Scenario 1 - Phase 1'!$E$8 -> 0 | N33: =E33/'LEVEL 3'!$E$8 -> 25.773196 | Q33: =H33/('Scenario 1 - Phase 1'!$E$8+'LEVEL 3'!$E$8) -> 9.2421442 | T33: =B33/'Scenario 1 - Phase 1'!$B$8 -> 0 | W33: =E33/'LEVEL 3'!$B$8 -> 0.025472645 | Z33: =H33/('Scenario 1 - Phase 1'!$B$8+'LEVEL 3'!$B$8) -> 0.0098535564
A34: Pool Eq. Shower Stone | B34: ='Scenario 1 - Phase 1'!K49 -> 0 | E34: ='LEVEL 3'!K49 -> 9000 | H34: =B34+E34 -> 9000 | K34: =B34/'Scenario 1 - Phase 1'!$E$8 -> 0 | N34: =E34/'LEVEL 3'!$E$8 -> 46.391753 | Q34: =H34/('Scenario 1 - Phase 1'!$E$8+'LEVEL 3'!$E$8) -> 16.63586 | T34: =B34/'Scenario 1 - Phase 1'!$B$8 -> 0 | W34: =E34/'LEVEL 3'!$B$8 -> 0.045850761 | Z34: =H34/('Scenario 1 - Phase 1'!$B$8+'LEVEL 3'!$B$8) -> 0.017736402
A35: Metals | C35: =SUM(B36:B43) -> 392720.43 | F35: =SUM(E36:E43) -> 325412.13 | I35: =SUM(H36:H43) -> 718132.56 | L35: =SUM(K36:K43) -> 1131.7592 | O35: =SUM(N36:N43) -> 1677.3821 | R35: =SUM(Q36:Q43) -> 1327.4169 | U35: =C35/'Scenario 1 - Phase 1'!$B$8 -> 1.2621904 | X35: =F35/'LEVEL 3'!$B$8 -> 1.6578215 | AA35: =I35/('Scenario 1 - Phase 1'!$B$8+'LEVEL 3'!$B$8) -> 1.4152319
A36: Structural Steel | B36: ='Scenario 1 - Phase 1'!K51 -> 0 | E36: ='LEVEL 3'!K51 -> 112826.13 | H36: =B36+E36 -> 112826.13 | K36: =B36/'Scenario 1 - Phase 1'!$E$8 -> 0 | N36: =E36/'LEVEL 3'!$E$8 -> 581.57798 | Q36: =H36/('Scenario 1 - Phase 1'!$E$8+'LEVEL 3'!$E$8) -> 208.55107 | T36: =B36/'Scenario 1 - Phase 1'!$B$8 -> 0 | W36: =E36/'LEVEL 3'!$B$8 -> 0.57479598 | Z36: =H36/('Scenario 1 - Phase 1'!$B$8+'LEVEL 3'!$B$8) -> 0.22234772
A37: Elevator Shaft Iron | B37: ='Scenario 1 - Phase 1'!K52 -> 23960 | E37: ='LEVEL 3'!K52 -> 8080 | H37: =B37+E37 -> 32040 | K37: =B37/'Scenario 1 - Phase 1'!$E$8 -> 69.048991 | N37: =E37/'LEVEL 3'!$E$8 -> 41.649485 | Q37: =H37/('Scenario 1 - Phase 1'!$E$8+'LEVEL 3'!$E$8) -> 59.22366 | T37: =B37/'Scenario 1 - Phase 1'!$B$8 -> 0.07700664 | W37: =E37/'LEVEL 3'!$B$8 -> 0.041163794 | Z37: =H37/('Scenario 1 - Phase 1'!$B$8+'LEVEL 3'!$B$8) -> 0.06314159
A38: Stair Handrails | B38: ='Scenario 1 - Phase 1'!K53 -> 129250 | E38: ='LEVEL 3'!K53 -> 56000 | H38: =B38+E38 -> 185250 | K38: =B38/'Scenario 1 - Phase 1'!$E$8 -> 372.47839 | N38: =E38/'LEVEL 3'!$E$8 -> 288.65979 | Q38: =H38/('Scenario 1 - Phase 1'!$E$8+'LEVEL 3'!$E$8) -> 342.42144 | T38: =B38/'Scenario 1 - Phase 1'!$B$8 -> 0.41540518 | W38: =E38/'LEVEL 3'!$B$8 -> 0.28529362 | Z38: =H38/('Scenario 1 - Phase 1'!$B$8+'LEVEL 3'!$B$8) -> 0.36507427
A39: Garage Stair Railings | B39: ='Scenario 1 - Phase 1'!K54 -> 0 | E39: ='LEVEL 3'!K54 -> 0 | H39: =B39+E39 -> 0 | K39: =B39/'Scenario 1 - Phase 1'!$E$8 -> 0 | N39: =E39/'LEVEL 3'!$E$8 -> 0 | Q39: =H39/('Scenario 1 - Phase 1'!$E$8+'LEVEL 3'!$E$8) -> 0 | T39: =B39/'Scenario 1 - Phase 1'!$B$8 -> 0 | W39: =E39/'LEVEL 3'!$B$8 -> 0 | Z39: =H39/('Scenario 1 - Phase 1'!$B$8+'LEVEL 3'!$B$8) -> 0
A40: Cabana Iron | B40: ='Scenario 1 - Phase 1'!K55 -> 0 | E40: ='LEVEL 3'!K55 -> 0 | H40: =B40+E40 -> 0 | K40: =B40/'Scenario 1 - Phase 1'!$E$8 -> 0 | N40: =E40/'LEVEL 3'!$E$8 -> 0 | Q40: =H40/('Scenario 1 - Phase 1'!$E$8+'LEVEL 3'!$E$8) -> 0 | T40: =B40/'Scenario 1 - Phase 1'!$B$8 -> 0 | W40: =E40/'LEVEL 3'!$B$8 -> 0 | Z40: =H40/('Scenario 1 - Phase 1'!$B$8+'LEVEL 3'!$B$8) -> 0
A41: Pool Equipment Gate | B41: ='Scenario 1 - Phase 1'!K56 -> 3900 | E41: ='LEVEL 3'!K56 -> 1950 | H41: =B41+E41 -> 5850 | K41: =B41/'Scenario 1 - Phase 1'!$E$8 -> 11.239193 | N41: =E41/'LEVEL 3'!$E$8 -> 10.051546 | Q41: =H41/('Scenario 1 - Phase 1'!$E$8+'LEVEL 3'!$E$8) -> 10.813309 | T41: =B41/'Scenario 1 - Phase 1'!$B$8 -> 0.01253447 | W41: =E41/'LEVEL 3'!$B$8 -> 0.0099343315 | Z41: =H41/('Scenario 1 - Phase 1'!$B$8+'LEVEL 3'!$B$8) -> 0.011528661
A42: Iron Railings | B42: ='Scenario 1 - Phase 1'!K57 -> 235610.43 | E42: ='LEVEL 3'!K57 -> 146556 | H42: =B42+E42 -> 382166.43 | K42: =B42/'Scenario 1 - Phase 1'!$E$8 -> 678.99261 | N42: =E42/'LEVEL 3'!$E$8 -> 755.4433 | Q42: =H42/('Scenario 1 - Phase 1'!$E$8+'LEVEL 3'!$E$8) -> 706.40746 | T42: =B42/'Scenario 1 - Phase 1'!$B$8 -> 0.75724407 | W42: =E42/'LEVEL 3'!$B$8 -> 0.74663379 | Z42: =H42/('Scenario 1 - Phase 1'!$B$8+'LEVEL 3'!$B$8) -> 0.75313971
A43: Cable Railings | B43: ='Scenario 1 - Phase 1'!K58 -> 0 | E43: ='LEVEL 3'!K58 -> 0 | H43: =B43+E43 -> 0 | K43: =B43/'Scenario 1 - Phase 1'!$E$8 -> 0 | N43: =E43/'LEVEL 3'!$E$8 -> 0 | Q43: =H43/('Scenario 1 - Phase 1'!$E$8+'LEVEL 3'!$E$8) -> 0 | T43: =B43/'Scenario 1 - Phase 1'!$B$8 -> 0 | W43: =E43/'LEVEL 3'!$B$8 -> 0 | Z43: =H43/('Scenario 1 - Phase 1'!$B$8+'LEVEL 3'!$B$8) -> 0
A44: Wood, Plastics, & Composites | C44: =SUM(B45:B56) -> 7663075.4 | F44: =SUM(E45:E56) -> #REF! | I44: =SUM(H45:H56) -> #REF! | L44: =SUM(K45:K56) -> 22083.791 | O44: =SUM(N45:N56) -> #REF! | R44: =SUM(Q45:Q56) -> #REF! | U44: =C44/'Scenario 1 - Phase 1'!$B$8 -> 24.628868 | X44: =F44/'LEVEL 3'!$B$8 -> #REF! | AA44: =I44/('Scenario 1 - Phase 1'!$B$8+'LEVEL 3'!$B$8) -> #REF!
A45: Dumpsters | B45: ='Scenario 1 - Phase 1'!K60 -> 27413 | E45: ='LEVEL 3'!#REF! -> #REF! | H45: =B45+E45 -> #REF! | K45: =B45/'Scenario 1 - Phase 1'!$E$8 -> 79 | N45: =E45/'LEVEL 3'!$E$8 -> #REF! | Q45: =H45/('Scenario 1 - Phase 1'!$E$8+'LEVEL 3'!$E$8) -> #REF! | T45: =B45/'Scenario 1 - Phase 1'!$B$8 -> 0.088104467 | W45: =E45/'LEVEL 3'!$B$8 -> #REF! | Z45: =H45/('Scenario 1 - Phase 1'!$B$8+'LEVEL 3'!$B$8) -> #REF!
A46: Framing | B46: ='Scenario 1 - Phase 1'!K61 -> 6197948.6 | E46: ='LEVEL 3'!K60 -> 4008924.5 | H46: =B46+E46 -> 10206873 | K46: =B46/'Scenario 1 - Phase 1'!$E$8 -> 17861.523 | N46: =E46/'LEVEL 3'!$E$8 -> 20664.559 | Q46: =H46/('Scenario 1 - Phase 1'!$E$8+'LEVEL 3'!$E$8) -> 18866.679 | T46: =B46/'Scenario 1 - Phase 1'!$B$8 -> 19.92 | W46: =E46/'LEVEL 3'!$B$8 -> 20.423582 | Z46: =H46/('Scenario 1 - Phase 1'!$B$8+'LEVEL 3'!$B$8) -> 20.1148
A47: Framing - Crane | B47: ='Scenario 1 - Phase 1'!K62 -> 0 | E47: ='LEVEL 3'!K62 -> 0 | H47: =B47+E47 -> 0 | K47: =B47/'Scenario 1 - Phase 1'!$E$8 -> 0 | N47: =E47/'LEVEL 3'!$E$8 -> 0 | Q47: =H47/('Scenario 1 - Phase 1'!$E$8+'LEVEL 3'!$E$8) -> 0 | T47: =B47/'Scenario 1 - Phase 1'!$B$8 -> 0 | W47: =E47/'LEVEL 3'!$B$8 -> 0 | Z47: =H47/('Scenario 1 - Phase 1'!$B$8+'LEVEL 3'!$B$8) -> 0
A48: Cabana Framing | B48: ='Scenario 1 - Phase 1'!K63 -> 0 | E48: ='LEVEL 3'!K63 -> 0 | H48: =B48+E48 -> 0 | K48: =B48/'Scenario 1 - Phase 1'!$E$8 -> 0 | N48: =E48/'LEVEL 3'!$E$8 -> 0 | Q48: =H48/('Scenario 1 - Phase 1'!$E$8+'LEVEL 3'!$E$8) -> 0 | T48: =B48/'Scenario 1 - Phase 1'!$B$8 -> 0 | W48: =E48/'LEVEL 3'!$B$8 -> 0 | Z48: =H48/('Scenario 1 - Phase 1'!$B$8+'LEVEL 3'!$B$8) -> 0
A49: BBQ Framing | B49: ='Scenario 1 - Phase 1'!K64 -> 5620 | E49: ='LEVEL 3'!K64 -> 2500 | H49: =B49+E49 -> 8120 | K49: =B49/'Scenario 1 - Phase 1'!$E$8 -> 16.195965 | N49: =E49/'LEVEL 3'!$E$8 -> 12.886598 | Q49: =H49/('Scenario 1 - Phase 1'!$E$8+'LEVEL 3'!$E$8) -> 15.009242 | T49: =B49/'Scenario 1 - Phase 1'!$B$8 -> 0.018062492 | W49: =E49/'LEVEL 3'!$B$8 -> 0.012736322 | Z49: =H49/('Scenario 1 - Phase 1'!$B$8+'LEVEL 3'!$B$8) -> 0.016002176
A50: Fireplace Framing | B50: ='Scenario 1 - Phase 1'!K65 -> 0 | E50: ='LEVEL 3'!K65 -> 0 | H50: =B50+E50 -> 0 | K50: =B50/'Scenario 1 - Phase 1'!$E$8 -> 0 | N50: =E50/'LEVEL 3'!$E$8 -> 0 | Q50: =H50/('Scenario 1 - Phase 1'!$E$8+'LEVEL 3'!$E$8) -> 0 | T50: =B50/'Scenario 1 - Phase 1'!$B$8 -> 0 | W50: =E50/'LEVEL 3'!$B$8 -> 0 | Z50: =H50/('Scenario 1 - Phase 1'!$B$8+'LEVEL 3'!$B$8) -> 0
A51: Trellis | B51: ='Scenario 1 - Phase 1'!K66 -> 0 | E51: ='LEVEL 3'!K66 -> 0 | H51: =B51+E51 -> 0 | K51: =B51/'Scenario 1 - Phase 1'!$E$8 -> 0 | N51: =E51/'LEVEL 3'!$E$8 -> 0 | Q51: =H51/('Scenario 1 - Phase 1'!$E$8+'LEVEL 3'!$E$8) -> 0 | T51: =B51/'Scenario 1 - Phase 1'!$B$8 -> 0 | W51: =E51/'LEVEL 3'!$B$8 -> 0 | Z51: =H51/('Scenario 1 - Phase 1'!$B$8+'LEVEL 3'!$B$8) -> 0
A52: Pool Equipment Framing | B52: ='Scenario 1 - Phase 1'!K67 -> 0 | E52: ='LEVEL 3'!K67 -> 0 | H52: =B52+E52 -> 0 | K52: =B52/'Scenario 1 - Phase 1'!$E$8 -> 0 | N52: =E52/'LEVEL 3'!$E$8 -> 0 | Q52: =H52/('Scenario 1 - Phase 1'!$E$8+'LEVEL 3'!$E$8) -> 0 | T52: =B52/'Scenario 1 - Phase 1'!$B$8 -> 0 | W52: =E52/'LEVEL 3'!$B$8 -> 0 | Z52: =H52/('Scenario 1 - Phase 1'!$B$8+'LEVEL 3'!$B$8) -> 0
A53: Finish Carpentry - Units | B53: ='Scenario 1 - Phase 1'!K68 -> 1069107 | E53: ='LEVEL 3'!K68 -> 614845 | H53: =B53+E53 -> 1683952 | K53: =B53/'Scenario 1 - Phase 1'!$E$8 -> 3081 | N53: =E53/'LEVEL 3'!$E$8 -> 3169.3041 | Q53: =H53/('Scenario 1 - Phase 1'!$E$8+'LEVEL 3'!$E$8) -> 3112.6654 | T53: =B53/'Scenario 1 - Phase 1'!$B$8 -> 3.4360742 | W53: =E53/'LEVEL 3'!$B$8 -> 3.1323457 | Z53: =H53/('Scenario 1 - Phase 1'!$B$8+'LEVEL 3'!$B$8) -> 3.3185832
A54: Finish Carpentry - Common | B54: ='Scenario 1 - Phase 1'!K69 -> 360924.72 | E54: ='LEVEL 3'!K69 -> 157031.2 | H54: =B54+E54 -> 517955.92 | K54: =B54/'Scenario 1 - Phase 1'!$E$8 -> 1040.1289 | N54: =E54/'LEVEL 3'!$E$8 -> 809.43918 | Q54: =H54/('Scenario 1 - Phase 1'!$E$8+'LEVEL 3'!$E$8) -> 957.40466 | T54: =B54/'Scenario 1 - Phase 1'!$B$8 -> 1.16 | W54: =E54/'LEVEL 3'!$B$8 -> 0.8 | Z54: =H54/('Scenario 1 - Phase 1'!$B$8+'LEVEL 3'!$B$8) -> 1.0207416
A55: BBQ Trim | B55: ='Scenario 1 - Phase 1'!K70 -> 2062 | E55: ='LEVEL 3'!K71 -> 1200 | H55: =B55+E55 -> 3262 | K55: =B55/'Scenario 1 - Phase 1'!$E$8 -> 5.9423631 | N55: =E55/'LEVEL 3'!$E$8 -> 6.185567 | Q55: =H55/('Scenario 1 - Phase 1'!$E$8+'LEVEL 3'!$E$8) -> 6.0295749 | T55: =B55/'Scenario 1 - Phase 1'!$B$8 -> 0.0066271992 | W55: =E55/'LEVEL 3'!$B$8 -> 0.0061134348 | Z55: =H55/('Scenario 1 - Phase 1'!$B$8+'LEVEL 3'!$B$8) -> 0.0064284602
A56: Shutters | B56: ='Scenario 1 - Phase 1'!K71 -> 0 | E56: ='LEVEL 3'!K72 -> 0 | H56: =B56+E56 -> 0 | K56: =B56/'Scenario 1 - Phase 1'!$E$8 -> 0 | N56: =E56/'LEVEL 3'!$E$8 -> 0 | Q56: =H56/('Scenario 1 - Phase 1'!$E$8+'LEVEL 3'!$E$8) -> 0 | T56: =B56/'Scenario 1 - Phase 1'!$B$8 -> 0 | W56: =E56/'LEVEL 3'!$B$8 -> 0 | Z56: =H56/('Scenario 1 - Phase 1'!$B$8+'LEVEL 3'!$B$8) -> 0
A57: Thermal & Moisture Protection | C57: =SUM(B58:B68) -> 1573821.8 | F57: =SUM(E58:E68) -> 902986.76 | I57: =SUM(H58:H68) -> 2476808.6 | L57: =SUM(K58:K68) -> 4535.5096 | O57: =SUM(N58:N68) -> 4654.5709 | R57: =SUM(Q58:Q68) -> 4578.2044 | U57: =C57/'Scenario 1 - Phase 1'!$B$8 -> 5.0582108 | X57: =F57/'LEVEL 3'!$B$8 -> 4.6002922 | AA57: =I57/('Scenario 1 - Phase 1'!$B$8+'LEVEL 3'!$B$8) -> 4.8810746
A58: Insulation | B58: ='Scenario 1 - Phase 1'!K73 -> 790300.68 | E58: ='LEVEL 3'!K74 -> 527480.3 | H58: =B58+E58 -> 1317781 | K58: =B58/'Scenario 1 - Phase 1'!$E$8 -> 2277.5236 | N58: =E58/'LEVEL 3'!$E$8 -> 2718.9706 | Q58: =H58/('Scenario 1 - Phase 1'!$E$8+'LEVEL 3'!$E$8) -> 2435.8244 | T58: =B58/'Scenario 1 - Phase 1'!$B$8 -> 2.54 | W58: =E58/'LEVEL 3'!$B$8 -> 2.6872637 | Z58: =H58/('Scenario 1 - Phase 1'!$B$8+'LEVEL 3'!$B$8) -> 2.5969659
A59: Roofing | B59: ='Scenario 1 - Phase 1'!K74 -> 650172.69 | E59: ='LEVEL 3'!K76 -> 303688.89 | H59: =B59+E59 -> 953861.58 | K59: =B59/'Scenario 1 - Phase 1'!$E$8 -> 1873.6965 | N59: =E59/'LEVEL 3'!$E$8 -> 1565.4066 | Q59: =H59/('Scenario 1 - Phase 1'!$E$8+'LEVEL 3'!$E$8) -> 1763.1452 | T59: =B59/'Scenario 1 - Phase 1'!$B$8 -> 2.0896333 | W59: =E59/'LEVEL 3'!$B$8 -> 1.5471519 | Z59: =H59/('Scenario 1 - Phase 1'!$B$8+'LEVEL 3'!$B$8) -> 1.8797858
A60: Cabana Roofing | B60: ='Scenario 1 - Phase 1'!K75 -> 0 | E60: ='LEVEL 3'!K77 -> 0 | H60: =B60+E60 -> 0 | K60: =B60/'Scenario 1 - Phase 1'!$E$8 -> 0 | N60: =E60/'LEVEL 3'!$E$8 -> 0 | Q60: =H60/('Scenario 1 - Phase 1'!$E$8+'LEVEL 3'!$E$8) -> 0 | T60: =B60/'Scenario 1 - Phase 1'!$B$8 -> 0 | W60: =E60/'LEVEL 3'!$B$8 -> 0 | Z60: =H60/('Scenario 1 - Phase 1'!$B$8+'LEVEL 3'!$B$8) -> 0
A61: Pump House Roofing | B61: ='Scenario 1 - Phase 1'!K76 -> 6700 | E61: ='LEVEL 3'!K78 -> 7500 | H61: =B61+E61 -> 14200 | K61: =B61/'Scenario 1 - Phase 1'!$E$8 -> 19.308357 | N61: =E61/'LEVEL 3'!$E$8 -> 38.659794 | Q61: =H61/('Scenario 1 - Phase 1'!$E$8+'LEVEL 3'!$E$8) -> 26.247689 | T61: =B61/'Scenario 1 - Phase 1'!$B$8 -> 0.021533576 | W61: =E61/'LEVEL 3'!$B$8 -> 0.038208967 | Z61: =H61/('Scenario 1 - Phase 1'!$B$8+'LEVEL 3'!$B$8) -> 0.0279841
A62: Pool Equipment Roofing | B62: ='Scenario 1 - Phase 1'!K77 -> 0 | E62: ='LEVEL 3'!K79 -> 7500 | H62: =B62+E62 -> 7500 | K62: =B62/'Scenario 1 - Phase 1'!$E$8 -> 0 | N62: =E62/'LEVEL 3'!$E$8 -> 38.659794 | Q62: =H62/('Scenario 1 - Phase 1'!$E$8+'LEVEL 3'!$E$8) -> 13.863216 | T62: =B62/'Scenario 1 - Phase 1'!$B$8 -> 0 | W62: =E62/'LEVEL 3'!$B$8 -> 0.038208967 | Z62: =H62/('Scenario 1 - Phase 1'!$B$8+'LEVEL 3'!$B$8) -> 0.014780335
A63: Trash Enclosure Cover | B63: ='Scenario 1 - Phase 1'!K78 -> 70000 | E63: ='LEVEL 3'!K80 -> 23200 | H63: =B63+E63 -> 93200 | K63: =B63/'Scenario 1 - Phase 1'!$E$8 -> 201.72911 | N63: =E63/'LEVEL 3'!$E$8 -> 119.58763 | Q63: =H63/('Scenario 1 - Phase 1'!$E$8+'LEVEL 3'!$E$8) -> 172.27357 | T63: =B63/'Scenario 1 - Phase 1'!$B$8 -> 0.22497766 | W63: =E63/'LEVEL 3'!$B$8 -> 0.11819307 | Z63: =H63/('Scenario 1 - Phase 1'!$B$8+'LEVEL 3'!$B$8) -> 0.18367029
A64: Pigeon Proofing | B64: ='Scenario 1 - Phase 1'!K79 -> 24891.36 | E64: ='LEVEL 3'!K81 -> 15703.12 | H64: =B64+E64 -> 40594.48 | K64: =B64/'Scenario 1 - Phase 1'!$E$8 -> 71.733026 | N64: =E64/'LEVEL 3'!$E$8 -> 80.943918 | Q64: =H64/('Scenario 1 - Phase 1'!$E$8+'LEVEL 3'!$E$8) -> 75.036007 | T64: =B64/'Scenario 1 - Phase 1'!$B$8 -> 0.08 | W64: =E64/'LEVEL 3'!$B$8 -> 0.08 | Z64: =H64/('Scenario 1 - Phase 1'!$B$8+'LEVEL 3'!$B$8) -> 0.08
A65: Gutters and Downspouts | B65: ='Scenario 1 - Phase 1'!K80 -> 15557.1 | E65: ='LEVEL 3'!K82 -> 9814.45 | H65: =B65+E65 -> 25371.55 | K65: =B65/'Scenario 1 - Phase 1'!$E$8 -> 44.833141 | N65: =E65/'LEVEL 3'!$E$8 -> 50.589948 | Q65: =H65/('Scenario 1 - Phase 1'!$E$8+'LEVEL 3'!$E$8) -> 46.897505 | T65: =B65/'Scenario 1 - Phase 1'!$B$8 -> 0.05 | W65: =E65/'LEVEL 3'!$B$8 -> 0.05 | Z65: =H65/('Scenario 1 - Phase 1'!$B$8+'LEVEL 3'!$B$8) -> 0.05
A66: Roof Ladders | B66: ='Scenario 1 - Phase 1'!K81 -> 6200 | E66: ='LEVEL 3'!K83 -> 3100 | H66: =B66+E66 -> 9300 | K66: =B66/'Scenario 1 - Phase 1'!$E$8 -> 17.867435 | N66: =E66/'LEVEL 3'!$E$8 -> 15.979381 | Q66: =H66/('Scenario 1 - Phase 1'!$E$8+'LEVEL 3'!$E$8) -> 17.190388 | T66: =B66/'Scenario 1 - Phase 1'!$B$8 -> 0.019926593 | W66: =E66/'LEVEL 3'!$B$8 -> 0.01579304 | Z66: =H66/('Scenario 1 - Phase 1'!$B$8+'LEVEL 3'!$B$8) -> 0.018327615
A67: Roof Access Doors | B67: ='Scenario 1 - Phase 1'!K82 -> 10000 | E67: ='LEVEL 3'!K84 -> 5000 | H67: =B67+E67 -> 15000 | K67: =B67/'Scenario 1 - Phase 1'!$E$8 -> 28.818444 | N67: =E67/'LEVEL 3'!$E$8 -> 25.773196 | Q67: =H67/('Scenario 1 - Phase 1'!$E$8+'LEVEL 3'!$E$8) -> 27.726433 | T67: =B67/'Scenario 1 - Phase 1'!$B$8 -> 0.032139666 | W67: =E67/'LEVEL 3'!$B$8 -> 0.025472645 | Z67: =H67/('Scenario 1 - Phase 1'!$B$8+'LEVEL 3'!$B$8) -> 0.029560669
A68: Roof Winch | B68: ='Scenario 1 - Phase 1'!K83 -> 0 | E68: ='LEVEL 3'!K85 -> 0 | H68: =B68+E68 -> 0 | K68: =B68/'Scenario 1 - Phase 1'!$E$8 -> 0 | N68: =E68/'LEVEL 3'!$E$8 -> 0 | Q68: =H68/('Scenario 1 - Phase 1'!$E$8+'LEVEL 3'!$E$8) -> 0 | T68: =B68/'Scenario 1 - Phase 1'!$B$8 -> 0 | W68: =E68/'LEVEL 3'!$B$8 -> 0 | Z68: =H68/('Scenario 1 - Phase 1'!$B$8+'LEVEL 3'!$B$8) -> 0
A69: Openings | C69: =SUM(B70:B84) -> 548400.7 | F69: =SUM(E70:E84) -> #REF! | I69: =SUM(H70:H84) -> #REF! | L69: =SUM(K70:K84) -> 1580.4055 | O69: =SUM(N70:N84) -> #REF! | R69: =SUM(Q70:Q84) -> #REF! | U69: =C69/'Scenario 1 - Phase 1'!$B$8 -> 1.7625415 | X69: =F69/'LEVEL 3'!$B$8 -> #REF! | AA69: =I69/('Scenario 1 - Phase 1'!$B$8+'LEVEL 3'!$B$8) -> #REF!
A70: Dumpsters | B70: ='Scenario 1 - Phase 1'!K85 -> 27413 | E70: ='LEVEL 3'!#REF! -> #REF! | H70: =B70+E70 -> #REF! | K70: =B70/'Scenario 1 - Phase 1'!$E$8 -> 79 | N70: =E70/'LEVEL 3'!$E$8 -> #REF! | Q70: =H70/('Scenario 1 - Phase 1'!$E$8+'LEVEL 3'!$E$8) -> #REF! | T70: =B70/'Scenario 1 - Phase 1'!$B$8 -> 0.088104467 | W70: =E70/'LEVEL 3'!$B$8 -> #REF! | Z70: =H70/('Scenario 1 - Phase 1'!$B$8+'LEVEL 3'!$B$8) -> #REF!
A71: Entry Doors | B71: ='Scenario 1 - Phase 1'!K86 -> 0 | E71: ='LEVEL 3'!K87 -> 8000 | H71: =B71+E71 -> 8000 | K71: =B71/'Scenario 1 - Phase 1'!$E$8 -> 0 | N71: =E71/'LEVEL 3'!$E$8 -> 41.237113 | Q71: =H71/('Scenario 1 - Phase 1'!$E$8+'LEVEL 3'!$E$8) -> 14.787431 | T71: =B71/'Scenario 1 - Phase 1'!$B$8 -> 0 | W71: =E71/'LEVEL 3'!$B$8 -> 0.040756232 | Z71: =H71/('Scenario 1 - Phase 1'!$B$8+'LEVEL 3'!$B$8) -> 0.01576569
A72: Common Doors | B72: ='Scenario 1 - Phase 1'!K87 -> 0 | E72: ='LEVEL 3'!K88 -> 0 | H72: =B72+E72 -> 0 | K72: =B72/'Scenario 1 - Phase 1'!$E$8 -> 0 | N72: =E72/'LEVEL 3'!$E$8 -> 0 | Q72: =H72/('Scenario 1 - Phase 1'!$E$8+'LEVEL 3'!$E$8) -> 0 | T72: =B72/'Scenario 1 - Phase 1'!$B$8 -> 0 | W72: =E72/'LEVEL 3'!$B$8 -> 0 | Z72: =H72/('Scenario 1 - Phase 1'!$B$8+'LEVEL 3'!$B$8) -> 0
A73: Pocket Doors - 3 Panel | B73: ='Scenario 1 - Phase 1'!K88 -> 0 | E73: ='LEVEL 3'!K89 -> 0 | H73: =B73+E73 -> 0 | K73: =B73/'Scenario 1 - Phase 1'!$E$8 -> 0 | N73: =E73/'LEVEL 3'!$E$8 -> 0 | Q73: =H73/('Scenario 1 - Phase 1'!$E$8+'LEVEL 3'!$E$8) -> 0 | T73: =B73/'Scenario 1 - Phase 1'!$B$8 -> 0 | W73: =E73/'LEVEL 3'!$B$8 -> 0 | Z73: =H73/('Scenario 1 - Phase 1'!$B$8+'LEVEL 3'!$B$8) -> 0
A74: Garage Doors | B74: ='Scenario 1 - Phase 1'!K89 -> 0 | E74: ='LEVEL 3'!K90 -> 0 | H74: =B74+E74 -> 0 | K74: =B74/'Scenario 1 - Phase 1'!$E$8 -> 0 | N74: =E74/'LEVEL 3'!$E$8 -> 0 | Q74: =H74/('Scenario 1 - Phase 1'!$E$8+'LEVEL 3'!$E$8) -> 0 | T74: =B74/'Scenario 1 - Phase 1'!$B$8 -> 0 | W74: =E74/'LEVEL 3'!$B$8 -> 0 | Z74: =H74/('Scenario 1 - Phase 1'!$B$8+'LEVEL 3'!$B$8) -> 0
A75: Windows and Sliding Glass Doors | B75: ='Scenario 1 - Phase 1'!K90 -> 431702.7 | E75: ='LEVEL 3'!K91 -> 224631.58 | H75: =B75+E75 -> 656334.28 | K75: =B75/'Scenario 1 - Phase 1'!$E$8 -> 1244.1 | N75: =E75/'LEVEL 3'!$E$8 -> 1157.8947 | Q75: =H75/('Scenario 1 - Phase 1'!$E$8+'LEVEL 3'!$E$8) -> 1213.1872 | T75: =B75/'Scenario 1 - Phase 1'!$B$8 -> 1.3874781 | W75: =E75/'LEVEL 3'!$B$8 -> 1.1443921 | Z75: =H75/('Scenario 1 - Phase 1'!$B$8+'LEVEL 3'!$B$8) -> 1.2934454
A76: Windows Repair and Replacement | B76: ='Scenario 1 - Phase 1'!K91 -> 26025 | E76: ='LEVEL 3'!K92 -> 14550 | H76: =B76+E76 -> 40575 | K76: =B76/'Scenario 1 - Phase 1'!$E$8 -> 75 | N76: =E76/'LEVEL 3'!$E$8 -> 75 | Q76: =H76/('Scenario 1 - Phase 1'!$E$8+'LEVEL 3'!$E$8) -> 75 | T76: =B76/'Scenario 1 - Phase 1'!$B$8 -> 0.083643481 | W76: =E76/'LEVEL 3'!$B$8 -> 0.074125397 | Z76: =H76/('Scenario 1 - Phase 1'!$B$8+'LEVEL 3'!$B$8) -> 0.079961611
A77: Pool Equipment Windows | B77: ='Scenario 1 - Phase 1'!K92 -> 0 | E77: ='LEVEL 3'!K93 -> 0 | H77: =B77+E77 -> 0 | K77: =B77/'Scenario 1 - Phase 1'!$E$8 -> 0 | N77: =E77/'LEVEL 3'!$E$8 -> 0 | Q77: =H77/('Scenario 1 - Phase 1'!$E$8+'LEVEL 3'!$E$8) -> 0 | T77: =B77/'Scenario 1 - Phase 1'!$B$8 -> 0 | W77: =E77/'LEVEL 3'!$B$8 -> 0 | Z77: =H77/('Scenario 1 - Phase 1'!$B$8+'LEVEL 3'!$B$8) -> 0
A78: Pool Glass Walls | B78: ='Scenario 1 - Phase 1'!K93 -> 0 | E78: ='LEVEL 3'!K94 -> 0 | H78: =B78+E78 -> 0 | K78: =B78/'Scenario 1 - Phase 1'!$E$8 -> 0 | N78: =E78/'LEVEL 3'!$E$8 -> 0 | Q78: =H78/('Scenario 1 - Phase 1'!$E$8+'LEVEL 3'!$E$8) -> 0 | T78: =B78/'Scenario 1 - Phase 1'!$B$8 -> 0 | W78: =E78/'LEVEL 3'!$B$8 -> 0 | Z78: =H78/('Scenario 1 - Phase 1'!$B$8+'LEVEL 3'!$B$8) -> 0
A79: Fixed Glass | B79: ='Scenario 1 - Phase 1'!K94 -> 0 | E79: ='LEVEL 3'!K95 -> 0 | H79: =B79+E79 -> 0 | K79: =B79/'Scenario 1 - Phase 1'!$E$8 -> 0 | N79: =E79/'LEVEL 3'!$E$8 -> 0 | Q79: =H79/('Scenario 1 - Phase 1'!$E$8+'LEVEL 3'!$E$8) -> 0 | T79: =B79/'Scenario 1 - Phase 1'!$B$8 -> 0 | W79: =E79/'LEVEL 3'!$B$8 -> 0 | Z79: =H79/('Scenario 1 - Phase 1'!$B$8+'LEVEL 3'!$B$8) -> 0
A80: Mirrors - LED | B80: ='Scenario 1 - Phase 1'!K95 -> 0 | E80: ='LEVEL 3'!K96 -> 0 | H80: =B80+E80 -> 0 | K80: =B80/'Scenario 1 - Phase 1'!$E$8 -> 0 | N80: =E80/'LEVEL 3'!$E$8 -> 0 | Q80: =H80/('Scenario 1 - Phase 1'!$E$8+'LEVEL 3'!$E$8) -> 0 | T80: =B80/'Scenario 1 - Phase 1'!$B$8 -> 0 | W80: =E80/'LEVEL 3'!$B$8 -> 0 | Z80: =H80/('Scenario 1 - Phase 1'!$B$8+'LEVEL 3'!$B$8) -> 0
A81: Mirrors - LED Install | B81: ='Scenario 1 - Phase 1'!K96 -> 0 | E81: ='LEVEL 3'!K97 -> 0 | H81: =B81+E81 -> 0 | K81: =B81/'Scenario 1 - Phase 1'!$E$8 -> 0 | N81: =E81/'LEVEL 3'!$E$8 -> 0 | Q81: =H81/('Scenario 1 - Phase 1'!$E$8+'LEVEL 3'!$E$8) -> 0 | T81: =B81/'Scenario 1 - Phase 1'!$B$8 -> 0 | W81: =E81/'LEVEL 3'!$B$8 -> 0 | Z81: =H81/('Scenario 1 - Phase 1'!$B$8+'LEVEL 3'!$B$8) -> 0
A82: Mirrors - Framed | B82: ='Scenario 1 - Phase 1'!K97 -> 0 | E82: ='LEVEL 3'!K98 -> 0 | H82: =B82+E82 -> 0 | K82: =B82/'Scenario 1 - Phase 1'!$E$8 -> 0 | N82: =E82/'LEVEL 3'!$E$8 -> 0 | Q82: =H82/('Scenario 1 - Phase 1'!$E$8+'LEVEL 3'!$E$8) -> 0 | T82: =B82/'Scenario 1 - Phase 1'!$B$8 -> 0 | W82: =E82/'LEVEL 3'!$B$8 -> 0 | Z82: =H82/('Scenario 1 - Phase 1'!$B$8+'LEVEL 3'!$B$8) -> 0
... A84: Mirrors - Polished Edges (Restrooms) | B84: ='Scenario 1 - Phase 1'!K99 -> 800 | E84: ='LEVEL 3'!K100 -> 500 | H84: =B84+E84 -> 1300 | K84: =B84/'Scenario 1 - Phase 1'!$E$8 -> 2.3054755 | N84: =E84/'LEVEL 3'!$E$8 -> 2.5773196 | Q84: =H84/('Scenario 1 - Phase 1'!$E$8+'LEVEL 3'!$E$8) -> 2.4029575 | T84: =B84/'Scenario 1 - Phase 1'!$B$8 -> 0.0025711733 | W84: =E84/'LEVEL 3'!$B$8 -> 0.0025472645 | Z84: =H84/('Scenario 1 - Phase 1'!$B$8+'LEVEL 3'!$B$8) -> 0.0025619247
A85: Finishes | C85: =SUM(B86:B121) -> 5170494.2 | F85: =SUM(E86:E121) -> #REF! | I85: =SUM(H86:H121) -> #REF! | L85: =SUM(K86:K121) -> 14900.56 | O85: =SUM(N86:N121) -> #REF! | R85: =SUM(Q86:Q121) -> #REF! | U85: =C85/'Scenario 1 - Phase 1'!$B$8 -> 16.617796 | X85: =F85/'LEVEL 3'!$B$8 -> #REF! | AA85: =I85/('Scenario 1 - Phase 1'!$B$8+'LEVEL 3'!$B$8) -> #REF!
A86: Cost Prep Labor | B86: ='Scenario 1 - Phase 1'!K101 -> 15557.1 | E86: ='LEVEL 3'!#REF! -> #REF! | H86: =B86+E86 -> #REF! | K86: =B86/'Scenario 1 - Phase 1'!$E$8 -> 44.833141 | N86: =E86/'LEVEL 3'!$E$8 -> #REF! | Q86: =H86/('Scenario 1 - Phase 1'!$E$8+'LEVEL 3'!$E$8) -> #REF! | T86: =B86/'Scenario 1 - Phase 1'!$B$8 -> 0.05 | W86: =E86/'LEVEL 3'!$B$8 -> #REF! | Z86: =H86/('Scenario 1 - Phase 1'!$B$8+'LEVEL 3'!$B$8) -> #REF!
A87: Cost Prep Mat | B87: ='Scenario 1 - Phase 1'!K102 -> 24891.36 | E87: ='LEVEL 3'!K102 -> 10000 | H87: =B87+E87 -> 34891.36 | K87: =B87/'Scenario 1 - Phase 1'!$E$8 -> 71.733026 | N87: =E87/'LEVEL 3'!$E$8 -> 51.546392 | Q87: =H87/('Scenario 1 - Phase 1'!$E$8+'LEVEL 3'!$E$8) -> 64.494196 | T87: =B87/'Scenario 1 - Phase 1'!$B$8 -> 0.08 | W87: =E87/'LEVEL 3'!$B$8 -> 0.05094529 | Z87: =H87/('Scenario 1 - Phase 1'!$B$8+'LEVEL 3'!$B$8) -> 0.068760797
A88: Clean Up - Final | B88: ='Scenario 1 - Phase 1'!K103 -> 186685.2 | E88: ='LEVEL 3'!K103 -> 166845.65 | H88: =B88+E88 -> 353530.85 | K88: =B88/'Scenario 1 - Phase 1'!$E$8 -> 537.99769 | N88: =E88/'LEVEL 3'!$E$8 -> 860.02912 | Q88: =H88/('Scenario 1 - Phase 1'!$E$8+'LEVEL 3'!$E$8) -> 653.47662 | T88: =B88/'Scenario 1 - Phase 1'!$B$8 -> 0.6 | W88: =E88/'LEVEL 3'!$B$8 -> 0.85 | Z88: =H88/('Scenario 1 - Phase 1'!$B$8+'LEVEL 3'!$B$8) -> 0.69670724
A89: Clean Up - During Construction | B89: ='Scenario 1 - Phase 1'!K104 -> 112011.12 | E89: ='LEVEL 3'!K104 -> 50000 | H89: =B89+E89 -> 162011.12 | K89: =B89/'Scenario 1 - Phase 1'!$E$8 -> 322.79862 | N89: =E89/'LEVEL 3'!$E$8 -> 257.73196 | Q89: =H89/('Scenario 1 - Phase 1'!$E$8+'LEVEL 3'!$E$8) -> 299.46603 | T89: =B89/'Scenario 1 - Phase 1'!$B$8 -> 0.36 | W89: =E89/'LEVEL 3'!$B$8 -> 0.25472645 | Z89: =H89/('Scenario 1 - Phase 1'!$B$8+'LEVEL 3'!$B$8) -> 0.31927714
A90: Dumpsters | B90: ='Scenario 1 - Phase 1'!K105 -> 27413 | E90: ='LEVEL 3'!K105 -> 15326 | H90: =B90+E90 -> 42739 | K90: =B90/'Scenario 1 - Phase 1'!$E$8 -> 79 | N90: =E90/'LEVEL 3'!$E$8 -> 79 | Q90: =H90/('Scenario 1 - Phase 1'!$E$8+'LEVEL 3'!$E$8) -> 79 | T90: =B90/'Scenario 1 - Phase 1'!$B$8 -> 0.088104467 | W90: =E90/'LEVEL 3'!$B$8 -> 0.078078751 | Z90: =H90/('Scenario 1 - Phase 1'!$B$8+'LEVEL 3'!$B$8) -> 0.08422623
A91: Clean Up - Hauling Exterior | B91: ='Scenario 1 - Phase 1'!K106 -> 34225.62 | E91: ='LEVEL 3'!K106 -> 10000 | H91: =B91+E91 -> 44225.62 | K91: =B91/'Scenario 1 - Phase 1'!$E$8 -> 98.632911 | N91: =E91/'LEVEL 3'!$E$8 -> 51.546392 | Q91: =H91/('Scenario 1 - Phase 1'!$E$8+'LEVEL 3'!$E$8) -> 81.747911 | T91: =B91/'Scenario 1 - Phase 1'!$B$8 -> 0.11 | W91: =E91/'LEVEL 3'!$B$8 -> 0.05094529 | Z91: =H91/('Scenario 1 - Phase 1'!$B$8+'LEVEL 3'!$B$8) -> 0.087155929
A92: Stucco | B92: ='Scenario 1 - Phase 1'!K107 -> 637587.69 | E92: ='LEVEL 3'!K107 -> 482655.68 | H92: =B92+E92 -> 1120243.4 | K92: =B92/'Scenario 1 - Phase 1'!$E$8 -> 1837.4285 | N92: =E92/'LEVEL 3'!$E$8 -> 2487.9159 | Q92: =H92/('Scenario 1 - Phase 1'!$E$8+'LEVEL 3'!$E$8) -> 2070.6901 | T92: =B92/'Scenario 1 - Phase 1'!$B$8 -> 2.0491855 | W92: =E92/'LEVEL 3'!$B$8 -> 2.4589034 | Z92: =H92/('Scenario 1 - Phase 1'!$B$8+'LEVEL 3'!$B$8) -> 2.2076762
A93: Stucco - Pump House | B93: ='Scenario 1 - Phase 1'!K108 -> 6000 | E93: ='LEVEL 3'!K108 -> 6000 | H93: =B93+E93 -> 12000 | K93: =B93/'Scenario 1 - Phase 1'!$E$8 -> 17.291066 | N93: =E93/'LEVEL 3'!$E$8 -> 30.927835 | Q93: =H93/('Scenario 1 - Phase 1'!$E$8+'LEVEL 3'!$E$8) -> 22.181146 | T93: =B93/'Scenario 1 - Phase 1'!$B$8 -> 0.0192838 | W93: =E93/'LEVEL 3'!$B$8 -> 0.030567174 | Z93: =H93/('Scenario 1 - Phase 1'!$B$8+'LEVEL 3'!$B$8) -> 0.023648535
A94: Stucco - Walls | B94: ='Scenario 1 - Phase 1'!K109 -> 0 | E94: ='LEVEL 3'!K109 -> 0 | H94: =B94+E94 -> 0 | K94: =B94/'Scenario 1 - Phase 1'!$E$8 -> 0 | N94: =E94/'LEVEL 3'!$E$8 -> 0 | Q94: =H94/('Scenario 1 - Phase 1'!$E$8+'LEVEL 3'!$E$8) -> 0 | T94: =B94/'Scenario 1 - Phase 1'!$B$8 -> 0 | W94: =E94/'LEVEL 3'!$B$8 -> 0 | Z94: =H94/('Scenario 1 - Phase 1'!$B$8+'LEVEL 3'!$B$8) -> 0
A95: Stucco - Pool Area | B95: ='Scenario 1 - Phase 1'!K110 -> 4000 | E95: ='LEVEL 3'!K110 -> 2000 | H95: =B95+E95 -> 6000 | K95: =B95/'Scenario 1 - Phase 1'!$E$8 -> 11.527378 | N95: =E95/'LEVEL 3'!$E$8 -> 10.309278 | Q95: =H95/('Scenario 1 - Phase 1'!$E$8+'LEVEL 3'!$E$8) -> 11.090573 | T95: =B95/'Scenario 1 - Phase 1'!$B$8 -> 0.012855866 | W95: =E95/'LEVEL 3'!$B$8 -> 0.010189058 | Z95: =H95/('Scenario 1 - Phase 1'!$B$8+'LEVEL 3'!$B$8) -> 0.011824268
A96: Stucco - Cabana | B96: ='Scenario 1 - Phase 1'!K111 -> 0 | E96: ='LEVEL 3'!K111 -> 0 | H96: =B96+E96 -> 0 | K96: =B96/'Scenario 1 - Phase 1'!$E$8 -> 0 | N96: =E96/'LEVEL 3'!$E$8 -> 0 | Q96: =H96/('Scenario 1 - Phase 1'!$E$8+'LEVEL 3'!$E$8) -> 0 | T96: =B96/'Scenario 1 - Phase 1'!$B$8 -> 0 | W96: =E96/'LEVEL 3'!$B$8 -> 0 | Z96: =H96/('Scenario 1 - Phase 1'!$B$8+'LEVEL 3'!$B$8) -> 0
A97: Stucco - Pool Equipment | B97: ='Scenario 1 - Phase 1'!K112 -> 0 | E97: ='LEVEL 3'!K112 -> 5000 | H97: =B97+E97 -> 5000 | K97: =B97/'Scenario 1 - Phase 1'!$E$8 -> 0 | N97: =E97/'LEVEL 3'!$E$8 -> 25.773196 | Q97: =H97/('Scenario 1 - Phase 1'!$E$8+'LEVEL 3'!$E$8) -> 9.2421442 | T97: =B97/'Scenario 1 - Phase 1'!$B$8 -> 0 | W97: =E97/'LEVEL 3'!$B$8 -> 0.025472645 | Z97: =H97/('Scenario 1 - Phase 1'!$B$8+'LEVEL 3'!$B$8) -> 0.0098535564
A98: Stucco - Repairs | B98: ='Scenario 1 - Phase 1'!K113 -> 4500 | E98: ='LEVEL 3'!K113 -> 1500 | H98: =B98+E98 -> 6000 | K98: =B98/'Scenario 1 - Phase 1'!$E$8 -> 12.9683 | N98: =E98/'LEVEL 3'!$E$8 -> 7.7319588 | Q98: =H98/('Scenario 1 - Phase 1'!$E$8+'LEVEL 3'!$E$8) -> 11.090573 | T98: =B98/'Scenario 1 - Phase 1'!$B$8 -> 0.01446285 | W98: =E98/'LEVEL 3'!$B$8 -> 0.0076417935 | Z98: =H98/('Scenario 1 - Phase 1'!$B$8+'LEVEL 3'!$B$8) -> 0.011824268
A99: Drywall | B99: ='Scenario 1 - Phase 1'!K114 -> 2495358.8 | E99: ='LEVEL 3'!K114 -> 1570737.8 | H99: =B99+E99 -> 4066096.6 | K99: =B99/'Scenario 1 - Phase 1'!$E$8 -> 7191.2359 | N99: =E99/'LEVEL 3'!$E$8 -> 8096.5865 | Q99: =H99/('Scenario 1 - Phase 1'!$E$8+'LEVEL 3'!$E$8) -> 7515.8902 | T99: =B99/'Scenario 1 - Phase 1'!$B$8 -> 8.02 | W99: =E99/'LEVEL 3'!$B$8 -> 8.0021691 | Z99: =H99/('Scenario 1 - Phase 1'!$B$8+'LEVEL 3'!$B$8) -> 8.0131025
A100: Drywall - Repairs | B100: ='Scenario 1 - Phase 1'!K115 -> 29495 | E100: ='LEVEL 3'!K116 -> 16490 | H100: =B100+E100 -> 45985 | K100: =B100/'Scenario 1 - Phase 1'!$E$8 -> 85 | N100: =E100/'LEVEL 3'!$E$8 -> 85 | Q100: =H100/('Scenario 1 - Phase 1'!$E$8+'LEVEL 3'!$E$8) -> 85 | T100: =B100/'Scenario 1 - Phase 1'!$B$8 -> 0.094795945 | W100: =E100/'LEVEL 3'!$B$8 -> 0.084008783 | Z100: =H100/('Scenario 1 - Phase 1'!$B$8+'LEVEL 3'!$B$8) -> 0.090623159
A101: Tile Tubs and Showers | B101: ='Scenario 1 - Phase 1'!K116 -> 0 | E101: ='LEVEL 3'!K117 -> 0 | H101: =B101+E101 -> 0 | K101: =B101/'Scenario 1 - Phase 1'!$E$8 -> 0 | N101: =E101/'LEVEL 3'!$E$8 -> 0 | Q101: =H101/('Scenario 1 - Phase 1'!$E$8+'LEVEL 3'!$E$8) -> 0 | T101: =B101/'Scenario 1 - Phase 1'!$B$8 -> 0 | W101: =E101/'LEVEL 3'!$B$8 -> 0 | Z101: =H101/('Scenario 1 - Phase 1'!$B$8+'LEVEL 3'!$B$8) -> 0
A102: Common Tile | B102: ='Scenario 1 - Phase 1'!K117 -> 51573 | E102: ='LEVEL 3'!K118 -> 67657 | H102: =B102+E102 -> 119230 | K102: =B102/'Scenario 1 - Phase 1'!$E$8 -> 148.62536 | N102: =E102/'LEVEL 3'!$E$8 -> 348.74742 | Q102: =H102/('Scenario 1 - Phase 1'!$E$8+'LEVEL 3'!$E$8) -> 220.38817 | T102: =B102/'Scenario 1 - Phase 1'!$B$8 -> 0.1657539 | W102: =E102/'LEVEL 3'!$B$8 -> 0.34468055 | Z102: =H102/('Scenario 1 - Phase 1'!$B$8+'LEVEL 3'!$B$8) -> 0.23496791
...

Sheet Summary Combined Ph 1 & 2 (2)
B1: TOTAL COST | K1: PER UNIT | T1: PER GROSS SQUARE FOOT
B3: Phase 1 | E3: Phase 2 | H3: TOTAL | K3: Phase 1 | N3: Phase 2 | Q3: TOTAL | T3: Phase 1 | W3: Phase 2 | Z3: TOTAL
A4: Description | B4: Sub Total | C4: Total | E4: Sub Total | F4: Total | H4: Sub Total | I4: Total | K4: Sub Total | L4: Total | N4: Sub Total | O4: Total | Q4: Sub Total | R4: Total | T4: Sub Total | U4: Total | W4: Sub Total | X4: Total | Z4: Sub Total | AA4: Total
A5: General Requirements | C5: =B6 -> 2008563.6 | F5: =E6 -> 1674318 | I5: =H6 -> 3682881.6 | L5: =C5/'Scenario 1 - Phase 1'!$E$8 -> 5788.3677 | O5: =F5/'LEVEL 3'!$E$8 -> 8630.5052 | R5: =I5/('Scenario 1 - Phase 1'!$E$8+'LEVEL 3'!$E$8) -> 6807.5445 | U5: =C5/'Scenario 1 - Phase 1'!$B$8 -> 6.4554564 | X5: =F5/'LEVEL 3'!$B$8 -> 8.5298616 | AA5: =I5/('Scenario 1 - Phase 1'!$B$8+'LEVEL 3'!$B$8) -> 7.2578963
A6: General Requirements | B6: ='Scenario 1 - Phase 1'!K21 -> 2008563.6 | E6: ='LEVEL 3'!K21 -> 1674318 | H6: =B6+E6 -> 3682881.6 | K6: =B6/'Scenario 1 - Phase 1'!$E$8 -> 5788.3677 | N6: =E6/'LEVEL 3'!$E$8 -> 8630.5052 | Q6: =H6/('Scenario 1 - Phase 1'!$E$8+'LEVEL 3'!$E$8) -> 6807.5445 | T6: =B6/'Scenario 1 - Phase 1'!$B$8 -> 6.4554564 | W6: =E6/'LEVEL 3'!$B$8 -> 8.5298616 | Z6: =H6/('Scenario 1 - Phase 1'!$B$8+'LEVEL 3'!$B$8) -> 7.2578963
A7: Existing Conditions | C7: =B8 -> 8000 | F7: =E8 -> 3500 | I7: =H8 -> 11500 | L7: =K8 -> 23.054755 | O7: =N8 -> 18.041237 | R7: =Q8 -> 21.256932 | U7: =C7/'Scenario 1 - Phase 1'!$B$8 -> 0.025711733 | X7: =F7/'LEVEL 3'!$B$8 -> 0.017830851 | AA7: =I7/('Scenario 1 - Phase 1'!$B$8+'LEVEL 3'!$B$8) -> 0.02266318
A8: Potholing | B8: ='Scenario 1 - Phase 1'!K23 -> 8000 | E8: ='LEVEL 3'!K23 -> 3500 | H8: =B8+E8 -> 11500 | K8: =B8/'Scenario 1 - Phase 1'!$E$8 -> 23.054755 | N8: =E8/'LEVEL 3'!$E$8 -> 18.041237 | Q8: =H8/('Scenario 1 - Phase 1'!$E$8+'LEVEL 3'!$E$8) -> 21.256932 | T8: =B8/'Scenario 1 - Phase 1'!$B$8 -> 0.025711733 | W8: =E8/'LEVEL 3'!$B$8 -> 0.017830851 | Z8: =H8/('Scenario 1 - Phase 1'!$B$8+'LEVEL 3'!$B$8) -> 0.02266318
A9: Concrete | C9: =SUM(B10:B19) -> 1975170 | F9: =SUM(E10:E19) -> 1089279.8 | I9: =SUM(H10:H19) -> 3064449.8 | L9: =SUM(K10:K19) -> 5692.1326 | O9: =SUM(N10:N19) -> 5614.8444 | R9: =SUM(Q10:Q19) -> 5664.4174 | U9: =C9/'Scenario 1 - Phase 1'!$B$8 -> 6.3481305 | X9: =F9/'LEVEL 3'!$B$8 -> 5.5493676 | AA9: =I9/('Scenario 1 - Phase 1'!$B$8+'LEVEL 3'!$B$8) -> 6.0391459
A10: Slabs | B10: ='Scenario 1 - Phase 1'!K25 -> 1243530.9 | E10: ='LEVEL 3'!K25 -> 576982.78 | H10: =B10+E10 -> 1820513.6 | K10: =B10/'Scenario 1 - Phase 1'!$E$8 -> 3583.6624 | N10: =E10/'LEVEL 3'!$E$8 -> 2974.138 | Q10: =H10/('Scenario 1 - Phase 1'!$E$8+'LEVEL 3'!$E$8) -> 3365.0899 | T10: =B10/'Scenario 1 - Phase 1'!$B$8 -> 3.9966667 | W10: =E10/'LEVEL 3'!$B$8 -> 2.9394555 | Z10: =H10/('Scenario 1 - Phase 1'!$B$8+'LEVEL 3'!$B$8) -> 3.5877068
A11: Deepened Footings | B11: ='Scenario 1 - Phase 1'!K26 -> 0 | E11: ='LEVEL 3'!K26 -> 0 | H11: =B11+E11 -> 0 | K11: =B11/'Scenario 1 - Phase 1'!$E$8 -> 0 | N11: =E11/'LEVEL 3'!$E$8 -> 0 | Q11: =H11/('Scenario 1 - Phase 1'!$E$8+'LEVEL 3'!$E$8) -> 0 | T11: =B11/'Scenario 1 - Phase 1'!$B$8 -> 0 | W11: =E11/'LEVEL 3'!$B$8 -> 0 | Z11: =H11/('Scenario 1 - Phase 1'!$B$8+'LEVEL 3'!$B$8) -> 0
A12: Concrete Slab Repairs | B12: ='Scenario 1 - Phase 1'!K27 -> 7500 | E12: ='LEVEL 3'!K27 -> 2500 | H12: =B12+E12 -> 10000 | K12: =B12/'Scenario 1 - Phase 1'!$E$8 -> 21.613833 | N12: =E12/'LEVEL 3'!$E$8 -> 12.886598 | Q12: =H12/('Scenario 1 - Phase 1'!$E$8+'LEVEL 3'!$E$8) -> 18.484288 | T12: =B12/'Scenario 1 - Phase 1'!$B$8 -> 0.02410475 | W12: =E12/'LEVEL 3'!$B$8 -> 0.012736322 | Z12: =H12/('Scenario 1 - Phase 1'!$B$8+'LEVEL 3'!$B$8) -> 0.019707113
A13: Pump House Concrete | B13: ='Scenario 1 - Phase 1'!K28 -> 3597 | E13: ='LEVEL 3'!K28 -> 3597 | H13: =B13+E13 -> 7194 | K13: =B13/'Scenario 1 - Phase 1'!$E$8 -> 10.365994 | N13: =E13/'LEVEL 3'!$E$8 -> 18.541237 | Q13: =H13/('Scenario 1 - Phase 1'!$E$8+'LEVEL 3'!$E$8) -> 13.297597 | T13: =B13/'Scenario 1 - Phase 1'!$B$8 -> 0.011560638 | W13: =E13/'LEVEL 3'!$B$8 -> 0.018325021 | Z13: =H13/('Scenario 1 - Phase 1'!$B$8+'LEVEL 3'!$B$8) -> 0.014177297
A14: Trash Enclosure Concrete | B14: ='Scenario 1 - Phase 1'!K29 -> 26980 | E14: ='LEVEL 3'!K29 -> 11030.8 | H14: =B14+E14 -> 38010.8 | K14: =B14/'Scenario 1 - Phase 1'!$E$8 -> 77.752161 | N14: =E14/'LEVEL 3'!$E$8 -> 56.859794 | Q14: =H14/('Scenario 1 - Phase 1'!$E$8+'LEVEL 3'!$E$8) -> 70.260259 | T14: =B14/'Scenario 1 - Phase 1'!$B$8 -> 0.086712819 | W14: =E14/'LEVEL 3'!$B$8 -> 0.05619673 | Z14: =H14/('Scenario 1 - Phase 1'!$B$8+'LEVEL 3'!$B$8) -> 0.074908313
A15: Pool Area Shower Concrete | B15: ='Scenario 1 - Phase 1'!K30 -> 5000 | E15: ='LEVEL 3'!K30 -> 2500 | H15: =B15+E15 -> 7500 | K15: =B15/'Scenario 1 - Phase 1'!$E$8 -> 14.409222 | N15: =E15/'LEVEL 3'!$E$8 -> 12.886598 | Q15: =H15/('Scenario 1 - Phase 1'!$E$8+'LEVEL 3'!$E$8) -> 13.863216 | T15: =B15/'Scenario 1 - Phase 1'!$B$8 -> 0.016069833 | W15: =E15/'LEVEL 3'!$B$8 -> 0.012736322 | Z15: =H15/('Scenario 1 - Phase 1'!$B$8+'LEVEL 3'!$B$8) -> 0.014780335
A16: Cabana Concrete | B16: ='Scenario 1 - Phase 1'!K31 -> 0 | E16: ='LEVEL 3'!K31 -> 0 | H16: =B16+E16 -> 0 | K16: =B16/'Scenario 1 - Phase 1'!$E$8 -> 0 | N16: =E16/'LEVEL 3'!$E$8 -> 0 | Q16: =H16/('Scenario 1 - Phase 1'!$E$8+'LEVEL 3'!$E$8) -> 0 | T16: =B16/'Scenario 1 - Phase 1'!$B$8 -> 0 | W16: =E16/'LEVEL 3'!$B$8 -> 0 | Z16: =H16/('Scenario 1 - Phase 1'!$B$8+'LEVEL 3'!$B$8) -> 0
A17: Pool Equipment Foundation | B17: ='Scenario 1 - Phase 1'!K32 -> 0 | E17: ='LEVEL 3'!K32 -> 0 | H17: =B17+E17 -> 0 | K17: =B17/'Scenario 1 - Phase 1'!$E$8 -> 0 | N17: =E17/'LEVEL 3'!$E$8 -> 0 | Q17: =H17/('Scenario 1 - Phase 1'!$E$8+'LEVEL 3'!$E$8) -> 0 | T17: =B17/'Scenario 1 - Phase 1'!$B$8 -> 0 | W17: =E17/'LEVEL 3'!$B$8 -> 0 | Z17: =H17/('Scenario 1 - Phase 1'!$B$8+'LEVEL 3'!$B$8) -> 0
A18: Lightweight Concrete | B18: ='Scenario 1 - Phase 1'!K33 -> 609838.32 | E18: ='LEVEL 3'!K33 -> 432915 | H18: =B18+E18 -> 1042753.3 | K18: =B18/'Scenario 1 - Phase 1'!$E$8 -> 1757.4591 | N18: =E18/'LEVEL 3'!$E$8 -> 2231.5206 | Q18: =H18/('Scenario 1 - Phase 1'!$E$8+'LEVEL 3'!$E$8) -> 1927.4553 | T18: =B18/'Scenario 1 - Phase 1'!$B$8 -> 1.96 | W18: =E18/'LEVEL 3'!$B$8 -> 2.205498 | Z18: =H18/('Scenario 1 - Phase 1'!$B$8+'LEVEL 3'!$B$8) -> 2.0549657
A19: Deck Concrete | B19: ='Scenario 1 - Phase 1'!K34 -> 78723.84 | E19: ='LEVEL 3'!K34 -> 59754.24 | H19: =B19+E19 -> 138478.08 | K19: =B19/'Scenario 1 - Phase 1'!$E$8 -> 226.86986 | N19: =E19/'LEVEL 3'!$E$8 -> 308.01155 | Q19: =H19/('Scenario 1 - Phase 1'!$E$8+'LEVEL 3'!$E$8) -> 255.96688 | T19: =B19/'Scenario 1 - Phase 1'!$B$8 -> 0.25301579 | W19: =E19/'LEVEL 3'!$B$8 -> 0.30441971 | Z19: =H19/('Scenario 1 - Phase 1'!$B$8+'LEVEL 3'!$B$8) -> 0.27290032
A20: Parking Garage | C20: =SUM(B21:B28) -> 0 | F20: =SUM(E21:E28) -> 0 | I20: =SUM(H21:H28) -> 0 | L20: =SUM(K21:K28) -> 0 | O20: =SUM(N21:N28) -> 0 | R20: =SUM(Q21:Q28) -> 0 | U20: =C20/'Scenario 1 - Phase 1'!$B$8 -> 0 | X20: =F20/'LEVEL 3'!$B$8 -> 0 | AA20: =I20/('Scenario 1 - Phase 1'!$B$8+'LEVEL 3'!$B$8) -> 0
A21: Parking Garage Structure | B21: ='Scenario 1 - Phase 1'!K36 -> 0 | E21: ='LEVEL 3'!K36 -> 0 | H21: =B21+E21 -> 0 | K21: =B21/'Scenario 1 - Phase 1'!$E$8 -> 0 | N21: =E21/'LEVEL 3'!$E$8 -> 0 | Q21: =H21/('Scenario 1 - Phase 1'!$E$8+'LEVEL 3'!$E$8) -> 0 | T21: =B21/'Scenario 1 - Phase 1'!$B$8 -> 0 | W21: =E21/'LEVEL 3'!$B$8 -> 0 | Z21: =H21/('Scenario 1 - Phase 1'!$B$8+'LEVEL 3'!$B$8) -> 0
A22: Core Slab Precast Concrete | B22: ='Scenario 1 - Phase 1'!K37 -> 0 | E22: ='LEVEL 3'!K37 -> 0 | H22: =B22+E22 -> 0 | K22: =B22/'Scenario 1 - Phase 1'!$E$8 -> 0 | N22: =E22/'LEVEL 3'!$E$8 -> 0 | Q22: =H22/('Scenario 1 - Phase 1'!$E$8+'LEVEL 3'!$E$8) -> 0 | T22: =B22/'Scenario 1 - Phase 1'!$B$8 -> 0 | W22: =E22/'LEVEL 3'!$B$8 -> 0 | Z22: =H22/('Scenario 1 - Phase 1'!$B$8+'LEVEL 3'!$B$8) -> 0
A23: Concrete Slab on Grade | B23: ='Scenario 1 - Phase 1'!K38 -> 0 | E23: ='LEVEL 3'!K38 -> 0 | H23: =B23+E23 -> 0 | K23: =B23/'Scenario 1 - Phase 1'!$E$8 -> 0 | N23: =E23/'LEVEL 3'!$E$8 -> 0 | Q23: =H23/('Scenario 1 - Phase 1'!$E$8+'LEVEL 3'!$E$8) -> 0 | T23: =B23/'Scenario 1 - Phase 1'!$B$8 -> 0 | W23: =E23/'LEVEL 3'!$B$8 -> 0 | Z23: =H23/('Scenario 1 - Phase 1'!$B$8+'LEVEL 3'!$B$8) -> 0
A24: Concrete Topping Slab 4" / Level | B24: ='Scenario 1 - Phase 1'!K39 -> 0 | E24: ='LEVEL 3'!K39 -> 0 | H24: =B24+E24 -> 0 | K24: =B24/'Scenario 1 - Phase 1'!$E$8 -> 0 | N24: =E24/'LEVEL 3'!$E$8 -> 0 | Q24: =H24/('Scenario 1 - Phase 1'!$E$8+'LEVEL 3'!$E$8) -> 0 | T24: =B24/'Scenario 1 - Phase 1'!$B$8 -> 0 | W24: =E24/'LEVEL 3'!$B$8 -> 0 | Z24: =H24/('Scenario 1 - Phase 1'!$B$8+'LEVEL 3'!$B$8) -> 0
A25: Electrical | B25: ='Scenario 1 - Phase 1'!K40 -> 0 | E25: ='LEVEL 3'!K40 -> 0 | H25: =B25+E25 -> 0 | K25: =B25/'Scenario 1 - Phase 1'!$E$8 -> 0 | N25: =E25/'LEVEL 3'!$E$8 -> 0 | Q25: =H25/('Scenario 1 - Phase 1'!$E$8+'LEVEL 3'!$E$8) -> 0 | T25: =B25/'Scenario 1 - Phase 1'!$B$8 -> 0 | W25: =E25/'LEVEL 3'!$B$8 -> 0 | Z25: =H25/('Scenario 1 - Phase 1'!$B$8+'LEVEL 3'!$B$8) -> 0
A26: Dry Sprinklers | B26: ='Scenario 1 - Phase 1'!K41 -> 0 | E26: ='LEVEL 3'!K41 -> 0 | H26: =B26+E26 -> 0 | K26: =B26/'Scenario 1 - Phase 1'!$E$8 -> 0 | N26: =E26/'LEVEL 3'!$E$8 -> 0 | Q26: =H26/('Scenario 1 - Phase 1'!$E$8+'LEVEL 3'!$E$8) -> 0 | T26: =B26/'Scenario 1 - Phase 1'!$B$8 -> 0 | W26: =E26/'LEVEL 3'!$B$8 -> 0 | Z26: =H26/('Scenario 1 - Phase 1'!$B$8+'LEVEL 3'!$B$8) -> 0
A27: Mechanical Ventilation | B27: ='Scenario 1 - Phase 1'!K42 -> 0 | E27: ='LEVEL 3'!K42 -> 0 | H27: =B27+E27 -> 0 | K27: =B27/'Scenario 1 - Phase 1'!$E$8 -> 0 | N27: =E27/'LEVEL 3'!$E$8 -> 0 | Q27: =H27/('Scenario 1 - Phase 1'!$E$8+'LEVEL 3'!$E$8) -> 0 | T27: =B27/'Scenario 1 - Phase 1'!$B$8 -> 0 | W27: =E27/'LEVEL 3'!$B$8 -> 0 | Z27: =H27/('Scenario 1 - Phase 1'!$B$8+'LEVEL 3'!$B$8) -> 0
A28: Stairs and Railings | B28: ='Scenario 1 - Phase 1'!K43 -> 0 | E28: ='LEVEL 3'!K43 -> 0 | H28: =B28+E28 -> 0 | K28: =B28/'Scenario 1 - Phase 1'!$E$8 -> 0 | N28: =E28/'LEVEL 3'!$E$8 -> 0 | Q28: =H28/('Scenario 1 - Phase 1'!$E$8+'LEVEL 3'!$E$8) -> 0 | T28: =B28/'Scenario 1 - Phase 1'!$B$8 -> 0 | W28: =E28/'LEVEL 3'!$B$8 -> 0 | Z28: =H28/('Scenario 1 - Phase 1'!$B$8+'LEVEL 3'!$B$8) -> 0
A29: Masonry | C29: =SUM(B30:B34) -> 171000 | F29: =SUM(E30:E34) -> 112800 | I29: =SUM(H30:H34) -> 283800 | L29: =SUM(K30:K34) -> 492.79539 | O29: =SUM(N30:N34) -> 581.4433 | R29: =SUM(Q30:Q34) -> 524.5841 | U29: =C29/'Scenario 1 - Phase 1'!$B$8 -> 0.54958829 | X29: =F29/'LEVEL 3'!$B$8 -> 0.57466287 | AA29: =I29/('Scenario 1 - Phase 1'!$B$8+'LEVEL 3'!$B$8) -> 0.55928786
A30: Elevator Shaft | B30: ='Scenario 1 - Phase 1'!K45 -> 114000 | E30: ='LEVEL 3'!K45 -> 76000 | H30: =B30+E30 -> 190000 | K30: =B30/'Scenario 1 - Phase 1'!$E$8 -> 328.53026 | N30: =E30/'LEVEL 3'!$E$8 -> 391.75258 | Q30: =H30/('Scenario 1 - Phase 1'!$E$8+'LEVEL 3'!$E$8) -> 351.20148 | T30: =B30/'Scenario 1 - Phase 1'!$B$8 -> 0.36639219 | W30: =E30/'LEVEL 3'!$B$8 -> 0.3871842 | Z30: =H30/('Scenario 1 - Phase 1'!$B$8+'LEVEL 3'!$B$8) -> 0.37443514
A31: Trash Enclosure | B31: ='Scenario 1 - Phase 1'!K46 -> 57000 | E31: ='LEVEL 3'!K46 -> 22800 | H31: =B31+E31 -> 79800 | K31: =B31/'Scenario 1 - Phase 1'!$E$8 -> 164.26513 | N31: =E31/'LEVEL 3'!$E$8 -> 117.52577 | Q31: =H31/('Scenario 1 - Phase 1'!$E$8+'LEVEL 3'!$E$8) -> 147.50462 | T31: =B31/'Scenario 1 - Phase 1'!$B$8 -> 0.1831961 | W31: =E31/'LEVEL 3'!$B$8 -> 0.11615526 | Z31: =H31/('Scenario 1 - Phase 1'!$B$8+'LEVEL 3'!$B$8) -> 0.15726276
A32: Masonry Veneer | B32: ='Scenario 1 - Phase 1'!K47 -> 0 | E32: ='LEVEL 3'!K47 -> 0 | H32: =B32+E32 -> 0 | K32: =B32/'Scenario 1 - Phase 1'!$E$8 -> 0 | N32: =E32/'LEVEL 3'!$E$8 -> 0 | Q32: =H32/('Scenario 1 - Phase 1'!$E$8+'LEVEL 3'!$E$8) -> 0 | T32: =B32/'Scenario 1 - Phase 1'!$B$8 -> 0 | W32: =E32/'LEVEL 3'!$B$8 -> 0 | Z32: =H32/('Scenario 1 - Phase 1'!$B$8+'LEVEL 3'!$B$8) -> 0
A33: Masonry Veneer Pool Area | B33: ='Scenario 1 - Phase 1'!K48 -> 0 | E33: ='LEVEL 3'!K48 -> 5000 | H33: =B33+E33 -> 5000 | K33: =B33/'Scenario 1 - Phase 1'!$E$8 -> 0 | N33: =E33/'LEVEL 3'!$E$8 -> 25.773196 | Q33: =H33/('Scenario 1 - Phase 1'!$E$8+'LEVEL 3'!$E$8) -> 9.2421442 | T33: =B33/'Scenario 1 - Phase 1'!$B$8 -> 0 | W33: =E33/'LEVEL 3'!$B$8 -> 0.025472645 | Z33: =H33/('Scenario 1 - Phase 1'!$B$8+'LEVEL 3'!$B$8) -> 0.0098535564
A34: Pool Eq. Shower Stone | B34: ='Scenario 1 - Phase 1'!K49 -> 0 | E34: ='LEVEL 3'!K49 -> 9000 | H34: =B34+E34 -> 9000 | K34: =B34/'Scenario 1 - Phase 1'!$E$8 -> 0 | N34: =E34/'LEVEL 3'!$E$8 -> 46.391753 | Q34: =H34/('Scenario 1 - Phase 1'!$E$8+'LEVEL 3'!$E$8) -> 16.63586 | T34: =B34/'Scenario 1 - Phase 1'!$B$8 -> 0 | W34: =E34/'LEVEL 3'!$B$8 -> 0.045850761 | Z34: =H34/('Scenario 1 - Phase 1'!$B$8+'LEVEL 3'!$B$8) -> 0.017736402
A35: Metals | C35: =SUM(B36:B43) -> 392720.43 | F35: =SUM(E36:E43) -> 325412.13 | I35: =SUM(H36:H43) -> 718132.56 | L35: =SUM(K36:K43) -> 1131.7592 | O35: =SUM(N36:N43) -> 1677.3821 | R35: =SUM(Q36:Q43) -> 1327.4169 | U35: =C35/'Scenario 1 - Phase 1'!$B$8 -> 1.2621904 | X35: =F35/'LEVEL 3'!$B$8 -> 1.6578215 | AA35: =I35/('Scenario 1 - Phase 1'!$B$8+'LEVEL 3'!$B$8) -> 1.4152319
A36: Structural Steel | B36: ='Scenario 1 - Phase 1'!K51 -> 0 | E36: ='LEVEL 3'!K51 -> 112826.13 | H36: =B36+E36 -> 112826.13 | K36: =B36/'Scenario 1 - Phase 1'!$E$8 -> 0 | N36: =E36/'LEVEL 3'!$E$8 -> 581.57798 | Q36: =H36/('Scenario 1 - Phase 1'!$E$8+'LEVEL 3'!$E$8) -> 208.55107 | T36: =B36/'Scenario 1 - Phase 1'!$B$8 -> 0 | W36: =E36/'LEVEL 3'!$B$8 -> 0.57479598 | Z36: =H36/('Scenario 1 - Phase 1'!$B$8+'LEVEL 3'!$B$8) -> 0.22234772
A37: Elevator Shaft Iron | B37: ='Scenario 1 - Phase 1'!K52 -> 23960 | E37: ='LEVEL 3'!K52 -> 8080 | H37: =B37+E37 -> 32040 | K37: =B37/'Scenario 1 - Phase 1'!$E$8 -> 69.048991 | N37: =E37/'LEVEL 3'!$E$8 -> 41.649485 | Q37: =H37/('Scenario 1 - Phase 1'!$E$8+'LEVEL 3'!$E$8) -> 59.22366 | T37: =B37/'Scenario 1 - Phase 1'!$B$8 -> 0.07700664 | W37: =E37/'LEVEL 3'!$B$8 -> 0.041163794 | Z37: =H37/('Scenario 1 - Phase 1'!$B$8+'LEVEL 3'!$B$8) -> 0.06314159
A38: Stair Handrails | B38: ='Scenario 1 - Phase 1'!K53 -> 129250 | E38: ='LEVEL 3'!K53 -> 56000 | H38: =B38+E38 -> 185250 | K38: =B38/'Scenario 1 - Phase 1'!$E$8 -> 372.47839 | N38: =E38/'LEVEL 3'!$E$8 -> 288.65979 | Q38: =H38/('Scenario 1 - Phase 1'!$E$8+'LEVEL 3'!$E$8) -> 342.42144 | T38: =B38/'Scenario 1 - Phase 1'!$B$8 -> 0.41540518 | W38: =E38/'LEVEL 3'!$B$8 -> 0.28529362 | Z38: =H38/('Scenario 1 - Phase 1'!$B$8+'LEVEL 3'!$B$8) -> 0.36507427
A39: Garage Stair Railings | B39: ='Scenario 1 - Phase 1'!K54 -> 0 | E39: ='LEVEL 3'!K54 -> 0 | H39: =B39+E39 -> 0 | K39: =B39/'Scenario 1 - Phase 1'!$E$8 -> 0 | N39: =E39/'LEVEL 3'!$E$8 -> 0 | Q39: =H39/('Scenario 1 - Phase 1'!$E$8+'LEVEL 3'!$E$8) -> 0 | T39: =B39/'Scenario 1 - Phase 1'!$B$8 -> 0 | W39: =E39/'LEVEL 3'!$B$8 -> 0 | Z39: =H39/('Scenario 1 - Phase 1'!$B$8+'LEVEL 3'!$B$8) -> 0
A40: Cabana Iron | B40: ='Scenario 1 - Phase 1'!K55 -> 0 | E40: ='LEVEL 3'!K55 -> 0 | H40: =B40+E40 -> 0 | K40: =B40/'Scenario 1 - Phase 1'!$E$8 -> 0 | N40: =E40/'LEVEL 3'!$E$8 -> 0 | Q40: =H40/('Scenario 1 - Phase 1'!$E$8+'LEVEL 3'!$E$8) -> 0 | T40: =B40/'Scenario 1 - Phase 1'!$B$8 -> 0 | W40: =E40/'LEVEL 3'!$B$8 -> 0 | Z40: =H40/('Scenario 1 - Phase 1'!$B$8+'LEVEL 3'!$B$8) -> 0
A41: Pool Equipment Gate | B41: ='Scenario 1 - Phase 1'!K56 -> 3900 | E41: ='LEVEL 3'!K56 -> 1950 | H41: =B41+E41 -> 5850 | K41: =B41/'Scenario 1 - Phase 1'!$E$8 -> 11.239193 | N41: =E41/'LEVEL 3'!$E$8 -> 10.051546 | Q41: =H41/('Scenario 1 - Phase 1'!$E$8+'LEVEL 3'!$E$8) -> 10.813309 | T41: =B41/'Scenario 1 - Phase 1'!$B$8 -> 0.01253447 | W41: =E41/'LEVEL 3'!$B$8 -> 0.0099343315 | Z41: =H41/('Scenario 1 - Phase 1'!$B$8+'LEVEL 3'!$B$8) -> 0.011528661
A42: Iron Railings | B42: ='Scenario 1 - Phase 1'!K57 -> 235610.43 | E42: ='LEVEL 3'!K57 -> 146556 | H42: =B42+E42 -> 382166.43 | K42: =B42/'Scenario 1 - Phase 1'!$E$8 -> 678.99261 | N42: =E42/'LEVEL 3'!$E$8 -> 755.4433 | Q42: =H42/('Scenario 1 - Phase 1'!$E$8+'LEVEL 3'!$E$8) -> 706.40746 | T42: =B42/'Scenario 1 - Phase 1'!$B$8 -> 0.75724407 | W42: =E42/'LEVEL 3'!$B$8 -> 0.74663379 | Z42: =H42/('Scenario 1 - Phase 1'!$B$8+'LEVEL 3'!$B$8) -> 0.75313971
A43: Cable Railings | B43: ='Scenario 1 - Phase 1'!K58 -> 0 | E43: ='LEVEL 3'!K58 -> 0 | H43: =B43+E43 -> 0 | K43: =B43/'Scenario 1 - Phase 1'!$E$8 -> 0 | N43: =E43/'LEVEL 3'!$E$8 -> 0 | Q43: =H43/('Scenario 1 - Phase 1'!$E$8+'LEVEL 3'!$E$8) -> 0 | T43: =B43/'Scenario 1 - Phase 1'!$B$8 -> 0 | W43: =E43/'LEVEL 3'!$B$8 -> 0 | Z43: =H43/('Scenario 1 - Phase 1'!$B$8+'LEVEL 3'!$B$8) -> 0
A44: Wood, Plastics, & Composites | C44: =SUM(B45:B56) -> 7663075.4 | F44: =SUM(E45:E56) -> #REF! | I44: =SUM(H45:H56) -> #REF! | L44: =SUM(K45:K56) -> 22083.791 | O44: =SUM(N45:N56) -> #REF! | R44: =SUM(Q45:Q56) -> #REF! | U44: =C44/'Scenario 1 - Phase 1'!$B$8 -> 24.628868 | X44: =F44/'LEVEL 3'!$B$8 -> #REF! | AA44: =I44/('Scenario 1 - Phase 1'!$B$8+'LEVEL 3'!$B$8) -> #REF!
A45: Dumpsters | B45: ='Scenario 1 - Phase 1'!K60 -> 27413 | E45: ='LEVEL 3'!#REF! -> #REF! | H45: =B45+E45 -> #REF! | K45: =B45/'Scenario 1 - Phase 1'!$E$8 -> 79 | N45: =E45/'LEVEL 3'!$E$8 -> #REF! | Q45: =H45/('Scenario 1 - Phase 1'!$E$8+'LEVEL 3'!$E$8) -> #REF! | T45: =B45/'Scenario 1 - Phase 1'!$B$8 -> 0.088104467 | W45: =E45/'LEVEL 3'!$B$8 -> #REF! | Z45: =H45/('Scenario 1 - Phase 1'!$B$8+'LEVEL 3'!$B$8) -> #REF!
A46: Framing | B46: ='Scenario 1 - Phase 1'!K61 -> 6197948.6 | E46: ='LEVEL 3'!K60 -> 4008924.5 | H46: =B46+E46 -> 10206873 | K46: =B46/'Scenario 1 - Phase 1'!$E$8 -> 17861.523 | N46: =E46/'LEVEL 3'!$E$8 -> 20664.559 | Q46: =H46/('Scenario 1 - Phase 1'!$E$8+'LEVEL 3'!$E$8) -> 18866.679 | T46: =B46/'Scenario 1 - Phase 1'!$B$8 -> 19.92 | W46: =E46/'LEVEL 3'!$B$8 -> 20.423582 | Z46: =H46/('Scenario 1 - Phase 1'!$B$8+'LEVEL 3'!$B$8) -> 20.1148
A47: Framing - Crane | B47: ='Scenario 1 - Phase 1'!K62 -> 0 | E47: ='LEVEL 3'!K62 -> 0 | H47: =B47+E47 -> 0 | K47: =B47/'Scenario 1 - Phase 1'!$E$8 -> 0 | N47: =E47/'LEVEL 3'!$E$8 -> 0 | Q47: =H47/('Scenario 1 - Phase 1'!$E$8+'LEVEL 3'!$E$8) -> 0 | T47: =B47/'Scenario 1 - Phase 1'!$B$8 -> 0 | W47: =E47/'LEVEL 3'!$B$8 -> 0 | Z47: =H47/('Scenario 1 - Phase 1'!$B$8+'LEVEL 3'!$B$8) -> 0
A48: Cabana Framing | B48: ='Scenario 1 - Phase 1'!K63 -> 0 | E48: ='LEVEL 3'!K63 -> 0 | H48: =B48+E48 -> 0 | K48: =B48/'Scenario 1 - Phase 1'!$E$8 -> 0 | N48: =E48/'LEVEL 3'!$E$8 -> 0 | Q48: =H48/('Scenario 1 - Phase 1'!$E$8+'LEVEL 3'!$E$8) -> 0 | T48: =B48/'Scenario 1 - Phase 1'!$B$8 -> 0 | W48: =E48/'LEVEL 3'!$B$8 -> 0 | Z48: =H48/('Scenario 1 - Phase 1'!$B$8+'LEVEL 3'!$B$8) -> 0
A49: BBQ Framing | B49: ='Scenario 1 - Phase 1'!K64 -> 5620 | E49: ='LEVEL 3'!K64 -> 2500 | H49: =B49+E49 -> 8120 | K49: =B49/'Scenario 1 - Phase 1'!$E$8 -> 16.195965 | N49: =E49/'LEVEL 3'!$E$8 -> 12.886598 | Q49: =H49/('Scenario 1 - Phase 1'!$E$8+'LEVEL 3'!$E$8) -> 15.009242 | T49: =B49/'Scenario 1 - Phase 1'!$B$8 -> 0.018062492 | W49: =E49/'LEVEL 3'!$B$8 -> 0.012736322 | Z49: =H49/('Scenario 1 - Phase 1'!$B$8+'LEVEL 3'!$B$8) -> 0.016002176
A50: Fireplace Framing | B50: ='Scenario 1 - Phase 1'!K65 -> 0 | E50: ='LEVEL 3'!K65 -> 0 | H50: =B50+E50 -> 0 | K50: =B50/'Scenario 1 - Phase 1'!$E$8 -> 0 | N50: =E50/'LEVEL 3'!$E$8 -> 0 | Q50: =H50/('Scenario 1 - Phase 1'!$E$8+'LEVEL 3'!$E$8) -> 0 | T50: =B50/'Scenario 1 - Phase 1'!$B$8 -> 0 | W50: =E50/'LEVEL 3'!$B$8 -> 0 | Z50: =H50/('Scenario 1 - Phase 1'!$B$8+'LEVEL 3'!$B$8) -> 0
A51: Trellis | B51: ='Scenario 1 - Phase 1'!K66 -> 0 | E51: ='LEVEL 3'!K66 -> 0 | H51: =B51+E51 -> 0 | K51: =B51/'Scenario 1 - Phase 1'!$E$8 -> 0 | N51: =E51/'LEVEL 3'!$E$8 -> 0 | Q51: =H51/('Scenario 1 - Phase 1'!$E$8+'LEVEL 3'!$E$8) -> 0 | T51: =B51/'Scenario 1 - Phase 1'!$B$8 -> 0 | W51: =E51/'LEVEL 3'!$B$8 -> 0 | Z51: =H51/('Scenario 1 - Phase 1'!$B$8+'LEVEL 3'!$B$8) -> 0
A52: Pool Equipment Framing | B52: ='Scenario 1 - Phase 1'!K67 -> 0 | E52: ='LEVEL 3'!K67 -> 0 | H52: =B52+E52 -> 0 | K52: =B52/'Scenario 1 - Phase 1'!$E$8 -> 0 | N52: =E52/'LEVEL 3'!$E$8 -> 0 | Q52: =H52/('Scenario 1 - Phase 1'!$E$8+'LEVEL 3'!$E$8) -> 0 | T52: =B52/'Scenario 1 - Phase 1'!$B$8 -> 0 | W52: =E52/'LEVEL 3'!$B$8 -> 0 | Z52: =H52/('Scenario 1 - Phase 1'!$B$8+'LEVEL 3'!$B$8) -> 0
A53: Finish Carpentry - Units | B53: ='Scenario 1 - Phase 1'!K68 -> 1069107 | E53: ='LEVEL 3'!K68 -> 614845 | H53: =B53+E53 -> 1683952 | K53: =B53/'Scenario 1 - Phase 1'!$E$8 -> 3081 | N53: =E53/'LEVEL 3'!$E$8 -> 3169.3041 | Q53: =H53/('Scenario 1 - Phase 1'!$E$8+'LEVEL 3'!$E$8) -> 3112.6654 | T53: =B53/'Scenario 1 - Phase 1'!$B$8 -> 3.4360742 | W53: =E53/'LEVEL 3'!$B$8 -> 3.1323457 | Z53: =H53/('Scenario 1 - Phase 1'!$B$8+'LEVEL 3'!$B$8) -> 3.3185832
A54: Finish Carpentry - Common | B54: ='Scenario 1 - Phase 1'!K69 -> 360924.72 | E54: ='LEVEL 3'!K69 -> 157031.2 | H54: =B54+E54 -> 517955.92 | K54: =B54/'Scenario 1 - Phase 1'!$E$8 -> 1040.1289 | N54: =E54/'LEVEL 3'!$E$8 -> 809.43918 | Q54: =H54/('Scenario 1 - Phase 1'!$E$8+'LEVEL 3'!$E$8) -> 957.40466 | T54: =B54/'Scenario 1 - Phase 1'!$B$8 -> 1.16 | W54: =E54/'LEVEL 3'!$B$8 -> 0.8 | Z54: =H54/('Scenario 1 - Phase 1'!$B$8+'LEVEL 3'!$B$8) -> 1.0207416
A55: BBQ Trim | B55: ='Scenario 1 - Phase 1'!K70 -> 2062 | E55: ='LEVEL 3'!K71 -> 1200 | H55: =B55+E55 -> 3262 | K55: =B55/'Scenario 1 - Phase 1'!$E$8 -> 5.9423631 | N55: =E55/'LEVEL 3'!$E$8 -> 6.185567 | Q55: =H55/('Scenario 1 - Phase 1'!$E$8+'LEVEL 3'!$E$8) -> 6.0295749 | T55: =B55/'Scenario 1 - Phase 1'!$B$8 -> 0.0066271992 | W55: =E55/'LEVEL 3'!$B$8 -> 0.0061134348 | Z55: =H55/('Scenario 1 - Phase 1'!$B$8+'LEVEL 3'!$B$8) -> 0.0064284602
A56: Shutters | B56: ='Scenario 1 - Phase 1'!K71 -> 0 | E56: ='LEVEL 3'!K72 -> 0 | H56: =B56+E56 -> 0 | K56: =B56/'Scenario 1 - Phase 1'!$E$8 -> 0 | N56: =E56/'LEVEL 3'!$E$8 -> 0 | Q56: =H56/('Scenario 1 - Phase 1'!$E$8+'LEVEL 3'!$E$8) -> 0 | T56: =B56/'Scenario 1 - Phase 1'!$B$8 -> 0 | W56: =E56/'LEVEL 3'!$B$8 -> 0 | Z56: =H56/('Scenario 1 - Phase 1'!$B$8+'LEVEL 3'!$B$8) -> 0
A57: Thermal & Moisture Protection | C57: =SUM(B58:B68) -> 1573821.8 | F57: =SUM(E58:E68) -> 902986.76 | I57: =SUM(H58:H68) -> 2476808.6 | L57: =SUM(K58:K68) -> 4535.5096 | O57: =SUM(N58:N68) -> 4654.5709 | R57: =SUM(Q58:Q68) -> 4578.2044 | U57: =C57/'Scenario 1 - Phase 1'!$B$8 -> 5.0582108 | X57: =F57/'LEVEL 3'!$B$8 -> 4.6002922 | AA57: =I57/('Scenario 1 - Phase 1'!$B$8+'LEVEL 3'!$B$8) -> 4.8810746
A58: Insulation | B58: ='Scenario 1 - Phase 1'!K73 -> 790300.68 | E58: ='LEVEL 3'!K74 -> 527480.3 | H58: =B58+E58 -> 1317781 | K58: =B58/'Scenario 1 - Phase 1'!$E$8 -> 2277.5236 | N58: =E58/'LEVEL 3'!$E$8 -> 2718.9706 | Q58: =H58/('Scenario 1 - Phase 1'!$E$8+'LEVEL 3'!$E$8) -> 2435.8244 | T58: =B58/'Scenario 1 - Phase 1'!$B$8 -> 2.54 | W58: =E58/'LEVEL 3'!$B$8 -> 2.6872637 | Z58: =H58/('Scenario 1 - Phase 1'!$B$8+'LEVEL 3'!$B$8) -> 2.5969659
A59: Roofing | B59: ='Scenario 1 - Phase 1'!K74 -> 650172.69 | E59: ='LEVEL 3'!K76 -> 303688.89 | H59: =B59+E59 -> 953861.58 | K59: =B59/'Scenario 1 - Phase 1'!$E$8 -> 1873.6965 | N59: =E59/'LEVEL 3'!$E$8 -> 1565.4066 | Q59: =H59/('Scenario 1 - Phase 1'!$E$8+'LEVEL 3'!$E$8) -> 1763.1452 | T59: =B59/'Scenario 1 - Phase 1'!$B$8 -> 2.0896333 | W59: =E59/'LEVEL 3'!$B$8 -> 1.5471519 | Z59: =H59/('Scenario 1 - Phase 1'!$B$8+'LEVEL 3'!$B$8) -> 1.8797858
A60: Cabana Roofing | B60: ='Scenario 1 - Phase 1'!K75 -> 0 | E60: ='LEVEL 3'!K77 -> 0 | H60: =B60+E60 -> 0 | K60: =B60/'Scenario 1 - Phase 1'!$E$8 -> 0 | N60: =E60/'LEVEL 3'!$E$8 -> 0 | Q60: =H60/('Scenario 1 - Phase 1'!$E$8+'LEVEL 3'!$E$8) -> 0 | T60: =B60/'Scenario 1 - Phase 1'!$B$8 -> 0 | W60: =E60/'LEVEL 3'!$B$8 -> 0 | Z60: =H60/('Scenario 1 - Phase 1'!$B$8+'LEVEL 3'!$B$8) -> 0
A61: Pump House Roofing | B61: ='Scenario 1 - Phase 1'!K76 -> 6700 | E61: ='LEVEL 3'!K78 -> 7500 | H61: =B61+E61 -> 14200 | K61: =B61/'Scenario 1 - Phase 1'!$E$8 -> 19.308357 | N61: =E61/'LEVEL 3'!$E$8 -> 38.659794 | Q61: =H61/('Scenario 1 - Phase 1'!$E$8+'LEVEL 3'!$E$8) -> 26.247689 | T61: =B61/'Scenario 1 - Phase 1'!$B$8 -> 0.021533576 | W61: =E61/'LEVEL 3'!$B$8 -> 0.038208967 | Z61: =H61/('Scenario 1 - Phase 1'!$B$8+'LEVEL 3'!$B$8) -> 0.0279841
A62: Pool Equipment Roofing | B62: ='Scenario 1 - Phase 1'!K77 -> 0 | E62: ='LEVEL 3'!K79 -> 7500 | H62: =B62+E62 -> 7500 | K62: =B62/'Scenario 1 - Phase 1'!$E$8 -> 0 | N62: =E62/'LEVEL 3'!$E$8 -> 38.659794 | Q62: =H62/('Scenario 1 - Phase 1'!$E$8+'LEVEL 3'!$E$8) -> 13.863216 | T62: =B62/'Scenario 1 - Phase 1'!$B$8 -> 0 | W62: =E62/'LEVEL 3'!$B$8 -> 0.038208967 | Z62: =H62/('Scenario 1 - Phase 1'!$B$8+'LEVEL 3'!$B$8) -> 0.014780335
A63: Trash Enclosure Cover | B63: ='Scenario 1 - Phase 1'!K78 -> 70000 | E63: ='LEVEL 3'!K80 -> 23200 | H63: =B63+E63 -> 93200 | K63: =B63/'Scenario 1 - Phase 1'!$E$8 -> 201.72911 | N63: =E63/'LEVEL 3'!$E$8 -> 119.58763 | Q63: =H63/('Scenario 1 - Phase 1'!$E$8+'LEVEL 3'!$E$8) -> 172.27357 | T63: =B63/'Scenario 1 - Phase 1'!$B$8 -> 0.22497766 | W63: =E63/'LEVEL 3'!$B$8 -> 0.11819307 | Z63: =H63/('Scenario 1 - Phase 1'!$B$8+'LEVEL 3'!$B$8) -> 0.18367029
A64: Pigeon Proofing | B64: ='Scenario 1 - Phase 1'!K79 -> 24891.36 | E64: ='LEVEL 3'!K81 -> 15703.12 | H64: =B64+E64 -> 40594.48 | K64: =B64/'Scenario 1 - Phase 1'!$E$8 -> 71.733026 | N64: =E64/'LEVEL 3'!$E$8 -> 80.943918 | Q64: =H64/('Scenario 1 - Phase 1'!$E$8+'LEVEL 3'!$E$8) -> 75.036007 | T64: =B64/'Scenario 1 - Phase 1'!$B$8 -> 0.08 | W64: =E64/'LEVEL 3'!$B$8 -> 0.08 | Z64: =H64/('Scenario 1 - Phase 1'!$B$8+'LEVEL 3'!$B$8) -> 0.08
A65: Gutters and Downspouts | B65: ='Scenario 1 - Phase 1'!K80 -> 15557.1 | E65: ='LEVEL 3'!K82 -> 9814.45 | H65: =B65+E65 -> 25371.55 | K65: =B65/'Scenario 1 - Phase 1'!$E$8 -> 44.833141 | N65: =E65/'LEVEL 3'!$E$8 -> 50.589948 | Q65: =H65/('Scenario 1 - Phase 1'!$E$8+'LEVEL 3'!$E$8) -> 46.897505 | T65: =B65/'Scenario 1 - Phase 1'!$B$8 -> 0.05 | W65: =E65/'LEVEL 3'!$B$8 -> 0.05 | Z65: =H65/('Scenario 1 - Phase 1'!$B$8+'LEVEL 3'!$B$8) -> 0.05
A66: Roof Ladders | B66: ='Scenario 1 - Phase 1'!K81 -> 6200 | E66: ='LEVEL 3'!K83 -> 3100 | H66: =B66+E66 -> 9300 | K66: =B66/'Scenario 1 - Phase 1'!$E$8 -> 17.867435 | N66: =E66/'LEVEL 3'!$E$8 -> 15.979381 | Q66: =H66/('Scenario 1 - Phase 1'!$E$8+'LEVEL 3'!$E$8) -> 17.190388 | T66: =B66/'Scenario 1 - Phase 1'!$B$8 -> 0.019926593 | W66: =E66/'LEVEL 3'!$B$8 -> 0.01579304 | Z66: =H66/('Scenario 1 - Phase 1'!$B$8+'LEVEL 3'!$B$8) -> 0.018327615
A67: Roof Access Doors | B67: ='Scenario 1 - Phase 1'!K82 -> 10000 | E67: ='LEVEL 3'!K84 -> 5000 | H67: =B67+E67 -> 15000 | K67: =B67/'Scenario 1 - Phase 1'!$E$8 -> 28.818444 | N67: =E67/'LEVEL 3'!$E$8 -> 25.773196 | Q67: =H67/('Scenario 1 - Phase 1'!$E$8+'LEVEL 3'!$E$8) -> 27.726433 | T67: =B67/'Scenario 1 - Phase 1'!$B$8 -> 0.032139666 | W67: =E67/'LEVEL 3'!$B$8 -> 0.025472645 | Z67: =H67/('Scenario 1 - Phase 1'!$B$8+'LEVEL 3'!$B$8) -> 0.029560669
A68: Roof Winch | B68: ='Scenario 1 - Phase 1'!K83 -> 0 | E68: ='LEVEL 3'!K85 -> 0 | H68: =B68+E68 -> 0 | K68: =B68/'Scenario 1 - Phase 1'!$E$8 -> 0 | N68: =E68/'LEVEL 3'!$E$8 -> 0 | Q68: =H68/('Scenario 1 - Phase 1'!$E$8+'LEVEL 3'!$E$8) -> 0 | T68: =B68/'Scenario 1 - Phase 1'!$B$8 -> 0 | W68: =E68/'LEVEL 3'!$B$8 -> 0 | Z68: =H68/('Scenario 1 - Phase 1'!$B$8+'LEVEL 3'!$B$8) -> 0
A69: Openings | C69: =SUM(B70:B84) -> 548400.7 | F69: =SUM(E70:E84) -> #REF! | I69: =SUM(H70:H84) -> #REF! | L69: =SUM(K70:K84) -> 1580.4055 | O69: =SUM(N70:N84) -> #REF! | R69: =SUM(Q70:Q84) -> #REF! | U69: =C69/'Scenario 1 - Phase 1'!$B$8 -> 1.7625415 | X69: =F69/'LEVEL 3'!$B$8 -> #REF! | AA69: =I69/('Scenario 1 - Phase 1'!$B$8+'LEVEL 3'!$B$8) -> #REF!
A70: Dumpsters | B70: ='Scenario 1 - Phase 1'!K85 -> 27413 | E70: ='LEVEL 3'!#REF! -> #REF! | H70: =B70+E70 -> #REF! | K70: =B70/'Scenario 1 - Phase 1'!$E$8 -> 79 | N70: =E70/'LEVEL 3'!$E$8 -> #REF! | Q70: =H70/('Scenario 1 - Phase 1'!$E$8+'LEVEL 3'!$E$8) -> #REF! | T70: =B70/'Scenario 1 - Phase 1'!$B$8 -> 0.088104467 | W70: =E70/'LEVEL 3'!$B$8 -> #REF! | Z70: =H70/('Scenario 1 - Phase 1'!$B$8+'LEVEL 3'!$B$8) -> #REF!
A71: Entry Doors | B71: ='Scenario 1 - Phase 1'!K86 -> 0 | E71: ='LEVEL 3'!K87 -> 8000 | H71: =B71+E71 -> 8000 | K71: =B71/'Scenario 1 - Phase 1'!$E$8 -> 0 | N71: =E71/'LEVEL 3'!$E$8 -> 41.237113 | Q71: =H71/('Scenario 1 - Phase 1'!$E$8+'LEVEL 3'!$E$8) -> 14.787431 | T71: =B71/'Scenario 1 - Phase 1'!$B$8 -> 0 | W71: =E71/'LEVEL 3'!$B$8 -> 0.040756232 | Z71: =H71/('Scenario 1 - Phase 1'!$B$8+'LEVEL 3'!$B$8) -> 0.01576569
A72: Common Doors | B72: ='Scenario 1 - Phase 1'!K87 -> 0 | E72: ='LEVEL 3'!K88 -> 0 | H72: =B72+E72 -> 0 | K72: =B72/'Scenario 1 - Phase 1'!$E$8 -> 0 | N72: =E72/'LEVEL 3'!$E$8 -> 0 | Q72: =H72/('Scenario 1 - Phase 1'!$E$8+'LEVEL 3'!$E$8) -> 0 | T72: =B72/'Scenario 1 - Phase 1'!$B$8 -> 0 | W72: =E72/'LEVEL 3'!$B$8 -> 0 | Z72: =H72/('Scenario 1 - Phase 1'!$B$8+'LEVEL 3'!$B$8) -> 0
A73: Pocket Doors - 3 Panel | B73: ='Scenario 1 - Phase 1'!K88 -> 0 | E73: ='LEVEL 3'!K89 -> 0 | H73: =B73+E73 -> 0 | K73: =B73/'Scenario 1 - Phase 1'!$E$8 -> 0 | N73: =E73/'LEVEL 3'!$E$8 -> 0 | Q73: =H73/('Scenario 1 - Phase 1'!$E$8+'LEVEL 3'!$E$8) -> 0 | T73: =B73/'Scenario 1 - Phase 1'!$B$8 -> 0 | W73: =E73/'LEVEL 3'!$B$8 -> 0 | Z73: =H73/('Scenario 1 - Phase 1'!$B$8+'LEVEL 3'!$B$8) -> 0
A74: Garage Doors | B74: ='Scenario 1 - Phase 1'!K89 -> 0 | E74: ='LEVEL 3'!K90 -> 0 | H74: =B74+E74 -> 0 | K74: =B74/'Scenario 1 - Phase 1'!$E$8 -> 0 | N74: =E74/'LEVEL 3'!$E$8 -> 0 | Q74: =H74/('Scenario 1 - Phase 1'!$E$8+'LEVEL 3'!$E$8) -> 0 | T74: =B74/'Scenario 1 - Phase 1'!$B$8 -> 0 | W74: =E74/'LEVEL 3'!$B$8 -> 0 | Z74: =H74/('Scenario 1 - Phase 1'!$B$8+'LEVEL 3'!$B$8) -> 0
A75: Windows and Sliding Glass Doors | B75: ='Scenario 1 - Phase 1'!K90 -> 431702.7 | E75: ='LEVEL 3'!K91 -> 224631.58 | H75: =B75+E75 -> 656334.28 | K75: =B75/'Scenario 1 - Phase 1'!$E$8 -> 1244.1 | N75: =E75/'LEVEL 3'!$E$8 -> 1157.8947 | Q75: =H75/('Scenario 1 - Phase 1'!$E$8+'LEVEL 3'!$E$8) -> 1213.1872 | T75: =B75/'Scenario 1 - Phase 1'!$B$8 -> 1.3874781 | W75: =E75/'LEVEL 3'!$B$8 -> 1.1443921 | Z75: =H75/('Scenario 1 - Phase 1'!$B$8+'LEVEL 3'!$B$8) -> 1.2934454
A76: Windows Repair and Replacement | B76: ='Scenario 1 - Phase 1'!K91 -> 26025 | E76: ='LEVEL 3'!K92 -> 14550 | H76: =B76+E76 -> 40575 | K76: =B76/'Scenario 1 - Phase 1'!$E$8 -> 75 | N76: =E76/'LEVEL 3'!$E$8 -> 75 | Q76: =H76/('Scenario 1 - Phase 1'!$E$8+'LEVEL 3'!$E$8) -> 75 | T76: =B76/'Scenario 1 - Phase 1'!$B$8 -> 0.083643481 | W76: =E76/'LEVEL 3'!$B$8 -> 0.074125397 | Z76: =H76/('Scenario 1 - Phase 1'!$B$8+'LEVEL 3'!$B$8) -> 0.079961611
A77: Pool Equipment Windows | B77: ='Scenario 1 - Phase 1'!K92 -> 0 | E77: ='LEVEL 3'!K93 -> 0 | H77: =B77+E77 -> 0 | K77: =B77/'Scenario 1 - Phase 1'!$E$8 -> 0 | N77: =E77/'LEVEL 3'!$E$8 -> 0 | Q77: =H77/('Scenario 1 - Phase 1'!$E$8+'LEVEL 3'!$E$8) -> 0 | T77: =B77/'Scenario 1 - Phase 1'!$B$8 -> 0 | W77: =E77/'LEVEL 3'!$B$8 -> 0 | Z77: =H77/('Scenario 1 - Phase 1'!$B$8+'LEVEL 3'!$B$8) -> 0
A78: Pool Glass Walls | B78: ='Scenario 1 - Phase 1'!K93 -> 0 | E78: ='LEVEL 3'!K94 -> 0 | H78: =B78+E78 -> 0 | K78: =B78/'Scenario 1 - Phase 1'!$E$8 -> 0 | N78: =E78/'LEVEL 3'!$E$8 -> 0 | Q78: =H78/('Scenario 1 - Phase 1'!$E$8+'LEVEL 3'!$E$8) -> 0 | T78: =B78/'Scenario 1 - Phase 1'!$B$8 -> 0 | W78: =E78/'LEVEL 3'!$B$8 -> 0 | Z78: =H78/('Scenario 1 - Phase 1'!$B$8+'LEVEL 3'!$B$8) -> 0
A79: Fixed Glass | B79: ='Scenario 1 - Phase 1'!K94 -> 0 | E79: ='LEVEL 3'!K95 -> 0 | H79: =B79+E79 -> 0 | K79: =B79/'Scenario 1 - Phase 1'!$E$8 -> 0 | N79: =E79/'LEVEL 3'!$E$8 -> 0 | Q79: =H79/('Scenario 1 - Phase 1'!$E$8+'LEVEL 3'!$E$8) -> 0 | T79: =B79/'Scenario 1 - Phase 1'!$B$8 -> 0 | W79: =E79/'LEVEL 3'!$B$8 -> 0 | Z79: =H79/('Scenario 1 - Phase 1'!$B$8+'LEVEL 3'!$B$8) -> 0
A80: Mirrors - LED | B80: ='Scenario 1 - Phase 1'!K95 -> 0 | E80: ='LEVEL 3'!K96 -> 0 | H80: =B80+E80 -> 0 | K80: =B80/'Scenario 1 - Phase 1'!$E$8 -> 0 | N80: =E80/'LEVEL 3'!$E$8 -> 0 | Q80: =H80/('Scenario 1 - Phase 1'!$E$8+'LEVEL 3'!$E$8) -> 0 | T80: =B80/'Scenario 1 - Phase 1'!$B$8 -> 0 | W80: =E80/'LEVEL 3'!$B$8 -> 0 | Z80: =H80/('Scenario 1 - Phase 1'!$B$8+'LEVEL 3'!$B$8) -> 0
A81: Mirrors - LED Install | B81: ='Scenario 1 - Phase 1'!K96 -> 0 | E81: ='LEVEL 3'!K97 -> 0 | H81: =B81+E81 -> 0 | K81: =B81/'Scenario 1 - Phase 1'!$E$8 -> 0 | N81: =E81/'LEVEL 3'!$E$8 -> 0 | Q81: =H81/('Scenario 1 - Phase 1'!$E$8+'LEVEL 3'!$E$8) -> 0 | T81: =B81/'Scenario 1 - Phase 1'!$B$8 -> 0 | W81: =E81/'LEVEL 3'!$B$8 -> 0 | Z81: =H81/('Scenario 1 - Phase 1'!$B$8+'LEVEL 3'!$B$8) -> 0
A82: Mirrors - Framed | B82: ='Scenario 1 - Phase 1'!K97 -> 0 | E82: ='LEVEL 3'!K98 -> 0 | H82: =B82+E82 -> 0 | K82: =B82/'Scenario 1 - Phase 1'!$E$8 -> 0 | N82: =E82/'LEVEL 3'!$E$8 -> 0 | Q82: =H82/('Scenario 1 - Phase 1'!$E$8+'LEVEL 3'!$E$8) -> 0 | T82: =B82/'Scenario 1 - Phase 1'!$B$8 -> 0 | W82: =E82/'LEVEL 3'!$B$8 -> 0 | Z82: =H82/('Scenario 1 - Phase 1'!$B$8+'LEVEL 3'!$B$8) -> 0
... A84: Mirrors - Polished Edges (Restrooms) | B84: ='Scenario 1 - Phase 1'!K99 -> 800 | E84: ='LEVEL 3'!K100 -> 500 | H84: =B84+E84 -> 1300 | K84: =B84/'Scenario 1 - Phase 1'!$E$8 -> 2.3054755 | N84: =E84/'LEVEL 3'!$E$8 -> 2.5773196 | Q84: =H84/('Scenario 1 - Phase 1'!$E$8+'LEVEL 3'!$E$8) -> 2.4029575 | T84: =B84/'Scenario 1 - Phase 1'!$B$8 -> 0.0025711733 | W84: =E84/'LEVEL 3'!$B$8 -> 0.0025472645 | Z84: =H84/('Scenario 1 - Phase 1'!$B$8+'LEVEL 3'!$B$8) -> 0.0025619247
A85: Finishes | C85: =SUM(B86:B121) -> 5170494.2 | F85: =SUM(E86:E121) -> #REF! | I85: =SUM(H86:H121) -> #REF! | L85: =SUM(K86:K121) -> 14900.56 | O85: =SUM(N86:N121) -> #REF! | R85: =SUM(Q86:Q121) -> #REF! | U85: =C85/'Scenario 1 - Phase 1'!$B$8 -> 16.617796 | X85: =F85/'LEVEL 3'!$B$8 -> #REF! | AA85: =I85/('Scenario 1 - Phase 1'!$B$8+'LEVEL 3'!$B$8) -> #REF!
A86: Cost Prep Labor | B86: ='Scenario 1 - Phase 1'!K101 -> 15557.1 | E86: ='LEVEL 3'!#REF! -> #REF! | H86: =B86+E86 -> #REF! | K86: =B86/'Scenario 1 - Phase 1'!$E$8 -> 44.833141 | N86: =E86/'LEVEL 3'!$E$8 -> #REF! | Q86: =H86/('Scenario 1 - Phase 1'!$E$8+'LEVEL 3'!$E$8) -> #REF! | T86: =B86/'Scenario 1 - Phase 1'!$B$8 -> 0.05 | W86: =E86/'LEVEL 3'!$B$8 -> #REF! | Z86: =H86/('Scenario 1 - Phase 1'!$B$8+'LEVEL 3'!$B$8) -> #REF!
A87: Cost Prep Mat | B87: ='Scenario 1 - Phase 1'!K102 -> 24891.36 | E87: ='LEVEL 3'!K102 -> 10000 | H87: =B87+E87 -> 34891.36 | K87: =B87/'Scenario 1 - Phase 1'!$E$8 -> 71.733026 | N87: =E87/'LEVEL 3'!$E$8 -> 51.546392 | Q87: =H87/('Scenario 1 - Phase 1'!$E$8+'LEVEL 3'!$E$8) -> 64.494196 | T87: =B87/'Scenario 1 - Phase 1'!$B$8 -> 0.08 | W87: =E87/'LEVEL 3'!$B$8 -> 0.05094529 | Z87: =H87/('Scenario 1 - Phase 1'!$B$8+'LEVEL 3'!$B$8) -> 0.068760797
A88: Clean Up - Final | B88: ='Scenario 1 - Phase 1'!K103 -> 186685.2 | E88: ='LEVEL 3'!K103 -> 166845.65 | H88: =B88+E88 -> 353530.85 | K88: =B88/'Scenario 1 - Phase 1'!$E$8 -> 537.99769 | N88: =E88/'LEVEL 3'!$E$8 -> 860.02912 | Q88: =H88/('Scenario 1 - Phase 1'!$E$8+'LEVEL 3'!$E$8) -> 653.47662 | T88: =B88/'Scenario 1 - Phase 1'!$B$8 -> 0.6 | W88: =E88/'LEVEL 3'!$B$8 -> 0.85 | Z88: =H88/('Scenario 1 - Phase 1'!$B$8+'LEVEL 3'!$B$8) -> 0.69670724
A89: Clean Up - During Construction | B89: ='Scenario 1 - Phase 1'!K104 -> 112011.12 | E89: ='LEVEL 3'!K104 -> 50000 | H89: =B89+E89 -> 162011.12 | K89: =B89/'Scenario 1 - Phase 1'!$E$8 -> 322.79862 | N89: =E89/'LEVEL 3'!$E$8 -> 257.73196 | Q89: =H89/('Scenario 1 - Phase 1'!$E$8+'LEVEL 3'!$E$8) -> 299.46603 | T89: =B89/'Scenario 1 - Phase 1'!$B$8 -> 0.36 | W89: =E89/'LEVEL 3'!$B$8 -> 0.25472645 | Z89: =H89/('Scenario 1 - Phase 1'!$B$8+'LEVEL 3'!$B$8) -> 0.31927714
A90: Dumpsters | B90: ='Scenario 1 - Phase 1'!K105 -> 27413 | E90: ='LEVEL 3'!K105 -> 15326 | H90: =B90+E90 -> 42739 | K90: =B90/'Scenario 1 - Phase 1'!$E$8 -> 79 | N90: =E90/'LEVEL 3'!$E$8 -> 79 | Q90: =H90/('Scenario 1 - Phase 1'!$E$8+'LEVEL 3'!$E$8) -> 79 | T90: =B90/'Scenario 1 - Phase 1'!$B$8 -> 0.088104467 | W90: =E90/'LEVEL 3'!$B$8 -> 0.078078751 | Z90: =H90/('Scenario 1 - Phase 1'!$B$8+'LEVEL 3'!$B$8) -> 0.08422623
A91: Clean Up - Hauling Exterior | B91: ='Scenario 1 - Phase 1'!K106 -> 34225.62 | E91: ='LEVEL 3'!K106 -> 10000 | H91: =B91+E91 -> 44225.62 | K91: =B91/'Scenario 1 - Phase 1'!$E$8 -> 98.632911 | N91: =E91/'LEVEL 3'!$E$8 -> 51.546392 | Q91: =H91/('Scenario 1 - Phase 1'!$E$8+'LEVEL 3'!$E$8) -> 81.747911 | T91: =B91/'Scenario 1 - Phase 1'!$B$8 -> 0.11 | W91: =E91/'LEVEL 3'!$B$8 -> 0.05094529 | Z91: =H91/('Scenario 1 - Phase 1'!$B$8+'LEVEL 3'!$B$8) -> 0.087155929
A92: Stucco | B92: ='Scenario 1 - Phase 1'!K107 -> 637587.69 | E92: ='LEVEL 3'!K107 -> 482655.68 | H92: =B92+E92 -> 1120243.4 | K92: =B92/'Scenario 1 - Phase 1'!$E$8 -> 1837.4285 | N92: =E92/'LEVEL 3'!$E$8 -> 2487.9159 | Q92: =H92/('Scenario 1 - Phase 1'!$E$8+'LEVEL 3'!$E$8) -> 2070.6901 | T92: =B92/'Scenario 1 - Phase 1'!$B$8 -> 2.0491855 | W92: =E92/'LEVEL 3'!$B$8 -> 2.4589034 | Z92: =H92/('Scenario 1 - Phase 1'!$B$8+'LEVEL 3'!$B$8) -> 2.2076762
A93: Stucco - Pump House | B93: ='Scenario 1 - Phase 1'!K108 -> 6000 | E93: ='LEVEL 3'!K108 -> 6000 | H93: =B93+E93 -> 12000 | K93: =B93/'Scenario 1 - Phase 1'!$E$8 -> 17.291066 | N93: =E93/'LEVEL 3'!$E$8 -> 30.927835 | Q93: =H93/('Scenario 1 - Phase 1'!$E$8+'LEVEL 3'!$E$8) -> 22.181146 | T93: =B93/'Scenario 1 - Phase 1'!$B$8 -> 0.0192838 | W93: =E93/'LEVEL 3'!$B$8 -> 0.030567174 | Z93: =H93/('Scenario 1 - Phase 1'!$B$8+'LEVEL 3'!$B$8) -> 0.023648535
A94: Stucco - Walls | B94: ='Scenario 1 - Phase 1'!K109 -> 0 | E94: ='LEVEL 3'!K109 -> 0 | H94: =B94+E94 -> 0 | K94: =B94/'Scenario 1 - Phase 1'!$E$8 -> 0 | N94: =E94/'LEVEL 3'!$E$8 -> 0 | Q94: =H94/('Scenario 1 - Phase 1'!$E$8+'LEVEL 3'!$E$8) -> 0 | T94: =B94/'Scenario 1 - Phase 1'!$B$8 -> 0 | W94: =E94/'LEVEL 3'!$B$8 -> 0 | Z94: =H94/('Scenario 1 - Phase 1'!$B$8+'LEVEL 3'!$B$8) -> 0
A95: Stucco - Pool Area | B95: ='Scenario 1 - Phase 1'!K110 -> 4000 | E95: ='LEVEL 3'!K110 -> 2000 | H95: =B95+E95 -> 6000 | K95: =B95/'Scenario 1 - Phase 1'!$E$8 -> 11.527378 | N95: =E95/'LEVEL 3'!$E$8 -> 10.309278 | Q95: =H95/('Scenario 1 - Phase 1'!$E$8+'LEVEL 3'!$E$8) -> 11.090573 | T95: =B95/'Scenario 1 - Phase 1'!$B$8 -> 0.012855866 | W95: =E95/'LEVEL 3'!$B$8 -> 0.010189058 | Z95: =H95/('Scenario 1 - Phase 1'!$B$8+'LEVEL 3'!$B$8) -> 0.011824268
A96: Stucco - Cabana | B96: ='Scenario 1 - Phase 1'!K111 -> 0 | E96: ='LEVEL 3'!K111 -> 0 | H96: =B96+E96 -> 0 | K96: =B96/'Scenario 1 - Phase 1'!$E$8 -> 0 | N96: =E96/'LEVEL 3'!$E$8 -> 0 | Q96: =H96/('Scenario 1 - Phase 1'!$E$8+'LEVEL 3'!$E$8) -> 0 | T96: =B96/'Scenario 1 - Phase 1'!$B$8 -> 0 | W96: =E96/'LEVEL 3'!$B$8 -> 0 | Z96: =H96/('Scenario 1 - Phase 1'!$B$8+'LEVEL 3'!$B$8) -> 0
A97: Stucco - Pool Equipment | B97: ='Scenario 1 - Phase 1'!K112 -> 0 | E97: ='LEVEL 3'!K112 -> 5000 | H97: =B97+E97 -> 5000 | K97: =B97/'Scenario 1 - Phase 1'!$E$8 -> 0 | N97: =E97/'LEVEL 3'!$E$8 -> 25.773196 | Q97: =H97/('Scenario 1 - Phase 1'!$E$8+'LEVEL 3'!$E$8) -> 9.2421442 | T97: =B97/'Scenario 1 - Phase 1'!$B$8 -> 0 | W97: =E97/'LEVEL 3'!$B$8 -> 0.025472645 | Z97: =H97/('Scenario 1 - Phase 1'!$B$8+'LEVEL 3'!$B$8) -> 0.0098535564
