Workbook
Name \A: #REF!
Name \A: #REF!
Name \A: #REF!
Name \A: #REF!
Name \A: #REF!
Name \B: #REF!
Name \B: #REF!
Name \B: #REF!
Name \B: #REF!
Name \C: #REF!
Name \C: #REF!
Name \C: #REF!
Name \D: #REF!
Name \D: #REF!
Name \D: #REF!
Name \E: #REF!
Name \E: #REF!
Name \E: #REF!
Name \F: #REF!
Name \F: #REF!
Name \F: #REF!
Name \i: #REF!
Name \i: #REF!
Name \i: #REF!
Name \M: #REF!
Name \M: #REF!
Name \M: #REF!
Name \N: #REF!
Name \N: #REF!
Name \N: #REF!
Name \O: #REF!
Name \O: #REF!
Name \O: #REF!
Name \P: #REF!
Name \P: #REF!
Name \P: #REF!
Name \Q: #REF!
Name \Q: #REF!
Name \Q: #REF!
Name \S: #REF!
Name \S: #REF!
Name \S: #REF!
Name \T: #REF!
Name \T: #REF!
Name \T: #REF!
Name \U: #REF!
Name \U: #REF!
Name \U: #REF!
Name \w: #REF!
Name \w: #REF!
Name \w: #REF!
Name \X: #REF!
Name \X: #REF!
Name \X: #REF!
Name \Y: #REF!
Name \Y: #REF!
Name \Y: #REF!
Name \Z: #REF!
Name \Z: #REF!
Name \Z: #REF!

Sheet _REFERENCE888777888
A1: WorkSheet Name | B1: Report Code | C1: Company Id | D1: Job Id | E1: Start Date | F1: End Date | G1: Payroll Subledger | H1: Pay Period Id

Sheet LEVEL 3
A1: Project Details
A2: Project | B2: Robindale & 215 | J2: Total Cost | K2: =L319 -> 68910228 | M2: Unit Breakdown | Q2: Parking
A3: Budget Level | B3: Level 3 | M3: Unit Type | N3: Number | O3: % | Q3: Cover Parking | S3: 286 | AE3: Railing Estimate | AI3: Building 3 | AJ3: =21*7 -> 147 | AL3: Stucco | AP3: Building 3 | AQ3: =15000+6560+6500+15400+4570+4635+4540+4250 -> 61455
A4: Product | B4: Senior | J4: Cost Per Unit | K4: =K2/N9 -> 189835.34 | M4: Studios | N4: 0 | O4: =N4/$N$9 -> 0 | Q4: Cover Accesible Parking | AE4: Building 1 | AJ4: =14*7 -> 98 | AL4: Building 1
A5: Start Date | M5: 1 Br - 1 Ba | N5: ='Assumptions & Takeoffs'!B4+'Assumptions & Takeoffs'!B5 -> 218 | O5: =N5/$N$9 -> 0.60055096 | Q5: Open Parking | S5: 112 | AE5: Northwest | AF5: =21*4+8*8+7*6 -> 190 | AJ5: =8*22 -> 176 | AL5: Northwest | AM5: 19256
A6: Timeline | B6: 24 | J6: Cost Per SF | K6: =K2/B8 -> 190.05995 | M6: 2 Br - 1 Ba | N6: ='Assumptions & Takeoffs'!B6+'Assumptions & Takeoffs'!B7 -> 145 | O6: =N6/$N$9 -> 0.39944904 | Q6: Accessible Parking | S6: 14 | AE6: Southwest | AF6: =14*4+21*2+8*6 -> 146 | AJ6: =7*10 -> 70 | AL6: Southwest | AM6: 8980
A7: Floors | B7: 2 | M7: 2 Br - 2 Ba | N7: 0 | O7: =N7/$N$9 -> 0 | Q7: Waiver | S7: 0 | AE7: Northeast | AF7: =21*2+14*2+8*6 -> 118 | AJ7: =SUM(AJ3:AJ6) -> 491 | AL7: Northeast | AM7: 8850
A8: Bldg. SF | B8: =98509+136604+127458 -> 362571 | J8: Efficiency | K8: ='Assumptions & Takeoffs'!D8/B8 -> 0.78175861 | M8: 3 Br - 2 Ba | N8: 0 | O8: =N8/$N$9 -> 0 | Q8: Total Parking Provided | S8: =SUM(S3:S7) -> 412 | AE8: Southeast | AF8: =21*2+14*8+8*12+7*8 -> 306 | AL8: Southeast | AM8: 19965
A9: Acres | B9: 17.35 | M9: Totals | N9: =SUM(N4:N8) -> 363 | O9: =N9/$N$9 -> 1 | Q9: Parking Ratio | S9: =S8/N9 -> 1.1349862 | AE9: More | AF9: =21*4+8*6 -> 132 | AG9: =SUM(AF5:AF9) -> 892 | AL9: More | AM9: =5870+6250+6290+5915 -> 24325 | AN9: =SUM(AM5:AM9) -> 81376
A10: Site SF | B10: =B9*43560 -> 755766
A11: Buildings | B11: 3 | AE11: Building 2 & 5 | AI11: Building 4 | AJ11: =14*8 -> 112 | AL11: Building 2 & 5 | AP11: Building 4 | AQ11: =5782+5760+8825+9150 -> 29517
AE12: Northwest | AJ12: =20*8 -> 160 | AL12: Northwest
A13: Description | B13: Cost Code | C13: Cost Category | D13: Sub job | E13: Source | F13: UMO | G13: Quantity | H13: U.P. | I13: Escal % | J13: Total U.P. | K13: Sub Total | L13: Total | M13: Description / Details
A14: General Requirement | B14: 01 | C14: S | F14: Mo | G14: =$B$6 -> 24 | H14: =N324 -> 139138.88 | I14: 0 | J14: =H14*(1+I14) -> 139138.88 | K14: =J14*G14 -> 3339333.1
A15: General Requirements | B15: 01 | L15: =K14 -> 3339333.1
A16: Potholing | B16: 02-3213 | C16: S | D16: ON-SITE | E16: Allowance | G16: 1 | H16: 16000 | I16: 0 | J16: =H16*(1+I16) -> 16000 | K16: =J16*G16 -> 16000
A17: Existing Conditions | B17: 02 | L17: =K16 -> 16000
A18: Slabs | B18: 03-3101 | C18: S | D18: BUILDING | E18: Proposal | F18: LS | G18: 1 | H18: 2185768 | I18: 0 | J18: =H18*(1+I18) -> 2185768 | K18: =J18*G18 -> 2185768 | M18: Proposal (Alpha) - High Bid | O18: NRC Concrete ($1,542,922) - Low Bid
A19: Deepened Footings | B19: 03-3101 | C19: S | D19: BUILDING | E19: N/A | J19: =H19*(1+I19) -> 0 | K19: =J19*G19 -> 0 | AB19: Grading & Paving | AC19: 1833769
A20: Concrete Slab Repairs | B20: 03-3101 | C20: RR | D20: BUILDING | E20: Allowance | F20: LS | G20: 1 | H20: 7500 | I20: 0 | J20: =H20*(1+I20) -> 7500 | K20: =J20*G20 -> 7500 | AB20: Wets | AC20: 1812662
A21: Pump House Concrete | B21: 03-3101 | C21: S | D21: PUMPHOUSE | E21: Allowance | F21: LS | G21: 1 | H21: 8500 | J21: =H21*(1+I21) -> 8500 | K21: =J21*G21 -> 8500 | AB21: Slabs | AC21: 1542922
A22: Trash Enclosure Concrete | B22: 03-3102 | C22: S | D22: OTHER SITE | E22: Proposal | F22: EA | G22: ='Assumptions & Takeoffs'!B14 -> 14 | H22: 2958 | I22: 0 | J22: =H22*(1+I22) -> 2958 | K22: =J22*G22 -> 41412 | M22: Proposal (Alpha) | AB22: Wood Framing | AC22: 6634921
A23: Pool Area Shower Concrete | B23: 03-3105 | C23: S | D23: POOL AREA | E23: Allowance | F23: LS | G23: 1 | H23: 23959 | I23: 0 | J23: =H23*(1+I23) -> 23959 | K23: =J23*G23 -> 23959 | AB23: Plumbing | AC23: 3325080
A24: Cabana Concrete | B24: 03-3107 | C24: S | D24: POOL AREA | E24: Allowance | F24: LS | G24: 1 | H24: 6500 | I24: 0 | J24: =H24*(1+I24) -> 6500 | K24: =J24*G24 -> 6500 | AB24: Electrical | AC24: 4641350
A25: Pool Equipment Foundation | B25: 03-3108 | C25: S | D25: POOL EQUIP | E25: Allowance | F25: LS | G25: 1 | H25: 4290 | I25: 0 | J25: =H25*(1+I25) -> 4290 | K25: =J25*G25 -> 4290 | M25: Proposal (Alpha) | AB25: Mechanical
A26: Lightweight Concrete | B26: 03-3116 | C26: S | D26: BUILDING | E26: Proposal | F26: LS | G26: 1 | H26: =73410+103920+96980 -> 274310 | I26: 0 | J26: =H26*(1+I26) -> 274310 | K26: =J26*G26 -> 274310 | M26: Propsal (Nevada Gyp) - Low Bid | O26: Sound-Crete ($289,353) - High Bid | AB26: Finished Carpentry
A27: Deck Concrete | B27: 03-5001 | C27: S | D27: BUILDING | E27: Proposal | F27: LS | G27: 1 | H27: =10030+12540+10030 -> 32600 | I27: 0 | J27: =H27*(1+I27) -> 32600 | K27: =J27*G27 -> 32600 | M27: Propsal (Nevada Gyp) - Low Bid | O27: Sound-Crete ($41,260) - High Bid | AB27: Drywall & Paint | AC27: 3860853
A28: Concrete | B28: 03 | L28: =SUM(K18:K27) -> 2584839 | AB28: Masonry | AC28: 737195
A29: Elevator Shaft | B29: 04-2201 | C29: S | D29: BUILDING | E29: N/A | F29: Stop | G29: 0 | H29: 11500 | I29: 0 | J29: =H29*(1+I29) -> 11500 | K29: =J29*G29 -> 0 | M29: Wood framed. | AB29: Structural Steel | AC29: 121085
A30: Trash Enclosure | B30: 04-2202 | C30: S | D30: OTHER SITE | E30: Budget | F30: Count | G30: 14 | H30: 7000 | I30: 0 | J30: =H30*(1+I30) -> 7000 | K30: =J30*G30 -> 98000 | M30: See Off and Onsite Budget | O30: AWAITING UPDATED PROPOSALS | AB30: Site Iron | AC30: 608507
A31: Masonry Veneer | B31: 04-4301 | C31: S | D31: ON-SITE | E31: N/A | H31: 0 | J31: =H31*(1+I31) -> 0 | K31: =J31*G31 -> 0 | AB31: Elevators
A32: Masonry Veneer Pool Area | B32: 04-4305 | C32: S | D32: POOL AREA | E32: Allowance | F32: LS | G32: 3 | H32: 5000 | I32: 0 | J32: =H32*(1+I32) -> 5000 | K32: =J32*G32 -> 15000 | O32: AWAITING UPDATED PROPOSALS | AB32: Sprinkler Systems
A33: Pool Eq. Shower | B33: 04-4306 | C33: A | D33: POOL EQUIP | E33: Allowance | F33: LS | G33: 1 | H33: 15000 | I33: 0 | J33: =H33*(1+I33) -> 15000 | K33: =J33*G33 -> 15000 | O33: AWAITING UPDATED PROPOSALS | AB33: Fire Alarm
A34: Masonry | B34: 04 | L34: =SUM(K29:K33) -> 128000 | AB34: Insulation | AC34: 572070
A35: Structural Steel | B35: 05-1201 | C35: S | D35: BUILDING | E35: Proposal | F35: LS | G35: 1 | H35: =51595+31455+26435 -> 109485 | I35: 0 | J35: =H35*(1+I35) -> 109485 | K35: =J35*G35 -> 109485 | M35: Proposal (Imperial Iron) | AB35: Stucco | AC35: 897250
A36: Elevator Shaft Iron | B36: 05-1202 | C36: S | D36: BUILDING | E36: Proposal | F36: LS | G36: 1 | H36: 9600 | I36: 0 | J36: =H36*(1+I36) -> 9600 | K36: =J36*G36 -> 9600 | M36: Proposal (Imperial Iron) | AB36: Roofing | AC36: 1492534
A37: Stair Handrails | B37: 05-5201 | C37: S | D37: BUILDING | E37: West Henderson | F37: Flight | G37: ='Assumptions & Takeoffs'!B15 -> 19 | H37: 3000 | I37: 0 | J37: =H37*(1+I37) -> 3000 | K37: =J37*G37 -> 57000 | M37: West Henderson proposal - Desert Steel | AB37: Dry Utilities
A38: Garage Stair Railings | B38: 05-5201 | C38: S | D38: BUILDING | E38: N/A | H38: 0 | I38: 0 | J38: =H38*(1+I38) -> 0 | K38: =J38*G38 -> 0 | AB38: Lightweight Concrete | AC38: 306910
A39: Cabana Iron | B39: 05-7004 | C39: S | D39: POOL AREA | E39: N/A | H39: 0 | I39: 0 | J39: =H39*(1+I39) -> 0 | K39: =J39*G39 -> 0 | AB39: Decks
A40: Pool Equipment Gate | B40: 05-7005 | C40: S | D40: POOL EQUIP | E40: Budget | F40: Count | G40: 2 | H40: 1950 | I40: 0 | J40: =H40*(1+I40) -> 1950 | K40: =J40*G40 -> 3900 | M40: See Off and Onsite Budget | O40: AWAITING UPDATED PROPOSALS | AB40: Const. Clean
A41: Iron Railings | B41: 05-7300 | C41: S | D41: BUILDING | E41: West Henderson | F41: LF | G41: ='Assumptions & Takeoffs'!$B$18 -> 2595 | H41: 92.5 | I41: 0 | J41: 92.5 | K41: =J41*G41 -> 240037.5 | M41: West Henderson proposal - Desert Steel | AB41: Security Systems
A42: Cable Railings | B42: 05-7316 | C42: S | D42: COMMON AREA | E42: N/A | H42: 0 | I42: 0 | J42: =H42*(1+I42) -> 0 | K42: =J42*G42 -> 0 | AB42: Windows & Sliders
A43: Metals | B43: 05 | L43: =SUM(K35:K42) -> 420022.5 | AB43: Pools & Spa
A44: Framing | B44: 06-1100 | C44: S | D44: BUILDING | E44: Proposal | F44: LS | G44: 1 | H44: 6634921 | I44: 0 | J44: =H44*(1+I44) -> 6634921 | K44: =J44*G44 -> 6634921 | M44: Proposal (National Builders) - Low Bid | P44: Rafael Construction ($9,293,005) - High Bidder | AB44: Carports & Iron
A45: Framing Pump House | B45: 06-1100 | C45: S | D45: PUMPHOUSE | E45: Bruner | F45: SF | G45: 600 | H45: 18.68 | I45: 0 | J45: =H45*(1+I45) -> 18.68 | K45: =J45*G45 -> 11208 | AB45: Site Concrete | AC45: 547947
A46: Framing - Crane | B46: 06-1100 | C46: S | D46: BUILDING | E46: N/A | I46: 0 | J46: =H46*(1+I46) -> 0 | K46: =J46*G46 -> 0 | AB46: Cabinets - Units
A47: Cabana Framing | B47: 06-1109 | C47: S | D47: COMMON AREA | E47: N/A | I47: 0 | J47: =H47*(1+I47) -> 0 | K47: =J47*G47 -> 0 | AB47: Cabinets - Common Areas
A48: BBQ Framing | B48: 06-1110 | C48: S | D48: COMMON AREA | E48: Allowance | F48: LS | G48: 4 | H48: 2500 | I48: 0 | J48: =H48*(1+I48) -> 2500 | K48: =J48*G48 -> 10000 | AB48: Countertops - Units
A49: Fireplace Framing | B49: 06-1111 | C49: S | D49: COMMON AREA | E49: N/A | I49: 0 | J49: =H49*(1+I49) -> 0 | K49: =J49*G49 -> 0 | AB49: Countertops - Common Areas
A50: Trellis | B50: 06-1114 | C50: S | D50: BUILDING | E50: N/A | I50: 0 | J50: =H50*(1+I50) -> 0 | K50: =J50*G50 -> 0 | AB50: Unit Tub/Shower Surrounds
A51: Pool Equipment Framing | B51: 06-1114 | C51: S | D51: POOL EQUIP | E51: N/A | I51: 0 | J51: =H51*(1+I51) -> 0 | K51: =J51*G51 -> 0 | AB51: Flooring - Units
A52: Finish Carpentry - Units | B52: 06-2001 | C52: S | D52: BUILDING | E52: West Henderson | F52: Liavable SF | G52: ='Assumptions & Takeoffs'!B21 -> 269691 | H52: 3.55 | I52: 0.1 | J52: =H52*(1+I52) -> 3.905 | K52: =J52*G52 -> 1053143.4 | M52: Per WH proposal based on liavable SF. | AB52: Flooring - Common Areas
A53: Finish Carpentry - Common | B53: 06-2001 | C53: S | D53: COMMON AREA | E53: Bruner | F53: SF | G53: =B8 -> 362571 | H53: 1.0800045 | I53: 0.1 | J53: =H53*(1+I53) -> 1.1880049 | K53: =J53*G53 -> 430736.14 | M53: Added 10% as we have indication BFS has purchased Rystin and Doors and Millwork companies. | AB53: Site Landscaping
A54: Finish Carpentry - Pump House | B54: 06-2001S | C54: S | D54: PUMPHOUSE | E54: Allowance | F54: LS | G54: 1 | H54: 4000 | I54: 0 | J54: =H54*(1+I54) -> 4000 | K54: =J54*G54 -> 4000 | AB54: Blinds
A55: BBQ Trim | B55: 06-2006 | C55: S | D55: COMMON AREA | E55: Allowance | F55: LS | G55: 4 | H55: 1250 | I55: 0 | J55: =H55*(1+I55) -> 1250 | K55: =J55*G55 -> 5000 | AB55: Unit Appliances
A56: Shutters | B56: 06-4919 | C56: S | D56: BUILDING | E56: N/A | I56: 0 | J56: =H56*(1+I56) -> 0 | K56: =J56*G56 -> 0 | AB56: Interior Furniture
A57: Wood, Plastics, & Composites | B57: 06 | L57: =SUM(K44:K56) -> 8149008.5 | AB57: Exterior Furniture
A58: Insulation | B58: 07-2101 | C58: S | D58: BUILDING | E58: Proposal | F58: LS | G58: 1 | H58: =153825+213360+204135 -> 571320 | I58: 0 | J58: =H58*(1+I58) -> 571320 | K58: =J58*G58 -> 571320 | M58: Proposal (Battle Born) - Low Bid | O58: TruTeam ($852,000) - Middle Bid | R58: Gold Star ($858,434) - High Bid | AB58: Solar Panels
A59: Insulation - PH | B59: 07-2101 | C59: S | D59: PUMPHOUSE | E59: Proposal | F59: LS | G59: 1 | H59: 750 | I59: 0 | J59: =H59*(1+I59) -> 750 | K59: =J59*G59 -> 750 | M59: Proposal (Battle Born) | AB59: DAS System
A60: Roofing | B60: 07-3001 | C60: S | D60: BUILDING | E60: Proposal | F60: LS | G60: 1 | H60: =259925+25335+362950+35470+337920+34290+32800 -> 1088690 | I60: 0 | J60: =H60*(1+I60) -> 1088690 | K60: =J60*G60 -> 1088690 | M60: Proposal (TORC) | O60: Xbuilt ($1,492,543) - High Bid | AB60: Street Signs
A61: Roofing - PH | B61: 07-3001 | C61: S | D61: PUMPHOUSE | E61: Proposal | F61: LS | G61: 1 | H61: 8295 | I61: 0 | J61: =H61*(1+I61) -> 8295 | K61: =J61*G61 -> 8295 | M61: Proposal (TORC) | O61: Xbuilt ($4,478) | AB61: Temp Power
A62: Cabana Roofing | B62: 07-3002 | C62: S | D62: COMMON AREA | E62: Proposal | F62: LS | G62: 1 | H62: 15685 | I62: 0 | J62: =H62*(1+I62) -> 15685 | K62: =J62*G62 -> 15685 | M62: Proposal (Xbuilt) | O62: TORC (Not Included) | AB62: Surveying/Testing
A63: Pump House Roofing | B63: 07-3002 | C63: S | D63: PUMPHOUSE | E63: Allowance | F63: LS | G63: 1 | H63: 7500 | I63: 0 | J63: =H63*(1+I63) -> 7500 | K63: =J63*G63 -> 7500 | AB63: Gym Equipment
A64: Pool Equipment Roofing | B64: 07-3003 | C64: S | D64: POOL EQUIP | E64: Allowance | F64: LS | G64: ='Assumptions & Takeoffs'!B16 -> 1 | H64: 7500 | I64: 0 | J64: =H64*(1+I64) -> 7500 | K64: =J64*G64 -> 7500 | AB64: Gym Flooring
A65: Trash Enclosure Cover | B65: 07-6101 | C65: S | D65: OTHER SITE | E65: Proposal | F65: LS | G65: 1 | H65: 250000 | I65: 0 | J65: =H65*(1+I65) -> 250000 | K65: =J65*G65 -> 250000 | M65: Proposal (Hirschi) | AB65: Electrical Fixtures
A66: Pigeon Proofing | B66: 07-7001 | C66: S | D66: BUILDING | E66: Allowance | F66: SF | G66: =$B$8 -> 362571 | H66: 0.08 | I66: 0 | J66: =H66*(1+I66) -> 0.08 | K66: =J66*G66 -> 29005.68 | AB66: Pavers and Pool Deck
A67: Gutters and Downspouts | B67: 07-7124 | C67: S | D67: BUILDING | E67: Allowance | F67: SF | G67: =$B$8 -> 362571 | H67: 0.05 | I67: 0 | J67: =H67*(1+I67) -> 0.05 | K67: =J67*G67 -> 18128.55 | AB67: Signage
A68: Roof Ladders | B68: 07-7210 | C68: S | D68: BUILDING | E68: Allowance | F68: Count | G68: =2*$B$11 -> 6 | H68: 1550 | I68: 0 | J68: =H68*(1+I68) -> 1550 | K68: =J68*G68 -> 9300 | M68: 2 Per building | AB68: Site Security
A69: Roof Access Doors | B69: 07-7233 | C69: S | D69: BUILDING | E69: Allowance | F69: Count | G69: =2*$B$11 -> 6 | H69: 2500 | I69: 0 | J69: =H69*(1+I69) -> 2500 | K69: =J69*G69 -> 15000 | M69: 2 Per building | AB69: Masonry Veneer
A70: Roof Winch | B70: 07-7250 | C70: S | D70: BUILDING | E70: N/A | I70: 0 | J70: =H70*(1+I70) -> 0 | K70: =J70*G70 -> 0 | AC70: =SUM(AC19:AC69) -> 28935055
A71: Thermal & Moisture Protection | B71: 07 | L71: =SUM(K58:K70) -> 2021174.2
A72: Entry Doors | B72: 08-1001 | C72: S | D72: COMMON AREA | E72: Allowance | F72: Count | G72: 3 | H72: 8000 | I72: 0 | J72: =H72*(1+I72) -> 8000 | K72: =J72*G72 -> 24000
A73: Common Doors | B73: 08-1002 | C73: S | D73: COMMON AREA | E73: Included | I73: 0 | J73: =H73*(1+I73) -> 0 | K73: =J73*G73 -> 0
A74: Pocket Doors - 3 Panel | B74: 08-1002 | C74: S | D74: BUILDING | E74: N/A | I74: 0 | J74: =H74*(1+I74) -> 0 | K74: =J74*G74 -> 0
A75: Garage Doors | B75: 08-3619 | C75: S | D75: BUILDING | E75: N/A | I75: 0 | J75: =H75*(1+I75) -> 0 | K75: =J75*G75 -> 0
A76: Windows and Sliding Glass Doors | B76: 08-5301 | C76: S | D76: BUILDING | E76: West Henderson | F76: Per Unit | G76: =$N$9 -> 363 | H76: =565499/390 -> 1449.9974 | I76: 0 | J76: =H76*(1+I76) -> 1449.9974 | K76: =J76*G76 -> 526349.07 | M76: Contempo unit windows Proposal plus $100 per unit for frontage windows.
A77: Windows Repair and Replacement | B77: 08-5301 | C77: RR | D77: BUILDING | E77: Allowance | F77: Per Unit | G77: =$N$9 -> 363 | H77: 75 | I77: 0 | J77: =H77*(1+I77) -> 75 | K77: =J77*G77 -> 27225
A78: Pool Equipment Windows | B78: 08-5303 | C78: S | D78: POOL EQUIP | E78: N/A | I78: 0 | J78: =H78*(1+I78) -> 0 | K78: =J78*G78 -> 0
A79: Pool Glass Walls | B79: 08-8001 | C79: S | D79: POOL AREA | E79: N/A | I79: 0 | J79: =H79*(1+I79) -> 0 | K79: =J79*G79 -> 0
A80: Fixed Glass | B80: 08-8002 | C80: S | D80: BUILDING | E80: N/A | I80: 0 | J80: =H80*(1+I80) -> 0 | K80: =J80*G80 -> 0
A81: Mirrors - LED | B81: 08-8301 | C81: S | D81: BUILDING | E81: N/A | I81: 0 | J81: =H81*(1+I81) -> 0 | K81: =J81*G81 -> 0
A82: Mirrors - LED Install | B82: 08-8302 | C82: S | D82: BUILDING | E82: N/A | I82: 0 | J82: =H82*(1+I82) -> 0 | K82: =J82*G82 -> 0
A83: Mirrors - Framed | B83: 08-8301 | C83: S | D83: BUILDING | E83: N/A | I83: 0 | J83: =H83*(1+I83) -> 0 | K83: =J83*G83 -> 0
A84: Mirrors - Polished Edges (Units) | B84: 08-8301 | C84: S | D84: BUILDING | E84: Bruner | F84: Bathroom | G84: =N9 -> 363 | H84: 175 | I84: 0 | J84: =H84*(1+I84) -> 175 | K84: =J84*G84 -> 63525 | M84: Updated based on Bruner budget
A85: Mirrors - Polished Edges (Restrooms) | B85: 08-8301 | C85: S | D85: BUILDING | E85: Allowance | F85: Count | G85: 6 | H85: 300 | I85: 0 | J85: =H85*(1+I85) -> 300 | K85: =J85*G85 -> 1800
A86: Openings | B86: 08 | L86: =SUM(K72:K85) -> 642899.07
A87: Cost Prep Labor | B87: 09-0101 | C87: S | D87: BUILDING | E87: N/A | I87: 0 | J87: =H87*(1+I87) -> 0 | K87: =J87*G87 -> 0
A88: Cost Prep Mat - Home Depot | B88: 09-0102 | C88: S | D88: BUILDING | E88: Allowance | F88: LS | G88: 1 | H88: 10000 | I88: 0 | J88: =H88*(1+I88) -> 10000 | K88: =J88*G88 -> 10000
A89: Clean Up - Final | B89: 09-0103 | C89: S | D89: BUILDING | E89: Bruner | F89: SF | G89: =$B$8 -> 362571 | H89: 0.85 | I89: 0 | J89: =H89*(1+I89) -> 0.85 | K89: =J89*G89 -> 308185.35 | M89: Includes Dumpters
A90: Clean Up - During Construction - Labor | B90: 09-0104 | C90: S | D90: BUILDING | E90: Allowance | F90: LS | G90: 1 | H90: 75000 | I90: 0 | J90: =H90*(1+I90) -> 75000 | K90: =J90*G90 -> 75000
A91: Dumpsters | B91: 09-0113 | C91: S | D91: DUMPSTERS | E91: Allowance | F91: Unit | G91: =$N$9 -> 363 | H91: 79 | I91: 0 | J91: =H91*(1+I91) -> 79 | K91: =J91*G91 -> 28677
A92: Clean Up - Hauling Exterior | B92: 09-0121 | C92: S | D92: ON-SITE | E92: Allowance | F92: LS | G92: 1 | H92: 10000 | I92: 0 | J92: =H92*(1+I92) -> 10000 | K92: =J92*G92 -> 10000 | M92: Included in Construction Cleaning Contract.
A93: Stucco | B93: 09-2423 | C93: S | D93: BUILDING | E93: Proposal | F93: LS | G93: 1 | H93: =246420+335664+315166 -> 897250 | I93: 0 | J93: =H93*(1+I93) -> 897250 | K93: =J93*G93 -> 897250 | M93: Proposal (Desert Plastering) - Low Bid | P93: Builder's First Source ($993,890) - High Bid
A94: Stucco - Pump House | B94: 09-2423S | C94: A | D94: PUMPHOUSE | E94: Allowance | F94: LS | G94: ='Assumptions & Takeoffs'!B24 -> 1 | H94: 6000 | I94: 0 | J94: =H94*(1+I94) -> 6000 | K94: =J94*G94 -> 6000
A95: Stucco - Walls | B95: 09-2424 | C95: S | D95: POOL AREA | E95: N/A | I95: 0 | J95: =H95*(1+I95) -> 0 | K95: =J95*G95 -> 0
A96: Stucco - Pool Area | B96: 09-2428 | C96: A | D96: POOL AREA | E96: Allowance | F96: LS | G96: ='Assumptions & Takeoffs'!$B$16 -> 1 | H96: 2000 | I96: 0 | J96: =H96*(1+I96) -> 2000 | K96: =J96*G96 -> 2000
A97: Stucco - Cabana | B97: 09-2429 | C97: S | D97: POOL AREA | E97: N/A | I97: 0 | J97: =H97*(1+I97) -> 0 | K97: =J97*G97 -> 0
A98: Stucco - Pool Equipment | B98: 09-2430 | C98: S | D98: POOL EQUIP | E98: Pebble | F98: LS | G98: 1 | H98: 5000 | I98: 0 | J98: =H98*(1+I98) -> 5000 | K98: =J98*G98 -> 5000
A99: Stucco - Repairs | B99: 09-2423A | C99: RR | D99: BUILDING | E99: Allowance | F99: LS | G99: 1 | H99: 1500 | I99: 0 | J99: =H99*(1+I99) -> 1500 | K99: =J99*G99 -> 1500
A100: Drywall | B100: 09-2905 | C100: S | D100: BUILDING | E100: Proposal | F100: LS | G100: 1 | H100: =701759+996592+926648+2351+2000 -> 2629350 | I100: 0 | J100: =H100*(1+I100) -> 2629350 | K100: =J100*G100 -> 2629350 | M100: Proposal (Classic Drywall & Paint)
...

Sheet Comparison - Level 3
B1: Level 2.1 | E1: Level 3 | H1: Variance
A3: Units | C3: ='LEVEL 1.2 BUDGET'!N9 -> 363 | F3: ='LEVEL 1.2 BUDGET'!N9 -> 363 | I3: =C3-F3 -> 0
A4: Building Gross Square Feet | C4: ='LEVEL 1.2 BUDGET'!B8 -> 362571 | F4: ='LEVEL 1.2 BUDGET'!B8 -> 362571 | I4: =F4-C4 -> 0
A6: Total Cost | C6: =C312 -> 68033846 | F6: =F312 -> 68938905 | I6: =C6-F6 -> -905059.05 | W6: Studios | X6: 0 | Y6: =X6/$X$10 -> 0 | AC6: Southeast | AD6: =21*2+14*8+8*12+7*8 -> 306 | AJ6: Southeast | AK6: 19965
A7: Cost Per Unit | C7: =C6/X10 -> 187421.06 | F7: =F6/X10 -> 189914.34 | I7: =C7-F7 -> -2493.2756 | W7: 1 Br - 1 Ba | X7: ='Assumptions & Takeoffs'!B4+'Assumptions & Takeoffs'!B5 -> 218 | Y7: =X7/$X$10 -> 0.60055096 | AC7: More | AD7: =21*4+8*6 -> 132 | AE7: =SUM(AD6:AD7) -> 438 | AJ7: More | AK7: =5870+6250+6290+5915 -> 24325 | AL7: =SUM(AK6:AK7) -> 44290
A8: Cost Per SF | C8: =C6/X23 -> 187.64282 | F8: =F6/X23 -> 190.13905 | I8: =C8-F8 -> -2.4962257 | W8: 2 Br - 1 Ba | X8: ='Assumptions & Takeoffs'!B6+'Assumptions & Takeoffs'!B7 -> 145 | Y8: =X8/$X$10 -> 0.39944904
W9: 2 Br - 2 Ba | X9: 0 | Y9: =X9/$X$10 -> 0 | AC9: Building 2 & 5 | AG9: Building 4 | AH9: =14*8 -> 112 | AJ9: Building 2 & 5 | AN9: Building 4 | AO9: =5782+5760+8825+9150 -> 29517
A10: Description | B10: Sub Total | C10: Total | E10: Sub Total | F10: Total | H10: Variance | I10: % Change | K10: Description / Details | W10: Totals | X10: =SUM(X6:X9) -> 363 | Y10: =X10/$X$10 -> 1
A11: General Requirement | B11: =VLOOKUP($A11,'LEVEL 2.1'!$A$13:$K$317,11,FALSE) -> 3292398.3 | E11: =VLOOKUP($A11,'LEVEL 3'!$A$13:$K$317,11,FALSE) -> 3339333.1 | H11: =B11-E11 -> -46934.782 | I11: =H11/B11 -> -0.014255499
A12: General Requirements | C12: =B11 -> 3292398.3 | F12: =E11 -> 3339333.1 | H12: =C12-F12 -> -46934.782 | I12: =H12/C12 -> -0.014255499
A13: Potholing | B13: =VLOOKUP($A13,'LEVEL 2.1'!$A$13:$K$317,11,FALSE) -> 16000 | E13: =VLOOKUP($A13,'LEVEL 3'!$A$13:$K$317,11,FALSE) -> 16000 | H13: =B13-E13 -> 0 | I13: =H13/B13 -> 0
A14: Existing Conditions | C14: =B13 -> 16000 | F14: =E13 -> 16000 | H14: =C14-F14 -> 0 | I14: =H14/C14 -> 0
A15: Slabs | B15: =VLOOKUP($A15,'LEVEL 2.1'!$A$13:$K$317,11,FALSE) -> 2125443.3 | E15: =VLOOKUP($A15,'LEVEL 3'!$A$13:$K$317,11,FALSE) -> 2185768 | H15: =B15-E15 -> -60324.68 | I15: =H15/B15 -> -0.028382164 | K15: Updated per Bids
A16: Concrete Slab Repairs | B16: =VLOOKUP($A16,'LEVEL 2.1'!$A$13:$K$317,11,FALSE) -> 7500 | E16: =VLOOKUP($A16,'LEVEL 3'!$A$13:$K$317,11,FALSE) -> 7500 | H16: =B16-E16 -> 0 | I16: =H16/B16 -> 0 | W16: Project Details
A17: Pump House Concrete | B17: =VLOOKUP($A17,'LEVEL 2.1'!$A$13:$K$317,11,FALSE) -> 8500 | E17: =VLOOKUP($A17,'LEVEL 3'!$A$13:$K$317,11,FALSE) -> 8500 | H17: =B17-E17 -> 0 | I17: =H17/B17 -> 0 | W17: Project | X17: Robindale &215
A18: Trash Enclosure Concrete | B18: =VLOOKUP($A18,'LEVEL 2.1'!$A$13:$K$317,11,FALSE) -> 70000 | E18: =VLOOKUP($A18,'LEVEL 3'!$A$13:$K$317,11,FALSE) -> 41412 | H18: =B18-E18 -> 28588 | I18: =H18/B18 -> 0.4084 | K18: Updated per Bids | W18: Budget Level | X18: Level 1
A19: Pool Area Shower Concrete | B19: =VLOOKUP($A19,'LEVEL 2.1'!$A$13:$K$317,11,FALSE) -> 23959 | E19: =VLOOKUP($A19,'LEVEL 3'!$A$13:$K$317,11,FALSE) -> 23959 | H19: =B19-E19 -> 0 | I19: =H19/B19 -> 0 | W19: Product | X19: Senior
A20: Cabana Concrete | B20: =VLOOKUP($A20,'LEVEL 2.1'!$A$13:$K$317,11,FALSE) -> 6500 | E20: =VLOOKUP($A20,'LEVEL 3'!$A$13:$K$317,11,FALSE) -> 6500 | H20: =B20-E20 -> 0 | I20: 0
A21: Pool Equipment Foundation | B21: =VLOOKUP($A21,'LEVEL 2.1'!$A$13:$K$317,11,FALSE) -> 6500 | E21: =VLOOKUP($A21,'LEVEL 3'!$A$13:$K$317,11,FALSE) -> 4290 | H21: =B21-E21 -> 2210 | I21: =IF(B21=0,"n/a",H21/B21) -> 0.34 | K21: Updated per Bids | W21: Timeline | X21: 30
A22: Lightweight Concrete | B22: =VLOOKUP($A22,'LEVEL 2.1'!$A$13:$K$317,11,FALSE) -> 481539.8 | E22: =VLOOKUP($A22,'LEVEL 3'!$A$13:$K$317,11,FALSE) -> 274310 | H22: =B22-E22 -> 207229.8 | I22: =H22/B22 -> 0.43034823 | K22: Updated per Bids | W22: Floors | X22: 2
A23: Deck Concrete | B23: =VLOOKUP($A23,'LEVEL 2.1'!$A$13:$K$317,11,FALSE) -> 45894.051 | E23: =VLOOKUP($A23,'LEVEL 3'!$A$13:$K$317,11,FALSE) -> 32600 | H23: =B23-E23 -> 13294.051 | I23: =H23/B23 -> 0.28966829 | K23: Updated per Bids | W23: Bldg. SF | X23: =98509+136604+127458 -> 362571
A24: Concrete | C24: =SUM(B15:B23) -> 2775836.2 | F24: =SUM(E15:E23) -> 2584839 | H24: =C24-F24 -> 190997.17 | I24: =H24/C24 -> 0.068807076 | W24: Acres | X24: 17.35
A25: Elevator Shaft | B25: =VLOOKUP($A25,'LEVEL 2.1'!$A$13:$K$317,11,FALSE) -> 0 | E25: =VLOOKUP($A25,'LEVEL 3'!$A$13:$K$317,11,FALSE) -> 0 | H25: =B25-E25 -> 0 | I25: =IF(B25=0,"n/a",H25/B25) -> n/a | W25: Site SF | X25: =X24*43560 -> 755766
A26: Trash Enclosure | B26: =VLOOKUP($A26,'LEVEL 2.1'!$A$13:$K$317,11,FALSE) -> 98000 | E26: =VLOOKUP($A26,'LEVEL 3'!$A$13:$K$317,11,FALSE) -> 98000 | H26: =B26-E26 -> 0 | I26: =H26/B26 -> 0 | W26: Buildings | X26: 3
A27: Masonry Veneer Pool Area | B27: =VLOOKUP($A27,'LEVEL 2.1'!$A$13:$K$317,11,FALSE) -> 15000 | E27: =VLOOKUP($A27,'LEVEL 3'!$A$13:$K$317,11,FALSE) -> 15000 | H27: =B27-E27 -> 0 | I27: =IF(B27=0,"n/a",H27/B27) -> 0
A28: Pool Eq. Shower | B28: =VLOOKUP($A28,'LEVEL 2.1'!$A$13:$K$317,11,FALSE) -> 15000 | E28: =VLOOKUP($A28,'LEVEL 3'!$A$13:$K$317,11,FALSE) -> 15000 | H28: =B28-E28 -> 0 | I28: =IF(B28=0,"n/a",H28/B28) -> 0
A29: Masonry | C29: =SUM(B25:B28) -> 128000 | F29: =SUM(E25:E28) -> 128000 | H29: =C29-F29 -> 0 | I29: =H29/C29 -> 0
A30: Structural Steel | B30: =VLOOKUP($A30,'LEVEL 2.1'!$A$13:$K$317,11,FALSE) -> 150000 | E30: =VLOOKUP($A30,'LEVEL 3'!$A$13:$K$317,11,FALSE) -> 109485 | H30: =B30-E30 -> 40515 | I30: =IF(B30=0,"n/a",H30/B30) -> 0.2701 | K30: Updated per Bids
A31: Elevator Shaft Iron | B31: =VLOOKUP($A31,'LEVEL 2.1'!$A$13:$K$317,11,FALSE) -> 25500 | E31: =VLOOKUP($A31,'LEVEL 3'!$A$13:$K$317,11,FALSE) -> 9600 | H31: =B31-E31 -> 15900 | I31: =H31/B31 -> 0.62352941 | K31: Updated per Bids
A32: Stair Handrails | B32: =VLOOKUP($A32,'LEVEL 2.1'!$A$13:$K$317,11,FALSE) -> 57000 | E32: =VLOOKUP($A32,'LEVEL 3'!$A$13:$K$317,11,FALSE) -> 57000 | H32: =B32-E32 -> 0 | I32: =H32/B32 -> 0
A33: Pool Equipment Gate | B33: =VLOOKUP($A33,'LEVEL 2.1'!$A$13:$K$317,11,FALSE) -> 1950 | E33: =VLOOKUP($A33,'LEVEL 3'!$A$13:$K$317,11,FALSE) -> 3900 | H33: =B33-E33 -> -1950 | I33: =H33/B33 -> -1 | K33: Updated per Bids - Only 1 pool equipment gate
A34: Iron Railings | B34: =VLOOKUP($A34,'LEVEL 2.1'!$A$13:$K$317,11,FALSE) -> 240037.5 | E34: =VLOOKUP($A34,'LEVEL 3'!$A$13:$K$317,11,FALSE) -> 240037.5 | H34: =B34-E34 -> 0 | I34: =H34/B34 -> 0
A35: Cable Railings | B35: =VLOOKUP($A35,'LEVEL 2.1'!$A$13:$K$317,11,FALSE) -> 0 | E35: =VLOOKUP($A35,'LEVEL 3'!$A$13:$K$317,11,FALSE) -> 0 | H35: =B35-E35 -> 0 | I35: =IF(B35=0,"n/a",H35/B35) -> n/a
A36: Metals | C36: =SUM(B30:B35) -> 474487.5 | F36: =SUM(E30:E35) -> 420022.5 | H36: =C36-F36 -> 54465 | I36: =H36/C36 -> 0.11478701
A37: Framing | B37: =VLOOKUP($A37,'LEVEL 2.1'!$A$13:$K$317,11,FALSE) -> 6772826.3 | E37: =VLOOKUP($A37,'LEVEL 3'!$A$13:$K$317,11,FALSE) -> 6634921 | H37: =B37-E37 -> 137905.28 | I37: =H37/B37 -> 0.020361556 | K37: Updated per Bids
A38: Framing Pump House | B38: =VLOOKUP($A38,'LEVEL 2.1'!$A$13:$K$317,11,FALSE) -> 11208 | E38: =VLOOKUP($A38,'LEVEL 3'!$A$13:$K$317,11,FALSE) -> 11208 | H38: =B38-E38 -> 0 | I38: =IF(B38=0,"n/a",H38/B38) -> 0
A39: Framing - Crane | B39: =VLOOKUP($A39,'LEVEL 2.1'!$A$13:$K$317,11,FALSE) -> 0 | E39: =VLOOKUP($A39,'LEVEL 3'!$A$13:$K$317,11,FALSE) -> 0 | H39: =B39-E39 -> 0 | I39: =IF(B39=0,"n/a",H39/B39) -> n/a
A40: Cabana Framing | B40: =VLOOKUP($A40,'LEVEL 2.1'!$A$13:$K$317,11,FALSE) -> 0 | E40: =VLOOKUP($A40,'LEVEL 3'!$A$13:$K$317,11,FALSE) -> 0 | H40: =B40-E40 -> 0 | I40: =IF(B40=0,"n/a",H40/B40) -> n/a
A41: BBQ Framing | B41: =VLOOKUP($A41,'LEVEL 2.1'!$A$13:$K$317,11,FALSE) -> 10000 | E41: =VLOOKUP($A41,'LEVEL 3'!$A$13:$K$317,11,FALSE) -> 10000 | H41: =B41-E41 -> 0 | I41: =H41/B41 -> 0
A42: Fireplace Framing | B42: =VLOOKUP($A42,'LEVEL 2.1'!$A$13:$K$317,11,FALSE) -> 0 | E42: =VLOOKUP($A42,'LEVEL 3'!$A$13:$K$317,11,FALSE) -> 0 | H42: =B42-E42 -> 0 | I42: =IF(B42=0,"n/a",H42/B42) -> n/a
A43: Trellis | B43: =VLOOKUP($A43,'LEVEL 2.1'!$A$13:$K$317,11,FALSE) -> 0 | E43: =VLOOKUP($A43,'LEVEL 3'!$A$13:$K$317,11,FALSE) -> 0 | H43: =B43-E43 -> 0 | I43: =IF(B43=0,"n/a",H43/B43) -> n/a
A44: Pool Equipment Framing | B44: =VLOOKUP($A44,'LEVEL 2.1'!$A$13:$K$317,11,FALSE) -> 0 | E44: =VLOOKUP($A44,'LEVEL 3'!$A$13:$K$317,11,FALSE) -> 0 | H44: =B44-E44 -> 0 | I44: =IF(B44=0,"n/a",H44/B44) -> n/a
A45: Finish Carpentry - Units | B45: =VLOOKUP($A45,'LEVEL 2.1'!$A$13:$K$317,11,FALSE) -> 1053143.4 | E45: =VLOOKUP($A45,'LEVEL 3'!$A$13:$K$317,11,FALSE) -> 1053143.4 | H45: =B45-E45 -> 0 | I45: =H45/B45 -> 0
A46: Finish Carpentry - Common | B46: =VLOOKUP($A46,'LEVEL 2.1'!$A$13:$K$317,11,FALSE) -> 430736.14 | E46: =VLOOKUP($A46,'LEVEL 3'!$A$13:$K$317,11,FALSE) -> 430736.14 | H46: =B46-E46 -> 0 | I46: =H46/B46 -> 0 | V46: 920930.34
A47: Finish Carpentry - Pump House | B47: =VLOOKUP($A47,'LEVEL 2.1'!$A$13:$K$317,11,FALSE) -> 4000 | E47: =VLOOKUP($A47,'LEVEL 3'!$A$13:$K$317,11,FALSE) -> 4000 | H47: =B47-E47 -> 0 | I47: =IF(B47=0,"n/a",H47/B47) -> 0 | V47: =E51 -> 571320
A48: BBQ Trim | B48: =VLOOKUP($A48,'LEVEL 2.1'!$A$13:$K$317,11,FALSE) -> 5000 | E48: =VLOOKUP($A48,'LEVEL 3'!$A$13:$K$317,11,FALSE) -> 5000 | H48: =B48-E48 -> 0 | I48: =H48/B48 -> 0 | V48: =V47-V46 -> -349610.34
A49: Shutters | B49: =VLOOKUP($A49,'LEVEL 2.1'!$A$13:$K$317,11,FALSE) -> 0 | E49: =VLOOKUP($A49,'LEVEL 3'!$A$13:$K$317,11,FALSE) -> 0 | H49: =B49-E49 -> 0 | I49: =IF(B49=0,"n/a",H49/B49) -> n/a
A50: Wood, Plastics, & Composites | C50: =SUM(B37:B49) -> 8286913.8 | F50: =SUM(E37:E49) -> 8149008.5 | H50: =C50-F50 -> 137905.28 | I50: =H50/C50 -> 0.016641332 | V50: 2.33
A51: Insulation | B51: =VLOOKUP($A51,'LEVEL 2.1'!$A$13:$K$317,11,FALSE) -> 906427.5 | E51: =VLOOKUP($A51,'LEVEL 3'!$A$13:$K$317,11,FALSE) -> 571320 | H51: =B51-E51 -> 335107.5 | I51: =H51/B51 -> 0.36970138 | K51: Updated per Bids | V51: 2.59
A52: Insulation - PH | B52: =VLOOKUP($A52,'LEVEL 2.1'!$A$13:$K$317,11,FALSE) -> 2000 | E52: =VLOOKUP($A52,'LEVEL 3'!$A$13:$K$317,11,FALSE) -> 750 | H52: =B52-E52 -> 1250 | I52: =IF(B52=0,"n/a",H52/B52) -> 0.625 | K52: Updated per Bids | V52: 2.7
A53: Roofing | B53: =VLOOKUP($A53,'LEVEL 2.1'!$A$13:$K$317,11,FALSE) -> 1277484.3 | E53: =VLOOKUP($A53,'LEVEL 3'!$A$13:$K$317,11,FALSE) -> 1088690 | H53: =B53-E53 -> 188794.28 | I53: =H53/B53 -> 0.14778599 | K53: Updated per Bids
A54: Roofing - PH | B54: =VLOOKUP($A54,'LEVEL 2.1'!$A$13:$K$317,11,FALSE) -> 10000 | E54: =VLOOKUP($A54,'LEVEL 3'!$A$13:$K$317,11,FALSE) -> 8295 | H54: =B54-E54 -> 1705 | I54: =IF(B54=0,"n/a",H54/B54) -> 0.1705 | K54: Updated per Bids
A55: Cabana Roofing | B55: =VLOOKUP($A55,'LEVEL 2.1'!$A$13:$K$317,11,FALSE) -> 0 | E55: =VLOOKUP($A55,'LEVEL 3'!$A$13:$K$317,11,FALSE) -> 15685 | H55: =B55-E55 -> -15685 | I55: =IF(B55=0,"n/a",H55/B55) -> n/a | K55: Updated per Bids
A56: Pump House Roofing | B56: =VLOOKUP($A56,'LEVEL 2.1'!$A$13:$K$317,11,FALSE) -> 7500 | E56: =VLOOKUP($A56,'LEVEL 3'!$A$13:$K$317,11,FALSE) -> 7500 | H56: =B56-E56 -> 0 | I56: =H56/B56 -> 0
A57: Pool Equipment Roofing | B57: =VLOOKUP($A57,'LEVEL 2.1'!$A$13:$K$317,11,FALSE) -> 7500 | E57: =VLOOKUP($A57,'LEVEL 3'!$A$13:$K$317,11,FALSE) -> 7500 | H57: =B57-E57 -> 0 | I57: =IF(B57=0,"n/a",H57/B57) -> 0
A58: Trash Enclosure Cover | B58: =VLOOKUP($A58,'LEVEL 2.1'!$A$13:$K$317,11,FALSE) -> 84000 | E58: =VLOOKUP($A58,'LEVEL 3'!$A$13:$K$317,11,FALSE) -> 250000 | H58: =B58-E58 -> -166000 | I58: =H58/B58 -> -1.9761905 | K58: Updated per Bids
A59: Pigeon Proofing | B59: =VLOOKUP($A59,'LEVEL 2.1'!$A$13:$K$317,11,FALSE) -> 29005.68 | E59: =VLOOKUP($A59,'LEVEL 3'!$A$13:$K$317,11,FALSE) -> 29005.68 | H59: =B59-E59 -> 0 | I59: =H59/B59 -> 0
A60: Gutters and Downspouts | B60: =VLOOKUP($A60,'LEVEL 2.1'!$A$13:$K$317,11,FALSE) -> 18128.55 | E60: =VLOOKUP($A60,'LEVEL 3'!$A$13:$K$317,11,FALSE) -> 18128.55 | H60: =B60-E60 -> 0 | I60: =H60/B60 -> 0
A61: Roof Ladders | B61: =VLOOKUP($A61,'LEVEL 2.1'!$A$13:$K$317,11,FALSE) -> 9300 | E61: =VLOOKUP($A61,'LEVEL 3'!$A$13:$K$317,11,FALSE) -> 9300 | H61: =B61-E61 -> 0 | I61: =H61/B61 -> 0
A62: Roof Access Doors | B62: =VLOOKUP($A62,'LEVEL 2.1'!$A$13:$K$317,11,FALSE) -> 15000 | E62: =VLOOKUP($A62,'LEVEL 3'!$A$13:$K$317,11,FALSE) -> 15000 | H62: =B62-E62 -> 0 | I62: =H62/B62 -> 0
A63: Roof Winch | B63: =VLOOKUP($A63,'LEVEL 2.1'!$A$13:$K$317,11,FALSE) -> 0 | E63: =VLOOKUP($A63,'LEVEL 3'!$A$13:$K$317,11,FALSE) -> 0 | H63: =B63-E63 -> 0 | I63: =IF(B63=0,"n/a",H63/B63) -> n/a
A64: Thermal & Moisture Protection | C64: =SUM(B51:B63) -> 2366346 | F64: =SUM(E51:E63) -> 2021174.2 | H64: =C64-F64 -> 345171.78 | I64: =H64/C64 -> 0.14586699
A65: Entry Doors | B65: =VLOOKUP($A65,'LEVEL 2.1'!$A$13:$K$317,11,FALSE) -> 24000 | E65: =VLOOKUP($A65,'LEVEL 3'!$A$13:$K$317,11,FALSE) -> 24000 | H65: =B65-E65 -> 0 | I65: =IF(B65=0,"n/a",H65/B65) -> 0
A66: Common Doors | B66: =VLOOKUP($A66,'LEVEL 2.1'!$A$13:$K$317,11,FALSE) -> 0 | E66: =VLOOKUP($A66,'LEVEL 3'!$A$13:$K$317,11,FALSE) -> 0 | H66: =B66-E66 -> 0 | I66: =IF(B66=0,"n/a",H66/B66) -> n/a
A67: Pocket Doors - 3 Panel | B67: =VLOOKUP($A67,'LEVEL 2.1'!$A$13:$K$317,11,FALSE) -> 0 | E67: =VLOOKUP($A67,'LEVEL 3'!$A$13:$K$317,11,FALSE) -> 0 | H67: =B67-E67 -> 0 | I67: =IF(B67=0,"n/a",H67/B67) -> n/a
A68: Garage Doors | B68: =VLOOKUP($A68,'LEVEL 2.1'!$A$13:$K$317,11,FALSE) -> 0 | E68: =VLOOKUP($A68,'LEVEL 3'!$A$13:$K$317,11,FALSE) -> 0 | H68: =B68-E68 -> 0 | I68: =IF(B68=0,"n/a",H68/B68) -> n/a
A69: Windows and Sliding Glass Doors | B69: =VLOOKUP($A69,'LEVEL 2.1'!$A$13:$K$317,11,FALSE) -> 526350 | E69: =VLOOKUP($A69,'LEVEL 3'!$A$13:$K$317,11,FALSE) -> 526349.07 | H69: =B69-E69 -> 0.93076923 | I69: =H69/B69 -> 1.7683466e-06
A70: Windows Repair and Replacement | B70: =VLOOKUP($A70,'LEVEL 2.1'!$A$13:$K$317,11,FALSE) -> 27225 | E70: =VLOOKUP($A70,'LEVEL 3'!$A$13:$K$317,11,FALSE) -> 27225 | H70: =B70-E70 -> 0 | I70: =H70/B70 -> 0
A71: Pool Equipment Windows | B71: =VLOOKUP($A71,'LEVEL 2.1'!$A$13:$K$317,11,FALSE) -> 0 | E71: =VLOOKUP($A71,'LEVEL 3'!$A$13:$K$317,11,FALSE) -> 0 | H71: =B71-E71 -> 0 | I71: =IF(B71=0,"n/a",H71/B71) -> n/a
A72: Pool Glass Walls | B72: =VLOOKUP($A72,'LEVEL 2.1'!$A$13:$K$317,11,FALSE) -> 0 | E72: =VLOOKUP($A72,'LEVEL 3'!$A$13:$K$317,11,FALSE) -> 0 | H72: =B72-E72 -> 0 | I72: =IF(B72=0,"n/a",H72/B72) -> n/a
A73: Fixed Glass | B73: =VLOOKUP($A73,'LEVEL 2.1'!$A$13:$K$317,11,FALSE) -> 0 | E73: =VLOOKUP($A73,'LEVEL 3'!$A$13:$K$317,11,FALSE) -> 0 | H73: =B73-E73 -> 0 | I73: =IF(B73=0,"n/a",H73/B73) -> n/a
A74: Mirrors - LED | B74: =VLOOKUP($A74,'LEVEL 2.1'!$A$13:$K$317,11,FALSE) -> 0 | E74: =VLOOKUP($A74,'LEVEL 3'!$A$13:$K$317,11,FALSE) -> 0 | H74: =B74-E74 -> 0 | I74: =IF(B74=0,"n/a",H74/B74) -> n/a
A75: Mirrors - LED Install | B75: =VLOOKUP($A75,'LEVEL 2.1'!$A$13:$K$317,11,FALSE) -> 0 | E75: =VLOOKUP($A75,'LEVEL 3'!$A$13:$K$317,11,FALSE) -> 0 | H75: =B75-E75 -> 0 | I75: =IF(B75=0,"n/a",H75/B75) -> n/a
A76: Mirrors - Framed | B76: =VLOOKUP($A76,'LEVEL 2.1'!$A$13:$K$317,11,FALSE) -> 0 | E76: =VLOOKUP($A76,'LEVEL 3'!$A$13:$K$317,11,FALSE) -> 0 | H76: =B76-E76 -> 0 | I76: =IF(B76=0,"n/a",H76/B76) -> n/a
A77: Mirrors - Polished Edges (Units) | B77: =VLOOKUP($A77,'LEVEL 2.1'!$A$13:$K$317,11,FALSE) -> 63525 | E77: =VLOOKUP($A77,'LEVEL 3'!$A$13:$K$317,11,FALSE) -> 63525 | H77: =B77-E77 -> 0 | I77: =H77/B77 -> 0
A78: Mirrors - Polished Edges (Restrooms) | B78: =VLOOKUP($A78,'LEVEL 2.1'!$A$13:$K$317,11,FALSE) -> 1800 | E78: =VLOOKUP($A78,'LEVEL 3'!$A$13:$K$317,11,FALSE) -> 1800 | H78: =B78-E78 -> 0 | I78: =H78/B78 -> 0
A79: Openings | C79: =SUM(B65:B78) -> 642900 | F79: =SUM(E65:E78) -> 642899.07 | H79: =C79-F79 -> 0.93076923 | I79: =H79/C79 -> 1.4477667e-06
A80: Cost Prep Labor | B80: =VLOOKUP($A80,'LEVEL 2.1'!$A$13:$K$317,11,FALSE) -> 0 | E80: =VLOOKUP($A80,'LEVEL 3'!$A$13:$K$317,11,FALSE) -> 0 | H80: =B80-E80 -> 0 | I80: n/a
A81: Cost Prep Mat - Home Depot | B81: =VLOOKUP($A81,'LEVEL 2.1'!$A$13:$K$317,11,FALSE) -> 10000 | E81: =VLOOKUP($A81,'LEVEL 3'!$A$13:$K$317,11,FALSE) -> 10000 | H81: =B81-E81 -> 0 | I81: =H81/B81 -> 0
A82: Clean Up - Final | B82: =VLOOKUP($A82,'LEVEL 2.1'!$A$13:$K$317,11,FALSE) -> 308185.35 | E82: =VLOOKUP($A82,'LEVEL 3'!$A$13:$K$317,11,FALSE) -> 308185.35 | H82: =B82-E82 -> 0 | I82: =H82/B82 -> 0
A83: Clean Up - During Construction - Labor | B83: =VLOOKUP($A83,'LEVEL 2.1'!$A$13:$K$317,11,FALSE) -> 75000 | E83: =VLOOKUP($A83,'LEVEL 3'!$A$13:$K$317,11,FALSE) -> 75000 | H83: =B83-E83 -> 0 | I83: =H83/B83 -> 0
A84: Dumpsters | B84: =VLOOKUP($A84,'LEVEL 2.1'!$A$13:$K$317,11,FALSE) -> 28677 | E84: =VLOOKUP($A84,'LEVEL 3'!$A$13:$K$317,11,FALSE) -> 28677 | H84: =B84-E84 -> 0 | I84: =H84/B84 -> 0
A85: Clean Up - Hauling Exterior | B85: =VLOOKUP($A85,'LEVEL 2.1'!$A$13:$K$317,11,FALSE) -> 10000 | E85: =VLOOKUP($A85,'LEVEL 3'!$A$13:$K$317,11,FALSE) -> 10000 | H85: =B85-E85 -> 0 | I85: =H85/B85 -> 0
A86: Stucco | B86: =VLOOKUP($A86,'LEVEL 2.1'!$A$13:$K$317,11,FALSE) -> 950639.3 | E86: =VLOOKUP($A86,'LEVEL 3'!$A$13:$K$317,11,FALSE) -> 897250 | H86: =B86-E86 -> 53389.296 | I86: =H86/B86 -> 0.056161466 | K86: Updated per Bids
A87: Stucco - Pump House | B87: =VLOOKUP($A87,'LEVEL 2.1'!$A$13:$K$317,11,FALSE) -> 6000 | E87: =VLOOKUP($A87,'LEVEL 3'!$A$13:$K$317,11,FALSE) -> 6000 | H87: =B87-E87 -> 0 | I87: =H87/B87 -> 0
A88: Stucco - Walls | B88: =VLOOKUP($A88,'LEVEL 2.1'!$A$13:$K$317,11,FALSE) -> 0 | E88: =VLOOKUP($A88,'LEVEL 3'!$A$13:$K$317,11,FALSE) -> 0 | H88: =B88-E88 -> 0 | I88: =IF(B88=0,"n/a",H88/B88) -> n/a
A89: Stucco - Pool Area | B89: =VLOOKUP($A89,'LEVEL 2.1'!$A$13:$K$317,11,FALSE) -> 2000 | E89: =VLOOKUP($A89,'LEVEL 3'!$A$13:$K$317,11,FALSE) -> 2000 | H89: =B89-E89 -> 0 | I89: =H89/B89 -> 0
A90: Stucco - Cabana | B90: =VLOOKUP($A90,'LEVEL 2.1'!$A$13:$K$317,11,FALSE) -> 0 | E90: =VLOOKUP($A90,'LEVEL 3'!$A$13:$K$317,11,FALSE) -> 0 | H90: =B90-E90 -> 0 | I90: =IF(B90=0,"n/a",H90/B90) -> n/a
A91: Stucco - Pool Equipment | B91: =VLOOKUP($A91,'LEVEL 2.1'!$A$13:$K$317,11,FALSE) -> 5000 | E91: =VLOOKUP($A91,'LEVEL 3'!$A$13:$K$317,11,FALSE) -> 5000 | H91: =B91-E91 -> 0 | I91: =IF(B91=0,"n/a",H91/B91) -> 0 | V91: 2875188
A92: Stucco - Repairs | B92: =VLOOKUP($A92,'LEVEL 2.1'!$A$13:$K$317,11,FALSE) -> 1500 | E92: =VLOOKUP($A92,'LEVEL 3'!$A$13:$K$317,11,FALSE) -> 1500 | H92: =B92-E92 -> 0 | I92: =H92/B92 -> 0 | V92: =E93 -> 2629350
A93: Drywall | B93: =VLOOKUP($A93,'LEVEL 2.1'!$A$13:$K$317,11,FALSE) -> 2773668.1 | E93: =VLOOKUP($A93,'LEVEL 3'!$A$13:$K$317,11,FALSE) -> 2629350 | H93: =B93-E93 -> 144318.15 | I93: =H93/B93 -> 0.052031513 | K93: Updated per Bids | V93: =V92-V91 -> -245838.03
A94: Drywall - Repairs | B94: =VLOOKUP($A94,'LEVEL 2.1'!$A$13:$K$317,11,FALSE) -> 30855 | E94: =VLOOKUP($A94,'LEVEL 3'!$A$13:$K$317,11,FALSE) -> 30855 | H94: =B94-E94 -> 0 | I94: =H94/B94 -> 0
A95: Drywall - Pump House | B95: =VLOOKUP($A95,'LEVEL 2.1'!$A$13:$K$317,11,FALSE) -> 1000 | E95: =VLOOKUP($A95,'LEVEL 3'!$A$13:$K$317,11,FALSE) -> 1000 | H95: =B95-E95 -> 0 | I95: =IF(B95=0,"n/a",H95/B95) -> 0
A96: Tile Tubs and Showers | B96: =VLOOKUP($A96,'LEVEL 2.1'!$A$13:$K$317,11,FALSE) -> 0 | E96: =VLOOKUP($A96,'LEVEL 3'!$A$13:$K$317,11,FALSE) -> 0 | H96: =B96-E96 -> 0 | I96: =IF(B96=0,"n/a",H96/B96) -> n/a
A97: Common Tile | B97: =VLOOKUP($A97,'LEVEL 2.1'!$A$13:$K$317,11,FALSE) -> 170141.73 | E97: =VLOOKUP($A97,'LEVEL 3'!$A$13:$K$317,11,FALSE) -> 170141.73 | H97: =B97-E97 -> 0 | I97: =H97/B97 -> 0
A98: Kitchen Backsplash | B98: =VLOOKUP($A98,'LEVEL 2.1'!$A$13:$K$317,11,FALSE) -> 0 | E98: =VLOOKUP($A98,'LEVEL 3'!$A$13:$K$317,11,FALSE) -> 0 | H98: =B98-E98 -> 0 | I98: =IF(B98=0,"n/a",H98/B98) -> n/a
A99: Cabana Tile | B99: =VLOOKUP($A99,'LEVEL 2.1'!$A$13:$K$317,11,FALSE) -> 0 | E99: =VLOOKUP($A99,'LEVEL 3'!$A$13:$K$317,11,FALSE) -> 0 | H99: =B99-E99 -> 0 | I99: =IF(B99=0,"n/a",H99/B99) -> n/a
A100: Flooring - Units | B100: =VLOOKUP($A100,'LEVEL 2.1'!$A$13:$K$317,11,FALSE) -> 513238.19 | E100: =VLOOKUP($A100,'LEVEL 3'!$A$13:$K$317,11,FALSE) -> 513238.19 | H100: =B100-E100 -> 0 | I100: =H100/B100 -> 0
A101: Common Wood | B101: =VLOOKUP($A101,'LEVEL 2.1'!$A$13:$K$317,11,FALSE) -> 0 | E101: =VLOOKUP($A101,'LEVEL 3'!$A$13:$K$317,11,FALSE) -> 0 | H101: =B101-E101 -> 0 | I101: 0
A102: Common Vinyl | B102: =VLOOKUP($A102,'LEVEL 2.1'!$A$13:$K$317,11,FALSE) -> 0 | E102: =VLOOKUP($A102,'LEVEL 3'!$A$13:$K$317,11,FALSE) -> 0 | H102: =B102-E102 -> 0 | I102: 0
...

Sheet LEVEL 2.1
A1: Project Details
A2: Project | B2: Robindale & 215 | J2: Total Cost | K2: =L319 -> 68005169 | M2: Unit Breakdown | Q2: Parking
A3: Budget Level | B3: Level 2 | M3: Unit Type | N3: Number | O3: % | Q3: Cover Parking | S3: 286 | AE3: Railing Estimate | AI3: Building 3 | AJ3: =21*7 -> 147 | AL3: Stucco | AP3: Building 3 | AQ3: =15000+6560+6500+15400+4570+4635+4540+4250 -> 61455
A4: Product | B4: Senior | J4: Cost Per Unit | K4: =K2/N9 -> 187342.06 | M4: Studios | N4: 0 | O4: =N4/$N$9 -> 0 | Q4: Cover Accesible Parking | AE4: Building 1 | AJ4: =14*7 -> 98 | AL4: Building 1
A5: Start Date | M5: 1 Br - 1 Ba | N5: ='Assumptions & Takeoffs'!B4+'Assumptions & Takeoffs'!B5 -> 218 | O5: =N5/$N$9 -> 0.60055096 | Q5: Open Parking | S5: 157 | AE5: Northwest | AF5: =21*4+8*8+7*6 -> 190 | AJ5: =8*22 -> 176 | AL5: Northwest | AM5: 19256
A6: Timeline | B6: 24 | E6: =80 -> 80 | J6: Cost Per SF | K6: =K2/B8 -> 187.56373 | M6: 2 Br - 1 Ba | N6: ='Assumptions & Takeoffs'!B6+'Assumptions & Takeoffs'!B7 -> 145 | O6: =N6/$N$9 -> 0.39944904 | Q6: Accessible Parking | S6: 14 | AE6: Southwest | AF6: =14*4+21*2+8*6 -> 146 | AJ6: =7*10 -> 70 | AL6: Southwest | AM6: 8980
A7: Floors | B7: 2 | E7: =1000/E6 -> 12.5 | M7: 2 Br - 2 Ba | N7: 0 | O7: =N7/$N$9 -> 0 | Q7: Waiver | S7: 0 | AE7: Northeast | AF7: =21*2+14*2+8*6 -> 118 | AJ7: =SUM(AJ3:AJ6) -> 491 | AL7: Northeast | AM7: 8850
A8: Bldg. SF | B8: =98509+136604+127458 -> 362571 | J8: Efficiency | K8: ='Assumptions & Takeoffs'!D8/B8 -> 0.78175861 | M8: 3 Br - 2 Ba | N8: 0 | O8: =N8/$N$9 -> 0 | Q8: Total Parking Provided | S8: =SUM(S3:S7) -> 457 | AE8: Southeast | AF8: =21*2+14*8+8*12+7*8 -> 306 | AL8: Southeast | AM8: 19965
A9: Acres | B9: 17.35 | M9: Totals | N9: =SUM(N4:N8) -> 363 | O9: =N9/$N$9 -> 1 | Q9: Parking Ratio | S9: =S8/N9 -> 1.2589532 | AE9: More | AF9: =21*4+8*6 -> 132 | AG9: =SUM(AF5:AF9) -> 892 | AL9: More | AM9: =5870+6250+6290+5915 -> 24325 | AN9: =SUM(AM5:AM9) -> 81376
A10: Site SF | B10: =B9*43560 -> 755766
A11: Buildings | B11: 3 | AE11: Building 2 & 5 | AI11: Building 4 | AJ11: =14*8 -> 112 | AL11: Building 2 & 5 | AP11: Building 4 | AQ11: =5782+5760+8825+9150 -> 29517
AE12: Northwest | AJ12: =20*8 -> 160 | AL12: Northwest
A13: Description | B13: Cost Code | C13: Cost Category | D13: Sub job | E13: Source | F13: UMO | G13: Quantity | H13: U.P. | I13: Escal % | J13: Total U.P. | K13: Sub Total | L13: Total | M13: Description / Details
A14: General Requirement | B14: 01 | C14: S | F14: Mo | G14: =$B$6 -> 24 | H14: =N324 -> 137183.26 | I14: 0 | J14: =H14*(1+I14) -> 137183.26 | K14: =J14*G14 -> 3292398.3
A15: General Requirements | B15: 01 | L15: =K14 -> 3292398.3
A16: Potholing | B16: 02-3213 | C16: S | D16: ON-SITE | E16: Allowance | G16: 1 | H16: 16000 | I16: 0 | J16: =H16*(1+I16) -> 16000 | K16: =J16*G16 -> 16000
A17: Existing Conditions | B17: 02 | L17: =K16 -> 16000
A18: Slabs | B18: 03-3101 | C18: S | D18: BUILDING | E18: Torrey Pines | F18: SF | G18: ='Assumptions & Takeoffs'!B11 -> 177268 | H18: 11.99 | I18: 0 | J18: =H18*(1+I18) -> 11.99 | K18: =J18*G18 -> 2125443.3 | M18: 4" over 4" slab profile. WH that has a proposal at $9.16 by NRC but all other competitors are over $12/sf.
A19: Deepened Footings | B19: 03-3101 | C19: S | D19: BUILDING | E19: N/A | J19: =H19*(1+I19) -> 0 | K19: =J19*G19 -> 0
A20: Concrete Slab Repairs | B20: 03-3101 | C20: RR | D20: BUILDING | E20: Allowance | F20: LS | G20: 1 | H20: 7500 | I20: 0 | J20: =H20*(1+I20) -> 7500 | K20: =J20*G20 -> 7500
A21: Pump House Concrete | B21: 03-3101 | C21: S | D21: PUMPHOUSE | E21: Allowance | F21: LS | G21: 1 | H21: 8500 | J21: =H21*(1+I21) -> 8500 | K21: =J21*G21 -> 8500
A22: Trash Enclosure Concrete | B22: 03-3102 | C22: S | D22: OTHER SITE | E22: Allowance | F22: EA | G22: ='Assumptions & Takeoffs'!B14 -> 14 | H22: 5000 | I22: 0 | J22: =H22*(1+I22) -> 5000 | K22: =J22*G22 -> 70000
A23: Pool Area Shower Concrete | B23: 03-3105 | C23: S | D23: POOL AREA | E23: Allowance | F23: LS | G23: 1 | H23: 23959 | I23: 0 | J23: =H23*(1+I23) -> 23959 | K23: =J23*G23 -> 23959
A24: Cabana Concrete | B24: 03-3107 | C24: S | D24: POOL AREA | E24: Allowance | F24: LS | G24: 1 | H24: 6500 | I24: 0 | J24: =H24*(1+I24) -> 6500 | K24: =J24*G24 -> 6500
A25: Pool Equipment Foundation | B25: 03-3108 | C25: S | D25: POOL EQUIP | E25: Allowance | F25: LS | G25: 1 | H25: 6500 | I25: 0 | J25: =H25*(1+I25) -> 6500 | K25: =J25*G25 -> 6500
A26: Lightweight Concrete | B26: 03-3116 | C26: S | D26: BUILDING | E26: Bruner | F26: SF | G26: ='Assumptions & Takeoffs'!E14 -> 171978.5 | H26: 2.8 | I26: 0 | J26: =H26*(1+I26) -> 2.8 | K26: =J26*G26 -> 481539.8 | M26: Nevada Gypsum 1" with Mat.
A27: Deck Concrete | B27: 03-5001 | C27: S | D27: BUILDING | E27: Bruner | F27: SF | G27: ='Assumptions & Takeoffs'!$H$16 -> 2236 | H27: 20.525068 | I27: 0 | J27: =H27*(1+I27) -> 20.525068 | K27: =J27*G27 -> 45894.051
A28: Concrete | B28: 03 | L28: =SUM(K18:K27) -> 2775836.2
A29: Elevator Shaft | B29: 04-2201 | C29: S | D29: BUILDING | E29: N/A | F29: Stop | G29: 0 | H29: 11500 | I29: 0 | J29: =H29*(1+I29) -> 11500 | K29: =J29*G29 -> 0 | M29: Wood framed.
A30: Trash Enclosure | B30: 04-2202 | C30: S | D30: OTHER SITE | E30: West H. | F30: Count | G30: 14 | H30: 7000 | I30: 0 | J30: =H30*(1+I30) -> 7000 | K30: =J30*G30 -> 98000
A31: Masonry Veneer | B31: 04-4301 | C31: S | D31: ON-SITE | E31: N/A | H31: 0 | J31: =H31*(1+I31) -> 0 | K31: =J31*G31 -> 0
A32: Masonry Veneer Pool Area | B32: 04-4305 | C32: S | D32: POOL AREA | E32: Allowance | F32: LS | G32: 3 | H32: 5000 | I32: 0 | J32: =H32*(1+I32) -> 5000 | K32: =J32*G32 -> 15000
A33: Pool Eq. Shower | B33: 04-4306 | C33: A | D33: POOL EQUIP | E33: Allowance | F33: LS | G33: 1 | H33: 15000 | I33: 0 | J33: =H33*(1+I33) -> 15000 | K33: =J33*G33 -> 15000
A34: Masonry | B34: 04 | L34: =SUM(K29:K33) -> 128000
A35: Structural Steel | B35: 05-1201 | C35: S | D35: BUILDING | E35: Allowance | F35: LS | G35: 1 | H35: 150000 | I35: 0 | J35: =H35*(1+I35) -> 150000 | K35: =J35*G35 -> 150000 | M35: Place holder. No Plans
A36: Elevator Shaft Iron | B36: 05-1202 | C36: S | D36: BUILDING | E36: Allowance | F36: Count | G36: ='Assumptions & Takeoffs'!$B$12 -> 6 | H36: 4250 | I36: 0 | J36: =H36*(1+I36) -> 4250 | K36: =J36*G36 -> 25500
A37: Stair Handrails | B37: 05-5201 | C37: S | D37: BUILDING | E37: West H. | F37: Flight | G37: ='Assumptions & Takeoffs'!B15 -> 19 | H37: 3000 | I37: 0 | J37: =H37*(1+I37) -> 3000 | K37: =J37*G37 -> 57000
A38: Garage Stair Railings | B38: 05-5201 | C38: S | D38: BUILDING | E38: N/A | H38: 0 | I38: 0 | J38: =H38*(1+I38) -> 0 | K38: =J38*G38 -> 0
A39: Cabana Iron | B39: 05-7004 | C39: S | D39: POOL AREA | E39: N/A | H39: 0 | I39: 0 | J39: =H39*(1+I39) -> 0 | K39: =J39*G39 -> 0
A40: Pool Equipment Gate | B40: 05-7005 | C40: S | D40: POOL EQUIP | E40: Torrey Pines | F40: Count | G40: 1 | H40: 1950 | I40: 0 | J40: =H40*(1+I40) -> 1950 | K40: =J40*G40 -> 1950
A41: Iron Railings | B41: 05-7300 | C41: S | D41: BUILDING | E41: West H. | F41: LF | G41: ='Assumptions & Takeoffs'!$B$18 -> 2595 | H41: 92.5 | I41: 0 | J41: 92.5 | K41: =J41*G41 -> 240037.5
A42: Cable Railings | B42: 05-7316 | C42: S | D42: COMMON AREA | E42: N/A | H42: 0 | I42: 0 | J42: =H42*(1+I42) -> 0 | K42: =J42*G42 -> 0
A43: Metals | B43: 05 | L43: =SUM(K35:K42) -> 474487.5
A44: Framing | B44: 06-1100 | C44: S | D44: BUILDING | E44: Bruner | F44: SF | G44: =B8 -> 362571 | H44: 18.68 | I44: 0 | J44: =H44*(1+I44) -> 18.68 | K44: =J44*G44 -> 6772826.3 | M44: Unchanged
A45: Framing Pump House | B45: 06-1100 | C45: S | D45: PUMPHOUSE | E45: Bruner | F45: SF | G45: 600 | H45: =H44 -> 18.68 | I45: 0 | J45: =H45*(1+I45) -> 18.68 | K45: =J45*G45 -> 11208
A46: Framing - Crane | B46: 06-1100 | C46: S | D46: BUILDING | E46: N/A | I46: 0 | J46: =H46*(1+I46) -> 0 | K46: =J46*G46 -> 0
A47: Cabana Framing | B47: 06-1109 | C47: S | D47: COMMON AREA | E47: N/A | I47: 0 | J47: =H47*(1+I47) -> 0 | K47: =J47*G47 -> 0
A48: BBQ Framing | B48: 06-1110 | C48: S | D48: COMMON AREA | E48: Allowance | F48: LS | G48: 4 | H48: 2500 | I48: 0 | J48: =H48*(1+I48) -> 2500 | K48: =J48*G48 -> 10000
A49: Fireplace Framing | B49: 06-1111 | C49: S | D49: COMMON AREA | E49: N/A | I49: 0 | J49: =H49*(1+I49) -> 0 | K49: =J49*G49 -> 0
A50: Trellis | B50: 06-1114 | C50: S | D50: BUILDING | E50: N/A | I50: 0 | J50: =H50*(1+I50) -> 0 | K50: =J50*G50 -> 0
A51: Pool Equipment Framing | B51: 06-1114 | C51: S | D51: POOL EQUIP | E51: N/A | I51: 0 | J51: =H51*(1+I51) -> 0 | K51: =J51*G51 -> 0
A52: Finish Carpentry - Units | B52: 06-2001 | C52: S | D52: BUILDING | E52: WH | F52: Liavable SF | G52: ='Assumptions & Takeoffs'!B21 -> 269691 | H52: 3.55 | I52: 0.1 | J52: =H52*(1+I52) -> 3.905 | K52: =J52*G52 -> 1053143.4 | M52: Per WH proposal based on liavable SF.
A53: Finish Carpentry - Common | B53: 06-2001 | C53: S | D53: COMMON AREA | E53: Bruner | F53: SF | G53: =B8 -> 362571 | H53: 1.0800045 | I53: 0.1 | J53: =H53*(1+I53) -> 1.1880049 | K53: =J53*G53 -> 430736.14 | M53: Added 10% as we have indication BFS has purchased Rystin and Doors and Millwork companies.
A54: Finish Carpentry - Pump House | B54: 06-2001S | C54: S | D54: PUMPHOUSE | E54: Allowance | F54: LS | G54: 1 | H54: 4000 | I54: 0 | J54: =H54*(1+I54) -> 4000 | K54: =J54*G54 -> 4000
A55: BBQ Trim | B55: 06-2006 | C55: S | D55: COMMON AREA | E55: Allowance | F55: LS | G55: 4 | H55: 1250 | I55: 0 | J55: =H55*(1+I55) -> 1250 | K55: =J55*G55 -> 5000
A56: Shutters | B56: 06-4919 | C56: S | D56: BUILDING | E56: N/A | I56: 0 | J56: =H56*(1+I56) -> 0 | K56: =J56*G56 -> 0
A57: Wood, Plastics, & Composites | B57: 06 | L57: =SUM(K44:K56) -> 8286913.8
A58: Insulation | B58: 07-2101 | C58: S | D58: BUILDING | E58: Bruner Ave | F58: SF | G58: =B8 -> 362571 | H58: 2.5 | I58: 0 | J58: =H58*(1+I58) -> 2.5 | K58: =J58*G58 -> 906427.5 | M58: Red Rock proposal.
A59: Insulation - PH | B59: 07-2101 | C59: S | D59: PUMPHOUSE | E59: Allowance | F59: LS | G59: 1 | H59: 2000 | I59: 0 | J59: =H59*(1+I59) -> 2000 | K59: =J59*G59 -> 2000
A60: Roofing | B60: 07-3001 | C60: S | D60: BUILDING | E60: Bruner | F60: Squares | G60: ='Assumptions & Takeoffs'!$B$19 -> 2143.43 | H60: 596 | I60: 0 | J60: =H60*(1+I60) -> 596 | K60: =J60*G60 -> 1277484.3
A61: Roofing - PH | B61: 07-3001 | C61: S | D61: PUMPHOUSE | E61: Allowance | F61: LS | G61: 1 | H61: 10000 | I61: 0 | J61: =H61*(1+I61) -> 10000 | K61: =J61*G61 -> 10000
A62: Cabana Roofing | B62: 07-3002 | C62: S | D62: COMMON AREA | E62: N/A | I62: 0 | J62: =H62*(1+I62) -> 0 | K62: =J62*G62 -> 0
A63: Pump House Roofing | B63: 07-3002 | C63: S | D63: PUMPHOUSE | E63: Allowance | F63: LS | G63: 1 | H63: 7500 | I63: 0 | J63: =H63*(1+I63) -> 7500 | K63: =J63*G63 -> 7500
A64: Pool Equipment Roofing | B64: 07-3003 | C64: S | D64: POOL EQUIP | E64: Allowance | F64: LS | G64: ='Assumptions & Takeoffs'!B16 -> 1 | H64: 7500 | I64: 0 | J64: =H64*(1+I64) -> 7500 | K64: =J64*G64 -> 7500
A65: Trash Enclosure Cover | B65: 07-6101 | C65: S | D65: OTHER SITE | E65: Bruner | F65: Count | G65: ='Assumptions & Takeoffs'!$B$14 -> 14 | H65: 6000 | I65: 0 | J65: =H65*(1+I65) -> 6000 | K65: =J65*G65 -> 84000
A66: Pigeon Proofing | B66: 07-7001 | C66: S | D66: BUILDING | E66: Allowance | F66: SF | G66: =$B$8 -> 362571 | H66: 0.08 | I66: 0 | J66: =H66*(1+I66) -> 0.08 | K66: =J66*G66 -> 29005.68
A67: Gutters and Downspouts | B67: 07-7124 | C67: S | D67: BUILDING | E67: Allowance | F67: SF | G67: =$B$8 -> 362571 | H67: 0.05 | I67: 0 | J67: =H67*(1+I67) -> 0.05 | K67: =J67*G67 -> 18128.55
A68: Roof Ladders | B68: 07-7210 | C68: S | D68: BUILDING | E68: Allowance | F68: Count | G68: =2*$B$11 -> 6 | H68: 1550 | I68: 0 | J68: =H68*(1+I68) -> 1550 | K68: =J68*G68 -> 9300 | M68: 2 Per building
A69: Roof Access Doors | B69: 07-7233 | C69: S | D69: BUILDING | E69: Allowance | F69: Count | G69: =2*$B$11 -> 6 | H69: 2500 | I69: 0 | J69: =H69*(1+I69) -> 2500 | K69: =J69*G69 -> 15000 | M69: 2 Per building
A70: Roof Winch | B70: 07-7250 | C70: S | D70: BUILDING | E70: N/A | I70: 0 | J70: =H70*(1+I70) -> 0 | K70: =J70*G70 -> 0
A71: Thermal & Moisture Protection | B71: 07 | C71: JASON | L71: =SUM(K58:K70) -> 2366346
A72: Entry Doors | B72: 08-1001 | C72: S | D72: COMMON AREA | E72: Allowance | F72: Count | G72: 3 | H72: 8000 | I72: 0 | J72: =H72*(1+I72) -> 8000 | K72: =J72*G72 -> 24000
A73: Common Doors | B73: 08-1002 | C73: S | D73: COMMON AREA | E73: Included | I73: 0 | J73: =H73*(1+I73) -> 0 | K73: =J73*G73 -> 0
A74: Pocket Doors - 3 Panel | B74: 08-1002 | C74: S | D74: BUILDING | E74: N/A | I74: 0 | J74: =H74*(1+I74) -> 0 | K74: =J74*G74 -> 0
A75: Garage Doors | B75: 08-3619 | C75: S | D75: BUILDING | E75: N/A | I75: 0 | J75: =H75*(1+I75) -> 0 | K75: =J75*G75 -> 0
A76: Windows and Sliding Glass Doors | B76: 08-5301 | C76: S | D76: BUILDING | E76: West H. | F76: Per Unit | G76: =$N$9 -> 363 | H76: =1450 -> 1450 | I76: 0 | J76: =H76*(1+I76) -> 1450 | K76: =J76*G76 -> 526350 | M76: Contempo unit windows Proposal plus $100 per unit for frontage windows.
A77: Windows Repair and Replacement | B77: 08-5301 | C77: RR | D77: BUILDING | E77: Allowance | F77: Per Unit | G77: =$N$9 -> 363 | H77: 75 | I77: 0 | J77: =H77*(1+I77) -> 75 | K77: =J77*G77 -> 27225
A78: Pool Equipment Windows | B78: 08-5303 | C78: S | D78: POOL EQUIP | E78: N/A | I78: 0 | J78: =H78*(1+I78) -> 0 | K78: =J78*G78 -> 0
A79: Pool Glass Walls | B79: 08-8001 | C79: S | D79: POOL AREA | E79: N/A | I79: 0 | J79: =H79*(1+I79) -> 0 | K79: =J79*G79 -> 0
A80: Fixed Glass | B80: 08-8002 | C80: S | D80: BUILDING | E80: N/A | I80: 0 | J80: =H80*(1+I80) -> 0 | K80: =J80*G80 -> 0
A81: Mirrors - LED | B81: 08-8301 | C81: S | D81: BUILDING | E81: N/A | I81: 0 | J81: =H81*(1+I81) -> 0 | K81: =J81*G81 -> 0
A82: Mirrors - LED Install | B82: 08-8302 | C82: S | D82: BUILDING | E82: N/A | I82: 0 | J82: =H82*(1+I82) -> 0 | K82: =J82*G82 -> 0
A83: Mirrors - Framed | B83: 08-8301 | C83: S | D83: BUILDING | E83: N/A | I83: 0 | J83: =H83*(1+I83) -> 0 | K83: =J83*G83 -> 0
A84: Mirrors - Polished Edges (Units) | B84: 08-8301 | C84: S | D84: BUILDING | E84: Bruner | F84: Bathroom | G84: =N9 -> 363 | H84: 175 | I84: 0 | J84: =H84*(1+I84) -> 175 | K84: =J84*G84 -> 63525 | M84: Updated based on Bruner budget
A85: Mirrors - Polished Edges (Restrooms) | B85: 08-8301 | C85: S | D85: BUILDING | E85: Allowance | F85: Count | G85: 6 | H85: 300 | I85: 0 | J85: =H85*(1+I85) -> 300 | K85: =J85*G85 -> 1800
A86: Openings | B86: 08 | C86: JASON | L86: =SUM(K72:K85) -> 642900
A87: Cost Prep Labor | B87: 09-0101 | C87: S | D87: BUILDING | E87: N/A | I87: 0 | J87: =H87*(1+I87) -> 0 | K87: =J87*G87 -> 0
A88: Cost Prep Mat - Home Depot | B88: 09-0102 | C88: S | D88: BUILDING | E88: Allowance | F88: LS | G88: 1 | H88: 10000 | I88: 0 | J88: =H88*(1+I88) -> 10000 | K88: =J88*G88 -> 10000
A89: Clean Up - Final | B89: 09-0103 | C89: S | D89: BUILDING | E89: Bruner | F89: SF | G89: =$B$8 -> 362571 | H89: 0.85 | I89: 0 | J89: =H89*(1+I89) -> 0.85 | K89: =J89*G89 -> 308185.35 | M89: Includes Dumpters
A90: Clean Up - During Construction - Labor | B90: 09-0104 | C90: S | D90: BUILDING | E90: Allowance | F90: LS | G90: 1 | H90: 75000 | I90: 0 | J90: =H90*(1+I90) -> 75000 | K90: =J90*G90 -> 75000
A91: Dumpsters | B91: 09-0113 | C91: S | D91: DUMPSTERS | E91: Allowance | F91: Unit | G91: =$N$9 -> 363 | H91: 79 | I91: 0 | J91: =H91*(1+I91) -> 79 | K91: =J91*G91 -> 28677
A92: Clean Up - Hauling Exterior | B92: 09-0121 | C92: S | D92: ON-SITE | E92: Allowance | F92: LS | G92: 1 | H92: 10000 | I92: 0 | J92: =H92*(1+I92) -> 10000 | K92: =J92*G92 -> 10000 | M92: Included in Construction Cleaning Contract.
A93: Stucco | B93: 09-2423 | C93: S | D93: BUILDING | E93: Bruner Ave | F93: SY | G93: ='Assumptions & Takeoffs'!B20 -> 23863.34 | H93: ='Unit Pricing Comparison'!I22 -> 39.836808 | I93: 0 | J93: =H93*(1+I93) -> 39.836808 | K93: =J93*G93 -> 950639.3 | M93: Pricing from Bruner contract.
A94: Stucco - Pump House | B94: 09-2423S | C94: A | D94: PUMPHOUSE | E94: Allowance | F94: LS | G94: ='Assumptions & Takeoffs'!B24 -> 1 | H94: 6000 | I94: 0 | J94: =H94*(1+I94) -> 6000 | K94: =J94*G94 -> 6000
A95: Stucco - Walls | B95: 09-2424 | C95: S | D95: POOL AREA | E95: N/A | I95: 0 | J95: =H95*(1+I95) -> 0 | K95: =J95*G95 -> 0
A96: Stucco - Pool Area | B96: 09-2428 | C96: A | D96: POOL AREA | E96: Allowance | F96: LS | G96: ='Assumptions & Takeoffs'!$B$16 -> 1 | H96: 2000 | I96: 0 | J96: =H96*(1+I96) -> 2000 | K96: =J96*G96 -> 2000
A97: Stucco - Cabana | B97: 09-2429 | C97: S | D97: POOL AREA | E97: N/A | I97: 0 | J97: =H97*(1+I97) -> 0 | K97: =J97*G97 -> 0
A98: Stucco - Pool Equipment | B98: 09-2430 | C98: S | D98: POOL EQUIP | E98: Pebble | F98: LS | G98: 1 | H98: 5000 | I98: 0 | J98: =H98*(1+I98) -> 5000 | K98: =J98*G98 -> 5000
A99: Stucco - Repairs | B99: 09-2423A | C99: RR | D99: BUILDING | E99: Allowance | F99: LS | G99: 1 | H99: 1500 | I99: 0 | J99: =H99*(1+I99) -> 1500 | K99: =J99*G99 -> 1500
A100: Drywall | B100: 09-2905 | C100: S | D100: BUILDING | E100: West H. | F100: SF | G100: =$B$8 -> 362571 | H100: 7.65 | I100: 0 | J100: =H100*(1+I100) -> 7.65 | K100: =J100*G100 -> 2773668.1 | M100: WH Classic proposal.
...

Sheet Assumptions & Takeoffs
A2: Unit Matrix | F2: Reports Available
A3: Unit Type | B3: Number | C3: % | D3: SF | F3: SER (GCW)
A4: 1A | B4: 170 | C4: =B4/$B$8 -> 0.46831956 | D4: 676 | F4: Soils Report
A5: 1B | B5: 48 | C5: =B5/$B$8 -> 0.1322314 | D5: 764 | F5: Alta Survey
A6: 2A | B6: 127 | C6: =B6/$B$8 -> 0.34986226 | D6: 901 | F6: Plans | K6: 10
A7: 2B | B7: 18 | C7: =B7/$B$8 -> 0.049586777 | D7: 968 | K7: =K6*16 -> 160
A8: Totals | B8: =SUM(B4:B7) -> 363 | C8: =B8/$B$8 -> 1 | D8: =SUMPRODUCT(B4:B7,D4:D7) -> 283443
K9: 600
A10: List of Take offs | D10: List of Take offs | G10: List of Take offs | K10: =1250-K9-K7 -> 490 | N10: Slabs | P10: Patios | R10: Lightweight
A11: Slab SF | B11: 177268 | C11: GSF | D11: Counter tops | E11: =(((16.19+55.2)*(23+34+30+24+30+27))+((17.33+77.17)*(8+10+8+8+10+8))+((20.29+64.88)*(12+24+24+14+25+26))+((18.98+64.6)*(1+1+2+4+5+5)))+((242.17+36.22)+(140.39+10.04)+(140.45+10.04)+(19.89+4.91)) -> 29662.32 | F11: SF | G11: Fitness Center | H11: 0 | I11: SF | N11: Building 1 | O11: =48798.63-P11 -> 48298.63 | P11: =4*125 -> 500 | R11: =45*3 -> 135 | S11: =O11-R11 -> 48163.63
A12: Elevators | B12: 6 | C12: Count | D12: Blinds | E12: 0 | G12: Unit Appliances | N12: Building 2 | O12: =67208.37-P12 -> 66583.37 | P12: =5*125 -> 625 | R12: =65*3 -> 195 | S12: =O12-R12 -> 66388.37
A13: Elevators Stops | B13: =B12*2 -> 12 | C13: Count | D13: Landscaping | E13: 316370.92 | F13: SF | G13: Kitchens | N13: Building 3 | O13: =63276.41-P13 -> 62776.41 | P13: =4*125 -> 500 | R13: =60*3 -> 180 | S13: =O13-R13 -> 62596.41
A14: Trash Encl. | B14: 14 | C14: Site Plan | D14: Lighweight | E14: 171978.5 | G14: Laundries | N14: Pump House | O14: 600 | Q14: Assumption
A15: Stairs | B15: 19 | C15: Count | D15: 1x1 Decks | E15: =64*48 -> 3072 | F15: SF | G15: Patio | H15: 1223.57 | I15: SF | N15: Pool Equipment | O15: 307
A16: Pool | B16: 1 | D16: 2x1 Decks | E16: 0 | F16: SF | G16: Deck | H16: =K29 -> 2236 | I16: SF
A17: Gym | B17: =869.71+1032.19 -> 1901.9 | C17: SF | D17: Lightweight | E17: 0 | F17: SF
A18: Iron Rail | B18: 2595 | C18: LF | D18: Pavers | E18: 0 | F18: SF | G18: Corridors | H18: 35218.83
A19: Roofing | B19: =1899.71+243.72 -> 2143.43 | C19: Square | D19: Pool Deck | E19: 0 | F19: SF | G19: Other Common Areas | H19: 5741.77
A20: Stucco | B20: =E32 -> 23863.34 | C20: Square Yard | D20: Pool Fence | E20: 0 | F20: LF | G20: Laundry | H20: 1103.55 | N20: Stucco | P20: Returns
A21: Livable Area | B21: =67855+103666+98170 -> 269691 | C21: SF | D21: Dog Park Fence | E21: 0 | F21: LF | G21: Great Room (c | H21: 4961.54 | N21: Building 1 | O21: 48784 | P21: 1800
A22: Carports | B22: ='LEVEL 1.2 BUDGET'!S3 -> 286 | C22: Count | D22: Common Bldg. 1 | E22: 0 | F22: SF | G22: Fitness Center | H22: 1956.73 | N22: Building 2 | O22: 64771 | P22: 2200
A23: Stairs Landings | B23: 0 | C23: Landings | D23: Asphalt | E23: 0 | G23: Leasing | H23: 674.75 | N23: Building 3 | O23: 66016 | P23: 2254
A24: Pump House | B24: 1 | C24: EA | D24: Pavers | E24: 0 | O24: =SUM(O21:O23) -> 179571 | P24: =SUM(P21:P23) -> 6254 | Q24: =P24+O24 -> 185825
A25: Lock Boxes | B25: 0 | C25: EA | D25: Pavers Pool | E25: 0 | K25: =86 -> 86 | N25: Squares | O25: =O24/9 -> 19952.333 | P25: =P24/9 -> 694.88889 | Q25: =Q24/9 -> 20647.222
A26: Awning Small | B26: =12+9+9 -> 30 | C26: EA | K26: =4*2 -> 8
A27: Awning Large | B27: =3+3+4 -> 10 | C27: EA | K27: =5*2 -> 10
D28: Stucco | K28: =4*2 -> 8 | N28: 1 | O28: 94262 | P28: 98509 | Q28: =P28-O28 -> 4247
D29: Building A | E29: 6633.44 | F29: SY | K29: =SUM(K26:K28)*K25 -> 2236 | N29: 2 | O29: 113176 | P29: 136604 | Q29: =P29-O29 -> 23428
D30: Building B | E30: 8701.64 | F30: SY | N30: 3 | O30: 121766 | P30: 127458 | Q30: =P30-O30 -> 5692
D31: Building C | E31: 8528.26 | F31: SY | O31: =SUM(O28:O30) -> 329204 | P31: =SUM(P28:P30) -> 362571 | Q31: =P31-O31 -> 33367
D32: Total | E32: =SUM(E29:E31) -> 23863.34
N37: Unit | P37: SF
N38: 1A | O38: 166
N39: 1B | O39: 52
N40: 2A | O40: 127
N41: 2B | O41: 18
O42: =SUM(O38:O41) -> 363

Sheet LEVEL 2
A1: Project Details
A2: Project | B2: Robindale & 215 | J2: Total Cost | K2: =L319 -> 68767994 | M2: Unit Breakdown | Q2: Parking
A3: Budget Level | B3: Level 2 | M3: Unit Type | N3: Number | O3: % | Q3: Cover Parking | S3: 286 | AE3: Railing Estimate | AI3: Building 3 | AJ3: =21*7 -> 147 | AL3: Stucco | AP3: Building 3 | AQ3: =15000+6560+6500+15400+4570+4635+4540+4250 -> 61455
A4: Product | B4: Senior | J4: Cost Per Unit | K4: =K2/N9 -> 189443.51 | M4: Studios | N4: 0 | O4: =N4/$N$9 -> 0 | Q4: Cover Accesible Parking | AE4: Building 1 | AJ4: =14*7 -> 98 | AL4: Building 1
A5: Start Date | M5: 1 Br - 1 Ba | N5: ='Assumptions & Takeoffs'!B4+'Assumptions & Takeoffs'!B5 -> 218 | O5: =N5/$N$9 -> 0.60055096 | Q5: Open Parking | S5: 157 | AE5: Northwest | AF5: =21*4+8*8+7*6 -> 190 | AJ5: =8*22 -> 176 | AL5: Northwest | AM5: 19256
A6: Timeline | B6: 24 | J6: Cost Per SF | K6: =K2/B8 -> 189.66766 | M6: 2 Br - 1 Ba | N6: ='Assumptions & Takeoffs'!B6+'Assumptions & Takeoffs'!B7 -> 145 | O6: =N6/$N$9 -> 0.39944904 | Q6: Accessible Parking | S6: 14 | AE6: Southwest | AF6: =14*4+21*2+8*6 -> 146 | AJ6: =7*10 -> 70 | AL6: Southwest | AM6: 8980
A7: Floors | B7: 2 | M7: 2 Br - 2 Ba | N7: 0 | O7: =N7/$N$9 -> 0 | Q7: Waiver | S7: 0 | AE7: Northeast | AF7: =21*2+14*2+8*6 -> 118 | AJ7: =SUM(AJ3:AJ6) -> 491 | AL7: Northeast | AM7: 8850
A8: Bldg. SF | B8: =98509+136604+127458 -> 362571 | J8: Efficiency | K8: ='Assumptions & Takeoffs'!D8/B8 -> 0.78175861 | M8: 3 Br - 2 Ba | N8: 0 | O8: =N8/$N$9 -> 0 | Q8: Total Parking Provided | S8: =SUM(S3:S7) -> 457 | AE8: Southeast | AF8: =21*2+14*8+8*12+7*8 -> 306 | AL8: Southeast | AM8: 19965
A9: Acres | B9: 17.35 | M9: Totals | N9: =SUM(N4:N8) -> 363 | O9: =N9/$N$9 -> 1 | Q9: Parking Ratio | S9: =S8/N9 -> 1.2589532 | AE9: More | AF9: =21*4+8*6 -> 132 | AG9: =SUM(AF5:AF9) -> 892 | AL9: More | AM9: =5870+6250+6290+5915 -> 24325 | AN9: =SUM(AM5:AM9) -> 81376
A10: Site SF | B10: =B9*43560 -> 755766
A11: Buildings | B11: 3 | AE11: Building 2 & 5 | AI11: Building 4 | AJ11: =14*8 -> 112 | AL11: Building 2 & 5 | AP11: Building 4 | AQ11: =5782+5760+8825+9150 -> 29517
AE12: Northwest | AJ12: =20*8 -> 160 | AL12: Northwest
A13: Description | B13: Cost Code | C13: Cost Category | D13: Sub job | E13: Source | F13: UMO | G13: Quantity | H13: U.P. | I13: Escal % | J13: Total U.P. | K13: Sub Total | L13: Total | M13: Description / Details
A14: General Requirement | B14: 01 | C14: S | F14: Mo | G14: =$B$6 -> 24 | H14: =N324 -> 138831.55 | I14: 0 | J14: =H14*(1+I14) -> 138831.55 | K14: =J14*G14 -> 3331957.1
A15: General Requirements | B15: 01 | L15: =K14 -> 3331957.1
A16: Potholing | B16: 02-3213 | C16: S | D16: ON-SITE | E16: Allowance | G16: 1 | H16: 16000 | I16: 0 | J16: =H16*(1+I16) -> 16000 | K16: =J16*G16 -> 16000
A17: Existing Conditions | B17: 02 | L17: =K16 -> 16000
A18: Slabs | B18: 03-3101 | C18: S | D18: BUILDING | E18: Torrey Pines | F18: SF | G18: ='Assumptions & Takeoffs'!B11 -> 177268 | H18: 11.99 | I18: 0 | J18: =H18*(1+I18) -> 11.99 | K18: =J18*G18 -> 2125443.3 | M18: 4" over 4" slab profile. WH that has a proposal at $9.16 by NRC but all other competitors are over $12/sf.
A19: Deepened Footings | B19: 03-3101 | C19: S | D19: BUILDING | E19: N/A | J19: =H19*(1+I19) -> 0 | K19: =J19*G19 -> 0
A20: Concrete Slab Repairs | B20: 03-3101 | C20: RR | D20: BUILDING | E20: Allowance | F20: LS | G20: 1 | H20: 7500 | I20: 0 | J20: =H20*(1+I20) -> 7500 | K20: =J20*G20 -> 7500
A21: Pump House Concrete | B21: 03-3101 | C21: S | D21: PUMPHOUSE | E21: Allowance | F21: LS | G21: 1 | H21: 8500 | J21: =H21*(1+I21) -> 8500 | K21: =J21*G21 -> 8500
A22: Trash Enclosure Concrete | B22: 03-3102 | C22: S | D22: OTHER SITE | E22: Allowance | F22: EA | G22: ='Assumptions & Takeoffs'!B14 -> 14 | H22: 5000 | I22: 0 | J22: =H22*(1+I22) -> 5000 | K22: =J22*G22 -> 70000
A23: Pool Area Shower Concrete | B23: 03-3105 | C23: S | D23: POOL AREA | E23: Allowance | F23: LS | G23: 1 | H23: 23959 | I23: 0 | J23: =H23*(1+I23) -> 23959 | K23: =J23*G23 -> 23959
A24: Cabana Concrete | B24: 03-3107 | C24: S | D24: POOL AREA | E24: Allowance | F24: LS | G24: 1 | H24: 6500 | I24: 0 | J24: =H24*(1+I24) -> 6500 | K24: =J24*G24 -> 6500
A25: Pool Equipment Foundation | B25: 03-3108 | C25: S | D25: POOL EQUIP | E25: Allowance | F25: LS | G25: 1 | H25: 6500 | I25: 0 | J25: =H25*(1+I25) -> 6500 | K25: =J25*G25 -> 6500
A26: Lightweight Concrete | B26: 03-3116 | C26: S | D26: BUILDING | E26: Bruner | F26: SF | G26: ='Assumptions & Takeoffs'!E14 -> 171978.5 | H26: 2.8 | I26: 0 | J26: =H26*(1+I26) -> 2.8 | K26: =J26*G26 -> 481539.8 | M26: Nevada Gypsum 1" with Mat.
A27: Deck Concrete | B27: 03-5001 | C27: S | D27: BUILDING | E27: Bruner | F27: SF | G27: ='Assumptions & Takeoffs'!$H$16 -> 2236 | H27: 20.525068 | I27: 0 | J27: =H27*(1+I27) -> 20.525068 | K27: =J27*G27 -> 45894.051
A28: Concrete | B28: 03 | L28: =SUM(K18:K27) -> 2775836.2
A29: Elevator Shaft | B29: 04-2201 | C29: S | D29: BUILDING | E29: N/A | F29: Stop | G29: 0 | H29: 11500 | I29: 0 | J29: =H29*(1+I29) -> 11500 | K29: =J29*G29 -> 0 | M29: Wood framed.
A30: Trash Enclosure | B30: 04-2202 | C30: S | D30: OTHER SITE | E30: West H. | F30: Count | G30: 14 | H30: 7000 | I30: 0 | J30: =H30*(1+I30) -> 7000 | K30: =J30*G30 -> 98000
A31: Masonry Veneer | B31: 04-4301 | C31: S | D31: ON-SITE | E31: N/A | H31: 0 | J31: =H31*(1+I31) -> 0 | K31: =J31*G31 -> 0
A32: Masonry Veneer Pool Area | B32: 04-4305 | C32: S | D32: POOL AREA | E32: Allowance | F32: LS | G32: 3 | H32: 5000 | I32: 0 | J32: =H32*(1+I32) -> 5000 | K32: =J32*G32 -> 15000
A33: Pool Eq. Shower | B33: 04-4306 | C33: A | D33: POOL EQUIP | E33: Allowance | F33: LS | G33: 1 | H33: 15000 | I33: 0 | J33: =H33*(1+I33) -> 15000 | K33: =J33*G33 -> 15000
A34: Masonry | B34: 04 | L34: =SUM(K29:K33) -> 128000
A35: Structural Steel | B35: 05-1201 | C35: S | D35: BUILDING | E35: Allowance | F35: LS | G35: 1 | H35: 150000 | I35: 0 | J35: =H35*(1+I35) -> 150000 | K35: =J35*G35 -> 150000 | M35: Place holder. No Plans
A36: Elevator Shaft Iron | B36: 05-1202 | C36: S | D36: BUILDING | E36: Allowance | F36: Count | G36: ='Assumptions & Takeoffs'!$B$12 -> 6 | H36: 4250 | I36: 0 | J36: =H36*(1+I36) -> 4250 | K36: =J36*G36 -> 25500
A37: Stair Handrails | B37: 05-5201 | C37: S | D37: BUILDING | E37: West H. | F37: Flight | G37: ='Assumptions & Takeoffs'!B15 -> 19 | H37: 3000 | I37: 0 | J37: =H37*(1+I37) -> 3000 | K37: =J37*G37 -> 57000
A38: Garage Stair Railings | B38: 05-5201 | C38: S | D38: BUILDING | E38: N/A | H38: 0 | I38: 0 | J38: =H38*(1+I38) -> 0 | K38: =J38*G38 -> 0
A39: Cabana Iron | B39: 05-7004 | C39: S | D39: POOL AREA | E39: N/A | H39: 0 | I39: 0 | J39: =H39*(1+I39) -> 0 | K39: =J39*G39 -> 0
A40: Pool Equipment Gate | B40: 05-7005 | C40: S | D40: POOL EQUIP | E40: Torrey Pines | F40: Count | G40: 1 | H40: 1950 | I40: 0 | J40: =H40*(1+I40) -> 1950 | K40: =J40*G40 -> 1950
A41: Iron Railings | B41: 05-7300 | C41: S | D41: BUILDING | E41: West H. | F41: LF | G41: ='Assumptions & Takeoffs'!$B$18 -> 2595 | H41: 92.5 | I41: 0 | J41: 92.5 | K41: =J41*G41 -> 240037.5
A42: Cable Railings | B42: 05-7316 | C42: S | D42: COMMON AREA | E42: N/A | H42: 0 | I42: 0 | J42: =H42*(1+I42) -> 0 | K42: =J42*G42 -> 0
A43: Metals | B43: 05 | L43: =SUM(K35:K42) -> 474487.5
A44: Framing | B44: 06-1100 | C44: S | D44: BUILDING | E44: Bruner | F44: SF | G44: =B8 -> 362571 | H44: 18.68 | I44: 0 | J44: =H44*(1+I44) -> 18.68 | K44: =J44*G44 -> 6772826.3 | M44: Unchanged
A45: Framing Pump House | B45: 06-1100 | C45: S | D45: PUMPHOUSE | E45: Bruner | F45: SF | G45: 600 | H45: =H44 -> 18.68 | I45: 0 | J45: =H45*(1+I45) -> 18.68 | K45: =J45*G45 -> 11208
A46: Framing - Crane | B46: 06-1100 | C46: S | D46: BUILDING | E46: N/A | I46: 0 | J46: =H46*(1+I46) -> 0 | K46: =J46*G46 -> 0
A47: Cabana Framing | B47: 06-1109 | C47: S | D47: COMMON AREA | E47: N/A | I47: 0 | J47: =H47*(1+I47) -> 0 | K47: =J47*G47 -> 0
A48: BBQ Framing | B48: 06-1110 | C48: S | D48: COMMON AREA | E48: Allowance | F48: LS | G48: 4 | H48: 2500 | I48: 0 | J48: =H48*(1+I48) -> 2500 | K48: =J48*G48 -> 10000
A49: Fireplace Framing | B49: 06-1111 | C49: S | D49: COMMON AREA | E49: N/A | I49: 0 | J49: =H49*(1+I49) -> 0 | K49: =J49*G49 -> 0
A50: Trellis | B50: 06-1114 | C50: S | D50: BUILDING | E50: N/A | I50: 0 | J50: =H50*(1+I50) -> 0 | K50: =J50*G50 -> 0
A51: Pool Equipment Framing | B51: 06-1114 | C51: S | D51: POOL EQUIP | E51: N/A | I51: 0 | J51: =H51*(1+I51) -> 0 | K51: =J51*G51 -> 0
A52: Finish Carpentry - Units | B52: 06-2001 | C52: S | D52: BUILDING | E52: Torrey Pines | F52: Unit | G52: =$N$9 -> 363 | H52: 3210.0359 | I52: 0.1 | J52: =H52*(1+I52) -> 3531.0395 | K52: =J52*G52 -> 1281767.4 | M52: Added 10% as we have indication BFS has purchased Rystin and Doors and Millwork companies.
A53: Finish Carpentry - Common | B53: 06-2001 | C53: S | D53: COMMON AREA | E53: Bruner | F53: SF | G53: =B8 -> 362571 | H53: 1.0800045 | I53: 0.1 | J53: =H53*(1+I53) -> 1.1880049 | K53: =J53*G53 -> 430736.14 | M53: Added 10% as we have indication BFS has purchased Rystin and Doors and Millwork companies.
A54: Finish Carpentry - Pump House | B54: 06-2001S | C54: S | D54: PUMPHOUSE | E54: Allowance | F54: LS | G54: 1 | H54: 4000 | I54: 0 | J54: =H54*(1+I54) -> 4000 | K54: =J54*G54 -> 4000
A55: BBQ Trim | B55: 06-2006 | C55: S | D55: COMMON AREA | E55: Allowance | F55: LS | G55: 4 | H55: 1250 | I55: 0 | J55: =H55*(1+I55) -> 1250 | K55: =J55*G55 -> 5000
A56: Shutters | B56: 06-4919 | C56: S | D56: BUILDING | E56: N/A | I56: 0 | J56: =H56*(1+I56) -> 0 | K56: =J56*G56 -> 0
A57: Wood, Plastics, & Composites | B57: 06 | L57: =SUM(K44:K56) -> 8515537.8
A58: Insulation | B58: 07-2101 | C58: S | D58: BUILDING | E58: Bruner Ave | F58: SF | G58: =B8 -> 362571 | H58: 2.5 | I58: 0 | J58: =H58*(1+I58) -> 2.5 | K58: =J58*G58 -> 906427.5 | M58: Red Rock proposal.
A59: Insulation - PH | B59: 07-2101 | C59: S | D59: PUMPHOUSE | E59: Allowance | F59: LS | G59: 1 | H59: 2000 | I59: 0 | J59: =H59*(1+I59) -> 2000 | K59: =J59*G59 -> 2000
A60: Roofing | B60: 07-3001 | C60: S | D60: BUILDING | E60: Bruner | F60: Squares | G60: ='Assumptions & Takeoffs'!$B$19 -> 2143.43 | H60: 596 | I60: 0 | J60: =H60*(1+I60) -> 596 | K60: =J60*G60 -> 1277484.3
A61: Roofing - PH | B61: 07-3001 | C61: S | D61: PUMPHOUSE | E61: Allowance | F61: LS | G61: 1 | H61: 10000 | I61: 0 | J61: =H61*(1+I61) -> 10000 | K61: =J61*G61 -> 10000
A62: Cabana Roofing | B62: 07-3002 | C62: S | D62: COMMON AREA | E62: N/A | I62: 0 | J62: =H62*(1+I62) -> 0 | K62: =J62*G62 -> 0
A63: Pump House Roofing | B63: 07-3002 | C63: S | D63: PUMPHOUSE | E63: Allowance | F63: LS | G63: 1 | H63: 7500 | I63: 0 | J63: =H63*(1+I63) -> 7500 | K63: =J63*G63 -> 7500
A64: Pool Equipment Roofing | B64: 07-3003 | C64: S | D64: POOL EQUIP | E64: Allowance | F64: LS | G64: ='Assumptions & Takeoffs'!B16 -> 1 | H64: 7500 | I64: 0 | J64: =H64*(1+I64) -> 7500 | K64: =J64*G64 -> 7500
A65: Trash Enclosure Cover | B65: 07-6101 | C65: S | D65: OTHER SITE | E65: Bruner | F65: Count | G65: ='Assumptions & Takeoffs'!$B$14 -> 14 | H65: 6000 | I65: 0 | J65: =H65*(1+I65) -> 6000 | K65: =J65*G65 -> 84000
A66: Pigeon Proofing | B66: 07-7001 | C66: S | D66: BUILDING | E66: Allowance | F66: SF | G66: =$B$8 -> 362571 | H66: 0.08 | I66: 0 | J66: =H66*(1+I66) -> 0.08 | K66: =J66*G66 -> 29005.68
A67: Gutters and Downspouts | B67: 07-7124 | C67: S | D67: BUILDING | E67: Allowance | F67: SF | G67: =$B$8 -> 362571 | H67: 0.05 | I67: 0 | J67: =H67*(1+I67) -> 0.05 | K67: =J67*G67 -> 18128.55
A68: Roof Ladders | B68: 07-7210 | C68: S | D68: BUILDING | E68: Allowance | F68: Count | G68: =2*$B$11 -> 6 | H68: 1550 | I68: 0 | J68: =H68*(1+I68) -> 1550 | K68: =J68*G68 -> 9300 | M68: 2 Per building
A69: Roof Access Doors | B69: 07-7233 | C69: S | D69: BUILDING | E69: Allowance | F69: Count | G69: =2*$B$11 -> 6 | H69: 2500 | I69: 0 | J69: =H69*(1+I69) -> 2500 | K69: =J69*G69 -> 15000 | M69: 2 Per building
A70: Roof Winch | B70: 07-7250 | C70: S | D70: BUILDING | E70: N/A | I70: 0 | J70: =H70*(1+I70) -> 0 | K70: =J70*G70 -> 0
A71: Thermal & Moisture Protection | B71: 07 | C71: JASON | L71: =SUM(K58:K70) -> 2366346
A72: Entry Doors | B72: 08-1001 | C72: S | D72: COMMON AREA | E72: Allowance | F72: Count | G72: 3 | H72: 8000 | I72: 0 | J72: =H72*(1+I72) -> 8000 | K72: =J72*G72 -> 24000
A73: Common Doors | B73: 08-1002 | C73: S | D73: COMMON AREA | E73: Included | I73: 0 | J73: =H73*(1+I73) -> 0 | K73: =J73*G73 -> 0
A74: Pocket Doors - 3 Panel | B74: 08-1002 | C74: S | D74: BUILDING | E74: N/A | I74: 0 | J74: =H74*(1+I74) -> 0 | K74: =J74*G74 -> 0
A75: Garage Doors | B75: 08-3619 | C75: S | D75: BUILDING | E75: N/A | I75: 0 | J75: =H75*(1+I75) -> 0 | K75: =J75*G75 -> 0
A76: Windows and Sliding Glass Doors | B76: 08-5301 | C76: S | D76: BUILDING | E76: West H. | F76: Per Unit | G76: =$N$9 -> 363 | H76: =1450+100 -> 1550 | I76: 0 | J76: =H76*(1+I76) -> 1550 | K76: =J76*G76 -> 562650 | M76: Contempo unit windows Proposal plus $100 per unit for frontage windows.
A77: Windows Repair and Replacement | B77: 08-5301 | C77: RR | D77: BUILDING | E77: Allowance | F77: Per Unit | G77: =$N$9 -> 363 | H77: 75 | I77: 0 | J77: =H77*(1+I77) -> 75 | K77: =J77*G77 -> 27225
A78: Pool Equipment Windows | B78: 08-5303 | C78: S | D78: POOL EQUIP | E78: N/A | I78: 0 | J78: =H78*(1+I78) -> 0 | K78: =J78*G78 -> 0
A79: Pool Glass Walls | B79: 08-8001 | C79: S | D79: POOL AREA | E79: N/A | I79: 0 | J79: =H79*(1+I79) -> 0 | K79: =J79*G79 -> 0
A80: Fixed Glass | B80: 08-8002 | C80: S | D80: BUILDING | E80: N/A | I80: 0 | J80: =H80*(1+I80) -> 0 | K80: =J80*G80 -> 0
A81: Mirrors - LED | B81: 08-8301 | C81: S | D81: BUILDING | E81: N/A | I81: 0 | J81: =H81*(1+I81) -> 0 | K81: =J81*G81 -> 0
A82: Mirrors - LED Install | B82: 08-8302 | C82: S | D82: BUILDING | E82: N/A | I82: 0 | J82: =H82*(1+I82) -> 0 | K82: =J82*G82 -> 0
A83: Mirrors - Framed | B83: 08-8301 | C83: S | D83: BUILDING | E83: N/A | I83: 0 | J83: =H83*(1+I83) -> 0 | K83: =J83*G83 -> 0
A84: Mirrors - Polished Edges (Units) | B84: 08-8301 | C84: S | D84: BUILDING | E84: Bruner | F84: Bathroom | G84: =N9 -> 363 | H84: 175 | I84: 0 | J84: =H84*(1+I84) -> 175 | K84: =J84*G84 -> 63525 | M84: Updated based on Bruner budget
A85: Mirrors - Polished Edges (Restrooms) | B85: 08-8301 | C85: S | D85: BUILDING | E85: Allowance | F85: Count | G85: 6 | H85: 300 | I85: 0 | J85: =H85*(1+I85) -> 300 | K85: =J85*G85 -> 1800
A86: Openings | B86: 08 | C86: JASON | L86: =SUM(K72:K85) -> 679200
A87: Cost Prep Labor | B87: 09-0101 | C87: S | D87: BUILDING | E87: N/A | I87: 0 | J87: =H87*(1+I87) -> 0 | K87: =J87*G87 -> 0
A88: Cost Prep Mat - Home Depot | B88: 09-0102 | C88: S | D88: BUILDING | E88: Allowance | F88: LS | G88: 1 | H88: 10000 | I88: 0 | J88: =H88*(1+I88) -> 10000 | K88: =J88*G88 -> 10000
A89: Clean Up - Final | B89: 09-0103 | C89: S | D89: BUILDING | E89: Bruner | F89: SF | G89: =$B$8 -> 362571 | H89: 0.85 | I89: 0 | J89: =H89*(1+I89) -> 0.85 | K89: =J89*G89 -> 308185.35 | M89: Includes Dumpters
A90: Clean Up - During Construction - Labor | B90: 09-0104 | C90: S | D90: BUILDING | E90: Allowance | F90: LS | G90: 1 | H90: 75000 | I90: 0 | J90: =H90*(1+I90) -> 75000 | K90: =J90*G90 -> 75000
A91: Dumpsters | B91: 09-0113 | C91: S | D91: DUMPSTERS | E91: Allowance | F91: Unit | G91: =$N$9 -> 363 | H91: 79 | I91: 0 | J91: =H91*(1+I91) -> 79 | K91: =J91*G91 -> 28677
A92: Clean Up - Hauling Exterior | B92: 09-0121 | C92: S | D92: ON-SITE | E92: Allowance | F92: LS | G92: 1 | H92: 10000 | I92: 0 | J92: =H92*(1+I92) -> 10000 | K92: =J92*G92 -> 10000 | M92: Included in Construction Cleaning Contract.
A93: Stucco | B93: 09-2423 | C93: S | D93: BUILDING | E93: Bruner Ave | F93: SY | G93: ='Assumptions & Takeoffs'!B20 -> 23863.34 | H93: ='Unit Pricing Comparison'!I22 -> 39.836808 | I93: 0 | J93: =H93*(1+I93) -> 39.836808 | K93: =J93*G93 -> 950639.3 | M93: Pricing from Bruner contract.
A94: Stucco - Pump House | B94: 09-2423S | C94: A | D94: PUMPHOUSE | E94: Allowance | F94: LS | G94: ='Assumptions & Takeoffs'!B24 -> 1 | H94: 6000 | I94: 0 | J94: =H94*(1+I94) -> 6000 | K94: =J94*G94 -> 6000
A95: Stucco - Walls | B95: 09-2424 | C95: S | D95: POOL AREA | E95: N/A | I95: 0 | J95: =H95*(1+I95) -> 0 | K95: =J95*G95 -> 0
A96: Stucco - Pool Area | B96: 09-2428 | C96: A | D96: POOL AREA | E96: Allowance | F96: LS | G96: ='Assumptions & Takeoffs'!$B$16 -> 1 | H96: 2000 | I96: 0 | J96: =H96*(1+I96) -> 2000 | K96: =J96*G96 -> 2000
A97: Stucco - Cabana | B97: 09-2429 | C97: S | D97: POOL AREA | E97: N/A | I97: 0 | J97: =H97*(1+I97) -> 0 | K97: =J97*G97 -> 0
A98: Stucco - Pool Equipment | B98: 09-2430 | C98: S | D98: POOL EQUIP | E98: Pebble | F98: LS | G98: 1 | H98: 5000 | I98: 0 | J98: =H98*(1+I98) -> 5000 | K98: =J98*G98 -> 5000
A99: Stucco - Repairs | B99: 09-2423A | C99: RR | D99: BUILDING | E99: Allowance | F99: LS | G99: 1 | H99: 1500 | I99: 0 | J99: =H99*(1+I99) -> 1500 | K99: =J99*G99 -> 1500
A100: Drywall | B100: 09-2905 | C100: S | D100: BUILDING | E100: West H. | F100: SF | G100: =$B$8 -> 362571 | H100: 7.65 | I100: 0 | J100: =H100*(1+I100) -> 7.65 | K100: =J100*G100 -> 2773668.1 | M100: WH Classic proposal.
...

Sheet Comparison
B1: Level 1.2 | E1: Level 2 | H1: Variance
A3: Units | C3: ='LEVEL 1.1 BUDGET'!I7 -> 363 | F3: ='LEVEL 1.2 BUDGET'!N9 -> 363 | I3: =C3-F3 -> 0
A4: Building Gross Square Feet | C4: ='Combined - vErik'!B8 -> 329194 | F4: ='LEVEL 1.2 BUDGET'!B8 -> 362571 | I4: =F4-C4 -> 33377
A6: Total Cost | C6: =C312 -> 68871988 | F6: =F312 -> 68767994 | I6: =C6-F6 -> 103993.77 | W6: Studios | X6: 0 | Y6: =X6/$X$10 -> 0 | AC6: Southeast | AD6: =21*2+14*8+8*12+7*8 -> 306 | AJ6: Southeast | AK6: 19965
A7: Cost Per Unit | C7: =C6/X10 -> 189729.99 | F7: =F6/X10 -> 189443.51 | I7: =C7-F7 -> 286.48422 | W7: 1 Br - 1 Ba | X7: ='Assumptions & Takeoffs'!B4+'Assumptions & Takeoffs'!B5 -> 218 | Y7: =X7/$X$10 -> 0.60055096 | AC7: More | AD7: =21*4+8*6 -> 132 | AE7: =SUM(AD6:AD7) -> 438 | AJ7: More | AK7: =5870+6250+6290+5915 -> 24325 | AL7: =SUM(AK6:AK7) -> 44290
A8: Cost Per SF | C8: =C6/'LEVEL 1.2 BUDGET'!$B$8 -> 189.95449 | F8: =F6/X23 -> 189.66766 | I8: =C8-F8 -> 0.2868232 | W8: 2 Br - 1 Ba | X8: ='Assumptions & Takeoffs'!B6+'Assumptions & Takeoffs'!B7 -> 145 | Y8: =X8/$X$10 -> 0.39944904
W9: 2 Br - 2 Ba | X9: 0 | Y9: =X9/$X$10 -> 0 | AC9: Building 2 & 5 | AG9: Building 4 | AH9: =14*8 -> 112 | AJ9: Building 2 & 5 | AN9: Building 4 | AO9: =5782+5760+8825+9150 -> 29517
A10: Description | B10: Sub Total | C10: Total | E10: Sub Total | F10: Total | H10: Variance | I10: % Change | K10: Description / Details | W10: Totals | X10: =SUM(X6:X9) -> 363 | Y10: =X10/$X$10 -> 1
A11: General Requirement | B11: =VLOOKUP($A11,'LEVEL 1.2 BUDGET'!$A$13:$K$316,11,FALSE) -> 3338816 | E11: =VLOOKUP($A11,'LEVEL 2'!$A$13:$K$317,11,FALSE) -> 3331957.1 | H11: =B11-E11 -> 6858.9165 | I11: =H11/B11 -> 0.002054296
A12: General Requirements | C12: 3338816 | F12: =E11 -> 3331957.1 | H12: =C12-F12 -> 6858.9165 | I12: =H12/C12 -> 0.002054296
A13: Potholing | B13: =VLOOKUP(A13,'LEVEL 1.2 BUDGET'!$A$13:$K$316,11,FALSE) -> 16000 | E13: =VLOOKUP($A13,'LEVEL 2'!$A$13:$K$317,11,FALSE) -> 16000 | H13: =B13-E13 -> 0 | I13: =H13/B13 -> 0
A14: Existing Conditions | C14: 16000 | F14: =E13 -> 16000 | H14: =C14-F14 -> 0 | I14: =H14/C14 -> 0
A15: Slabs | B15: =VLOOKUP(A15,'LEVEL 1.2 BUDGET'!$A$13:$K$316,11,FALSE) -> 2130124.3 | E15: =VLOOKUP($A15,'LEVEL 2'!$A$13:$K$317,11,FALSE) -> 2125443.3 | H15: =B15-E15 -> 4681.0159 | I15: =H15/B15 -> 0.0021975318
A16: Concrete Slab Repairs | B16: =VLOOKUP(A16,'LEVEL 1.2 BUDGET'!$A$13:$K$316,11,FALSE) -> 7500 | E16: =VLOOKUP($A16,'LEVEL 2'!$A$13:$K$317,11,FALSE) -> 7500 | H16: =B16-E16 -> 0 | I16: =H16/B16 -> 0 | W16: Project Details
A17: Pump House Concrete | B17: =VLOOKUP(A17,'LEVEL 1.2 BUDGET'!$A$13:$K$316,11,FALSE) -> 8500 | E17: =VLOOKUP($A17,'LEVEL 2'!$A$13:$K$317,11,FALSE) -> 8500 | H17: =B17-E17 -> 0 | I17: =H17/B17 -> 0 | W17: Project | X17: Robindale &215
A18: Trash Enclosure Concrete | B18: =VLOOKUP(A18,'LEVEL 1.2 BUDGET'!$A$13:$K$316,11,FALSE) -> 70000 | E18: =VLOOKUP($A18,'LEVEL 2'!$A$13:$K$317,11,FALSE) -> 70000 | H18: =B18-E18 -> 0 | I18: =H18/B18 -> 0 | W18: Budget Level | X18: Level 1
A19: Pool Area Shower Concrete | B19: =VLOOKUP(A19,'LEVEL 1.2 BUDGET'!$A$13:$K$316,11,FALSE) -> 20200 | E19: =VLOOKUP($A19,'LEVEL 2'!$A$13:$K$317,11,FALSE) -> 23959 | H19: =B19-E19 -> -3759 | I19: =H19/B19 -> -0.18608911 | W19: Product | X19: Senior
A20: Cabana Concrete | B20: =VLOOKUP(A20,'LEVEL 1.2 BUDGET'!$A$13:$K$316,11,FALSE) -> 0 | E20: =VLOOKUP($A20,'LEVEL 2'!$A$13:$K$317,11,FALSE) -> 6500 | H20: =B20-E20 -> -6500 | I20: 0
A21: Pool Equipment Foundation | B21: =VLOOKUP(A21,'LEVEL 1.2 BUDGET'!$A$13:$K$316,11,FALSE) -> 10000 | E21: =VLOOKUP($A21,'LEVEL 2'!$A$13:$K$317,11,FALSE) -> 6500 | H21: =B21-E21 -> 3500 | I21: =IF(B21=0,"n/a",H21/B21) -> 0.35 | W21: Timeline | X21: 30
A22: Lightweight Concrete | B22: =VLOOKUP(A22,'LEVEL 1.2 BUDGET'!$A$13:$K$316,11,FALSE) -> 496015.55 | E22: =VLOOKUP($A22,'LEVEL 2'!$A$13:$K$317,11,FALSE) -> 481539.8 | H22: =B22-E22 -> 14475.748 | I22: =H22/B22 -> 0.029184061 | K22: Updated take off | W22: Floors | X22: 2
A23: Deck Concrete | B23: =VLOOKUP(A23,'LEVEL 1.2 BUDGET'!$A$13:$K$316,11,FALSE) -> 43318 | E23: =VLOOKUP($A23,'LEVEL 2'!$A$13:$K$317,11,FALSE) -> 45894.051 | H23: =B23-E23 -> -2576.0515 | I23: =H23/B23 -> -0.059468385 | W23: Bldg. SF | X23: =98509+136604+127458 -> 362571
A24: Concrete | C24: =SUM(B15:B23) -> 2785657.9 | F24: =SUM(E15:E23) -> 2775836.2 | H24: =C24-F24 -> 9821.7124 | I24: =H24/C24 -> 0.0035258143 | W24: Acres | X24: 17.35
A25: Elevator Shaft | B25: =VLOOKUP(A25,'LEVEL 1.2 BUDGET'!$A$13:$K$316,11,FALSE) -> 138000 | E25: =VLOOKUP($A25,'LEVEL 2'!$A$13:$K$317,11,FALSE) -> 0 | H25: =B25-E25 -> 138000 | I25: =H25/B25 -> 1 | K25: Eliminated CMU shaft for framing. | W25: Site SF | X25: =X24*43560 -> 755766
A26: Trash Enclosure | B26: =VLOOKUP(A26,'LEVEL 1.2 BUDGET'!$A$13:$K$316,11,FALSE) -> 102200 | E26: =VLOOKUP($A26,'LEVEL 2'!$A$13:$K$317,11,FALSE) -> 98000 | H26: =B26-E26 -> 4200 | I26: =H26/B26 -> 0.04109589 | W26: Buildings | X26: 3
A27: Masonry Veneer Pool Area | B27: =VLOOKUP(A27,'LEVEL 1.2 BUDGET'!$A$13:$K$316,11,FALSE) -> 5000 | E27: =VLOOKUP($A27,'LEVEL 2'!$A$13:$K$317,11,FALSE) -> 15000 | H27: =B27-E27 -> -10000 | I27: =IF(B27=0,"n/a",H27/B27) -> -2
A28: Pool Eq. Shower | B28: =VLOOKUP(A28,'LEVEL 1.2 BUDGET'!$A$13:$K$316,11,FALSE) -> 10000 | E28: =VLOOKUP($A28,'LEVEL 2'!$A$13:$K$317,11,FALSE) -> 15000 | H28: =B28-E28 -> -5000 | I28: =IF(B28=0,"n/a",H28/B28) -> -0.5
A29: Masonry | C29: =SUM(B25:B28) -> 255200 | F29: =SUM(E25:E28) -> 128000 | H29: =C29-F29 -> 127200 | I29: =H29/C29 -> 0.4984326
A30: Structural Steel | B30: =VLOOKUP(A30,'LEVEL 1.2 BUDGET'!$A$13:$K$316,11,FALSE) -> 150000 | E30: =VLOOKUP($A30,'LEVEL 2'!$A$13:$K$317,11,FALSE) -> 150000 | H30: =B30-E30 -> 0 | I30: =IF(B30=0,"n/a",H30/B30) -> 0
A31: Elevator Shaft Iron | B31: =VLOOKUP(A31,'LEVEL 1.2 BUDGET'!$A$13:$K$316,11,FALSE) -> 24540 | E31: =VLOOKUP($A31,'LEVEL 2'!$A$13:$K$317,11,FALSE) -> 25500 | H31: =B31-E31 -> -960 | I31: =H31/B31 -> -0.039119804
A32: Stair Handrails | B32: =VLOOKUP(A32,'LEVEL 1.2 BUDGET'!$A$13:$K$316,11,FALSE) -> 45000 | E32: =VLOOKUP($A32,'LEVEL 2'!$A$13:$K$317,11,FALSE) -> 57000 | H32: =B32-E32 -> -12000 | I32: =H32/B32 -> -0.26666667
A33: Pool Equipment Gate | B33: =VLOOKUP(A33,'LEVEL 1.2 BUDGET'!$A$13:$K$316,11,FALSE) -> 1950 | E33: =VLOOKUP($A33,'LEVEL 2'!$A$13:$K$317,11,FALSE) -> 1950 | H33: =B33-E33 -> 0 | I33: =H33/B33 -> 0
A34: Iron Railings | B34: =VLOOKUP(A34,'LEVEL 1.2 BUDGET'!$A$13:$K$316,11,FALSE) -> 238464 | E34: =VLOOKUP($A34,'LEVEL 2'!$A$13:$K$317,11,FALSE) -> 240037.5 | H34: =B34-E34 -> -1573.5 | I34: =H34/B34 -> -0.0065984803
A35: Cable Railings | B35: =VLOOKUP(A35,'LEVEL 1.2 BUDGET'!$A$13:$K$316,11,FALSE) -> 0 | E35: =VLOOKUP($A35,'LEVEL 2'!$A$13:$K$317,11,FALSE) -> 0 | H35: =B35-E35 -> 0 | I35: =IF(B35=0,"n/a",H35/B35) -> n/a
A36: Metals | C36: =SUM(B30:B35) -> 459954 | F36: =SUM(E30:E35) -> 474487.5 | H36: =C36-F36 -> -14533.5 | I36: =H36/C36 -> -0.031597725
A37: Framing | B37: =VLOOKUP(A37,'LEVEL 1.2 BUDGET'!$A$13:$K$316,11,FALSE) -> 6772826.3 | E37: =VLOOKUP($A37,'LEVEL 2'!$A$13:$K$317,11,FALSE) -> 6772826.3 | H37: =B37-E37 -> 0 | I37: =H37/B37 -> 0
A38: Framing Pump House | B38: =VLOOKUP(A38,'LEVEL 1.2 BUDGET'!$A$13:$K$316,11,FALSE) -> 11208 | E38: =VLOOKUP($A38,'LEVEL 2'!$A$13:$K$317,11,FALSE) -> 11208 | H38: =B38-E38 -> 0 | I38: =IF(B38=0,"n/a",H38/B38) -> 0
A39: Framing - Crane | B39: =VLOOKUP(A39,'LEVEL 1.2 BUDGET'!$A$13:$K$316,11,FALSE) -> 0 | E39: =VLOOKUP($A39,'LEVEL 2'!$A$13:$K$317,11,FALSE) -> 0 | H39: =B39-E39 -> 0 | I39: =IF(B39=0,"n/a",H39/B39) -> n/a
A40: Cabana Framing | B40: =VLOOKUP(A40,'LEVEL 1.2 BUDGET'!$A$13:$K$316,11,FALSE) -> 0 | E40: =VLOOKUP($A40,'LEVEL 2'!$A$13:$K$317,11,FALSE) -> 0 | H40: =B40-E40 -> 0 | I40: =IF(B40=0,"n/a",H40/B40) -> n/a
A41: BBQ Framing | B41: =VLOOKUP(A41,'LEVEL 1.2 BUDGET'!$A$13:$K$316,11,FALSE) -> 10000 | E41: =VLOOKUP($A41,'LEVEL 2'!$A$13:$K$317,11,FALSE) -> 10000 | H41: =B41-E41 -> 0 | I41: =H41/B41 -> 0
A42: Fireplace Framing | B42: =VLOOKUP(A42,'LEVEL 1.2 BUDGET'!$A$13:$K$316,11,FALSE) -> 0 | E42: =VLOOKUP($A42,'LEVEL 2'!$A$13:$K$317,11,FALSE) -> 0 | H42: =B42-E42 -> 0 | I42: =IF(B42=0,"n/a",H42/B42) -> n/a
A43: Trellis | B43: =VLOOKUP(A43,'LEVEL 1.2 BUDGET'!$A$13:$K$316,11,FALSE) -> 0 | E43: =VLOOKUP($A43,'LEVEL 2'!$A$13:$K$317,11,FALSE) -> 0 | H43: =B43-E43 -> 0 | I43: =IF(B43=0,"n/a",H43/B43) -> n/a
A44: Pool Equipment Framing | B44: =VLOOKUP(A44,'LEVEL 1.2 BUDGET'!$A$13:$K$316,11,FALSE) -> 0 | E44: =VLOOKUP($A44,'LEVEL 2'!$A$13:$K$317,11,FALSE) -> 0 | H44: =B44-E44 -> 0 | I44: =IF(B44=0,"n/a",H44/B44) -> n/a
A45: Finish Carpentry - Units | B45: =VLOOKUP(A45,'LEVEL 1.2 BUDGET'!$A$13:$K$316,11,FALSE) -> 1125300 | E45: =VLOOKUP($A45,'LEVEL 2'!$A$13:$K$317,11,FALSE) -> 1281767.4 | H45: =B45-E45 -> -156467.35 | I45: =H45/B45 -> -0.13904501 | K45: Added 10% as we have indication BFS has purchased Rystin and Doors and Millwork companies.
A46: Finish Carpentry - Common | B46: =VLOOKUP(A46,'LEVEL 1.2 BUDGET'!$A$13:$K$316,11,FALSE) -> 398828.1 | E46: =VLOOKUP($A46,'LEVEL 2'!$A$13:$K$317,11,FALSE) -> 430736.14 | H46: =B46-E46 -> -31908.036 | I46: =H46/B46 -> -0.080004483 | K46: Added 10% as we have indication BFS has purchased Rystin and Doors and Millwork companies. | V46: 920930.34
A47: Finish Carpentry - Pump House | B47: =VLOOKUP(A47,'LEVEL 1.2 BUDGET'!$A$13:$K$316,11,FALSE) -> 4000 | E47: =VLOOKUP($A47,'LEVEL 2'!$A$13:$K$317,11,FALSE) -> 4000 | H47: =B47-E47 -> 0 | I47: =IF(B47=0,"n/a",H47/B47) -> 0 | V47: =E51 -> 906427.5
A48: BBQ Trim | B48: =VLOOKUP(A48,'LEVEL 1.2 BUDGET'!$A$13:$K$316,11,FALSE) -> 5000 | E48: =VLOOKUP($A48,'LEVEL 2'!$A$13:$K$317,11,FALSE) -> 5000 | H48: =B48-E48 -> 0 | I48: =H48/B48 -> 0 | V48: =V47-V46 -> -14502.84
A49: Shutters | B49: =VLOOKUP(A49,'LEVEL 1.2 BUDGET'!$A$13:$K$316,11,FALSE) -> 0 | E49: =VLOOKUP($A49,'LEVEL 2'!$A$13:$K$317,11,FALSE) -> 0 | H49: =B49-E49 -> 0 | I49: =IF(B49=0,"n/a",H49/B49) -> n/a
A50: Wood, Plastics, & Composites | C50: =SUM(B37:B49) -> 8327162.4 | F50: =SUM(E37:E49) -> 8515537.8 | H50: =C50-F50 -> -188375.39 | I50: =H50/C50 -> -0.022621799 | V50: 2.33
A51: Insulation | B51: =VLOOKUP(A51,'LEVEL 1.2 BUDGET'!$A$13:$K$316,11,FALSE) -> 906427.5 | E51: =VLOOKUP($A51,'LEVEL 2'!$A$13:$K$317,11,FALSE) -> 906427.5 | H51: =B51-E51 -> 0 | I51: =H51/B51 -> 0 | V51: 2.59
A52: Insulation - PH | B52: =VLOOKUP(A52,'LEVEL 1.2 BUDGET'!$A$13:$K$316,11,FALSE) -> 2000 | E52: =VLOOKUP($A52,'LEVEL 2'!$A$13:$K$317,11,FALSE) -> 2000 | H52: =B52-E52 -> 0 | I52: =IF(B52=0,"n/a",H52/B52) -> 0 | V52: 2.7
A53: Roofing | B53: =VLOOKUP(A53,'LEVEL 1.2 BUDGET'!$A$13:$K$316,11,FALSE) -> 1071280.2 | E53: =VLOOKUP($A53,'LEVEL 2'!$A$13:$K$317,11,FALSE) -> 1277484.3 | H53: =B53-E53 -> -206204.07 | I53: =H53/B53 -> -0.19248378 | K53: New takeoff based on 50% DD yielded 366 more squares (added parapet walls to take off).
A54: Roofing - PH | B54: =VLOOKUP(A54,'LEVEL 1.2 BUDGET'!$A$13:$K$316,11,FALSE) -> 10000 | E54: =VLOOKUP($A54,'LEVEL 2'!$A$13:$K$317,11,FALSE) -> 10000 | H54: =B54-E54 -> 0 | I54: =IF(B54=0,"n/a",H54/B54) -> 0
A55: Cabana Roofing | B55: =VLOOKUP(A55,'LEVEL 1.2 BUDGET'!$A$13:$K$316,11,FALSE) -> 0 | E55: =VLOOKUP($A55,'LEVEL 2'!$A$13:$K$317,11,FALSE) -> 0 | H55: =B55-E55 -> 0 | I55: =IF(B55=0,"n/a",H55/B55) -> n/a
A56: Pump House Roofing | B56: =VLOOKUP(A56,'LEVEL 1.2 BUDGET'!$A$13:$K$316,11,FALSE) -> 7500 | E56: =VLOOKUP($A56,'LEVEL 2'!$A$13:$K$317,11,FALSE) -> 7500 | H56: =B56-E56 -> 0 | I56: =H56/B56 -> 0
A57: Pool Equipment Roofing | B57: =VLOOKUP(A57,'LEVEL 1.2 BUDGET'!$A$13:$K$316,11,FALSE) -> 7500 | E57: =VLOOKUP($A57,'LEVEL 2'!$A$13:$K$317,11,FALSE) -> 7500 | H57: =B57-E57 -> 0 | I57: =IF(B57=0,"n/a",H57/B57) -> 0
A58: Trash Enclosure Cover | B58: =VLOOKUP(A58,'LEVEL 1.2 BUDGET'!$A$13:$K$316,11,FALSE) -> 81200 | E58: =VLOOKUP($A58,'LEVEL 2'!$A$13:$K$317,11,FALSE) -> 84000 | H58: =B58-E58 -> -2800 | I58: =H58/B58 -> -0.034482759
A59: Pigeon Proofing | B59: =VLOOKUP(A59,'LEVEL 1.2 BUDGET'!$A$13:$K$316,11,FALSE) -> 29005.68 | E59: =VLOOKUP($A59,'LEVEL 2'!$A$13:$K$317,11,FALSE) -> 29005.68 | H59: =B59-E59 -> 0 | I59: =H59/B59 -> 0
A60: Gutters and Downspouts | B60: =VLOOKUP(A60,'LEVEL 1.2 BUDGET'!$A$13:$K$316,11,FALSE) -> 18128.55 | E60: =VLOOKUP($A60,'LEVEL 2'!$A$13:$K$317,11,FALSE) -> 18128.55 | H60: =B60-E60 -> 0 | I60: =H60/B60 -> 0
A61: Roof Ladders | B61: =VLOOKUP(A61,'LEVEL 1.2 BUDGET'!$A$13:$K$316,11,FALSE) -> 9300 | E61: =VLOOKUP($A61,'LEVEL 2'!$A$13:$K$317,11,FALSE) -> 9300 | H61: =B61-E61 -> 0 | I61: =H61/B61 -> 0
A62: Roof Access Doors | B62: =VLOOKUP(A62,'LEVEL 1.2 BUDGET'!$A$13:$K$316,11,FALSE) -> 15000 | E62: =VLOOKUP($A62,'LEVEL 2'!$A$13:$K$317,11,FALSE) -> 15000 | H62: =B62-E62 -> 0 | I62: =H62/B62 -> 0
A63: Roof Winch | B63: =VLOOKUP(A63,'LEVEL 1.2 BUDGET'!$A$13:$K$316,11,FALSE) -> 0 | E63: =VLOOKUP($A63,'LEVEL 2'!$A$13:$K$317,11,FALSE) -> 0 | H63: =B63-E63 -> 0 | I63: =IF(B63=0,"n/a",H63/B63) -> n/a
A64: Thermal & Moisture Protection | C64: =SUM(B51:B63) -> 2157341.9 | F64: =SUM(E51:E63) -> 2366346 | H64: =C64-F64 -> -209004.07 | I64: =H64/C64 -> -0.096880362
A65: Entry Doors | B65: =VLOOKUP(A65,'LEVEL 1.2 BUDGET'!$A$13:$K$316,11,FALSE) -> 8000 | E65: =VLOOKUP($A65,'LEVEL 2'!$A$13:$K$317,11,FALSE) -> 24000 | H65: =B65-E65 -> -16000 | I65: =IF(B65=0,"n/a",H65/B65) -> -2
A66: Common Doors | B66: =VLOOKUP(A66,'LEVEL 1.2 BUDGET'!$A$13:$K$316,11,FALSE) -> 0 | E66: =VLOOKUP($A66,'LEVEL 2'!$A$13:$K$317,11,FALSE) -> 0 | H66: =B66-E66 -> 0 | I66: =IF(B66=0,"n/a",H66/B66) -> n/a
A67: Pocket Doors - 3 Panel | B67: =VLOOKUP(A67,'LEVEL 1.2 BUDGET'!$A$13:$K$316,11,FALSE) -> 0 | E67: =VLOOKUP($A67,'LEVEL 2'!$A$13:$K$317,11,FALSE) -> 0 | H67: =B67-E67 -> 0 | I67: =IF(B67=0,"n/a",H67/B67) -> n/a
A68: Garage Doors | B68: =VLOOKUP(A68,'LEVEL 1.2 BUDGET'!$A$13:$K$316,11,FALSE) -> 0 | E68: =VLOOKUP($A68,'LEVEL 2'!$A$13:$K$317,11,FALSE) -> 0 | H68: =B68-E68 -> 0 | I68: =IF(B68=0,"n/a",H68/B68) -> n/a
A69: Windows and Sliding Glass Doors | B69: =VLOOKUP(A69,'LEVEL 1.2 BUDGET'!$A$13:$K$316,11,FALSE) -> 501303 | E69: =VLOOKUP($A69,'LEVEL 2'!$A$13:$K$317,11,FALSE) -> 562650 | H69: =B69-E69 -> -61347 | I69: =H69/B69 -> -0.12237509 | K69: Contempo W. Henderson proposal plus $100 /unit for frontage windows.
A70: Windows Repair and Replacement | B70: =VLOOKUP(A70,'LEVEL 1.2 BUDGET'!$A$13:$K$316,11,FALSE) -> 27225 | E70: =VLOOKUP($A70,'LEVEL 2'!$A$13:$K$317,11,FALSE) -> 27225 | H70: =B70-E70 -> 0 | I70: =H70/B70 -> 0
A71: Pool Equipment Windows | B71: =VLOOKUP(A71,'LEVEL 1.2 BUDGET'!$A$13:$K$316,11,FALSE) -> 0 | E71: =VLOOKUP($A71,'LEVEL 2'!$A$13:$K$317,11,FALSE) -> 0 | H71: =B71-E71 -> 0 | I71: =IF(B71=0,"n/a",H71/B71) -> n/a
A72: Pool Glass Walls | B72: =VLOOKUP(A72,'LEVEL 1.2 BUDGET'!$A$13:$K$316,11,FALSE) -> 0 | E72: =VLOOKUP($A72,'LEVEL 2'!$A$13:$K$317,11,FALSE) -> 0 | H72: =B72-E72 -> 0 | I72: =IF(B72=0,"n/a",H72/B72) -> n/a
A73: Fixed Glass | B73: =VLOOKUP(A73,'LEVEL 1.2 BUDGET'!$A$13:$K$316,11,FALSE) -> 0 | E73: =VLOOKUP($A73,'LEVEL 2'!$A$13:$K$317,11,FALSE) -> 0 | H73: =B73-E73 -> 0 | I73: =IF(B73=0,"n/a",H73/B73) -> n/a
A74: Mirrors - LED | B74: =VLOOKUP(A74,'LEVEL 1.2 BUDGET'!$A$13:$K$316,11,FALSE) -> 0 | E74: =VLOOKUP($A74,'LEVEL 2'!$A$13:$K$317,11,FALSE) -> 0 | H74: =B74-E74 -> 0 | I74: =IF(B74=0,"n/a",H74/B74) -> n/a
A75: Mirrors - LED Install | B75: =VLOOKUP(A75,'LEVEL 1.2 BUDGET'!$A$13:$K$316,11,FALSE) -> 0 | E75: =VLOOKUP($A75,'LEVEL 2'!$A$13:$K$317,11,FALSE) -> 0 | H75: =B75-E75 -> 0 | I75: =IF(B75=0,"n/a",H75/B75) -> n/a
A76: Mirrors - Framed | B76: =VLOOKUP(A76,'LEVEL 1.2 BUDGET'!$A$13:$K$316,11,FALSE) -> 0 | E76: =VLOOKUP($A76,'LEVEL 2'!$A$13:$K$317,11,FALSE) -> 0 | H76: =B76-E76 -> 0 | I76: =IF(B76=0,"n/a",H76/B76) -> n/a
A77: Mirrors - Polished Edges (Units) | B77: =VLOOKUP(A77,'LEVEL 1.2 BUDGET'!$A$13:$K$316,11,FALSE) -> 59895 | E77: =VLOOKUP($A77,'LEVEL 2'!$A$13:$K$317,11,FALSE) -> 63525 | H77: =B77-E77 -> -3630 | I77: =H77/B77 -> -0.060606061
A78: Mirrors - Polished Edges (Restrooms) | B78: =VLOOKUP(A78,'LEVEL 1.2 BUDGET'!$A$13:$K$316,11,FALSE) -> 1500 | E78: =VLOOKUP($A78,'LEVEL 2'!$A$13:$K$317,11,FALSE) -> 1800 | H78: =B78-E78 -> -300 | I78: =H78/B78 -> -0.2
A79: Openings | C79: =SUM(B65:B78) -> 597923 | F79: =SUM(E65:E78) -> 679200 | H79: =C79-F79 -> -81277 | I79: =H79/C79 -> -0.13593222
A80: Cost Prep Labor | B80: =VLOOKUP(A80,'LEVEL 1.2 BUDGET'!$A$13:$K$316,11,FALSE) -> 0 | E80: =VLOOKUP($A80,'LEVEL 2'!$A$13:$K$317,11,FALSE) -> 0 | H80: =B80-E80 -> 0 | I80: =H80/B80 -> #DIV/0!
A81: Cost Prep Mat - Home Depot | B81: =VLOOKUP(A81,'LEVEL 1.2 BUDGET'!$A$13:$K$316,11,FALSE) -> 10000 | E81: =VLOOKUP($A81,'LEVEL 2'!$A$13:$K$317,11,FALSE) -> 10000 | H81: =B81-E81 -> 0 | I81: =H81/B81 -> 0
A82: Clean Up - Final | B82: =VLOOKUP(A82,'LEVEL 1.2 BUDGET'!$A$13:$K$316,11,FALSE) -> 308185.35 | E82: =VLOOKUP($A82,'LEVEL 2'!$A$13:$K$317,11,FALSE) -> 308185.35 | H82: =B82-E82 -> 0 | I82: =H82/B82 -> 0
A83: Clean Up - During Construction - Labor | B83: =VLOOKUP(A83,'LEVEL 1.2 BUDGET'!$A$13:$K$316,11,FALSE) -> 75000 | E83: =VLOOKUP($A83,'LEVEL 2'!$A$13:$K$317,11,FALSE) -> 75000 | H83: =B83-E83 -> 0 | I83: =H83/B83 -> 0
A84: Dumpsters | B84: =VLOOKUP(A84,'LEVEL 1.2 BUDGET'!$A$13:$K$316,11,FALSE) -> 28677 | E84: =VLOOKUP($A84,'LEVEL 2'!$A$13:$K$317,11,FALSE) -> 28677 | H84: =B84-E84 -> 0 | I84: =H84/B84 -> 0
A85: Clean Up - Hauling Exterior | B85: =VLOOKUP(A85,'LEVEL 1.2 BUDGET'!$A$13:$K$316,11,FALSE) -> 10000 | E85: =VLOOKUP($A85,'LEVEL 2'!$A$13:$K$317,11,FALSE) -> 10000 | H85: =B85-E85 -> 0 | I85: =H85/B85 -> 0
A86: Stucco | B86: =VLOOKUP(A86,'LEVEL 1.2 BUDGET'!$A$13:$K$316,11,FALSE) -> 842819.61 | E86: =VLOOKUP($A86,'LEVEL 2'!$A$13:$K$317,11,FALSE) -> 950639.3 | H86: =B86-E86 -> -107819.69 | I86: =H86/B86 -> -0.12792736 | K86: New take off based on 50% DD tielded 3k SY more than previous.
A87: Stucco - Pump House | B87: =VLOOKUP(A87,'LEVEL 1.2 BUDGET'!$A$13:$K$316,11,FALSE) -> 6000 | E87: =VLOOKUP($A87,'LEVEL 2'!$A$13:$K$317,11,FALSE) -> 6000 | H87: =B87-E87 -> 0 | I87: =H87/B87 -> 0
A88: Stucco - Walls | B88: =VLOOKUP(A88,'LEVEL 1.2 BUDGET'!$A$13:$K$316,11,FALSE) -> 0 | E88: =VLOOKUP($A88,'LEVEL 2'!$A$13:$K$317,11,FALSE) -> 0 | H88: =B88-E88 -> 0 | I88: =IF(B88=0,"n/a",H88/B88) -> n/a
A89: Stucco - Pool Area | B89: =VLOOKUP(A89,'LEVEL 1.2 BUDGET'!$A$13:$K$316,11,FALSE) -> 2000 | E89: =VLOOKUP($A89,'LEVEL 2'!$A$13:$K$317,11,FALSE) -> 2000 | H89: =B89-E89 -> 0 | I89: =H89/B89 -> 0
A90: Stucco - Cabana | B90: =VLOOKUP(A90,'LEVEL 1.2 BUDGET'!$A$13:$K$316,11,FALSE) -> 0 | E90: =VLOOKUP($A90,'LEVEL 2'!$A$13:$K$317,11,FALSE) -> 0 | H90: =B90-E90 -> 0 | I90: =IF(B90=0,"n/a",H90/B90) -> n/a
A91: Stucco - Pool Equipment | B91: =VLOOKUP(A91,'LEVEL 1.2 BUDGET'!$A$13:$K$316,11,FALSE) -> 5000 | E91: =VLOOKUP($A91,'LEVEL 2'!$A$13:$K$317,11,FALSE) -> 5000 | H91: =B91-E91 -> 0 | I91: =IF(B91=0,"n/a",H91/B91) -> 0 | V91: 2875188
A92: Stucco - Repairs | B92: =VLOOKUP(A92,'LEVEL 1.2 BUDGET'!$A$13:$K$316,11,FALSE) -> 1500 | E92: =VLOOKUP($A92,'LEVEL 2'!$A$13:$K$317,11,FALSE) -> 1500 | H92: =B92-E92 -> 0 | I92: =H92/B92 -> 0 | V92: =E93 -> 2773668.1
A93: Drywall | B93: =VLOOKUP(A93,'LEVEL 1.2 BUDGET'!$A$13:$K$316,11,FALSE) -> 2791796.7 | E93: =VLOOKUP($A93,'LEVEL 2'!$A$13:$K$317,11,FALSE) -> 2773668.1 | H93: =B93-E93 -> 18128.55 | I93: =H93/B93 -> 0.0064935065 | V93: =V92-V91 -> -101519.88
A94: Drywall - Repairs | B94: =VLOOKUP(A94,'LEVEL 1.2 BUDGET'!$A$13:$K$316,11,FALSE) -> 30855 | E94: =VLOOKUP($A94,'LEVEL 2'!$A$13:$K$317,11,FALSE) -> 30855 | H94: =B94-E94 -> 0 | I94: =H94/B94 -> 0
A95: Drywall - Pump House | B95: =VLOOKUP(A95,'LEVEL 1.2 BUDGET'!$A$13:$K$316,11,FALSE) -> 1000 | E95: =VLOOKUP($A95,'LEVEL 2'!$A$13:$K$317,11,FALSE) -> 1000 | H95: =B95-E95 -> 0 | I95: =IF(B95=0,"n/a",H95/B95) -> 0
A96: Tile Tubs and Showers | B96: =VLOOKUP(A96,'LEVEL 1.2 BUDGET'!$A$13:$K$316,11,FALSE) -> 0 | E96: =VLOOKUP($A96,'LEVEL 2'!$A$13:$K$317,11,FALSE) -> 0 | H96: =B96-E96 -> 0 | I96: =IF(B96=0,"n/a",H96/B96) -> n/a
A97: Common Tile | B97: =VLOOKUP(A97,'LEVEL 1.2 BUDGET'!$A$13:$K$316,11,FALSE) -> 75000 | E97: =VLOOKUP($A97,'LEVEL 2'!$A$13:$K$317,11,FALSE) -> 170141.73 | H97: =B97-E97 -> -95141.73 | I97: =H97/B97 -> -1.2685564 | K97: Increase as an allowance per building.
A98: Kitchen Backsplash | B98: =VLOOKUP(A98,'LEVEL 1.2 BUDGET'!$A$13:$K$316,11,FALSE) -> 0 | E98: =VLOOKUP($A98,'LEVEL 2'!$A$13:$K$317,11,FALSE) -> 0 | H98: =B98-E98 -> 0 | I98: =IF(B98=0,"n/a",H98/B98) -> n/a
A99: Cabana Tile | B99: =VLOOKUP(A99,'LEVEL 1.2 BUDGET'!$A$13:$K$316,11,FALSE) -> 0 | E99: =VLOOKUP($A99,'LEVEL 2'!$A$13:$K$317,11,FALSE) -> 0 | H99: =B99-E99 -> 0 | I99: =IF(B99=0,"n/a",H99/B99) -> n/a
A100: Flooring - Units | B100: =VLOOKUP(A100,'LEVEL 1.2 BUDGET'!$A$13:$K$316,11,FALSE) -> 538541.7 | E100: =VLOOKUP($A100,'LEVEL 2'!$A$13:$K$317,11,FALSE) -> 513238.19 | H100: =B100-E100 -> 25303.511 | I100: =H100/B100 -> 0.046985241
A101: Common Wood | B101: =VLOOKUP(A101,'LEVEL 1.2 BUDGET'!$A$13:$K$316,11,FALSE) -> 0 | E101: =VLOOKUP($A101,'LEVEL 2'!$A$13:$K$317,11,FALSE) -> 0 | H101: =B101-E101 -> 0 | I101: 0
A102: Common Vinyl | B102: =VLOOKUP(A102,'LEVEL 1.2 BUDGET'!$A$13:$K$316,11,FALSE) -> 0 | E102: =VLOOKUP($A102,'LEVEL 2'!$A$13:$K$317,11,FALSE) -> 0 | H102: =B102-E102 -> 0 | I102: 0
...

Sheet What Changed
A1: ROBINDALE AND 215 - DETAILS OF BUDGET CHANGE
B3: Budget 1.2 | D3: Budget 2 | F3: Variance | H3: Reason for Change
A4: Elevator Shaft | B4: =Comparison!B25 -> 138000 | D4: =Comparison!E25 -> 0 | F4: =B4-D4 -> 138000 | G4: 0 | H4: Elevator Shaft to be framed, not CMU.
A5: Masonry | C5: =Comparison!C29 -> 255200 | E5: =Comparison!F29 -> 128000 | F5: =C5-E5 -> 127200 | G5: =Comparison!$I$29 -> 0.4984326
A6: Finish Carpentry - Units | B6: =Comparison!B45 -> 1125300 | D6: =Comparison!E45 -> 1281767.4 | F6: =B6-D6 -> -156467.35 | G6: =Comparison!$I$37 -> 0 | H6: Added 10% as we have indication BFS has purchased Rystin and Doors and Millwork companies.
A7: Finish Carpentry - Common | B7: =Comparison!B46 -> 398828.1 | D7: =Comparison!E46 -> 430736.14 | F7: =B7-D7 -> -31908.036 | G7: =Comparison!$I$37 -> 0 | H7: Added 10% as we have indication BFS has purchased Rystin and Doors and Millwork companies.
A8: Wood, Plastics, & Composites | C8: =Comparison!C50 -> 8327162.4 | E8: =Comparison!F50 -> 8515537.8 | F8: =C8-E8 -> -188375.39 | G8: =Comparison!$I$50 -> -0.022621799
A9: Roofing | B9: =Comparison!B53 -> 1071280.2 | D9: =Comparison!E53 -> 1277484.3 | F9: =B9-D9 -> -206204.07 | G9: =Comparison!$I$53 -> -0.19248378 | H9: New takeoff based on 50% DD yielded 366 more squares (added parapet walls to take off).
A10: Thermal & Moisture Protection | C10: =Comparison!$C$64 -> 2157341.9 | E10: =Comparison!$F$64 -> 2366346 | F10: =C10-E10 -> -209004.07 | G10: =Comparison!$I$64 -> -0.096880362
A11: Stucco | B11: =Comparison!B86 -> 842819.61 | D11: =Comparison!E86 -> 950639.3 | F11: =B11-D11 -> -107819.69 | G11: =Comparison!$I$69 -> -0.12237509 | H11: New take off based on 50% DD tielded 3k SY more than previous.
A12: Common Tile | B12: =Comparison!B97 -> 75000 | D12: =Comparison!E97 -> 170141.73 | F12: =B12-D12 -> -95141.73 | G12: =Comparison!$I$69 -> -0.12237509 | H12: Increase as an allowance per building.
A13: Hall Flooring | B13: =Comparison!B103 -> 170408.37 | D13: =Comparison!E103 -> 271928.25 | F13: =B13-D13 -> -101519.88 | G13: =Comparison!$I$69 -> -0.12237509 | H13: Updated pricing to Torrey Pines contract versus previous budget using Pebble.
A14: Hall Runner Materials | B14: =Comparison!B110 -> 107683.44 | D14: =Comparison!E110 -> 0 | F14: =B14-D14 -> 107683.44 | G14: =Comparison!$I$141 -> 0 | H14: Deleted hallway runners in latest plans.
A15: Painting | B15: =Comparison!B112 -> 572862.18 | D15: =Comparison!E112 -> 717890.58 | F15: =B15-D15 -> -145028.4 | G15: =Comparison!$I$144 -> 0.051782919 | H15: Based on West Henderson Paint proposal by Classic.
A16: Finishes | C16: =Comparison!$C$148 -> 2059949 | E16: =Comparison!$F$148 -> 1826689.4 | F16: =C16-E16 -> 233259.64 | G16: =Comparison!$I$148 -> 0.11323564
A17: Appliances | B17: =Comparison!B136 -> 1009140 | D17: =Comparison!E136 -> 1220061.2 | F17: =B17-D17 -> -210921.15 | G17: =Comparison!$I$150 -> 0 | H17: Updated to Bruner and 5% for annual increase in appliance cost.
A18: Equipment | C18: =Comparison!$C$152 -> 907561 | E18: =Comparison!$F$152 -> 953492.67 | F18: =C18-E18 -> -45931.667 | G18: =Comparison!$I$152 -> -0.050610005
A19: Cabinets Units | B19: =Comparison!B142 -> 1143813 | D19: =Comparison!E142 -> 941174 | F19: =B19-D19 -> 202639 | G19: =Comparison!$I$150 -> 0 | H19: Using Thermafoil White, W.H. units. Add $150,260 if upgrading to Morning Dew ($159.80 / SF)
A20: Furnishings | C20: =Comparison!C148 -> 2059949 | E20: =Comparison!F148 -> 1826689.4 | F20: =C20-E20 -> 233259.64 | G20: =Comparison!$I$152 -> -0.050610005
A21: Elevator | B21: =Comparison!$B$155 -> 426560 | D21: =Comparison!$E$155 -> 483797 | F21: =B21-D21 -> -57237 | G21: =Comparison!$I$155 -> -0.13418276 | H21: Based on Otis discussion on estimated cost per 2-stop elevator
A22: Conveying Equipment | C22: =Comparison!$C$157 -> 439560 | E22: =Comparison!$F$157 -> 496797 | F22: =C22-E22 -> -57237 | G22: =Comparison!$I$157 -> -0.13021431
A23: Electrical | B23: =Comparison!$B$171 -> 3651773 | D23: =Comparison!$E$171 -> 3846878.3 | F23: =B23-D23 -> -195105.33 | G23: =Comparison!$I$171 -> -0.053427562 | H23: Updated to West Henderson proposal by Sigma (cost/SF).
A24: Electrical | C24: =Comparison!$C$188 -> 4194934 | E24: =Comparison!$F$188 -> 4455520.8 | F24: =C24-E24 -> -260586.83 | G24: =Comparison!$I$188 -> -0.062119411
A25: Fire Alarm / Two Way | B25: =Comparison!$B$195 -> 506841.64 | D25: =Comparison!$E$195 -> 701583.54 | F25: =B25-D25 -> -194741.9 | G25: =Comparison!$I$195 -> -0.38422632 | H25: Used Decatur due to expectation that all Jurisdictions would implement new code.
A26: Electronic Safety & Security | C26: =Comparison!$C$197 -> 848751.36 | E26: =Comparison!$F$197 -> 1047129.9 | F26: =C26-E26 -> -198378.54 | G26: =Comparison!$I$197 -> -0.23372986
A27: Mass Grading | B27: =Comparison!$B$202 -> 1067126 | D27: =Comparison!$E$202 -> 1257581.4 | F27: =B27-D27 -> -190455.36 | G27: =Comparison!$I$202 -> -0.17847505 | H27: Preliminary civil shows an 50k CY export site. Increase export while decreasing hard dig and excavation based on take off.
A28: Earthwork | C28: =Comparison!$C$207 -> 1546728 | E28: =Comparison!$F$207 -> 1777422.5 | F28: =C28-E28 -> -230694.5 | G28: =Comparison!$I$207 -> -0.14915001
A29: Paving | B29: =Comparison!$B$211 -> 670743 | D29: =Comparison!$E$211 -> 601630.93 | F29: =B29-D29 -> 69112.07 | G29: =Comparison!$I$211 -> 0.10303808 | H29: Updated takeoff based on preliminary civil plans.
A30: Walls Iron | B30: =Comparison!$B$221 -> 91085 | D30: =Comparison!$E$221 -> 164035.4 | F30: =B30-D30 -> -72950.4 | G30: =Comparison!$I$221 -> -0.80090465 | H30: Updated takeoff based on preliminary civil plans.
A31: Walls Masonry | B31: =Comparison!$B$232 -> 376743 | D31: =Comparison!$E$232 -> 493481.67 | F31: =B31-D31 -> -116738.67 | G31: =Comparison!$I$232 -> -0.30986289 | H31: Updated takeoff based on preliminary civil plans.
A32: Retaining Walls | B32: =Comparison!$B$234 -> 331457 | D32: =Comparison!$E$234 -> 303105.8 | F32: =B32-D32 -> 28351.2 | G32: =Comparison!$I$234 -> 0.085535077 | H32: Updated takeoff based on preliminary civil plans.
A33: Site Landscaping | B33: =Comparison!$B$237 -> 3976294.8 | D33: =Comparison!$E$237 -> 2847338.3 | F33: =B33-D33 -> 1128956.5 | G33: =Comparison!$I$237 -> 0.28392174 | H33: Updated pricing at West Henderson increased by $0.50 / sf. Robindale assimilates WH based on project size and large open spaces.
A34: Offsite Paving | B34: =Comparison!$B$241 -> 413660 | D34: =Comparison!$E$241 -> 341251.06 | F34: =B34-D34 -> 72408.938 | G34: =(B34-D34)/B34 -> 0.17504457 | H34: Civil plans shows minimal but this budget assumes the entire Robindale frontage to be paved due to poor currect conditions.
A35: Exterior Improvements | C35: =Comparison!$C$245 -> 6907826.6 | E35: =Comparison!$F$245 -> 5896648.9 | F35: =C35-E35 -> 1011177.6 | G35: =Comparison!$I$245 -> 0.14638145
A36: Sewer | B36: =Comparison!$B$249 -> 823398 | D36: =Comparison!$E$249 -> 516087 | F36: =B36-D36 -> 307311 | G36: =Comparison!$I$249 -> 0.37322291 | H36: Preliminary Civils show no lift station ($200k) and hard dig decreased by $50k. Soils show limited hard dig.
A37: Electric | B37: =Comparison!$B$253 -> 452076 | D37: =Comparison!$E$253 -> 350575.2 | F37: =B37-D37 -> 101500.8 | G37: =Comparison!$I$253 -> 0.22452154 | H37: Updated with a internal power design based on previous projects. Lowered Hard dig to $50k from $100k.
A38: Off Site Water | B38: =Comparison!$B$258 -> 345550 | D38: =Comparison!$E$258 -> 387993.65 | F38: =B38-D38 -> -42443.65 | G38: =Comparison!$I$258 -> -0.12282926 | H38: Based on preliminary civils take offs.
A39: Off Site Sewer | B39: =Comparison!$B$259 -> 75000 | D39: =Comparison!$E$259 -> 91720 | F39: =B39-D39 -> -16720 | G39: =Comparison!$I$259 -> -0.22293333 | H39: Based on preliminary civils take offs.
A40: Utilities | C40: =Comparison!$C$262 -> 3305385 | E40: =Comparison!$F$262 -> 2941601.8 | F40: =C40-E40 -> 363783.17 | G40: =Comparison!$I$262 -> 0.11005773
A41: Interior Furniture | B41: =Comparison!$B$294 -> 1500000 | D41: =Comparison!$E$294 -> 1200000 | F41: =B41-D41 -> 300000 | G41: =Comparison!$I$294 -> 0.2 | H41: Assuming Main Building approximatly $500k and $350k for each of the 2 other buidlings.
A42: FFE | C42: =Comparison!$C$299 -> 1972848 | E42: =Comparison!$F$299 -> 1681753.2 | F42: =C42-E42 -> 291094.84 | G42: =Comparison!$I$299 -> 0.14755057
A43: Total Hard Costs | C43: =Comparison!$C$312 -> 68871988 | E43: =Comparison!$F$312 -> 68767994 | F43: =C43-E43 -> 103993.77 | G43: =Comparison!$I$312 -> 0.0015099575

Sheet Unit Pricing Comparison
I1: SENIOR / AFFORABLE PROJECTS
C2: Robindale & 215 (Level 2) | H2: West Henderson Level 3 | I2: Bruner | J2: South Nellis | K2: Torrey Pines | L2: Decatur | M2: Pebble
A3: Budget | E3: Units | F3: ='LEVEL 2'!N9 -> 363 | H3: 380 | I3: 194 | J3: 50 | K3: 190 | L3: 276 | M3: 195
A4: Proposal | E4: GSF | F4: ='LEVEL 2'!B8 -> 362571 | H4: 422635 | I4: 196289 | J4: 34388 | K4: 188825 | L4: 258464 | M4: 184108
A5: Contract | E5: Acres | F5: ='LEVEL 2'!B9 -> 17.35 | H5: 15.83 | I5: 4.9 | J5: 1.3 | K5: 5 | L5: 9.45 | M5: 5
E6: Site SF | F6: =F5*43560 -> 755766 | H6: =H5*43560 -> 689554.8 | I6: =I5*43560 -> 213444 | J6: =J5*43560 -> 56628 | K6: =K5*43560 -> 217800 | L6: 411642 | M6: 217800
A7: Description | B7: % | C7: Cost | D7: UOM | E7: U | F7: PU | H7: PU | I7: PU | J7: PU | K7: PU | L7: PU | M7: PU | O7: COMMENTS ROBINDALE VS WEST HENDERSON | Q7: Recommendation for Robindale
A8: Framing | B8: =C8/$C$29 -> 0.098488059 | C8: =VLOOKUP(A8,'LEVEL 2'!$A$14:$K$317,11,FALSE) -> 6772826.3 | D8: SF | E8: =$F$4 -> 362571 | F8: =C8/E8 -> 18.68 | H8: 17.716624 | I8: 18.68 | J8: 20.075375 | K8: 19.921525 | L8: 22.888453 | M8: 19.011015 | O8: WH is ave between the 3 current proposal. | Q8: Leave as budgeted
A9: Electrical | B9: =C9/$C$29 -> 0.055939952 | C9: =VLOOKUP(A9,'LEVEL 2'!$A$14:$K$317,11,FALSE) -> 3846878.3 | D9: SF (Bldg) | E9: =$F$4 -> 362571 | F9: =C9/E9 -> 10.61 | H9: 11.33 | I9: 10.06 | J9: 12.504362 | K9: 9.2699537 | L9: 10.176018 | M9: 12.13429 | O9: WH is ave between the 3 current proposal. | Q9: Increase to WH
A10: HVAC Standard | B10: =C10/$C$29 -> 0.051969903 | C10: =VLOOKUP(A10,'LEVEL 2'!$A$14:$K$317,11,FALSE) -> 3573866 | D10: Unit | E10: =$F$3 -> 363 | F10: =C10/E10 -> 9845.3608 | H10: 10558.306 | I10: 9845.36 | J10: 10148.68 | K10: 9739.2737 | L10: 10104.674 | M10: 9218.2513 | O10: WH ave of 2 best proposal. 3rd is an outlier. Larger units at WH. | Q10: Increase to WH
A11: Drywall | B11: =C11/$C$29 -> 0.040333707 | C11: =VLOOKUP(A11,'LEVEL 2'!$A$14:$K$317,11,FALSE) -> 2773668.1 | D11: SF (Bldg) | E11: =$F$4 -> 362571 | F11: =C11/E11 -> 7.65 | H11: 7.6967218 | I11: 7.2940664 | J11: 7.7384864 | K11: 8.0157077 | L11: 7.3585311 | M11: 8.0768353 | O11: WH is ave between the 3 current proposal. | Q11: Leave as budgeted
A12: 1 Bathroom Unit | B12: =C12/$C$29 -> 0.053150409 | C12: =VLOOKUP(A12,'LEVEL 2'!$A$14:$K$317,11,FALSE) -> 3655047 | D12: 1 Bath Unit | E12: =F3 -> 363 | F12: =C12/E12 -> 10069 | H12: 10250 | I12: 10069 | J12: 10196.24 | K12: 10526.311 | L12: 11042.514 | M12: =1959791/$M$3 -> 10050.21 | O12: WH is tied to JMAC proposal. | Q12: Increase to WH
A13: Appliances | B13: =C13/$C$29 -> 0.0177417 | C13: =VLOOKUP(A13,'LEVEL 2'!$A$14:$K$317,11,FALSE) -> 1220061.2 | D13: Unit | E13: =$F$3 -> 363 | F13: =C13/E13 -> 3361.05 | H13: 3328.1895 | I13: =614922.64/I3 -> 3169.7043 | J13: 3064.485 | K13: 3144.7947 | L13: 3454.4783 | M13: 3201.4974 | Q13: Decrease to Bruner
A14: Sprinkler System | B14: =C14/$C$29 -> 0.013971807 | C14: =VLOOKUP(A14,'LEVEL 2'!$A$14:$K$317,11,FALSE) -> 960813.15 | D14: SF (Bldg) | E14: =$F$4 -> 362571 | F14: =C14/E14 -> 2.65 | H14: 2.65 | I14: 2.65 | J14: 3.2147842 | K14: 2.453065 | L14: 2.94 | M14: 2.4480196 | Q14: Leave as budgeted
A15: Cabinets Units | B15: =C15/$C$29 -> 0.013686222 | C15: =VLOOKUP(A15,'LEVEL 2'!$A$14:$K$317,11,FALSE) -> 941174 | D15: Unit | E15: =$F$3 -> 363 | F15: =C15/E15 -> 2592.7658 | H15: 3072.4615 | I15: 4150.2474 | J15: 1985.2 | K15: 3778.0053 | L15: 3705.4275 | M15: 3113.7333 | O15: WH has more cabinet boxes due to extra bathrooms (increase/unit) | Q15: Leave as budgeted
A16: Windows and Sliding Glass Doors | B16: =C16/$C$29 -> 0.0081818586 | C16: =VLOOKUP(A16,'LEVEL 2'!$A$14:$K$317,11,FALSE) -> 562650 | D16: Unit | E16: =$F$3 -> 363 | F16: =C16/E16 -> 1550 | H16: 1400 | I16: 1335.866 | J16: 1300.6084 | K16: 1157.8947 | L16: 1408.8261 | M16: 739.27144 | Q16: Leave as budgeted
A17: Finish Carpentry - Units | B17: =C17/$C$29 -> 0.01863901 | C17: =VLOOKUP(A17,'LEVEL 2'!$A$14:$K$317,11,FALSE) -> 1281767.4 | D17: Unit | E17: =$F$3 -> 363 | F17: =C17/E17 -> 3531.0395 | H17: 3002.6901 | I17: 2607.1546 | J17: 2710.9005 | K17: 3210.0359 | L17: 2983.3587 | M17: 3081.2324 | O17: Budgeted basd on WH proposal per liavable SF | Q17: Decrese to WH $/SF
A18: Slabs | B18: =C18/$C$29 -> 0.03090745 | C18: =VLOOKUP(A18,'LEVEL 2'!$A$14:$K$317,11,FALSE) -> 2125443.3 | D18: SF (Slab) | E18: ='Assumptions & Takeoffs'!B11 -> 177268 | F18: =C18/E18 -> 11.99 | H18: 9.5 | I18: 11.11 | J18: 16.778816 | K18: 11.989967 | L18: 15.882903 | M18: 16.060895 | O18: WH has low outlier proposal. | Q18: Leave as budgeted
A19: Insulation | B19: =C19/$C$29 -> 0.01318095 | C19: =VLOOKUP(A19,'LEVEL 2'!$A$14:$K$317,11,FALSE) -> 906427.5 | D19: SF (Bldg) | E19: =$F$4 -> 362571 | F19: =C19/E19 -> 2.5 | H19: 2.3794882 | I19: 2.5 | J19: 2.5423113 | K19: 2.6983715 | L19: 2.2715182 | M19: 2.5011406 | Q19: Leave as budgeted
A20: Fire Alarm / Two Way Comm AOR | B20: =C20/$C$29 -> 0.010202181 | C20: =VLOOKUP(A20,'LEVEL 2'!$A$14:$K$317,11,FALSE) -> 701583.54 | D20: SF (Bldg) | E20: =$F$4 -> 362571 | F20: =C20/E20 -> 1.9350239 | H20: 2.25 | I20: 1.3350213 | J20: 1.977434 | K20: 1.6733483 | L20: 1.94 | M20: 1.553436 | O20: Henderson has signicant higher permit fees | Q20: Leave as budgeted
A21: Site Landscaping | B21: =C21/$C$29 -> 0.041404993 | C21: =VLOOKUP(A21,'LEVEL 2'!$A$14:$K$317,11,FALSE) -> 2847338.3 | D21: Site SF | E21: ='Assumptions & Takeoffs'!E13 -> 316370.92 | F21: =C21/$E$21 -> 9 | H21: 7.5062348 | I21: 13.681367 | J21: 10.5 | K21: 12.007558 | L21: 13.483701 | M21: 21.389001 | O21: Selected a budget cost/SF in between WH and Bruner. | Q21: Leave as budgeted
A22: Stucco | B22: =C22/$C$29 -> 0.013823863 | C22: =VLOOKUP(A22,'LEVEL 2'!$A$14:$K$317,11,FALSE) -> 950639.3 | D22: SY (Bldg) | E22: ='Assumptions & Takeoffs'!B20 -> 23863.34 | F22: =C22/E22 -> 39.836808 | H22: 39.311357 | I22: 39.836808 | J22: 39.371016 | K22: 40.818674 | L22: 42.234692 | M22: 46.688382 | Q22: Leave as budgeted
A23: Counter Tops Units | B23: =C23/$C$29 -> 0.0081535949 | C23: =VLOOKUP(A23,'LEVEL 2'!$A$14:$K$317,11,FALSE) -> 560706.36 | D23: Unit | E23: =$F$3 -> 363 | F23: =C23/E23 -> 1544.6456 | H23: 2157.06 | I23: 1868.4433 | J23: 1100 | K23: 1724 | L23: 1551.7283 | M23: 1600.2513 | O23: WH has more countertops with secondary bathrooms. | Q23: Increase to Bruner
A24: Lightweight Concrete | B24: =C24/$C$29 -> 0.0070023825 | C24: =VLOOKUP(A24,'LEVEL 2'!$A$14:$K$317,11,FALSE) -> 481539.8 | D24: LW SF | E24: ='Assumptions & Takeoffs'!E14 -> 171978.5 | F24: =C24/E24 -> 2.8 | H24: 2.6 | I24: 2.8 | J24: 2.9324031 | K24: 2.9421304 | L24: 1.2965678 | M24: 1.1 | Q24: Leave as budgeted
A25: Pools and Spas | B25: =C25/$C$29 -> 0.004230626 | C25: =VLOOKUP(A25,'LEVEL 2'!$A$14:$K$317,11,FALSE) -> 290931.67 | D25: LS | E25: 1 | F25: =C25/E25 -> 290931.67 | H25: 253813.33 | I25: 249085 | J25: N/A | K25: 245000 | L25: 228710 | M25: 208310 | O25: Budgeted in the event a second spa is designed. | Q25: Leave as budgeted
A26: Painting | B26: =C26/$C$29 -> 0.010439313 | C26: =VLOOKUP(A26,'LEVEL 2'!$A$14:$K$317,11,FALSE) -> 717890.58 | D26: SF (Bldg) | E26: =$F$4 -> 362571 | F26: =C26/E26 -> 1.98 | H26: 1.92 | I26: 1.58 | J26: 2.0533616 | K26: 1.8370925 | L26: 2.0978638 | M26: 1.9319964 | Q26: Leave as budgeted
A27: Roofing | B27: =C27/$C$29 -> 0.018576727 | C27: =VLOOKUP(A27,'LEVEL 2'!$A$14:$K$317,11,FALSE) -> 1277484.3 | D27: Square | E27: ='Assumptions & Takeoffs'!B19 -> 2143.43 | F27: =C27/E27 -> 596 | H27: 573 | I27: 596 | J27: 491.39689 | K27: 603.3984 | L27: 598.38652 | M27: 535.7424 | Q27: Leave as budgeted
A28: Fire Pump | B28: =C28/$C$29 -> 0.0018177061 | C28: =VLOOKUP(A28,'LEVEL 2'!$A$14:$K$317,11,FALSE) -> 125000 | D28: LS | E28: 1 | F28: =C28 -> 125000 | H28: 160560 | I28: 103700 | J28: N/A | K28: =133300 -> 133300 | L28: 160560 | M28: =120800 -> 120800 | Q28: Leave as budgeted
A29: Total Hard Costs (Level 2) | C29: ='LEVEL 2'!K2 -> 68767994 | D29: GSF | E29: =$F$4 -> 362571 | F29: =C29/E29 -> 189.66766
A31: Total Hard Costs (Level 2.1) | C31: ='LEVEL 2.1'!K2 -> 68005169
A32: Variance | C32: =C29-C31 -> 762825.28

Sheet Division Comparison
A1: Project Details | B1: Level 1.2 | D1: Level 2 | F1: Variance
A2: No Units | B2: ='LEVEL 1.2 BUDGET'!N9 -> 363 | D2: ='LEVEL 2'!N9 -> 363 | F2: =D2-B2 -> 0
A3: 1 Br - 1 Ba | B3: ='LEVEL 1.2 BUDGET'!N5 -> 218 | D3: ='LEVEL 2'!N5 -> 218 | F3: =D3-B3 -> 0
A4: 2 Br - 1 Ba | B4: ='LEVEL 1.2 BUDGET'!N6 -> 145 | D4: ='LEVEL 2'!N6 -> 145 | F4: =D4-B4 -> 0
A6: Parking Spaces | B6: ='LEVEL 1.2 BUDGET'!S8 -> 457 | D6: ='LEVEL 2'!S8 -> 457 | F6: =D6-B6 -> 0
A7: Building SF | B7: ='LEVEL 1.2 BUDGET'!B8 -> 362571 | D7: ='LEVEL 2'!B8 -> 362571 | F7: =D7-B7 -> 0 | G7: =F7/B7 -> 0
A8: Building Efficiency | B8: ='LEVEL 1.2 BUDGET'!K8 -> 0.78175861 | D8: ='LEVEL 2'!K8 -> 0.78175861 | F8: =D8-B8 -> 0
A10: Total Cost | B10: ='LEVEL 1.2 BUDGET'!K2 -> 68871988 | D10: ='LEVEL 2'!K2 -> 68767994 | F10: =B10-D10 -> 103993.77
A11: Cost Per SF | B11: =B10/B7 -> 189.95449 | D11: =D10/D7 -> 189.66766 | F11: 0
A12: Cost Per Unit | B12: =B10/B2 -> 189729.99 | D12: =D10/D2 -> 189443.51 | F12: 0
G14: 0.05
A15: Description | B15: Level 1.2 | D15: Level 2 | F15: Variance | G15: % Change | I15: Description / Details
A16: General Requirements | B16: =VLOOKUP($A16,'LEVEL 1.2 BUDGET'!$A$15:$L$318,12,FALSE) -> 3338816 | D16: =VLOOKUP($A16,'LEVEL 2'!$A$15:$L$318,12,FALSE) -> 3331957.1 | F16: =B16-D16 -> 6858.9165 | G16: =F16/B16 -> 0.002054296
A17: Existing Conditions | B17: =VLOOKUP(A17,'LEVEL 1.2 BUDGET'!$A$15:$L$318,12,FALSE) -> 16000 | D17: =VLOOKUP($A17,'LEVEL 2'!$A$15:$L$318,12,FALSE) -> 16000 | F17: =B17-D17 -> 0 | G17: =F17/B17 -> 0
A18: Concrete | B18: =VLOOKUP(A18,'LEVEL 1.2 BUDGET'!$A$15:$L$318,12,FALSE) -> 2785657.9 | D18: =VLOOKUP($A18,'LEVEL 2'!$A$15:$L$318,12,FALSE) -> 2775836.2 | F18: =B18-D18 -> 9821.7124 | G18: =F18/B18 -> 0.0035258143
A19: Masonry | B19: =VLOOKUP(A19,'LEVEL 1.2 BUDGET'!$A$15:$L$318,12,FALSE) -> 255200 | D19: =VLOOKUP($A19,'LEVEL 2'!$A$15:$L$318,12,FALSE) -> 128000 | F19: =B19-D19 -> 127200 | G19: =F19/B19 -> 0.4984326
A20: Metals | B20: =VLOOKUP(A20,'LEVEL 1.2 BUDGET'!$A$15:$L$318,12,FALSE) -> 459954 | D20: =VLOOKUP($A20,'LEVEL 2'!$A$15:$L$318,12,FALSE) -> 474487.5 | F20: =B20-D20 -> -14533.5 | G20: =F20/B20 -> -0.031597725
A21: Wood, Plastics, & Composites | B21: =VLOOKUP(A21,'LEVEL 1.2 BUDGET'!$A$15:$L$318,12,FALSE) -> 8327162.4 | D21: =VLOOKUP($A21,'LEVEL 2'!$A$15:$L$318,12,FALSE) -> 8515537.8 | F21: =B21-D21 -> -188375.39 | G21: =F21/B21 -> -0.022621799
A22: Thermal & Moisture Protection | B22: =VLOOKUP(A22,'LEVEL 1.2 BUDGET'!$A$15:$L$318,12,FALSE) -> 2157341.9 | D22: =VLOOKUP($A22,'LEVEL 2'!$A$15:$L$318,12,FALSE) -> 2366346 | F22: =B22-D22 -> -209004.07 | G22: =F22/B22 -> -0.096880362
A23: Openings | B23: =VLOOKUP(A23,'LEVEL 1.2 BUDGET'!$A$15:$L$318,12,FALSE) -> 597923 | D23: =VLOOKUP($A23,'LEVEL 2'!$A$15:$L$318,12,FALSE) -> 679200 | F23: =B23-D23 -> -81277 | G23: =F23/B23 -> -0.13593222
A24: Finishes | B24: =VLOOKUP(A24,'LEVEL 1.2 BUDGET'!$A$15:$L$318,12,FALSE) -> 5644662.8 | D24: =VLOOKUP($A24,'LEVEL 2'!$A$15:$L$318,12,FALSE) -> 5963501.4 | F24: =B24-D24 -> -318838.54 | G24: =F24/B24 -> -0.056484957
A25: Specialties | B25: =VLOOKUP(A25,'LEVEL 1.2 BUDGET'!$A$15:$L$318,12,FALSE) -> 468431 | D25: =VLOOKUP($A25,'LEVEL 2'!$A$15:$L$318,12,FALSE) -> 525785 | F25: =B25-D25 -> -57354 | G25: =F25/B25 -> -0.12243852
A26: Equipment | B26: =VLOOKUP(A26,'LEVEL 1.2 BUDGET'!$A$15:$L$318,12,FALSE) -> 1168905 | D26: =VLOOKUP($A26,'LEVEL 2'!$A$15:$L$318,12,FALSE) -> 1379826.2 | F26: =B26-D26 -> -210921.15 | G26: =F26/B26 -> -0.18044336
A27: Furnishings | B27: =VLOOKUP(A27,'LEVEL 1.2 BUDGET'!$A$15:$L$318,12,FALSE) -> 2059949 | D27: =VLOOKUP($A27,'LEVEL 2'!$A$15:$L$318,12,FALSE) -> 1826689.4 | F27: =B27-D27 -> 233259.64 | G27: =F27/B27 -> 0.11323564
A28: Special Construction | B28: =VLOOKUP(A28,'LEVEL 1.2 BUDGET'!$A$15:$L$318,12,FALSE) -> 907561 | D28: =VLOOKUP($A28,'LEVEL 2'!$A$15:$L$318,12,FALSE) -> 953492.67 | F28: =B28-D28 -> -45931.667 | G28: =F28/B28 -> -0.050610005
A29: Trash Chute | B29: =VLOOKUP(A29,'LEVEL 1.2 BUDGET'!$A$15:$L$318,12,FALSE) -> 0 | D29: =VLOOKUP($A29,'LEVEL 2'!$A$15:$L$318,12,FALSE) -> 0 | F29: =B29-D29 -> 0 | G29: =IF(B29=0,0,F29/B29) -> 0
A30: Conveying Equipment | B30: =VLOOKUP(A30,'LEVEL 1.2 BUDGET'!$A$15:$L$318,12,FALSE) -> 439560 | D30: =VLOOKUP($A30,'LEVEL 2'!$A$15:$L$318,12,FALSE) -> 496797 | F30: =B30-D30 -> -57237 | G30: =F30/B30 -> -0.13021431
A31: Fire Suppression | B31: =VLOOKUP(A31,'LEVEL 1.2 BUDGET'!$A$15:$L$318,12,FALSE) -> 1110813.1 | D31: =VLOOKUP($A31,'LEVEL 2'!$A$15:$L$318,12,FALSE) -> 1110813.1 | F31: =B31-D31 -> 0 | G31: =F31/B31 -> 0
A32: Plumbing | B32: =VLOOKUP(A32,'LEVEL 1.2 BUDGET'!$A$15:$L$318,12,FALSE) -> 3688547 | D32: =VLOOKUP($A32,'LEVEL 2'!$A$15:$L$318,12,FALSE) -> 3688547 | F32: =B32-D32 -> 0 | G32: =F32/B32 -> 0
A33: HVAC | B33: =VLOOKUP(A33,'LEVEL 1.2 BUDGET'!$A$15:$L$318,12,FALSE) -> 3588866 | D33: =VLOOKUP($A33,'LEVEL 2'!$A$15:$L$318,12,FALSE) -> 3588866 | F33: =B33-D33 -> 0 | G33: =F33/B33 -> 0
A34: Electrical | B34: =VLOOKUP(A34,'LEVEL 1.2 BUDGET'!$A$15:$L$318,12,FALSE) -> 4194934 | D34: =VLOOKUP($A34,'LEVEL 2'!$A$15:$L$318,12,FALSE) -> 4455520.8 | F34: =B34-D34 -> -260586.83 | G34: =F34/B34 -> -0.062119411
A35: Communications | B35: =VLOOKUP(A35,'LEVEL 1.2 BUDGET'!$A$15:$L$318,12,FALSE) -> 166956.95 | D35: =VLOOKUP($A35,'LEVEL 2'!$A$15:$L$318,12,FALSE) -> 166956.95 | F35: =B35-D35 -> 0 | G35: =F35/B35 -> 0
A36: Electronic Safety & Security | B36: =VLOOKUP(A36,'LEVEL 1.2 BUDGET'!$A$15:$L$318,12,FALSE) -> 848751.36 | D36: =VLOOKUP($A36,'LEVEL 2'!$A$15:$L$318,12,FALSE) -> 1047129.9 | F36: =B36-D36 -> -198378.54 | G36: =F36/B36 -> -0.23372986
A37: Earthwork | B37: =VLOOKUP(A37,'LEVEL 1.2 BUDGET'!$A$15:$L$318,12,FALSE) -> 1546728 | D37: =VLOOKUP($A37,'LEVEL 2'!$A$15:$L$318,12,FALSE) -> 1777422.5 | F37: =B37-D37 -> -230694.5 | G37: =F37/B37 -> -0.14915001
A38: Exterior Improvements | B38: =VLOOKUP(A38,'LEVEL 1.2 BUDGET'!$A$15:$L$318,12,FALSE) -> 6907826.6 | D38: =VLOOKUP($A38,'LEVEL 2'!$A$15:$L$318,12,FALSE) -> 5896648.9 | F38: =B38-D38 -> 1011177.6 | G38: =F38/B38 -> 0.14638145
A39: Utilities | B39: =VLOOKUP(A39,'LEVEL 1.2 BUDGET'!$A$15:$L$318,12,FALSE) -> 3305385 | D39: =VLOOKUP($A39,'LEVEL 2'!$A$15:$L$318,12,FALSE) -> 2941601.8 | F39: =B39-D39 -> 363783.17 | G39: =F39/B39 -> 0.11005773
A40: Bridge | B40: ='LEVEL 1.2 BUDGET'!L271 -> 1288500 | D40: ='LEVEL 2'!L272 -> 1488500 | F40: =B40-D40 -> -200000 | G40: =F40/B40 -> -0.15521925
A41: Transportation | B41: =VLOOKUP(A41,'LEVEL 1.2 BUDGET'!$A$15:$L$318,12,FALSE) -> 7500 | D41: =VLOOKUP($A41,'LEVEL 2'!$A$15:$L$318,12,FALSE) -> 7500 | F41: =B41-D41 -> 0 | G41: =F41/B41 -> 0
A42: Electrical Power Generation | B42: =VLOOKUP(A42,'LEVEL 1.2 BUDGET'!$A$15:$L$318,12,FALSE) -> 1077434 | D42: =VLOOKUP($A42,'LEVEL 2'!$A$15:$L$318,12,FALSE) -> 1077434 | F42: =B42-D42 -> 0 | G42: =F42/B42 -> 0
A43: Field Surveys, Staking | B43: =VLOOKUP(A43,'LEVEL 1.2 BUDGET'!$A$15:$L$318,12,FALSE) -> 626535.45 | D43: =VLOOKUP($A43,'LEVEL 2'!$A$15:$L$318,12,FALSE) -> 502425 | F43: =B43-D43 -> 124110.45 | G43: =F43/B43 -> 0.19809007
A44: Bid Risk | B44: ='LEVEL 1.2 BUDGET'!L290 -> 1112398.7 | D44: ='LEVEL 2'!L291 -> 1110652.4 | F44: =B44-D44 -> 1746.3055 | G44: =F44/B44 -> 0.0015698558
A45: FFE | B45: =VLOOKUP(A45,'LEVEL 1.2 BUDGET'!$A$15:$L$318,12,FALSE) -> 1972848 | D45: =VLOOKUP($A45,'LEVEL 2'!$A$15:$L$318,12,FALSE) -> 1681753.2 | F45: =B45-D45 -> 291094.84 | G45: =F45/B45 -> 0.14755057
A46: Construction Contingency | B46: ='LEVEL 1.2 BUDGET'!L307 -> 2782346.7 | D46: ='LEVEL 2'!L308 -> 2776630.9 | F46: =B46-D46 -> 5715.7637 | G46: =F46/B46 -> 0.002054296
A47: Sub Bonds | B47: ='LEVEL 1.2 BUDGET'!L309 -> 945538.87 | D47: ='LEVEL 2'!L310 -> 944054.51 | F47: =B47-D47 -> 1484.3597 | G47: =F47/B47 -> 0.0015698558
A48: GL Insurance | B48: ='LEVEL 1.2 BUDGET'!L313 -> 621199.33 | D48: =VLOOKUP($A48,'LEVEL 2'!$A$15:$L$318,12,FALSE) -> 620326.18 | F48: =B48-D48 -> 873.15275 | G48: =F48/B48 -> 0.0014055919
A49: OH & Contractor Fee | B49: =VLOOKUP(A49,'LEVEL 1.2 BUDGET'!$A$15:$L$318,12,FALSE) -> 4451754.7 | D49: =VLOOKUP($A49,'LEVEL 2'!$A$15:$L$318,12,FALSE) -> 4451754.7 | F49: =B49-D49 -> 0 | G49: =F49/B49 -> 0
A50: Total Hard Cost | B50: =SUM(B16:B49) -> 68871988 | D50: =SUM(D16:D49) -> 68767994 | F50: =SUM(F16:F49) -> 103993.77

Sheet Comparison to Projects
C3: TOTAL BUDGET | J3: TOTAL BUDGET PER UNIT | U3: Variance Per Unit
J4: ='LEVEL 1.1 BUDGET'!$E$8 -> 363 | L4: 190 | M4: 276 | N4: 208 | O4: 195 | U4: 190 | V4: 276 | W4: 208 | X4: 195
A5: Hard Cost Divisions | C5: Robindale | E5: Torrey Pines | F5: Decatur | G5: Russell IV | H5: Pebble | J5: Robindale | L5: Torrey Pines | M5: Decatur | N5: Russell IV | O5: Pebble | Q5: AVE | S5: Var to Comp | U5: Torrey Pines | V5: Decatur | W5: Russell IV | X5: Pebble
A6: Existing Conditions | C6: =VLOOKUP(A6,'LEVEL 2'!$A$13:$L$319,12,FALSE) -> 16000 | E6: 3500 | F6: 3500 | G6: 1625 | H6: 4640 | J6: =C6/'LEVEL 1.1 BUDGET'!$E$8 -> 44.077135 | L6: =E6/L$4 -> 18.421053 | M6: =F6/M$4 -> 12.681159 | N6: =G6/N$4 -> 7.8125 | O6: =H6/O$4 -> 23.794872 | Q6: =AVERAGE(L6:O6) -> 15.677396 | S6: =Q6-J6 -> -28.399739 | U6: =$J6-L6 -> 25.656082 | V6: =$J6-M6 -> 31.395976 | W6: =$J6-N6 -> 36.264635 | X6: =$J6-O6 -> 20.282263
A7: Concrete | C7: =VLOOKUP(A7,'LEVEL 2'!$A$13:$L$319,12,FALSE) -> 2775836.2 | E7: 855751.3 | F7: 2000752.3 | G7: 872411 | H7: 923880.71 | J7: =C7/'LEVEL 1.1 BUDGET'!$E$8 -> 7646.9316 | L7: =E7/L$4 -> 4503.9542 | M7: =F7/M$4 -> 7249.1027 | N7: =G7/N$4 -> 4194.2837 | O7: =H7/O$4 -> 4737.8498 | Q7: =AVERAGE(L7:O7) -> 5171.2976 | S7: =Q7-J7 -> -2475.634 | U7: =$J7-L7 -> 3142.9774 | V7: =$J7-M7 -> 397.82891 | W7: =$J7-N7 -> 3452.6479 | X7: =$J7-O7 -> 2909.0818
A8: Masonry | C8: =VLOOKUP(A8,'LEVEL 2'!$A$13:$L$319,12,FALSE) -> 128000 | E8: 154110 | F8: 177000 | G8: 172404.61 | H8: 113987.04 | J8: =C8/'LEVEL 1.1 BUDGET'!$E$8 -> 352.61708 | L8: =E8/L$4 -> 811.10526 | M8: =F8/M$4 -> 641.30435 | N8: =G8/N$4 -> 828.86832 | O8: =H8/O$4 -> 584.54892 | Q8: =AVERAGE(L8:O8) -> 716.45671 | S8: =Q8-J8 -> 363.83963 | U8: =$J8-L8 -> -458.48818 | V8: =$J8-M8 -> -288.68727 | W8: =$J8-N8 -> -476.25124 | X8: =$J8-O8 -> -231.93184
A9: Metals | C9: =VLOOKUP(A9,'LEVEL 2'!$A$13:$L$319,12,FALSE) -> 474487.5 | E9: 288724 | F9: 318241 | G9: 282542 | H9: 293620 | J9: =C9/'LEVEL 1.1 BUDGET'!$E$8 -> 1307.1281 | L9: =E9/L$4 -> 1519.6 | M9: =F9/M$4 -> 1153.0471 | N9: =G9/N$4 -> 1358.375 | O9: =H9/O$4 -> 1505.7436 | Q9: =AVERAGE(L9:O9) -> 1384.1914 | S9: =Q9-J9 -> 77.063324 | U9: =$J9-L9 -> -212.4719 | V9: =$J9-M9 -> 154.081 | W9: =$J9-N9 -> -51.246901 | X9: =$J9-O9 -> -198.61549
A10: Wood, Plastics, & Composites | C10: =VLOOKUP(A10,'LEVEL 2'!$A$13:$L$319,12,FALSE) -> 8515537.8 | E10: 4782473.5 | F10: 7142611.9 | G10: 5373532.6 | H10: 4318539.1 | J10: =C10/'LEVEL 1.1 BUDGET'!$E$8 -> 23458.782 | L10: =E10/L$4 -> 25170.913 | M10: =F10/M$4 -> 25879.029 | N10: =G10/N$4 -> 25834.291 | O10: =H10/O$4 -> 22146.355 | Q10: =AVERAGE(L10:O10) -> 24757.647 | S10: =Q10-J10 -> 1298.8652 | U10: =$J10-L10 -> -1712.1314 | V10: =$J10-M10 -> -2420.247 | W10: =$J10-N10 -> -2375.5095 | X10: =$J10-O10 -> 1312.4272
A11: Thermal & Moisture Protection | C11: =VLOOKUP(A11,'LEVEL 2'!$A$13:$L$319,12,FALSE) -> 2366346 | E11: 886843.75 | F11: 1514404.5 | G11: 925801 | H11: 815319.47 | J11: =C11/'LEVEL 1.1 BUDGET'!$E$8 -> 6518.8595 | L11: =E11/L$4 -> 4667.5987 | M11: =F11/M$4 -> 5486.9728 | N11: =G11/N$4 -> 4450.9663 | O11: =H11/O$4 -> 4181.1255 | Q11: =AVERAGE(L11:O11) -> 4696.6658 | S11: =Q11-J11 -> -1822.1937 | U11: =$J11-L11 -> 1851.2608 | V11: =$J11-M11 -> 1031.8867 | W11: =$J11-N11 -> 2067.8932 | X11: =$J11-O11 -> 2337.734
A12: Openings | C12: =VLOOKUP(A12,'LEVEL 2'!$A$13:$L$319,12,FALSE) -> 679200 | E12: 462292.91 | F12: 695411 | G12: 448928.79 | H12: 404995.16 | J12: =C12/'LEVEL 1.1 BUDGET'!$E$8 -> 1871.0744 | L12: =E12/L$4 -> 2433.1206 | M12: =F12/M$4 -> 2519.6051 | N12: =G12/N$4 -> 2158.3115 | O12: =H12/O$4 -> 2076.8983 | Q12: =AVERAGE(L12:O12) -> 2296.9838 | S12: =Q12-J12 -> 425.90947 | U12: =$J12-L12 -> -562.0462 | V12: =$J12-M12 -> -648.53069 | W12: =$J12-N12 -> -287.23711 | X12: =$J12-O12 -> -205.82388
A13: Finishes | C13: =VLOOKUP(A13,'LEVEL 2'!$A$13:$L$319,12,FALSE) -> 5963501.4 | E13: 3275902.9 | F13: 4733364.5 | G13: 3225416.7 | H13: 2994978.9 | J13: =C13/'LEVEL 1.1 BUDGET'!$E$8 -> 16428.378 | L13: =E13/L$4 -> 17241.594 | M13: =F13/M$4 -> 17149.871 | N13: =G13/N$4 -> 15506.811 | O13: =H13/O$4 -> 15358.866 | Q13: =AVERAGE(L13:O13) -> 16314.286 | S13: =Q13-J13 -> -114.09277 | U13: =$J13-L13 -> -813.21595 | V13: =$J13-M13 -> -721.49297 | W13: =$J13-N13 -> 921.56751 | X13: =$J13-O13 -> 1069.5125
A14: Specialties | C14: =VLOOKUP(A14,'LEVEL 2'!$A$13:$L$319,12,FALSE) -> 525785 | E14: 207648 | F14: 271520.35 | G14: 177129.21 | H14: 183305.17 | J14: =C14/'LEVEL 1.1 BUDGET'!$E$8 -> 1448.4435 | L14: =E14/L$4 -> 1092.8842 | M14: =F14/M$4 -> 983.76939 | N14: =G14/N$4 -> 851.58274 | O14: =H14/O$4 -> 940.02651 | Q14: =AVERAGE(L14:O14) -> 967.06571 | S14: =Q14-J14 -> -481.37781 | U14: =$J14-L14 -> 355.55932 | V14: =$J14-M14 -> 464.67414 | W14: =$J14-N14 -> 596.86079 | X14: =$J14-O14 -> 508.41701
A15: Equipment | C15: =VLOOKUP(A15,'LEVEL 2'!$A$13:$L$319,12,FALSE) -> 1379826.2 | E15: 555940 | F15: 838575.4 | G15: 586774 | H15: 619814 | J15: =C15/'LEVEL 1.1 BUDGET'!$E$8 -> 3801.174 | L15: =E15/L$4 -> 2926 | M15: =F15/M$4 -> 3038.3167 | N15: =G15/N$4 -> 2821.0288 | O15: =H15/O$4 -> 3178.5333 | Q15: =AVERAGE(L15:O15) -> 2990.9697 | S15: =Q15-J15 -> -810.20428 | U15: =$J15-L15 -> 875.174 | V15: =$J15-M15 -> 762.85733 | W15: =$J15-N15 -> 980.14515 | X15: =$J15-O15 -> 622.64066
A16: Furnishings | C16: =VLOOKUP(A16,'LEVEL 2'!$A$13:$L$319,12,FALSE) -> 1826689.4 | E16: 1126769 | F16: 1462590.1 | G16: 1141152.8 | H16: 1036514.1 | J16: =C16/'LEVEL 1.1 BUDGET'!$E$8 -> 5032.2021 | L16: =E16/L$4 -> 5930.3632 | M16: =F16/M$4 -> 5299.2394 | N16: =G16/N$4 -> 5486.3116 | O16: =H16/O$4 -> 5315.4571 | Q16: =AVERAGE(L16:O16) -> 5507.8428 | S16: =Q16-J16 -> 475.64072 | U16: =$J16-L16 -> -898.16106 | V16: =$J16-M16 -> -267.03729 | W16: =$J16-N16 -> -454.10954 | X16: =$J16-O16 -> -283.25498
A17: Special Construction | C17: =VLOOKUP(A17,'LEVEL 2'!$A$13:$L$319,12,FALSE) -> 953492.67 | E17: 514455.07 | F17: 731169 | G17: 488086 | H17: 456527 | J17: =C17/'LEVEL 1.1 BUDGET'!$E$8 -> 2626.7016 | L17: =E17/L$4 -> 2707.6583 | M17: =F17/M$4 -> 2649.163 | N17: =G17/N$4 -> 2346.5673 | O17: =H17/O$4 -> 2341.1641 | Q17: =AVERAGE(L17:O17) -> 2511.1382 | S17: =Q17-J17 -> -115.56338 | U17: =$J17-L17 -> -80.956702 | V17: =$J17-M17 -> -22.461482 | W17: =$J17-N17 -> 280.13425 | X17: =$J17-O17 -> 285.53746
... A27: Utilities | C27: =VLOOKUP(A27,'LEVEL 2'!$A$13:$L$319,12,FALSE) -> 2941601.8 | E27: 1788881 | F27: 2288417.6 | G27: 1316600.5 | H27: 1167559.8 | J27: =C27/'LEVEL 1.1 BUDGET'!$E$8 -> 8103.5863 | L27: =E27/L$4 -> 9415.1632 | M27: =F27/M$4 -> 8291.3683 | N27: =G27/N$4 -> 6329.8101 | O27: =H27/O$4 -> 5987.4861 | Q27: =AVERAGE(L27:O27) -> 7505.9569 | S27: =Q27-J27 -> -597.62942 | U27: =$J27-L27 -> -1311.5768 | V27: =$J27-M27 -> -187.78195 | W27: =$J27-N27 -> 1773.7762 | X27: =$J27-O27 -> 2116.1003
A28: Brigde Over Duct Creek Wash | C28: =VLOOKUP(A28,'LEVEL 2'!$A$13:$L$319,12,FALSE) -> 1488500 | E28: 0 | F28: 0 | G28: 0 | H28: 0 | J28: =C28/'LEVEL 1.1 BUDGET'!$E$8 -> 4100.551 | L28: 0 | M28: 0 | N28: 0 | O28: 0 | Q28: =AVERAGE(L28:O28) -> 0 | S28: =Q28-J28 -> -4100.551 | U28: =$J28-L28 -> 4100.551 | V28: =$J28-M28 -> 4100.551 | W28: =$J28-N28 -> 4100.551 | X28: =$J28-O28 -> 4100.551
A29: Transportation | C29: =VLOOKUP(A29,'LEVEL 2'!$A$13:$L$319,12,FALSE) -> 7500 | E29: 7500 | F29: 15000 | G29: 0 | H29: 15000 | J29: =C29/'LEVEL 1.1 BUDGET'!$E$8 -> 20.661157 | L29: =E29/L$4 -> 39.473684 | M29: =F29/M$4 -> 54.347826 | N29: =G29/N$4 -> 0 | O29: =H29/O$4 -> 76.923077 | Q29: =AVERAGE(L29:O29) -> 42.686147 | S29: =Q29-J29 -> 22.02499 | U29: =$J29-L29 -> -18.812527 | V29: =$J29-M29 -> -33.686669 | W29: =$J29-N29 -> 20.661157 | X29: =$J29-O29 -> -56.26192
A30: Electrical Power Generation | C30: =VLOOKUP(A30,'LEVEL 2'!$A$13:$L$319,12,FALSE) -> 1077434 | E30: 707152.38 | F30: 178738.2 | G30: 444320.52 | H30: 202992.5 | J30: =C30/'LEVEL 1.1 BUDGET'!$E$8 -> 2968.1377 | L30: =E30/L$4 -> 3721.8546 | M30: =F30/M$4 -> 647.60217 | N30: =G30/N$4 -> 2136.1563 | O30: =H30/O$4 -> 1040.9872 | Q30: =AVERAGE(L30:O30) -> 1886.6501 | S30: =Q30-J30 -> -1081.4877 | U30: =$J30-L30 -> -753.71689 | V30: =$J30-M30 -> 2320.5356 | W30: =$J30-N30 -> 831.98139 | X30: =$J30-O30 -> 1927.1506
A31: Field Surveys, Staking | C31: =VLOOKUP(A31,'LEVEL 2'!$A$13:$L$319,12,FALSE) -> 502425 | E31: 149353.1 | F31: 440850 | G31: 148310 | H31: 217223.1 | J31: =C31/'LEVEL 1.1 BUDGET'!$E$8 -> 1384.0909 | L31: =E31/L$4 -> 786.06895 | M31: =F31/M$4 -> 1597.2826 | N31: =G31/N$4 -> 713.02885 | O31: =H31/O$4 -> 1113.9646 | Q31: =AVERAGE(L31:O31) -> 1052.5863 | S31: =Q31-J31 -> -331.50465 | U31: =$J31-L31 -> 598.02196 | V31: =$J31-M31 -> -213.1917 | W31: =$J31-N31 -> 671.06206 | X31: =$J31-O31 -> 270.12629
A32: FFE | C32: =VLOOKUP(A32,'LEVEL 2'!$A$13:$L$319,12,FALSE) -> 1681753.2 | E32: 1161406.5 | F32: 939893.04 | G32: 926137.36 | H32: 960082.51 | J32: =C32/'LEVEL 1.1 BUDGET'!$E$8 -> 4632.9288 | L32: =E32/L$4 -> 6112.666 | M32: =F32/M$4 -> 3405.4096 | N32: =G32/N$4 -> 4452.5835 | O32: =H32/O$4 -> 4923.5001 | Q32: =AVERAGE(L32:O32) -> 4723.5398 | S32: =Q32-J32 -> 90.61094 | U32: =$J32-L32 -> -1479.7371 | V32: =$J32-M32 -> 1227.5192 | W32: =$J32-N32 -> 180.34536 | X32: =$J32-O32 -> -290.57123
A33: Subtotal | C33: =SUM(C6:C32) -> 55532618 | E33: =SUM(E6:E32) -> 27364988 | F33: =SUM(F6:F32) -> 39636267 | G33: =SUM(G6:G32) -> 27403468 | H33: =SUM(H6:H32) -> 24345543 | J33: =C33/'LEVEL 1.1 BUDGET'!$E$8 -> 152982.42 | L33: =E33/L$4 -> 144026.25 | M33: =F33/M$4 -> 143609.66 | N33: =G33/N$4 -> 131747.44 | O33: =H33/O$4 -> 124848.94 | Q33: =AVERAGE(L33:O33) -> 136058.07 | S33: =Q33-J33 -> -16924.345 | U33: =$J33-L33 -> 8956.1671 | V33: =$J33-M33 -> 9372.7577 | W33: =$J33-N33 -> 21234.975 | X33: =$J33-O33 -> 28133.482
A35: General Requirements | C35: ='LEVEL 2'!L15 -> 3331957.1
A36: Bid Risk | C36: ='LEVEL 2'!L291 -> 1110652.4 | H36: Slab | J36: ='Assumptions & Takeoffs'!B11 -> 177268 | L36: 46943
A37: Construction Contingency | C37: ='LEVEL 2'!L308 -> 2776630.9 | H37: Slab Per Unit | J37: =J36/J4 -> 488.3416 | L37: =L36/L4 -> 247.06842
A38: Sub Bonds | C38: ='LEVEL 2'!L310 -> 944054.51 | L38: =(J37-L37)/J37 -> 0.4940664
A39: GL Insurance | C39: ='LEVEL 2'!L314 -> 620326.18
A40: Contractor Fee & OH | C40: ='LEVEL 2'!L317 -> 4451754.7 | H40: Roof | J40: ='Assumptions & Takeoffs'!B19 -> 2143.43 | L40: 539
A41: Total Hard Cost Budget | C41: =SUM(C33:C40) -> 68767994 | H41: Roof SQ Per Unit | J41: =J40/J4 -> 5.9047658 | L41: =L40/L4 -> 2.8368421
L42: =(J41-L41)/J41 -> 0.51956738
H44: Acres | J44: ='LEVEL 2'!B9 -> 17.35 | L44: 5
H45: Unit / Acre | J45: =J4/J44 -> 20.92219 | L45: =L4/L44 -> 38

Sheet LEVEL 1.2 BUDGET
A1: Project Details
A2: Project | B2: Robindale & 215 | J2: Total Cost | K2: =L318 -> 68871988 | M2: Unit Breakdown | Q2: Parking
A3: Budget Level | B3: Level 1 | M3: Unit Type | N3: Number | O3: % | Q3: Cover Parking | S3: 286 | AE3: Railing Estimate | AI3: Building 3 | AJ3: =21*7 -> 147 | AL3: Stucco | AP3: Building 3 | AQ3: =15000+6560+6500+15400+4570+4635+4540+4250 -> 61455
A4: Product | B4: Senior | J4: Cost Per Unit | K4: =K2/N9 -> 189729.99 | M4: Studios | N4: 0 | O4: =N4/$N$9 -> 0 | Q4: Cover Accesible Parking | AE4: Building 1 | AJ4: =14*7 -> 98 | AL4: Building 1
A5: Start Date | M5: 1 Br - 1 Ba | N5: ='Assumptions & Takeoffs'!B4+'Assumptions & Takeoffs'!B5 -> 218 | O5: =N5/$N$9 -> 0.60055096 | Q5: Open Parking | S5: 157 | AE5: Northwest | AF5: =21*4+8*8+7*6 -> 190 | AJ5: =8*22 -> 176 | AL5: Northwest | AM5: 19256
A6: Timeline | B6: 30 | J6: Cost Per SF | K6: =K2/B8 -> 189.95449 | M6: 2 Br - 1 Ba | N6: ='Assumptions & Takeoffs'!B6+'Assumptions & Takeoffs'!B7 -> 145 | O6: =N6/$N$9 -> 0.39944904 | Q6: Accessible Parking | S6: 14 | AE6: Southwest | AF6: =14*4+21*2+8*6 -> 146 | AJ6: =7*10 -> 70 | AL6: Southwest | AM6: 8980
A7: Floors | B7: 2 | M7: 2 Br - 2 Ba | N7: 0 | O7: =N7/$N$9 -> 0 | Q7: Waiver | S7: 0 | AE7: Northeast | AF7: =21*2+14*2+8*6 -> 118 | AJ7: =SUM(AJ3:AJ6) -> 491 | AL7: Northeast | AM7: 8850
A8: Bldg. SF | B8: =98509+136604+127458 -> 362571 | J8: Efficiency | K8: ='Assumptions & Takeoffs'!D8/B8 -> 0.78175861 | M8: 3 Br - 2 Ba | N8: 0 | O8: =N8/$N$9 -> 0 | Q8: Total Parking Provided | S8: =SUM(S3:S7) -> 457 | AE8: Southeast | AF8: =21*2+14*8+8*12+7*8 -> 306 | AL8: Southeast | AM8: 19965
A9: Acres | B9: 17.35 | M9: Totals | N9: =SUM(N4:N8) -> 363 | O9: =N9/$N$9 -> 1 | Q9: Parking Ratio | S9: =S8/N9 -> 1.2589532 | AE9: More | AF9: =21*4+8*6 -> 132 | AG9: =SUM(AF5:AF9) -> 892 | AL9: More | AM9: =5870+6250+6290+5915 -> 24325 | AN9: =SUM(AM5:AM9) -> 81376
A10: Site SF | B10: =B9*43560 -> 755766
A11: Buildings | B11: 3 | AE11: Building 2 & 5 | AI11: Building 4 | AJ11: =14*8 -> 112 | AL11: Building 2 & 5 | AP11: Building 4 | AQ11: =5782+5760+8825+9150 -> 29517
AE12: Northwest | AJ12: =20*8 -> 160 | AL12: Northwest
A13: Description | B13: Cost Code | C13: Cost Category | D13: Sub job | E13: Source | F13: UMO | G13: Quantity | H13: U.P. | I13: Escal % | J13: Total U.P. | K13: Sub Total | L13: Total | M13: Description / Details
A14: General Requirement | B14: 01 | C14: S | F14: Mo | G14: =$B$6 -> 30 | H14: 111293.87 | I14: 0 | J14: 111293.87 | K14: =J14*G14 -> 3338816
A15: General Requirements | B15: 01 | L15: =K14 -> 3338816
A16: Potholing | B16: 02-3213 | C16: S | D16: ON-SITE | E16: Allowance | G16: 1 | H16: 16000 | I16: 0 | J16: =H16*(1+I16) -> 16000 | K16: =J16*G16 -> 16000
A17: Existing Conditions | B17: 02 | L17: =K16 -> 16000
A18: Slabs | B18: 03-3101 | C18: S | D18: BUILDING | E18: Torrey Pines | F18: SF | G18: 177658.41 | H18: 11.99 | I18: 0 | J18: =H18*(1+I18) -> 11.99 | K18: =J18*G18 -> 2130124.3 | M18: 4" over 4" slab profile.
A19: Deepened Footings | B19: 03-3101 | C19: S | D19: BUILDING | E19: N/A | J19: =H19*(1+I19) -> 0 | K19: =J19*G19 -> 0
A20: Concrete Slab Repairs | B20: 03-3101 | C20: RR | D20: BUILDING | E20: Allowance | F20: LS | G20: 1 | H20: 7500 | I20: 0 | J20: =H20*(1+I20) -> 7500 | K20: =J20*G20 -> 7500
A21: Pump House Concrete | B21: 03-3101 | C21: S | D21: PUMPHOUSE | E21: Bruner | F21: LS | G21: 1 | H21: 8500 | J21: =H21*(1+I21) -> 8500 | K21: =J21*G21 -> 8500
A22: Trash Enclosure Concrete | B22: 03-3102 | C22: S | D22: OTHER SITE | E22: Bruner | F22: EA | G22: 14 | H22: 5000 | I22: 0 | J22: =H22*(1+I22) -> 5000 | K22: =J22*G22 -> 70000
A23: Pool Area Shower Concrete | B23: 03-3105 | C23: S | D23: POOL AREA | E23: Bruner | F23: LS | G23: 1 | H23: 20200 | I23: 0 | J23: =H23*(1+I23) -> 20200 | K23: =J23*G23 -> 20200
A24: Cabana Concrete | B24: 03-3107 | C24: S | D24: POOL AREA | E24: N/A | I24: 0 | J24: =H24*(1+I24) -> 0 | K24: =J24*G24 -> 0
A25: Pool Equipment Foundation | B25: 03-3108 | C25: S | D25: POOL EQUIP | E25: Allowance | F25: LS | G25: 1 | H25: 10000 | I25: 0 | J25: =H25*(1+I25) -> 10000 | K25: =J25*G25 -> 10000
A26: Lightweight Concrete | B26: 03-3116 | C26: S | D26: BUILDING | E26: Bruner | F26: SF | G26: 177148.41 | H26: 2.8 | I26: 0 | J26: =H26*(1+I26) -> 2.8 | K26: =J26*G26 -> 496015.55 | M26: Nevada Gypsum 1" with Mat.
A27: Deck Concrete | B27: 03-5001 | C27: S | D27: BUILDING | E27: Bruner | F27: SF | G27: 2200 | H27: 19.69 | I27: 0 | J27: =H27*(1+I27) -> 19.69 | K27: =J27*G27 -> 43318 | M27: Ave between NV Gyp and Sound-Crete
A28: Concrete | B28: 03 | L28: =SUM(K18:K27) -> 2785657.9
A29: Elevator Shaft | B29: 04-2201 | C29: S | D29: BUILDING | E29: Bruner | F29: Stop | G29: ='Assumptions & Takeoffs'!B13 -> 12 | H29: 11500 | I29: 0 | J29: =H29*(1+I29) -> 11500 | K29: =J29*G29 -> 138000 | M29: Integrity proposal at Bruner (Desert is at $10k per stop)
A30: Trash Enclosure | B30: 04-2202 | C30: S | D30: OTHER SITE | E30: Bruner | F30: Count | G30: ='Assumptions & Takeoffs'!$B$14 -> 14 | H30: 7300 | I30: 0 | J30: =H30*(1+I30) -> 7300 | K30: =J30*G30 -> 102200 | M30: Integrity proposal at Bruner (Desert is at $5,600 per enclosure)
A31: Masonry Veneer | B31: 04-4301 | C31: S | D31: ON-SITE | E31: N/A | H31: 0 | J31: =H31*(1+I31) -> 0 | K31: =J31*G31 -> 0
A32: Masonry Veneer Pool Area | B32: 04-4305 | C32: S | D32: POOL AREA | E32: Allowance | F32: LS | G32: 1 | H32: 5000 | I32: 0 | J32: =H32*(1+I32) -> 5000 | K32: =J32*G32 -> 5000
A33: Pool Eq. Shower | B33: 04-4306 | C33: A | D33: POOL EQUIP | E33: Allowance | F33: LS | G33: 1 | H33: 10000 | I33: 0 | J33: =H33*(1+I33) -> 10000 | K33: =J33*G33 -> 10000
A34: Masonry | B34: 04 | L34: =SUM(K29:K33) -> 255200
A35: Structural Steel | B35: 05-1201 | C35: S | D35: BUILDING | E35: Allowance | F35: LS | G35: 1 | H35: 150000 | I35: 0 | J35: =H35*(1+I35) -> 150000 | K35: =J35*G35 -> 150000
A36: Elevator Shaft Iron | B36: 05-1202 | C36: S | D36: BUILDING | E36: Bruner | F36: Count | G36: 6 | H36: =24540/6 -> 4090 | I36: 0 | J36: =H36*(1+I36) -> 4090 | K36: =J36*G36 -> 24540
A37: Stair Handrails | B37: 05-5201 | C37: S | D37: BUILDING | E37: Bruner | F37: Flight | G37: 18 | H37: 2500 | I37: 0 | J37: =H37*(1+I37) -> 2500 | K37: =J37*G37 -> 45000
A38: Garage Stair Railings | B38: 05-5201 | C38: S | D38: BUILDING | E38: N/A | H38: 0 | I38: 0 | J38: =H38*(1+I38) -> 0 | K38: =J38*G38 -> 0
A39: Cabana Iron | B39: 05-7004 | C39: S | D39: POOL AREA | E39: N/A | H39: 0 | I39: 0 | J39: =H39*(1+I39) -> 0 | K39: =J39*G39 -> 0
A40: Pool Equipment Gate | B40: 05-7005 | C40: S | D40: POOL EQUIP | E40: Torrey Pines | F40: Count | G40: 1 | H40: 1950 | I40: 0 | J40: =H40*(1+I40) -> 1950 | K40: =J40*G40 -> 1950
A41: Iron Railings | B41: 05-7300 | C41: S | D41: BUILDING | E41: Bruner | F41: LF | G41: 1648 | H41: 92 | I41: 0 | J41: =H41*(1+I41) -> 92 | K41: 238464
A42: Cable Railings | B42: 05-7316 | C42: S | D42: COMMON AREA | E42: N/A | H42: 0 | I42: 0 | J42: =H42*(1+I42) -> 0 | K42: =J42*G42 -> 0
A43: Metals | B43: 05 | L43: =SUM(K35:K42) -> 459954
A44: Framing | B44: 06-1100 | C44: S | D44: BUILDING | E44: Bruner | F44: SF | G44: =B8 -> 362571 | H44: 18.68 | I44: 0 | J44: =H44*(1+I44) -> 18.68 | K44: =J44*G44 -> 6772826.3 | M44: Focus Framing signed off proposal at Bruner.
A45: Framing Pump House | B45: 06-1100 | C45: S | D45: PUMPHOUSE | E45: Moving Ave | F45: SF | G45: 600 | H45: =H44 -> 18.68 | I45: 0 | J45: =H45*(1+I45) -> 18.68 | K45: =J45*G45 -> 11208
A46: Framing - Crane | B46: 06-1100 | C46: S | D46: BUILDING | E46: N/A | I46: 0 | J46: =H46*(1+I46) -> 0 | K46: =J46*G46 -> 0
A47: Cabana Framing | B47: 06-1109 | C47: S | D47: COMMON AREA | E47: N/A | I47: 0 | J47: =H47*(1+I47) -> 0 | K47: =J47*G47 -> 0
A48: BBQ Framing | B48: 06-1110 | C48: S | D48: COMMON AREA | E48: Allowance | F48: LS | G48: 4 | H48: 2500 | I48: 0 | J48: =H48*(1+I48) -> 2500 | K48: =J48*G48 -> 10000
A49: Fireplace Framing | B49: 06-1111 | C49: S | D49: COMMON AREA | E49: N/A | I49: 0 | J49: =H49*(1+I49) -> 0 | K49: =J49*G49 -> 0
A50: Trellis | B50: 06-1114 | C50: S | D50: BUILDING | E50: N/A | I50: 0 | J50: =H50*(1+I50) -> 0 | K50: =J50*G50 -> 0
A51: Pool Equipment Framing | B51: 06-1114 | C51: S | D51: POOL EQUIP | E51: N/A | I51: 0 | J51: =H51*(1+I51) -> 0 | K51: =J51*G51 -> 0
A52: Finish Carpentry - Units | B52: 06-2001 | C52: S | D52: BUILDING | E52: Bruner | F52: Unit | G52: =$N$9 -> 363 | H52: 3100 | I52: 0 | J52: =H52*(1+I52) -> 3100 | K52: =J52*G52 -> 1125300 | M52: Average of 3 proposals at Bruner.
A53: Finish Carpentry - Common | B53: 06-2001 | C53: S | D53: COMMON AREA | E53: Bruner | F53: SF | G53: =B8 -> 362571 | H53: 1.1 | I53: 0 | J53: =H53*(1+I53) -> 1.1 | K53: =J53*G53 -> 398828.1 | M53: Comparable cost at Bruner.
A54: Finish Carpentry - Pump House | B54: 06-2001S | C54: S | D54: PUMPHOUSE | E54: Allowance | F54: LS | G54: 1 | H54: 4000 | I54: 0 | J54: =H54*(1+I54) -> 4000 | K54: =J54*G54 -> 4000
A55: BBQ Trim | B55: 06-2006 | C55: S | D55: COMMON AREA | E55: Allowance | F55: LS | G55: 4 | H55: 1250 | I55: 0 | J55: =H55*(1+I55) -> 1250 | K55: =J55*G55 -> 5000
A56: Shutters | B56: 06-4919 | C56: S | D56: BUILDING | E56: N/A | I56: 0 | J56: =H56*(1+I56) -> 0 | K56: =J56*G56 -> 0
A57: Wood, Plastics, & Composites | B57: 06 | L57: =SUM(K44:K56) -> 8327162.4
A58: Insulation | B58: 07-2101 | C58: S | D58: BUILDING | E58: Bruner Ave | F58: SF | G58: 362571 | H58: 2.5 | I58: 0 | J58: =H58*(1+I58) -> 2.5 | K58: =J58*G58 -> 906427.5 | M58: Red Rock proposal.
A59: Insulation - PH | B59: 07-2101 | C59: S | D59: PUMPHOUSE | E59: Allowance | F59: LS | G59: 1 | H59: 2000 | I59: 0 | J59: =H59*(1+I59) -> 2000 | K59: =J59*G59 -> 2000
A60: Roofing | B60: 07-3001 | C60: S | D60: BUILDING | E60: Torrey Pines | F60: Squares | G60: 1776.5841 | H60: 603 | I60: 0 | J60: =H60*(1+I60) -> 603 | K60: =J60*G60 -> 1071280.2
A61: Roofing - PH | B61: 07-3001 | C61: S | D61: PUMPHOUSE | E61: Allowance | F61: LS | G61: 1 | H61: 10000 | I61: 0 | J61: =H61*(1+I61) -> 10000 | K61: =J61*G61 -> 10000
A62: Cabana Roofing | B62: 07-3002 | C62: S | D62: COMMON AREA | E62: N/A | I62: 0 | J62: =H62*(1+I62) -> 0 | K62: =J62*G62 -> 0
A63: Pump House Roofing | B63: 07-3002 | C63: S | D63: PUMPHOUSE | E63: Allowance | F63: LS | G63: 1 | H63: 7500 | I63: 0 | J63: =H63*(1+I63) -> 7500 | K63: =J63*G63 -> 7500
A64: Pool Equipment Roofing | B64: 07-3003 | C64: S | D64: POOL EQUIP | E64: Allowance | F64: LS | G64: 1 | H64: 7500 | I64: 0 | J64: =H64*(1+I64) -> 7500 | K64: =J64*G64 -> 7500
A65: Trash Enclosure Cover | B65: 07-6101 | C65: S | D65: OTHER SITE | E65: Decatur | F65: Count | G65: 14 | H65: 5800 | I65: 0 | J65: =H65*(1+I65) -> 5800 | K65: =J65*G65 -> 81200
A66: Pigeon Proofing | B66: 07-7001 | C66: S | D66: BUILDING | E66: Torrey Pines | F66: SF | G66: 362571 | H66: 0.08 | I66: 0 | J66: =H66*(1+I66) -> 0.08 | K66: =J66*G66 -> 29005.68
A67: Gutters and Downspouts | B67: 07-7124 | C67: S | D67: BUILDING | E67: Torrey Pines | F67: SF | G67: 362571 | H67: 0.05 | I67: 0 | J67: =H67*(1+I67) -> 0.05 | K67: =J67*G67 -> 18128.55
A68: Roof Ladders | B68: 07-7210 | C68: S | D68: BUILDING | E68: Torrey Pines | F68: Count | G68: 6 | H68: 1550 | I68: 0 | J68: =H68*(1+I68) -> 1550 | K68: =J68*G68 -> 9300 | M68: 2 Per building
A69: Roof Access Doors | B69: 07-7233 | C69: S | D69: BUILDING | E69: Torrey Pines | F69: Count | G69: 6 | H69: 2500 | I69: 0 | J69: =H69*(1+I69) -> 2500 | K69: =J69*G69 -> 15000 | M69: 2 Per building
A70: Roof Winch | B70: 07-7250 | C70: S | D70: BUILDING | E70: N/A | I70: 0 | J70: =H70*(1+I70) -> 0 | K70: =J70*G70 -> 0
A71: Thermal & Moisture Protection | B71: 07 | L71: =SUM(K58:K70) -> 2157341.9
A72: Entry Doors | B72: 08-1001 | C72: S | D72: COMMON AREA | E72: Allowance | F72: Count | G72: 1 | H72: 8000 | I72: 0 | J72: =H72*(1+I72) -> 8000 | K72: =J72*G72 -> 8000
A73: Common Doors | B73: 08-1002 | C73: S | D73: COMMON AREA | E73: Included | I73: 0 | J73: =H73*(1+I73) -> 0 | K73: =J73*G73 -> 0
A74: Pocket Doors - 3 Panel | B74: 08-1002 | C74: S | D74: BUILDING | E74: N/A | I74: 0 | J74: =H74*(1+I74) -> 0 | K74: =J74*G74 -> 0
A75: Garage Doors | B75: 08-3619 | C75: S | D75: BUILDING | E75: N/A | I75: 0 | J75: =H75*(1+I75) -> 0 | K75: =J75*G75 -> 0
A76: Windows and Sliding Glass Doors | B76: 08-5301 | C76: S | D76: BUILDING | E76: Bruner | F76: Per Unit | G76: =$N$9 -> 363 | H76: 1381 | I76: 0 | J76: =H76*(1+I76) -> 1381 | K76: =J76*G76 -> 501303
A77: Windows Repair and Replacement | B77: 08-5301 | C77: RR | D77: BUILDING | E77: Allowance | F77: Per Unit | G77: =$N$9 -> 363 | H77: 75 | I77: 0 | J77: =H77*(1+I77) -> 75 | K77: =J77*G77 -> 27225
A78: Pool Equipment Windows | B78: 08-5303 | C78: S | D78: POOL EQUIP | E78: N/A | I78: 0 | J78: =H78*(1+I78) -> 0 | K78: =J78*G78 -> 0
A79: Pool Glass Walls | B79: 08-8001 | C79: S | D79: POOL AREA | E79: N/A | I79: 0 | J79: =H79*(1+I79) -> 0 | K79: =J79*G79 -> 0
A80: Fixed Glass | B80: 08-8002 | C80: S | D80: BUILDING | E80: N/A | I80: 0 | J80: =H80*(1+I80) -> 0 | K80: =J80*G80 -> 0
A81: Mirrors - LED | B81: 08-8301 | C81: S | D81: BUILDING | E81: N/A | I81: 0 | J81: =H81*(1+I81) -> 0 | K81: =J81*G81 -> 0
A82: Mirrors - LED Install | B82: 08-8302 | C82: S | D82: BUILDING | E82: N/A | I82: 0 | J82: =H82*(1+I82) -> 0 | K82: =J82*G82 -> 0
A83: Mirrors - Framed | B83: 08-8301 | C83: S | D83: BUILDING | E83: N/A | I83: 0 | J83: =H83*(1+I83) -> 0 | K83: =J83*G83 -> 0
A84: Mirrors - Polished Edges (Units) | B84: 08-8301 | C84: S | D84: BUILDING | E84: Pebble | F84: Unit | G84: =N9 -> 363 | H84: 165 | I84: 0 | J84: =H84*(1+I84) -> 165 | K84: =J84*G84 -> 59895
A85: Mirrors - Polished Edges (Restrooms) | B85: 08-8301 | C85: S | D85: BUILDING | E85: Allowance | F85: Count | G85: 6 | H85: 250 | I85: 0 | J85: =H85*(1+I85) -> 250 | K85: =J85*G85 -> 1500
A86: Openings | B86: 08 | L86: =SUM(K72:K85) -> 597923
A87: Cost Prep Labor | B87: 09-0101 | C87: S | D87: BUILDING | E87: N/A | I87: 0 | J87: =H87*(1+I87) -> 0 | K87: =J87*G87 -> 0
A88: Cost Prep Mat - Home Depot | B88: 09-0102 | C88: S | D88: BUILDING | E88: Allowance | F88: LS | G88: 1 | H88: 10000 | I88: 0 | J88: =H88*(1+I88) -> 10000 | K88: =J88*G88 -> 10000
A89: Clean Up - Final | B89: 09-0103 | C89: S | D89: BUILDING | E89: Torrey Pines | F89: SF | G89: 362571 | H89: 0.85 | I89: 0 | J89: =H89*(1+I89) -> 0.85 | K89: =J89*G89 -> 308185.35 | M89: Includes Dumpters
A90: Clean Up - During Construction - Labor | B90: 09-0104 | C90: S | D90: BUILDING | E90: Allowance | F90: LS | G90: 1 | H90: 75000 | I90: 0 | J90: =H90*(1+I90) -> 75000 | K90: =J90*G90 -> 75000
A91: Dumpsters | B91: 09-0113 | C91: S | D91: DUMPSTERS | E91: Allowance | F91: Unit | G91: 363 | H91: 79 | I91: 0 | J91: =H91*(1+I91) -> 79 | K91: =J91*G91 -> 28677
A92: Clean Up - Hauling Exterior | B92: 09-0121 | C92: S | D92: ON-SITE | E92: Allowance | F92: LS | G92: 1 | H92: 10000 | I92: 0 | J92: =H92*(1+I92) -> 10000 | K92: =J92*G92 -> 10000 | M92: Included in Construction Cleaning Contract.
A93: Stucco | B93: 09-2423 | C93: S | D93: BUILDING | E93: Bruner Ave | F93: SY | G93: 20647.222 | H93: 40.82 | I93: 0 | J93: =H93*(1+I93) -> 40.82 | K93: =J93*G93 -> 842819.61 | M93: Bruner proposal.
A94: Stucco - Pump House | B94: 09-2423S | C94: A | D94: PUMPHOUSE | E94: Allowance | F94: LS | G94: 1 | H94: 6000 | I94: 0 | J94: =H94*(1+I94) -> 6000 | K94: =J94*G94 -> 6000
A95: Stucco - Walls | B95: 09-2424 | C95: S | D95: POOL AREA | E95: N/A | I95: 0 | J95: =H95*(1+I95) -> 0 | K95: =J95*G95 -> 0
A96: Stucco - Pool Area | B96: 09-2428 | C96: A | D96: POOL AREA | E96: Allowance | F96: LS | G96: 1 | H96: 2000 | I96: 0 | J96: =H96*(1+I96) -> 2000 | K96: =J96*G96 -> 2000
A97: Stucco - Cabana | B97: 09-2429 | C97: S | D97: POOL AREA | E97: N/A | I97: 0 | J97: =H97*(1+I97) -> 0 | K97: =J97*G97 -> 0
A98: Stucco - Pool Equipment | B98: 09-2430 | C98: S | D98: POOL EQUIP | E98: Pebble | F98: LS | G98: 1 | H98: 5000 | I98: 0 | J98: =H98*(1+I98) -> 5000 | K98: =J98*G98 -> 5000
A99: Stucco - Repairs | B99: 09-2423A | C99: RR | D99: BUILDING | E99: Allowance | F99: LS | G99: 1 | H99: 1500 | I99: 0 | J99: =H99*(1+I99) -> 1500 | K99: =J99*G99 -> 1500
A100: Drywall | B100: 09-2905 | C100: S | D100: BUILDING | E100: Bruner | F100: SF | G100: 362571 | H100: 7.7 | I100: 0 | J100: =H100*(1+I100) -> 7.7 | K100: =J100*G100 -> 2791796.7 | M100: Wall Constructors proposal.
...

Sheet LEVEL 1.1 BUDGET
A1: Project Details | D1: Unit Breakdown | H1: Unit Matrix | N1: List of Take offs | Q1: List of Take offs | T1: List of Take offs
A2: Project | B2: Robindale &215 | D2: Unit Type | E2: Number | F2: % | H2: Unit Type | I2: Number | J2: % | K2: SF | N2: Slab SF | O2: 174940 | P2: GSF | Q2: Counter tops | R2: 0 | S2: SF | T2: Fitness Center | U2: 0 | V2: SF
A3: Budget Level | B3: Level 1 | D3: Studios | E3: 0 | F3: =E3/$E$8 -> 0 | H3: 1A | I3: 170 | J3: =I3/$I$7 -> 0.46831956 | K3: 676 | N3: Elevators | O3: 6 | P3: Count | Q3: Blinds | R3: 0 | AG3: Railing Estimate | AK3: Building 3 | AL3: =21*7 -> 147 | AN3: Stucco | AR3: Building 3 | AS3: =15000+6560+6500+15400+4570+4635+4540+4250 -> 61455
A4: Product | B4: Senior | D4: 1 Br - 1 Ba | E4: 218 | F4: =E4/$E$8 -> 0.60055096 | H4: 1B | I4: 48 | J4: =I4/$I$7 -> 0.1322314 | K4: 764 | N4: Elevators Stops | O4: =O3*2 -> 12 | P4: Count | Q4: Landscaping | R4: 331082 | S4: SF | AG4: Building 1 | AL4: =14*7 -> 98 | AN4: Building 1
A5: Start Date | B5: 46127 | D5: 2 Br - 1 Ba | E5: 145 | F5: =E5/$E$8 -> 0.39944904 | H5: 2A | I5: 127 | J5: =I5/$I$7 -> 0.34986226 | K5: 901 | N5: Trash Encl. | O5: 14 | P5: Site Plan | AG5: Northwest | AH5: =21*4+8*8+7*6 -> 190 | AL5: =8*22 -> 176 | AN5: Northwest | AO5: 19256
A6: Timeline | B6: 30 | D6: 2 Br - 2 Ba | E6: 0 | F6: =E6/$E$8 -> 0 | H6: 2B | I6: 18 | J6: =I6/$I$7 -> 0.049586777 | K6: 968 | N6: Stairs | O6: =7+6+5 -> 18 | P6: Count | Q6: 1x1 Decks | R6: =64*48 -> 3072 | S6: SF | AG6: Southwest | AH6: =14*4+21*2+8*6 -> 146 | AL6: =7*10 -> 70 | AN6: Southwest | AO6: 8980
A7: Floors | B7: 2 | D7: 3 Br - 2 Ba | E7: 0 | F7: =E7/$E$8 -> 0 | H7: Totals | I7: =SUM(I3:I6) -> 363 | J7: =I7/$I$7 -> 1 | K7: =SUMPRODUCT(I3:I6,K3:K6) -> 283443 | N7: Pool | O7: 1 | Q7: 2x1 Decks | R7: 0 | S7: SF | AG7: Northeast | AH7: =21*2+14*2+8*6 -> 118 | AL7: =SUM(AL3:AL6) -> 491 | AN7: Northeast | AO7: 8850
A8: Bldg. SF | B8: 361641 | D8: Totals | E8: =SUM(E3:E7) -> 363 | F8: =E8/$E$8 -> 1 | N8: Gym | O8: 1 | Q8: Lightweight | R8: 0 | S8: SF | AA8: 347 | AG8: Southeast | AH8: =21*2+14*8+8*12+7*8 -> 306 | AN8: Southeast | AO8: 19965
A9: Acres | B9: 17.25 | D9: Parking | N9: Iron Rail | O9: =13.5*48+1000 -> 1648 | P9: LF | Q9: Pavers | R9: 0 | S9: SF | AA9: 385 | AG9: More | AH9: =21*4+8*6 -> 132 | AI9: =SUM(AH5:AH9) -> 892 | AN9: More | AO9: =5870+6250+6290+5915 -> 24325 | AP9: =SUM(AO5:AO9) -> 81376
A10: Site SF | B10: =B9*43560 -> 751410 | D10: Cover Parking | F10: 295 | N10: Roofing | O10: =174940/100 -> 1749.4 | P10: Square | Q10: Pool Deck | R10: 0 | S10: SF | AA10: 300
A11: Buildings | B11: 3 | D11: Cover Accesible Parking | N11: Stucco | O11: =(39388+45217+40885)*0.111111+(3000*3+3000*4+3000*3)*2*0.111111 -> 20609.979 | P11: Square Yard | Q11: Pool Fence | R11: 0 | S11: LF | AG11: Building 2 & 5 | AK11: Building 4 | AL11: =14*8 -> 112 | AN11: Building 2 & 5 | AR11: Building 4 | AS11: =5782+5760+8825+9150 -> 29517
A12: Reports Available | D12: Open Parking | F12: 147 | N12: Livable Area | O12: 0 | P12: SF | Q12: Dog Park Fence | R12: 0 | S12: LF | AG12: Northwest | AL12: =20*8 -> 160 | AN12: Northwest
A13: Site Evaluation Report (GCW) | D13: Accessible Parking | F13: 14 | N13: Carports | O13: =F10 -> 295 | P13: Count | Q13: Common Bldg. 1 | R13: 0 | S13: SF | AG13: Southwest | AL13: =8*18 -> 144 | AN13: Southwest
A14: Soils Report (Nova or Universal) | D14: Waiver | F14: 0 | H14: TOTAL COST | J14: =L320 -> 69361424 | N14: Stairs Landings | O14: 0 | P14: Landings | Q14: Asphalt | R14: 0 | AG14: Northeast | AL14: =7*12 -> 84 | AN14: Northeast
A15: Alta Survey (Wallace) | D15: Total Parking Provided | F15: =SUM(F10:F14) -> 456 | H15: PER UNIT | J15: =J14/E8 -> 191078.3 | N15: Pump House | O15: 1 | P15: EA | Q15: Pavers | R15: 0 | AG15: Southeast | AH15: =21*2+14*2+8*6+7*6 -> 160 | AI15: =AH15*2 -> 320 | AL15: =SUM(AL11:AL14) -> 500 | AN15: Southeast | AO15: =5035+5775+1960+1960 -> 14730 | AP15: =AO15*2 -> 29460
A16: Plans | D16: Parking Ratio | F16: =F15/E8 -> 1.2561983 | H16: PER GSF | J16: =J14/B8 -> 191.79635 | N16: Lock Boxes | O16: 0 | P16: EA | Q16: Pavers Pool | R16: 0
H17: Efficiency Factor | J17: =K7/B8 -> 0.78376899 | N17: Awning Small | O17: =12+9+9 -> 30 | P17: EA | AG17: B1B Railings | AH17: =12.5*62 -> 775 | AN17: B1B Railings | AO17: =12.5*62 -> 775
N18: Awning Large | O18: =3+3+4 -> 10 | P18: EA
A19: Description | B19: Cost Code | C19: Cost Category | D19: Sub job | E19: Source | F19: UMO | G19: Quantity | H19: U.P. | I19: Escal % | J19: Total U.P. | K19: Sub Total | L19: Total | M19: Description / Details
A20: General Requirements | B20: 01 | L20: =K21 -> 3443297.7
A21: General Requirement | B21: 01 | C21: S | F21: Mo | G21: =$B$6 -> 30 | H21: =SUM(L22:L291,L294,L311)*0.06/B6 -> 114776.59 | I21: 0 | J21: =H21*(1+I21) -> 114776.59 | K21: =J21*G21 -> 3443297.7 | M21: Change timeline from 24 to 30 months due to complexcity of bridges, underground and project size 17.25 acres/363 units.
A22: Existing Conditions | B22: 02 | L22: =K23 -> 16000
A23: Potholing | B23: 02-3213 | C23: S | D23: ON-SITE | E23: Allowance | G23: 1 | H23: 16000 | I23: 0 | J23: =H23*(1+I23) -> 16000 | K23: =J23*G23 -> 16000
A24: Concrete | B24: 03 | L24: =SUM(K25:K34) -> 2697268.5
A25: Slabs | B25: 03-3101 | C25: S | D25: BUILDING | E25: Torrey Pines | F25: SF | G25: =O2 -> 174940 | H25: 11.99 | I25: 0 | J25: =H25*(1+I25) -> 11.99 | K25: =J25*G25 -> 2097530.6
A26: Deepened Footings | B26: 03-3101 | C26: S | D26: BUILDING | E26: N/A | J26: =H26*(1+I26) -> 0 | K26: =J26*G26 -> 0
A27: Concrete Slab Repairs | B27: 03-3101 | C27: RR | D27: BUILDING | E27: Allowance | F27: LS | G27: 1 | H27: 2500 | I27: 0 | J27: =H27*(1+I27) -> 2500 | K27: =J27*G27 -> 2500
A28: Pump House Concrete | B28: 03-3101 | C28: S | D28: PUMPHOUSE | E28: Torrey Pines | F28: SF | G28: 300 | H28: 11.99 | J28: =H28*(1+I28) -> 11.99 | K28: =J28*G28 -> 3597
A29: Trash Enclosure Concrete | B29: 03-3102 | C29: S | D29: OTHER SITE | E29: Allowance | F29: SF | G29: =12*8*O5 -> 1344 | H29: 11.99 | I29: 0 | J29: =H29*(1+I29) -> 11.99 | K29: =J29*G29 -> 16114.56
A30: Pool Area Shower Concrete | B30: 03-3105 | C30: S | D30: POOL AREA | E30: Torrey Pines | F30: LS | G30: 1 | H30: 2500 | I30: 0 | J30: =H30*(1+I30) -> 2500 | K30: =J30*G30 -> 2500
A31: Cabana Concrete | B31: 03-3107 | C31: S | D31: POOL AREA | E31: N/A | J31: =H31*(1+I31) -> 0 | K31: =J31*G31 -> 0
A32: Pool Equipment Foundation | B32: 03-3108 | C32: S | D32: POOL EQUIP | E32: N/A | J32: =H32*(1+I32) -> 0 | K32: =J32*G32 -> 0
A33: Lightweight Concrete | B33: 03-3116 | C33: S | D33: BUILDING | E33: Torrey Pines | F33: SF | G33: =O2 -> 174940 | H33: 2.94 | I33: 0 | J33: =H33*(1+I33) -> 2.94 | K33: =J33*G33 -> 514323.6
A34: Deck Concrete | B34: 03-5001 | C34: S | D34: BUILDING | E34: Torrey Pines | F34: SF | G34: =R6 -> 3072 | H34: 19.76 | I34: 0 | J34: =H34*(1+I34) -> 19.76 | K34: =J34*G34 -> 60702.72
A35: Masonry | B35: 04 | L35: =SUM(K36:K40) -> 207800
A36: Elevator Shaft | B36: 04-2201 | C36: S | D36: BUILDING | E36: Torrey Pines | F36: Stop | G36: =O4 -> 12 | H36: 9500 | I36: 0 | J36: =H36*(1+I36) -> 9500 | K36: =J36*G36 -> 114000
A37: Trash Enclosure | B37: 04-2202 | C37: S | D37: OTHER SITE | E37: Torrey Pines | F37: Count | G37: =$O$5 -> 14 | H37: 5700 | I37: 0 | J37: =H37*(1+I37) -> 5700 | K37: =J37*G37 -> 79800
A38: Masonry Veneer | B38: 04-4301 | C38: S | D38: ON-SITE | E38: N/A | H38: 0 | J38: =H38*(1+I38) -> 0 | K38: =J38*G38 -> 0
A39: Masonry Veneer Pool Area | B39: 04-4305 | C39: S | D39: POOL AREA | E39: Allowance | F39: LS | G39: 1 | H39: 5000 | I39: 0 | J39: =H39*(1+I39) -> 5000 | K39: =J39*G39 -> 5000
A40: Pool Eq. Shower Stone | B40: 04-4306 | C40: A | D40: POOL EQUIP | E40: Torrey Pines | F40: LS | G40: 1 | H40: 9000 | I40: 0 | J40: =H40*(1+I40) -> 9000 | K40: =J40*G40 -> 9000
A41: Metals | B41: 05 | L41: =SUM(K42:K49) -> 349806
A42: Structural Steel | B42: 05-1201 | C42: S | D42: BUILDING | E42: Torrey Pines | F42: LS | G42: 1 | H42: 100000 | I42: 0 | J42: =H42*(1+I42) -> 100000 | K42: =J42*G42 -> 100000
A43: Elevator Shaft Iron | B43: 05-1202 | C43: S | D43: BUILDING | E43: Torrey Pines | F43: Count | G43: =$O$3 -> 6 | H43: =1950+2090 -> 4040 | I43: 0 | J43: =H43*(1+I43) -> 4040 | K43: =J43*G43 -> 24240
A44: Stair Handrails | B44: 05-5201 | C44: S | D44: BUILDING | E44: Torrey Pines | F44: Flight | G44: =O6*2 -> 36 | H44: 2000 | I44: 0 | J44: =H44*(1+I44) -> 2000 | K44: =J44*G44 -> 72000
A45: Garage Stair Railings | B45: 05-5201 | C45: S | D45: BUILDING | E45: N/A | H45: 0 | I45: 0 | J45: =H45*(1+I45) -> 0 | K45: =J45*G45 -> 0
A46: Cabana Iron | B46: 05-7004 | C46: S | D46: POOL AREA | E46: N/A | H46: 0 | I46: 0 | J46: =H46*(1+I46) -> 0 | K46: =J46*G46 -> 0
A47: Pool Equipment Gate | B47: 05-7005 | C47: S | D47: POOL EQUIP | E47: Torrey Pines | F47: Count | G47: 1 | H47: 1950 | I47: 0 | J47: =H47*(1+I47) -> 1950 | K47: =J47*G47 -> 1950
A48: Iron Railings | B48: 05-7300 | C48: S | D48: BUILDING | E48: Torrey Pines | F48: LF | G48: =$O$9 -> 1648 | H48: 92 | I48: 0 | J48: =H48*(1+I48) -> 92 | K48: =J48*G48 -> 151616
A49: Cable Railings | B49: 05-7316 | C49: S | D49: COMMON AREA | E49: N/A | H49: 0 | I49: 0 | J49: =H49*(1+I49) -> 0 | K49: =J49*G49 -> 0
A50: Wood, Plastics, & Composites | B50: 06 | L50: =SUM(K51:K63) -> 8880630.8
A51: Dumpsters | B51: 06-0111 | C51: S | D51: DUMPSTERS | I51: 0 | J51: =H51*(1+I51) -> 0 | K51: =J51*G51 -> 0 | M51: Included in Construction Cleaning Contract
A52: Framing | B52: 06-1100 | C52: S | D52: BUILDING | E52: Moving Ave | F52: SF | G52: =B8 -> 361641 | H52: 20.5 | I52: 0 | J52: =H52*(1+I52) -> 20.5 | K52: =J52*G52 -> 7413640.5
A53: Framing - Crane | B53: 06-1100 | C53: S | D53: BUILDING | E53: N/A | I53: 0 | J53: =H53*(1+I53) -> 0 | K53: =J53*G53 -> 0
A54: Cabana Framing | B54: 06-1109 | C54: S | D54: COMMON AREA | E54: N/A | I54: 0 | J54: =H54*(1+I54) -> 0 | K54: =J54*G54 -> 0
A55: BBQ Framing | B55: 06-1110 | C55: S | D55: COMMON AREA | E55: Allowance | F55: LS | G55: 4 | H55: 2500 | I55: 0 | J55: =H55*(1+I55) -> 2500 | K55: =J55*G55 -> 10000
A56: Fireplace Framing | B56: 06-1111 | C56: S | D56: COMMON AREA | E56: N/A | I56: 0 | J56: =H56*(1+I56) -> 0 | K56: =J56*G56 -> 0
A57: Trellis | B57: 06-1114 | C57: S | D57: BUILDING | E57: N/A | I57: 0 | J57: =H57*(1+I57) -> 0 | K57: =J57*G57 -> 0
A58: Pool Equipment Framing | B58: 06-1114 | C58: S | D58: POOL EQUIP | E58: N/A | I58: 0 | J58: =H58*(1+I58) -> 0 | K58: =J58*G58 -> 0
A59: Finish Carpentry - Units | B59: 06-2001 | C59: S | D59: BUILDING | E59: Torrey Pines | F59: Unit | G59: =$E$8 -> 363 | H59: 3192.5 | I59: 0 | J59: =H59*(1+I59) -> 3192.5 | K59: =J59*G59 -> 1158877.5
A60: Finish Carpentry - Common | B60: 06-2001 | C60: S | D60: COMMON AREA | E60: Torrey Pines | F60: SF | G60: =B8 -> 361641 | H60: 0.8 | I60: 0 | J60: =H60*(1+I60) -> 0.8 | K60: =J60*G60 -> 289312.8
A61: Finish Carpentry - Pump House | B61: 06-2001S | C61: S | D61: PUMPHOUSE | E61: Flamingo | F61: LS | G61: 1 | H61: 4000 | I61: 0 | J61: =H61*(1+I61) -> 4000 | K61: =J61*G61 -> 4000
A62: BBQ Trim | B62: 06-2006 | C62: S | D62: COMMON AREA | E62: Allowance | F62: LS | G62: 4 | H62: 1200 | I62: 0 | J62: =H62*(1+I62) -> 1200 | K62: =J62*G62 -> 4800
A63: Shutters | B63: 06-4919 | C63: S | D63: BUILDING | E63: N/A | I63: 0 | J63: =H63*(1+I63) -> 0 | K63: =J63*G63 -> 0
A64: Thermal & Moisture Protection | B64: 07 | L64: =SUM(K65:K75) -> 2198832.2
A65: Insulation | B65: 07-2101 | C65: S | D65: BUILDING | E65: Torrey Pines | F65: SF | G65: =B8 -> 361641 | H65: 2.7 | I65: 0 | J65: =H65*(1+I65) -> 2.7 | K65: =J65*G65 -> 976430.7 | M65: It includes the material increased since for 2nd half of 2024.
A66: Roofing | B66: 07-3001 | C66: S | D66: BUILDING | E66: Torrey Pines | F66: Squares | G66: =$O$10 -> 1749.4 | H66: 603 | I66: 0 | J66: =H66*(1+I66) -> 603 | K66: =J66*G66 -> 1054888.2
A67: Cabana Roofing | B67: 07-3002 | C67: S | D67: COMMON AREA | E67: N/A | I67: 0 | J67: =H67*(1+I67) -> 0 | K67: =J67*G67 -> 0
A68: Pump House Roofing | B68: 07-3002 | C68: S | D68: PUMPHOUSE | E68: Allowance | F68: LS | G68: 1 | H68: 7500 | I68: 0 | J68: =H68*(1+I68) -> 7500 | K68: =J68*G68 -> 7500
A69: Pool Equipment Roofing | B69: 07-3003 | C69: S | D69: POOL EQUIP | E69: Allowance | F69: LS | G69: =O7 -> 1 | H69: 7500 | I69: 0 | J69: =H69*(1+I69) -> 7500 | K69: =J69*G69 -> 7500
A70: Trash Enclosure Cover | B70: 07-6101 | C70: S | D70: OTHER SITE | E70: Decatur | F70: Count | G70: =$O$5 -> 14 | H70: 5800 | I70: 0 | J70: =H70*(1+I70) -> 5800 | K70: =J70*G70 -> 81200
A71: Pigeon Proofing | B71: 07-7001 | C71: S | D71: BUILDING | E71: Torrey Pines | F71: SF | G71: =$B$8 -> 361641 | H71: 0.08 | I71: 0 | J71: =H71*(1+I71) -> 0.08 | K71: =J71*G71 -> 28931.28
A72: Gutters and Downspouts | B72: 07-7124 | C72: S | D72: BUILDING | E72: Torrey Pines | F72: SF | G72: =$B$8 -> 361641 | H72: 0.05 | I72: 0 | J72: =H72*(1+I72) -> 0.05 | K72: =J72*G72 -> 18082.05
A73: Roof Ladders | B73: 07-7210 | C73: S | D73: BUILDING | E73: Torrey Pines | F73: Count | G73: =2*$B$11 -> 6 | H73: 1550 | I73: 0 | J73: =H73*(1+I73) -> 1550 | K73: =J73*G73 -> 9300 | M73: 2 Per building
A74: Roof Access Doors | B74: 07-7233 | C74: S | D74: BUILDING | E74: Torrey Pines | F74: Count | G74: =2*$B$11 -> 6 | H74: 2500 | I74: 0 | J74: =H74*(1+I74) -> 2500 | K74: =J74*G74 -> 15000 | M74: 2 Per building
A75: Roof Winch | B75: 07-7250 | C75: S | D75: BUILDING | E75: N/A | I75: 0 | J75: =H75*(1+I75) -> 0 | K75: =J75*G75 -> 0
A76: Openings | B76: 08 | L76: =SUM(K77:K91) -> 516935.79
A77: Dumpsters | B77: 08-0151 | C77: S | D77: DUMPSTERS | I77: 0 | J77: =H77*(1+I77) -> 0 | K77: =J77*G77 -> 0 | M77: Inclunded with Construction Cleaning Contract.
A78: Entry Doors | B78: 08-1001 | C78: S | D78: COMMON AREA | E78: Allowance | F78: Count | G78: 1 | H78: 8000 | I78: 0 | J78: =H78*(1+I78) -> 8000 | K78: =J78*G78 -> 8000
A79: Common Doors | B79: 08-1002 | C79: S | D79: COMMON AREA | E79: Included | I79: 0 | J79: =H79*(1+I79) -> 0 | K79: =J79*G79 -> 0
A80: Pocket Doors - 3 Panel | B80: 08-1002 | C80: S | D80: BUILDING | E80: N/A | I80: 0 | J80: =H80*(1+I80) -> 0 | K80: =J80*G80 -> 0
A81: Garage Doors | B81: 08-3619 | C81: S | D81: BUILDING | E81: N/A | I81: 0 | J81: =H81*(1+I81) -> 0 | K81: =J81*G81 -> 0
A82: Windows and Sliding Glass Doors | B82: 08-5301 | C82: S | D82: BUILDING | E82: Torrey Pines | F82: Per Unit | G82: =$E$8 -> 363 | H82: 1157.8947 | I82: 0 | J82: =H82*(1+I82) -> 1157.8947 | K82: =J82*G82 -> 420315.79
A83: Windows Repair and Replacement | B83: 08-5301 | C83: RR | D83: BUILDING | E83: Allowance | F83: Per Unit | G83: =$E$8 -> 363 | H83: 75 | I83: 0 | J83: =H83*(1+I83) -> 75 | K83: =J83*G83 -> 27225
A84: Pool Equipment Windows | B84: 08-5303 | C84: S | D84: POOL EQUIP | E84: N/A | I84: 0 | J84: =H84*(1+I84) -> 0 | K84: =J84*G84 -> 0
A85: Pool Glass Walls | B85: 08-8001 | C85: S | D85: POOL AREA | E85: N/A | I85: 0 | J85: =H85*(1+I85) -> 0 | K85: =J85*G85 -> 0
A86: Fixed Glass | B86: 08-8002 | C86: S | D86: BUILDING | E86: N/A | I86: 0 | J86: =H86*(1+I86) -> 0 | K86: =J86*G86 -> 0
A87: Mirrors - LED | B87: 08-8301 | C87: S | D87: BUILDING | E87: N/A | I87: 0 | J87: =H87*(1+I87) -> 0 | K87: =J87*G87 -> 0
A88: Mirrors - LED Install | B88: 08-8302 | C88: S | D88: BUILDING | E88: N/A | I88: 0 | J88: =H88*(1+I88) -> 0 | K88: =J88*G88 -> 0
A89: Mirrors - Framed | B89: 08-8301 | C89: S | D89: BUILDING | E89: N/A | I89: 0 | J89: =H89*(1+I89) -> 0 | K89: =J89*G89 -> 0
A90: Mirrors - Polished Edges (Units) | B90: 08-8301 | C90: S | D90: BUILDING | E90: Pebble | F90: Unit | G90: =E8 -> 363 | H90: 165 | I90: 0 | J90: =H90*(1+I90) -> 165 | K90: =J90*G90 -> 59895
A91: Mirrors - Polished Edges (Restrooms) | B91: 08-8301 | C91: S | D91: BUILDING | E91: Allowance | F91: Count | G91: 6 | H91: 250 | I91: 0 | J91: =H91*(1+I91) -> 250 | K91: =J91*G91 -> 1500
A92: Finishes | B92: 09 | L92: =SUM(K93:K130) -> 5549735.3
A93: Cost Prep Labor | B93: 09-0101 | C93: S | D93: BUILDING | E93: N/A | I93: 0 | J93: =H93*(1+I93) -> 0 | K93: =J93*G93 -> 0
A94: Cost Prep Mat - Home Depot | B94: 09-0102 | C94: S | D94: BUILDING | E94: Allowance | F94: LS | G94: 1 | H94: 10000 | I94: 0 | J94: =H94*(1+I94) -> 10000 | K94: =J94*G94 -> 10000
A95: Clean Up - Final | B95: 09-0103 | C95: S | D95: BUILDING | E95: Torrey Pines | F95: SF | G95: =$B$8 -> 361641 | H95: 0.85 | I95: 0 | J95: =H95*(1+I95) -> 0.85 | K95: =J95*G95 -> 307394.85 | M95: Includes Dumpters
A96: Clean Up - During Construction - Labor | B96: 09-0104 | C96: S | D96: BUILDING | E96: Allowance | F96: LS | G96: 1 | H96: 75000 | I96: 0 | J96: =H96*(1+I96) -> 75000 | K96: =J96*G96 -> 75000
A97: Dumpsters | B97: 09-0113 | C97: S | D97: DUMPSTERS | E97: Allowance | F97: Unit | G97: =$E$8 -> 363 | H97: 79 | I97: 0 | J97: =H97*(1+I97) -> 79 | K97: =J97*G97 -> 28677
A98: Clean Up - Hauling Exterior | B98: 09-0121 | C98: S | D98: ON-SITE | E98: Allowance | F98: LS | G98: 1 | H98: 10000 | I98: 0 | J98: =H98*(1+I98) -> 10000 | K98: =J98*G98 -> 10000 | M98: Included in Construction Cleaning Contract.
A99: Stucco | B99: 09-2423 | C99: S | D99: BUILDING | E99: Torrey Pines | F99: SY | G99: =O11 -> 20609.979 | H99: 40.82 | I99: 0 | J99: =H99*(1+I99) -> 40.82 | K99: =J99*G99 -> 841299.36 | M99: 12 Month Moving Average
A100: Stucco - Pump House | B100: 09-2423S | C100: A | D100: PUMPHOUSE | E100: Allowance | F100: LS | G100: =O15 -> 1 | H100: 6000 | I100: 0 | J100: =H100*(1+I100) -> 6000 | K100: =J100*G100 -> 6000
...

Sheet Combined - vErik
A1: Project Details | D1: Unit Breakdown | H1: Breakdown Per Building | N1: List of Take offs | R1: List of Take offs
A2: Project | B2: Robindale & 215 | D2: Unit Type | E2: Number | F2: % | H2: Bldg. | I2: Unit | J2: GSF | N2: Slab SF | O2: ='[59]Scenario 2 - Phase 1'!O2+'[59]Scenario 2 - Phase 2'!O2 -> 164597 | P2: GSF / 2 | R2: 1x1 Counter tops | S2: ='[59]Scenario 2 - Phase 1'!S2+'[59]Scenario 2 - Phase 2'!S2 -> 14292 | T2: SF
A3: Budget Level | B3: Level 1 | D3: Studios | E3: ='[59]Scenario 2 - Phase 1'!E3+'[59]Scenario 2 - Phase 2'!E3 -> 0 | F3: =E3/$E$8 -> 0 | H3: 1 | I3: =155-53 -> 102 | J3: =47126*2 -> 94252 | N3: Elevators | O3: ='[59]Scenario 2 - Phase 1'!O3+'[59]Scenario 2 - Phase 2'!O3 -> 6 | P3: Count Est. | R3: 2x1 Counter Tops | S3: ='[59]Scenario 2 - Phase 1'!S3+'[59]Scenario 2 - Phase 2'!S3 -> 10833 | T3: SF
A4: Product | B4: Senior | D4: 1 Br - 1 Ba | E4: ='[59]Scenario 2 - Phase 1'!E4+'[59]Scenario 2 - Phase 2'!E4 -> 218 | F4: =E4/$E$8 -> 0.60055096 | H4: 2 | I4: =192-65 -> 127 | J4: =56588*2 -> 113176 | N4: Trash Encl. | O4: ='[59]Scenario 2 - Phase 1'!O4+'[59]Scenario 2 - Phase 2'!O4 -> 10.542857 | P4: Count Est. 1 per 35 Units | R4: 1x1 Cab Boxes | S4: ='[59]Scenario 2 - Phase 1'!S4+'[59]Scenario 2 - Phase 2'!S4 -> 0 | T4: Boxes
A5: Start Date | B5: 45809 | D5: 2 Br - 1 Ba | E5: ='[59]Scenario 2 - Phase 1'!E5+'[59]Scenario 2 - Phase 2'!E5 -> 145 | F5: =E5/$E$8 -> 0.39944904 | H5: 3 | I5: ='[59]Scenario 2 - Phase 2'!I3 -> 134 | J5: ='[59]Scenario 2 - Phase 2'!J3 -> 121766 | N5: Stairs | O5: ='[59]Scenario 2 - Phase 1'!O5+'[59]Scenario 2 - Phase 2'!O5 -> 16 | P5: Count | R5: 2x1 Cab Boxes | S5: ='[59]Scenario 2 - Phase 1'!S5+'[59]Scenario 2 - Phase 2'!S5 -> 0 | T5: Boxes
A6: Timline | B6: 24 | D6: 2 Br - 2 Ba | E6: ='[59]Scenario 2 - Phase 1'!E6+'[59]Scenario 2 - Phase 2'!E6 -> 0 | F6: =E6/$E$8 -> 0 | H6: Totals | I6: =E8 -> 363 | J6: =SUM(J3:J5) -> 329194 | N6: Pool | O6: ='[59]Scenario 2 - Phase 1'!O6+'[59]Scenario 2 - Phase 2'!O6 -> 2 | R6: 1x1 Decks | S6: ='[59]Scenario 2 - Phase 1'!S6+'[59]Scenario 2 - Phase 2'!S6 -> 3984 | T6: SF
A7: Floors | B7: Bldg 1 = 2, Bldg 2 =2, Bldg 3=2 | D7: 3 Br - 2 Ba | E7: ='[59]Scenario 2 - Phase 1'!E7+'[59]Scenario 2 - Phase 2'!E7 -> 0 | F7: =E7/$E$8 -> 0 | N7: Gym | O7: ='[59]Scenario 2 - Phase 1'!O7+'[59]Scenario 2 - Phase 2'!O7 -> 2 | R7: 2x1 Decks | S7: ='[59]Scenario 2 - Phase 1'!S7+'[59]Scenario 2 - Phase 2'!S7 -> 0 | T7: SF
A8: Bldg SF | B8: =J6 -> 329194 | D8: Totals | E8: =SUM(E3:E7) -> 363 | F8: =E8/$E$8 -> 1 | H8: TOTAL COST | J8: =L326 -> 69293294 | N8: Iron Rail | O8: ='[59]Scenario 2 - Phase 1'!O8+'[59]Scenario 2 - Phase 2'!O8 -> 2682.74 | P8: Prorate to Bruner SF | R8: Pavers | S8: ='[59]Scenario 2 - Phase 1'!S8+'[59]Scenario 2 - Phase 2'!S8 -> 0 | T8: SF
A9: Acres | B9: ='[59]Scenario 2 - Phase 1'!B9+'[59]Scenario 2 - Phase 2'!B9 -> 17.25 | D9: Parking | H9: PER UNIT | J9: =J8/E8 -> 190890.62 | N9: Roofing | O9: ='[59]Scenario 2 - Phase 1'!O9+'[59]Scenario 2 - Phase 2'!O9 -> 1693.23 | P9: Square | R9: Site Landscaping | S9: ='[59]Scenario 2 - Phase 1'!S9+'[59]Scenario 2 - Phase 2'!S9 -> 77100 | T9: Building 1 SF
A10: Site SF | B10: =B9*43560 -> 751410 | D10: Garage Parking | F10: ='[59]Scenario 2 - Phase 1'!F10+'[59]Scenario 2 - Phase 2'!F10 -> 0 | H10: PER GSF | J10: =J8/B8 -> 210.49379 | N10: Stucco | O10: ='[59]Scenario 2 - Phase 1'!O10+'[59]Scenario 2 - Phase 2'!O10 -> 18377.333 | P10: Square Yard | R10: Site Landscaping | S10: ='[59]Scenario 2 - Phase 1'!S10+'[59]Scenario 2 - Phase 2'!S10 -> 94000 | T10: Building 2 SF
A11: Buildings | B11: 3 | D11: Cover Parking | F11: ='[59]Scenario 2 - Phase 1'!F11+'[59]Scenario 2 - Phase 2'!F11 -> 0 | N11: Liavable Area | O11: ='[59]Scenario 2 - Phase 1'!O11+'[59]Scenario 2 - Phase 2'!O11 -> 282874 | P11: SF | R11: Site Landscaping | S11: ='[59]Scenario 2 - Phase 1'!S11+'[59]Scenario 2 - Phase 2'!S11 -> 97500 | T11: Building 3 SF
A12: Reports Available | D12: Open Parking | F12: ='[59]Scenario 2 - Phase 1'!F12+'[59]Scenario 2 - Phase 2'!F12 -> 706 | N12: Carports | O12: ='[59]Scenario 2 - Phase 1'!O12+'[59]Scenario 2 - Phase 2'!O12 -> 423.6 | P12: 60% of spaces (Bruner) | R12: Pool Fence | S12: ='[59]Scenario 2 - Phase 1'!S12+'[59]Scenario 2 - Phase 2'!S12 -> 254
A13: Site Evaluation Report (GCW) | D13: Accessible Parking | F13: ='[59]Scenario 2 - Phase 1'!F13+'[59]Scenario 2 - Phase 2'!F13 -> 8 | N13: Seal Coat | O13: ='[59]Scenario 2 - Phase 1'!O13+'[59]Scenario 2 - Phase 2'!O13 -> 285447 | P13: Asphalt SF | R13: Dog Park Fence | S13: ='[59]Scenario 2 - Phase 1'!S13+'[59]Scenario 2 - Phase 2'!S13 -> 255
A14: Soils Report (Universal) | D14: Private Garages | F14: ='[59]Scenario 2 - Phase 1'!F14+'[59]Scenario 2 - Phase 2'!F14 -> 0 | N14: Building Perimeter | O14: ='[59]Scenario 2 - Phase 1'!O14+'[59]Scenario 2 - Phase 2'!O14 -> 1699.5 | P14: Bldg 1 LF | R14: Corridor | S14: ='[59]Scenario 2 - Phase 1'!S14+'[59]Scenario 2 - Phase 2'!S14 -> 9315 | T14: Building 1 SF
A15: Alta Survey (Wallace) | D15: Total Parking Provided | F15: =SUM(F10:F12) -> 706 | N15: Building Perimeter | O15: ='[59]Scenario 2 - Phase 1'!O15+'[59]Scenario 2 - Phase 2'!O15 -> 1815 | P15: Bldg 2 LF | R15: Corridor | S15: ='[59]Scenario 2 - Phase 1'!S15+'[59]Scenario 2 - Phase 2'!S15 -> 12738 | T15: Building 2 SF
A16: Plans | D16: Parking Ratio | F16: =SUM(F10:F12)/E8 -> 1.9449036 | N16: Building Perimeter | O16: ='[59]Scenario 2 - Phase 1'!O16+'[59]Scenario 2 - Phase 2'!O16 -> 2392.5 | P16: Bldg 3 LF | R16: Corridor | S16: ='[59]Scenario 2 - Phase 1'!S16+'[59]Scenario 2 - Phase 2'!S16 -> 14079 | T16: Building 3 SF | X16: 219566.77
R17: Pool Deck | S17: ='[59]Scenario 2 - Phase 1'!S17+'[59]Scenario 2 - Phase 2'!S17 -> 7800 | T17: SF
A19: Description | B19: Cost Code | C19: Cost Category | D19: Subjob | E19: Source | F19: Unit Meas. | G19: Quantity | H19: Unit Cost | I19: Escalation % | J19: T. Unit Cost | K19: Sub Total | L19: Total | N19: Description / Details
A20: General Requirements | B20: 01 | L20: =K21 -> 3514986.3 | AB20: 3514986.3 | AC20: =AA20-K20 -> 0 | AD20: =AB20-L20 -> 0
A21: General Requirements | B21: 01 | C21: S | F21: Mo | G21: ='[59]Scenario 2 - Phase 1'!G21+'[59]Scenario 2 - Phase 2'!G21 -> 42 | H21: 83690.15 | I21: 0 | J21: =H21*(1+I21) -> 83690.15 | K21: =J21*G21 -> 3514986.3 | AA21: 3514986.3 | AC21: =AA21-K21 -> 0 | AD21: =AB21-L21 -> 0
A22: Existing Conditions | B22: 02 | L22: =K23 -> 16000 | AB22: 16000 | AC22: =AA22-K22 -> 0 | AD22: =AB22-L22 -> 0
A23: Potholing | B23: 02-3213 | C23: S | D23: ON-SITE | E23: Allowance | G23: 1 | H23: ='[59]Scenario 2 - Phase 1'!H23+'[59]Scenario 2 - Phase 2'!H23 -> 16000 | I23: 0 | J23: =H23*(1+I23) -> 16000 | K23: =J23*G23 -> 16000 | AA23: 16000 | AC23: =AA23-K23 -> 0 | AD23: =AB23-L23 -> 0
A24: Concrete | B24: 03 | L24: =SUM(K25:K34) -> 2594295.7 | X24: =L24/E8 -> 7146.8201 | AB24: 2594295.7 | AC24: =AA24-K24 -> 0 | AD24: =AB24-L24 -> 0
A25: Slabs | B25: 03-3101 | C25: S | D25: BUILDING | E25: Torrey Pines | F25: SF | G25: =O2 -> 164597 | H25: 11.99 | I25: 0 | J25: =H25*(1+I25) -> 11.99 | K25: =J25*G25 -> 1973518 | AA25: 1973518 | AC25: =AA25-K25 -> 0 | AD25: =AB25-L25 -> 0
A26: Deepened Footings | B26: 03-3101 | C26: S | D26: BUILDING | E26: N/A | G26: 0 | H26: 0 | I26: 0 | J26: =H26*(1+I26) -> 0 | K26: =J26*G26 -> 0 | AA26: 0 | AC26: =AA26-K26 -> 0 | AD26: =AB26-L26 -> 0
A27: Concrete Slab Repairs | B27: 03-3101 | C27: RR | D27: BUILDING | E27: Allowance | F27: LS | G27: 1 | H27: ='[59]Scenario 2 - Phase 1'!H27+'[59]Scenario 2 - Phase 2'!H27 -> 15000 | I27: 0 | J27: =H27*(1+I27) -> 15000 | K27: =J27*G27 -> 15000 | AA27: 15000 | AC27: =AA27-K27 -> 0 | AD27: =AB27-L27 -> 0
A28: Pump House Concrete | B28: 03-3101 | C28: S | D28: PUMPHOUSE | E28: Torrey Pines | F28: SF | G28: ='[59]Scenario 2 - Phase 1'!G28+'[59]Scenario 2 - Phase 2'!G28 -> 600 | H28: 11.99 | I28: 0 | J28: =H28*(1+I28) -> 11.99 | K28: =J28*G28 -> 7194 | AA28: 7194 | AC28: =AA28-K28 -> 0 | AD28: =AB28-L28 -> 0
A29: Trash Enclosure Concrete | B29: 03-3102 | C29: S | D29: OTHER SITE | E29: Russell IV | F29: Count | G29: =O4 -> 10.542857 | H29: 2698 | I29: 0 | J29: =H29*(1+I29) -> 2698 | K29: =J29*G29 -> 28444.629 | AA29: 28444.629 | AC29: =AA29-K29 -> 0 | AD29: =AB29-L29 -> 0
A30: Pool Area Shower Concrete | B30: 03-3105 | C30: S | D30: POOL AREA | E30: Torrey Pines | F30: LS | G30: ='[59]Scenario 2 - Phase 1'!G30+'[59]Scenario 2 - Phase 2'!G30 -> 3 | H30: 2500 | I30: 0 | J30: =H30*(1+I30) -> 2500 | K30: =J30*G30 -> 7500 | AA30: 7500 | AC30: =AA30-K30 -> 0 | AD30: =AB30-L30 -> 0
A31: Cabana Concrete | B31: 03-3107 | C31: S | D31: POOL AREA | E31: N/A | J31: =H31*(1+I31) -> 0 | K31: =J31*G31 -> 0 | AA31: 0 | AC31: =AA31-K31 -> 0 | AD31: =AB31-L31 -> 0
A32: Pool Equipment Foundation | B32: 03-3108 | C32: S | D32: POOL EQUIP | E32: N/A | J32: =H32*(1+I32) -> 0 | K32: =J32*G32 -> 0 | AA32: 0 | AC32: =AA32-K32 -> 0 | AD32: =AB32-L32 -> 0
A33: Lightweight Concrete | B33: 03-3116 | C33: S | D33: BUILDING | E33: Torrey Pines | F33: SF | G33: =J6/2 -> 164597 | H33: 2.94 | I33: 0 | J33: =H33*(1+I33) -> 2.94 | K33: =J33*G33 -> 483915.18 | AA33: 483915.18 | AC33: =AA33-K33 -> 0 | AD33: =AB33-L33 -> 0
A34: Deck Concrete | B34: 03-5001 | C34: S | D34: BUILDING | E34: Torrey Pines | F34: SF | G34: =SUM($S$6:$S$7) -> 3984 | H34: 19.76 | I34: 0 | J34: =H34*(1+I34) -> 19.76 | K34: =J34*G34 -> 78723.84 | AA34: 78723.84 | AC34: =AA34-K34 -> 0 | AD34: =AB34-L34 -> 0
A35: Parking Garage | B35: 03-G | L35: =SUM(K36:K43) -> 0 | AB35: 0 | AC35: =AA35-K35 -> 0 | AD35: =AB35-L35 -> 0
A36: Parking Garage Structure | C36: S | E36: N/A | J36: =H36*(1+I36) -> 0 | K36: =J36*G36 -> 0 | AA36: 0 | AC36: =AA36-K36 -> 0 | AD36: =AB36-L36 -> 0
A37: Core Slab Precast Concrete | C37: S | E37: N/A | J37: =H37*(1+I37) -> 0 | K37: =J37*G37 -> 0 | AA37: 0 | AC37: =AA37-K37 -> 0 | AD37: =AB37-L37 -> 0
A38: Concrete Slab on Grade | C38: S | E38: N/A | J38: =H38*(1+I38) -> 0 | K38: =J38*G38 -> 0 | AA38: 0 | AC38: =AA38-K38 -> 0 | AD38: =AB38-L38 -> 0
A39: Concrete Topping Slab 4" / Level | C39: S | E39: N/A | J39: =H39*(1+I39) -> 0 | K39: =J39*G39 -> 0 | AA39: 0 | AC39: =AA39-K39 -> 0 | AD39: =AB39-L39 -> 0
A40: Electrical | C40: S | E40: N/A | J40: =H40*(1+I40) -> 0 | K40: =J40*G40 -> 0 | AA40: 0 | AC40: =AA40-K40 -> 0 | AD40: =AB40-L40 -> 0
A41: Dry Sprinklers | C41: S | E41: N/A | J41: =H41*(1+I41) -> 0 | K41: =J41*G41 -> 0 | AA41: 0 | AC41: =AA41-K41 -> 0 | AD41: =AB41-L41 -> 0
A42: Mechanical Ventilation | C42: S | E42: N/A | J42: =H42*(1+I42) -> 0 | K42: =J42*G42 -> 0 | AA42: 0 | AC42: =AA42-K42 -> 0 | AD42: =AB42-L42 -> 0
A43: Stairs and Railings | C43: S | E43: N/A | J43: =H43*(1+I43) -> 0 | K43: =J43*G43 -> 0 | AA43: 0 | AC43: =AA43-K43 -> 0 | AD43: =AB43-L43 -> 0
A44: Masonry | B44: 04 | L44: =SUM(K45:K49) -> 174094.29 | AB44: 174094.29 | AC44: =AA44-K44 -> 0 | AD44: =AB44-L44 -> 0
A45: Elevator Shaft | B45: 04-2201 | C45: S | D45: BUILDING | E45: Torrey Pines | F45: Count | G45: =$O$3 -> 6 | H45: =28500/3*2 -> 19000 | I45: 0 | J45: =H45*(1+I45) -> 19000 | K45: =J45*G45 -> 114000 | AA45: 114000 | AC45: =AA45-K45 -> 0 | AD45: =AB45-L45 -> 0
A46: Trash Enclosure | B46: 04-2202 | C46: S | D46: OTHER SITE | E46: Torrey Pines | F46: Count | G46: =$O$4 -> 10.542857 | H46: 5700 | I46: 0 | J46: =H46*(1+I46) -> 5700 | K46: =J46*G46 -> 60094.286 | AA46: 60094.286 | AC46: =AA46-K46 -> 0 | AD46: =AB46-L46 -> 0
A47: Masonry Veneer | B47: 04-4301 | C47: S | D47: ON-SITE | E47: N/A | J47: =H47*(1+I47) -> 0 | K47: =J47*G47 -> 0 | AA47: 0 | AC47: =AA47-K47 -> 0 | AD47: =AB47-L47 -> 0
A48: Masonry Veneer Pool Area | B48: 04-4305 | C48: S | D48: POOL AREA | E48: N/A | J48: =H48*(1+I48) -> 0 | K48: =J48*G48 -> 0 | AA48: 0 | AC48: =AA48-K48 -> 0 | AD48: =AB48-L48 -> 0
A49: Pool Eq. Shower Stone | B49: 04-4306 | C49: S | D49: POOL EQUIP | E49: N/A | J49: =H49*(1+I49) -> 0 | K49: =J49*G49 -> 0 | AA49: 0 | AC49: =AA49-K49 -> 0 | AD49: =AB49-L49 -> 0
A50: Metals | B50: 05 | L50: =SUM(K51:K58) -> 413758.91 | AB50: 413758.91 | AC50: =AA50-K50 -> 0 | AD50: =AB50-L50 -> 0
A51: Structural Steel | B51: 05-1201 | C51: S | D51: BUILDING | E51: N/A | H51: 186154 | I51: 0 | J51: =H51*(1+I51) -> 186154 | K51: =J51*G51 -> 0 | N51: Per Derek No Structural Steel in Common Areas | AA51: 0 | AC51: =AA51-K51 -> 0 | AD51: =AB51-L51 -> 0
A52: Elevator Shaft Iron | B52: 05-1202 | C52: S | D52: BUILDING | E52: Russell IV | F52: Count | G52: =$O$3 -> 6 | H52: 5990 | I52: 0 | J52: =H52*(1+I52) -> 5990 | K52: =J52*G52 -> 35940 | AA52: 35940 | AC52: =AA52-K52 -> 0 | AD52: =AB52-L52 -> 0
A53: Stair Handrails | B53: 05-5201 | C53: S | D53: BUILDING | E53: Russell IV | F53: LS | G53: =$O$5 -> 16 | H53: =11750/3*2 -> 7833.3333 | I53: 0 | J53: =H53*(1+I53) -> 7833.3333 | K53: =J53*G53 -> 125333.33 | AA53: 125333.33 | AC53: =AA53-K53 -> 0 | AD53: =AB53-L53 -> 0
A54: Garage Stair Railings | B54: 05-5201 | C54: S | D54: BUILDING | E54: N/A | H54: 0 | I54: 0 | J54: =H54*(1+I54) -> 0 | K54: =J54*G54 -> 0 | AA54: 0 | AC54: =AA54-K54 -> 0 | AD54: =AB54-L54 -> 0
A55: Cabana Iron | B55: 05-7004 | C55: S | D55: POOL AREA | E55: N/A | H55: 0 | I55: 0 | J55: =H55*(1+I55) -> 0 | K55: =J55*G55 -> 0 | AA55: 0 | AC55: =AA55-K55 -> 0 | AD55: =AB55-L55 -> 0
A56: Pool Equipment Gate | B56: 05-7005 | C56: S | D56: POOL EQUIP | E56: Russell IV | F56: Count | G56: =$O$6 -> 2 | H56: 1950 | I56: 0 | J56: =H56*(1+I56) -> 1950 | K56: =J56*G56 -> 3900 | AA56: 3900 | AC56: =AA56-K56 -> 0 | AD56: =AB56-L56 -> 0
A57: Iron Railings | B57: 05-7300 | C57: S | D57: BUILDING | E57: Russell IV | F57: Linear Foot | G57: ='[59]Scenario 2 - Phase 1'!G57+'[59]Scenario 2 - Phase 2'!G57 -> 2682.74 | H57: =K57/G57 -> 92.661076 | I57: 0 | K57: ='[59]Scenario 2 - Phase 1'!K57+'[59]Scenario 2 - Phase 2'!K57 -> 248585.58 | AA57: 248585.58 | AC57: =AA57-K57 -> 0 | AD57: =AB57-L57 -> 0
A58: Cable Railings | B58: 05-7316 | C58: S | D58: COMMON AREA | E58: N/A | H58: 0 | I58: 0 | J58: =H58*(1+I58) -> 0 | K58: =J58*G58 -> 0 | AA58: 0 | AC58: =AA58-K58 -> 0 | AD58: =AB58-L58 -> 0
A59: Wood, Plastics, & Composites | B59: 06 | L59: =SUM(K60:K71) -> 8101853.5 | AB59: 8101853.5 | AC59: =AA59-K59 -> 0 | AD59: =AB59-L59 -> 0
A60: Dumpsters | B60: 06-0111 | C60: S | D60: DUMPSTERS | E60: Torrey Pines | F60: Unit | G60: =E8 -> 363 | H60: 79 | I60: 0 | J60: =H60*(1+I60) -> 79 | K60: =J60*G60 -> 28677 | AA60: 28677 | AC60: =AA60-K60 -> 0 | AD60: =AB60-L60 -> 0
A61: Framing | B61: 06-1100 | C61: S | D61: BUILDING | E61: Torrey Pines | F61: SF | G61: =B8 -> 329194 | H61: 19.92 | I61: 0 | J61: =H61*(1+I61) -> 19.92 | K61: =J61*G61 -> 6557544.5 | AA61: 6557544.5 | AC61: =AA61-K61 -> 0 | AD61: =AB61-L61 -> 0
A62: Framing - Crane | B62: 06-1100 | C62: S | D62: BUILDING | E62: N/A | I62: 0 | J62: =H62*(1+I62) -> 0 | K62: =J62*G62 -> 0 | AA62: 0 | AC62: =AA62-K62 -> 0 | AD62: =AB62-L62 -> 0
A63: Cabana Framing | B63: 06-1109 | C63: S | D63: COMMON AREA | E63: N/A | I63: 0 | J63: =H63*(1+I63) -> 0 | K63: =J63*G63 -> 0 | AA63: 0 | AC63: =AA63-K63 -> 0 | AD63: =AB63-L63 -> 0
A64: BBQ Framing | B64: 06-1110 | C64: S | D64: COMMON AREA | E64: Pebble | F64: LS | G64: ='[59]Scenario 2 - Phase 1'!G64+'[59]Scenario 2 - Phase 2'!G64 -> 4 | H64: 2810 | I64: 0 | J64: =H64*(1+I64) -> 2810 | K64: =J64*G64 -> 11240 | AA64: 11240 | AC64: =AA64-K64 -> 0 | AD64: =AB64-L64 -> 0
A65: Fireplace Framing | B65: 06-1111 | C65: S | D65: COMMON AREA | E65: N/A | I65: 0 | J65: =H65*(1+I65) -> 0 | K65: =J65*G65 -> 0 | AA65: 0 | AC65: =AA65-K65 -> 0 | AD65: =AB65-L65 -> 0
A66: Trellis | B66: 06-1114 | C66: S | D66: BUILDING | E66: N/A | I66: 0 | J66: =H66*(1+I66) -> 0 | K66: =J66*G66 -> 0 | AA66: 0 | AC66: =AA66-K66 -> 0 | AD66: =AB66-L66 -> 0
A67: Pool Equipment Framing | B67: 06-1114 | C67: S | D67: POOL EQUIP | E67: N/A | I67: 0 | J67: =H67*(1+I67) -> 0 | K67: =J67*G67 -> 0 | AA67: 0 | AC67: =AA67-K67 -> 0 | AD67: =AB67-L67 -> 0
A68: Finish Carpentry - Units | B68: 06-2001 | C68: S | D68: BUILDING | E68: Pebble | F68: Unit | G68: =E8 -> 363 | H68: 3081 | I68: 0 | J68: =H68*(1+I68) -> 3081 | K68: =J68*G68 -> 1118403 | AA68: 1118403 | AC68: =AA68-K68 -> 0 | AD68: =AB68-L68 -> 0
A69: Finish Carpentry - Common | B69: 06-2001 | C69: S | D69: COMMON AREA | E69: Pebble | F69: SF | G69: =B8 -> 329194 | H69: 1.16 | I69: 0 | J69: =H69*(1+I69) -> 1.16 | K69: =J69*G69 -> 381865.04 | AA69: 381865.04 | AC69: =AA69-K69 -> 0 | AD69: =AB69-L69 -> 0
A70: BBQ Trim | B70: 06-2006 | C70: S | D70: COMMON AREA | E70: Pebble | F70: LS | G70: ='[59]Scenario 2 - Phase 1'!G70+'[59]Scenario 2 - Phase 2'!G70 -> 4 | H70: =K70/G70 -> 1031 | I70: 0 | K70: ='[59]Scenario 2 - Phase 1'!K70+'[59]Scenario 2 - Phase 2'!K70 -> 4124 | AA70: 4124 | AC70: =AA70-K70 -> 0 | AD70: =AB70-L70 -> 0
A71: Shutters | B71: 06-4919 | C71: S | D71: BUILDING | E71: N/A | I71: 0 | J71: =H71*(1+I71) -> 0 | K71: =J71*G71 -> 0 | AA71: 0 | AC71: =AA71-K71 -> 0 | AD71: =AB71-L71 -> 0
A72: Thermal & Moisture Protection | B72: 07 | L72: =SUM(K73:K83) -> 2004765.7 | AB72: 2004765.7 | AC72: =AA72-K72 -> 0 | AD72: =AB72-L72 -> 0
A73: Insulation | B73: 07-2101 | C73: S | D73: BUILDING | E73: Torrey Pines | F73: SF | G73: =B8 -> 329194 | H73: 2.54 | I73: 0 | J73: =H73*(1+I73) -> 2.54 | K73: =J73*G73 -> 836152.76 | AA73: 836152.76 | AC73: =AA73-K73 -> 0 | AD73: =AB73-L73 -> 0
A74: Roofing | B74: 07-3001 | C74: S | D74: BUILDING | E74: Torrey Pines | F74: Square | G74: =O9 -> 1693.23 | H74: 603 | I74: 0 | J74: =H74*(1+I74) -> 603 | K74: =J74*G74 -> 1021017.7 | AA74: 1021017.7 | AC74: =AA74-K74 -> 0 | AD74: =AB74-L74 -> 0
A75: Cabana Roofing | B75: 07-3002 | C75: S | D75: COMMON AREA | E75: N/A | I75: 0 | J75: =H75*(1+I75) -> 0 | K75: =J75*G75 -> 0 | AA75: 0 | AC75: =AA75-K75 -> 0 | AD75: =AB75-L75 -> 0
A76: Pump House Roofing | B76: 07-3002 | C76: S | D76: PUMPHOUSE | E76: Allowance | F76: LS | G76: 1 | H76: 6700 | I76: 0 | J76: =H76*(1+I76) -> 6700 | K76: =J76*G76 -> 6700 | AA76: 6700 | AC76: =AA76-K76 -> 0 | AD76: =AB76-L76 -> 0
A77: Pool Equipment Roofing | B77: 07-3003 | C77: S | D77: POOL EQUIP | E77: N/A | I77: 0 | J77: =H77*(1+I77) -> 0 | K77: =J77*G77 -> 0 | AA77: 0 | AC77: =AA77-K77 -> 0 | AD77: =AB77-L77 -> 0
A78: Trash Enclosure Cover | B78: 07-6101 | C78: S | D78: OTHER SITE | E78: Torrey Pines | F78: Count | G78: =$O$4 -> 10.542857 | H78: 7000 | I78: 0 | J78: =H78*(1+I78) -> 7000 | K78: =J78*G78 -> 73800 | AA78: 73800 | AC78: =AA78-K78 -> 0 | AD78: =AB78-L78 -> 0
A79: Pigeon Proofing | B79: 07-7001 | C79: S | D79: BUILDING | E79: Torrey Pines | F79: SF | G79: =$B$8 -> 329194 | H79: 0.08 | I79: 0 | J79: =H79*(1+I79) -> 0.08 | K79: =J79*G79 -> 26335.52 | AA79: 26335.52 | AC79: =AA79-K79 -> 0 | AD79: =AB79-L79 -> 0
A80: Gutters and Downspouts | B80: 07-7124 | C80: S | D80: BUILDING | E80: Torrey Pines | F80: SF | G80: =$B$8 -> 329194 | H80: 0.05 | I80: 0 | J80: =H80*(1+I80) -> 0.05 | K80: =J80*G80 -> 16459.7 | AA80: 16459.7 | AC80: =AA80-K80 -> 0 | AD80: =AB80-L80 -> 0
A81: Roof Ladders | B81: 07-7210 | C81: S | D81: BUILDING | E81: Torrey Pines | F81: Count | G81: =2*$B$11 -> 6 | H81: 1550 | I81: 0 | J81: =H81*(1+I81) -> 1550 | K81: =J81*G81 -> 9300 | N81: 2 Per building | AA81: 9300 | AC81: =AA81-K81 -> 0 | AD81: =AB81-L81 -> 0
A82: Roof Access Doors | B82: 07-7233 | C82: S | D82: BUILDING | E82: Torrey Pines | F82: Count | G82: =2*$B$11 -> 6 | H82: 2500 | I82: 0 | J82: =H82*(1+I82) -> 2500 | K82: =J82*G82 -> 15000 | N82: 2 Per building | AA82: 15000 | AC82: =AA82-K82 -> 0 | AD82: =AB82-L82 -> 0
A83: Roof Winch | B83: 07-7250 | C83: S | D83: BUILDING | E83: N/A | I83: 0 | J83: =H83*(1+I83) -> 0 | K83: =J83*G83 -> 0 | AA83: 0 | AC83: =AA83-K83 -> 0 | AD83: =AB83-L83 -> 0
A84: Openings | B84: 08 | L84: =SUM(K85:K99) -> 574050.3 | AB84: 574050.3 | AC84: =AA84-K84 -> 0 | AD84: =AB84-L84 -> 0
A85: Dumpsters | B85: 08-0151 | C85: S | D85: DUMPSTERS | F85: Per Unit | G85: =$E$8 -> 363 | H85: 79 | I85: 0 | J85: =H85*(1+I85) -> 79 | K85: =J85*G85 -> 28677 | AA85: 28677 | AC85: =AA85-K85 -> 0 | AD85: =AB85-L85 -> 0
A86: Entry Doors | B86: 08-1001 | C86: S | D86: COMMON AREA | E86: N/A | I86: 0 | J86: =H86*(1+I86) -> 0 | K86: =J86*G86 -> 0 | AA86: 0 | AC86: =AA86-K86 -> 0 | AD86: =AB86-L86 -> 0
A87: Common Doors | B87: 08-1002 | C87: S | D87: COMMON AREA | E87: Included | I87: 0 | J87: =H87*(1+I87) -> 0 | K87: =J87*G87 -> 0 | AA87: 0 | AC87: =AA87-K87 -> 0 | AD87: =AB87-L87 -> 0
A88: Pocket Doors - 3 Panel | B88: 08-1002 | C88: S | D88: BUILDING | E88: N/A | I88: 0 | J88: =H88*(1+I88) -> 0 | K88: =J88*G88 -> 0 | AA88: 0 | AC88: =AA88-K88 -> 0 | AD88: =AB88-L88 -> 0
A89: Garage Doors | B89: 08-3619 | C89: S | D89: BUILDING | E89: N/A | I89: 0 | J89: =H89*(1+I89) -> 0 | K89: =J89*G89 -> 0 | AA89: 0 | AC89: =AA89-K89 -> 0 | AD89: =AB89-L89 -> 0
A90: Windows and Sliding Glass Doors | B90: 08-5301 | C90: S | D90: BUILDING | E90: Decatur | F90: Per Unit | G90: =$E$8 -> 363 | H90: 1244.1 | I90: 0 | J90: =H90*(1+I90) -> 1244.1 | K90: =J90*G90 -> 451608.3 | N90: Per Solar Industries include +10% Due to New Energy Star U Factor Requirement Less than or equall to 0.28 | AA90: 451608.3 | AC90: =AA90-K90 -> 0 | AD90: =AB90-L90 -> 0
A91: Windows Repair and Replacement | B91: 08-5301 | C91: RR | D91: BUILDING | E91: Allowance | F91: Per Unit | G91: =$E$8 -> 363 | H91: 75 | I91: 0 | J91: =H91*(1+I91) -> 75 | K91: =J91*G91 -> 27225 | AA91: 27225 | AC91: =AA91-K91 -> 0 | AD91: =AB91-L91 -> 0
A92: Pool Equipment Windows | B92: 08-5303 | C92: S | D92: POOL EQUIP | E92: N/A | I92: 0 | J92: =H92*(1+I92) -> 0 | K92: =J92*G92 -> 0 | AA92: 0 | AC92: =AA92-K92 -> 0 | AD92: =AB92-L92 -> 0
A93: Pool Glass Walls | B93: 08-8001 | C93: S | D93: POOL AREA | E93: N/A | I93: 0 | J93: =H93*(1+I93) -> 0 | K93: =J93*G93 -> 0 | AA93: 0 | AC93: =AA93-K93 -> 0 | AD93: =AB93-L93 -> 0
A94: Fixed Glass | B94: 08-8002 | C94: S | D94: BUILDING | E94: N/A | I94: 0 | J94: =H94*(1+I94) -> 0 | K94: =J94*G94 -> 0 | AA94: 0 | AC94: =AA94-K94 -> 0 | AD94: =AB94-L94 -> 0
A95: Mirrors - LED | B95: 08-8301 | C95: S | D95: BUILDING | E95: N/A | I95: 0 | J95: =H95*(1+I95) -> 0 | K95: =J95*G95 -> 0 | AA95: 0 | AC95: =AA95-K95 -> 0 | AD95: =AB95-L95 -> 0
A96: Mirrors - LED Install | B96: 08-8302 | C96: S | D96: BUILDING | E96: N/A | I96: 0 | J96: =H96*(1+I96) -> 0 | K96: =J96*G96 -> 0 | AA96: 0 | AC96: =AA96-K96 -> 0 | AD96: =AB96-L96 -> 0
A97: Mirrors - Framed | B97: 08-8301 | C97: S | D97: BUILDING | E97: N/A | I97: 0 | J97: =H97*(1+I97) -> 0 | K97: =J97*G97 -> 0 | AA97: 0 | AC97: =AA97-K97 -> 0 | AD97: =AB97-L97 -> 0
A98: Mirrors - Polished Edges (Units) | B98: 08-8301 | C98: S | D98: BUILDING | E98: Russell IV | F98: Unit | G98: =$E$8 -> 363 | H98: 180 | I98: 0 | J98: =H98*(1+I98) -> 180 | K98: =J98*G98 -> 65340 | AA98: 65340 | AC98: =AA98-K98 -> 0 | AD98: =AB98-L98 -> 0
A99: Mirrors - Polished Edges (Restrooms) | B99: 08-8301 | C99: S | D99: BUILDING | E99: Russell IV | F99: Count | G99: =$B$11*2 -> 6 | H99: 200 | I99: 0 | J99: =H99*(1+I99) -> 200 | K99: =J99*G99 -> 1200 | AA99: 1200 | AC99: =AA99-K99 -> 0 | AD99: =AB99-L99 -> 0
A100: Finishes | B100: 09 | L100: =SUM(K101:K136) -> 5615983.3 | AB100: 5615983.3 | AC100: =AA100-K100 -> 0 | AD100: =AB100-L100 -> 0
A101: Cost Prep Labor | B101: 09-0101 | C101: S | D101: BUILDING | E101: Wigwam | F101: SF | G101: =$B$8 -> 329194 | H101: 0.05 | I101: 0 | J101: =H101*(1+I101) -> 0.05 | K101: =J101*G101 -> 16459.7 | AA101: 16459.7 | AC101: =AA101-K101 -> 0 | AD101: =AB101-L101 -> 0
...

Sheet Sheet2
C1: Robindale Senior Apartments | S1: Hard Costs Budget
C2: Las Vegas, NV
D6: Hard Cost Item | E6: Cost Code | F6: ROM Total | H6: "% Factor" Adj. | I6: $ | J6: $ / GSF | K6: $ / U
B7: 01 | D7: 01 - General Requirements | E7: 01 | F7: 3514986.3 | G7: 0.06 | H7: =G7*SUM($I$8:$I$35) -> 3435050 | I7: =IF(ISBLANK(H7)=FALSE,H7,F7) -> 3435050 | J7: =I7/[60]Input!$C$20 -> 11.040136 | K7: =I7/[60]Input!$C$13 -> 9462.9476
B8: 02-49 | D8: 02 - Existing Conditions | E8: 02 | F8: 16000 | I8: =IF(ISBLANK(H8)=FALSE,H8,F8) -> 16000 | J8: =I8/[60]Input!$C$20 -> 0.051423466 | K8: =I8/[60]Input!$C$13 -> 44.077135
B9: 02-49 | D9: 03 - Concrete | E9: 03 | F9: 3882795.7 | I9: =IF(ISBLANK(H9)=FALSE,H9,F9) -> 3882795.7 | J9: =I9/[60]Input!$C$20 -> 12.479176 | K9: =I9/[60]Input!$C$13 -> 10696.407
B10: 02-49 | D10: 04 - Masonry | E10: 04 | F10: 174094.29 | I10: =IF(ISBLANK(H10)=FALSE,H10,F10) -> 174094.29 | J10: =I10/[60]Input!$C$20 -> 0.55953322 | K10: =I10/[60]Input!$C$13 -> 479.59858
B11: 02-49 | D11: 05 - Metals | E11: 05 | F11: 413758.91 | I11: =IF(ISBLANK(H11)=FALSE,H11,F11) -> 413758.91 | J11: =I11/[60]Input!$C$20 -> 1.3298073 | K11: =I11/[60]Input!$C$13 -> 1139.8317
B12: 02-49 | D12: 06 - Wood, Plastics, & Composites | E12: 06 | F12: 8101853.5 | I12: =IF(ISBLANK(H12)=FALSE,H12,F12) -> 8101853.5 | J12: =I12/[60]Input!$C$20 -> 26.039087 | K12: =I12/[60]Input!$C$13 -> 22319.156
B13: 02-49 | D13: 07 - Thermal & Moisture Protection | E13: 07 | F13: 2004765.7 | I13: =IF(ISBLANK(H13)=FALSE,H13,F13) -> 2004765.7 | J13: =I13/[60]Input!$C$20 -> 6.4432499 | K13: =I13/[60]Input!$C$13 -> 5522.7704
B14: 02-49 | D14: 08 - Openings | E14: 08 | F14: 574050.3 | I14: =IF(ISBLANK(H14)=FALSE,H14,F14) -> 574050.3 | J14: =I14/[60]Input!$C$20 -> 1.8449785 | K14: =I14/[60]Input!$C$13 -> 1581.4058
B15: 02-49 | D15: 09 - Finishes | E15: 09 | F15: 5615983.3 | I15: =IF(ISBLANK(H15)=FALSE,H15,F15) -> 5615983.3 | J15: =I15/[60]Input!$C$20 -> 18.049583 | K15: =I15/[60]Input!$C$13 -> 15471.028
B16: 02-49 | D16: 10 - Specialties | E16: 10 | F16: 373369 | I16: =IF(ISBLANK(H16)=FALSE,H16,F16) -> 373369 | J16: =I16/[60]Input!$C$20 -> 1.1999955 | K16: =I16/[60]Input!$C$13 -> 1028.5647
B17: 02-49 | D17: 11 - Equipment | E17: 11 | F17: 1160874 | I17: =IF(ISBLANK(H17)=FALSE,H17,F17) -> 1160874 | J17: =I17/[60]Input!$C$20 -> 3.7310103 | K17: =I17/[60]Input!$C$13 -> 3198
B18: 02-49 | D18: 12 - Furnishings | E18: 12 | F18: 2185435.2 | I18: =IF(ISBLANK(H18)=FALSE,H18,F18) -> 2185435.2 | J18: =I18/[60]Input!$C$20 -> 7.0239156 | K18: =I18/[60]Input!$C$13 -> 6020.4825
B19: 02-49 | D19: 13 - Special Construction | E19: 13 | F19: 1491093.8 | I19: =IF(ISBLANK(H19)=FALSE,H19,F19) -> 1491093.8 | J19: =I19/[60]Input!$C$20 -> 4.7923256 | K19: =I19/[60]Input!$C$13 -> 4107.6963
... B32: 02-49 | D32: 49 - Field Surveys, Staking | E32: 49 | F32: 465812.1 | I32: =IF(ISBLANK(H32)=FALSE,H32,F32) -> 465812.1 | J32: =I32/[60]Input!$C$20 -> 1.4971045 | K32: =I32/[60]Input!$C$13 -> 1283.2289
B33: Bid Risk | D33: Bid Risk | E33: Bid Risk | F33: 1052926.4 | G33: 0 | H33: =G33*SUM(I8:I32) -> 0 | I33: =IF(ISBLANK(H33)=FALSE,H33,F33) -> 0 | J33: =I33/[60]Input!$C$20 -> 0 | K33: =I33/[60]Input!$C$13 -> 0
B34: FFE Extra | D34: FFE Extra | E34: FFE Extra | F34: 3014642.8 | I34: =IF(ISBLANK(H34)=FALSE,H34,F34) -> 3014642.8 | J34: =I34/[60]Input!$C$20 -> 9.6889613 | K34: =I34/[60]Input!$C$13 -> 8304.8011
B35: 50 | D35: 50 - Sub Bonds / Contractor Insurance | E35: 50 | F35: 1070872.5 | H35: =556000-59000+22000 -> 519000 | I35: =IF(ISBLANK(H35)=FALSE,H35+F35,F35) -> 1589872.5 | J35: =I35/[60]Input!$C$20 -> 5.1097971 | K35: =I35/[60]Input!$C$13 -> 4379.814
B36: 55 | D36: 55 - Construction Contingency | E36: 55 | F36: 2860711.5 | G36: 0.05 | H36: =G36*SUM(I7:I35,I37:I37) -> 3263297.5 | I36: =IF(ISBLANK(H36)=FALSE,H36,F36) -> 3263297.5 | J36: =I36/[60]Input!$C$20 -> 10.488129 | K36: =I36/[60]Input!$C$13 -> 8989.8002
B37: 56 | D37: 56 - Contractor Fee | E37: 56 | F37: 5132836.6 | G37: 0.08 | H37: =G37*SUM($I$8:$I$35) -> 4580066.6 | I37: =IF(ISBLANK(H37)=FALSE,H37,F37) -> 4580066.6 | J37: =I37/[60]Input!$C$20 -> 14.720181 | K37: =I37/[60]Input!$C$13 -> 12617.263
D39: Total Hard Costs | F39: =SUM(F7:F37) -> 69293294 | I39: =SUM(I7:I37) -> 68529247 | J39: =I39/[60]Input!$C$20 -> 220.25071 | K39: =I39/[60]Input!$C$13 -> 188785.8

Sheet Sheet3
B4: Differences Onsite Water
B5: Hard Dig | C5: 125000
B6: Fire Hydrants | C6: =281450-198000 -> 83450
B7: 6" Domestic | C7: =301916.16-109008 -> 192908.16 | D7: 8" line
B8: 10" Fire Line | C8: =339456-322420 -> 17036
B9: Fittings & Valves | C9: =364153-206648 -> 157505
B10: Total | C10: =SUM(C5:C9) -> 575899.16

Sheet Sheet1
